Workbook

Sheet Perfil_Egreso
A1: ANEXO Nº9 PERFIL DE EGRESO CETPRO
A3: DENOMINACIÓN DE LA INSTITUCIÓN | B3: CETPRO JUANJUI | D3: CÓDIGO MODULAR DEL CETPRO | E3: 0533836
A5: SECTOR ECONÓMICO | B5: Actividades profesionales, científicas y técnicas | C5: FAMILIA PRODUCTIVA | D5: Servicios prestados a empresas
A7: ACTIVIDAD ECONÓMICA | B7: Actividades administrativas y de apoyo de oficina y otras actividades de apoyo a las empresas
A10: DENOMINACIÓN DEL PROGRAMA DE ESTUDIOS SEGÚN CNOF (según corresponda) | B10: APOYO ADMINISTRATIVO | D10: CÓDIGO * | E10: M2982-1-002
A12: FORMACIÓN** | B12: AUXILIAR TECNICO | C12: MODALIDAD DEL SERVICIO EDUCATIVO | D12: PRESENCIAL
A14: NIVEL FORMATIVO | B14: AUXILIAR TÉCNICO
A16: DESCRIPCIÓN DEL PERFIL DE EGRESO | F16: Filtrar
A17: El Auxiliar Técnico de Apoyo administrativo es capaz de proveer información, procesar documentación de las distintas áreas de la organización, custodiar la documentación, según políticas y procedimientos de la organización, y normativa correspondiente. Asimismo, se comunica con otros en forma efectiva, busca y analiza información haciendo uso de herramientas informáticas, desarrolla y lidera proyectos o negocios que generen valor y sean sostenibles; estableciendo relaciones con respeto y justicia en el ámbito personal y colectivo, contribuyendo a una convivencia democrática, orientada al bien común, promoviendo prácticas orientadas al cuidado del medio ambiente. | F17: =A17 -> El Auxiliar Técnico de Apoyo administrativo es capaz de proveer información, procesar documentación de las distintas áreas de la organización, custodiar la documentación, según políticas y procedimientos de la organización, y normativa correspondiente. Asimismo, se comunica con otros en forma efectiva, busca y analiza información haciendo uso de herramientas informáticas, desarrolla y lidera proyectos o negocios que generen valor y sean sostenibles; estableciendo relaciones con respeto y justicia en el ámbito personal y colectivo, contribuyendo a una convivencia democrática, orientada al bien común, promoviendo prácticas orientadas al cuidado del medio ambiente.
A18: COMPETENCIAS ESPECÍFICAS (UNIDAD DE COMPETENCIA) | F18: =A18 -> COMPETENCIAS ESPECÍFICAS (UNIDAD DE COMPETENCIA)
A19: UC1. Proveer información, según políticas y procedimientos de la organización, y normativa correspondiente. | F19: =A19 -> UC1. Proveer información, según políticas y procedimientos de la organización, y normativa correspondiente.
A20: UC2. Procesar la documentación de las distintas áreas de la organización, en función a sus políticas y normativa correspondiente. | F20: =A20 -> UC2. Procesar la documentación de las distintas áreas de la organización, en función a sus políticas y normativa correspondiente.
A21: UC3. Custodiar la documentación, según políticas y procedimientos de la organización, y normativa correspondiente. | F21: =A21 -> UC3. Custodiar la documentación, según políticas y procedimientos de la organización, y normativa correspondiente.
F22: =A22 -> 0
F23: =A23 -> 0
F24: =A24 -> 0
F25: =A25 -> 0
F26: =A26 -> 0
F27: =A27 -> 0
F28: =A28 -> 0
A29: COMPETENCIAS PARA LA EMPLEABILIDAD | F29: =A29 -> COMPETENCIAS PARA LA EMPLEABILIDAD
A30: CE1 Comunicación efectiva.- Expresar de manera clara los conceptos, ideas, sentimientos, hechos y opiniones en forma oral y escrita para comunicarse e interactuar con otras personas en contextos sociales y laborales diversos. (UD) | F30: =A30 -> CE1 Comunicación efectiva.- Expresar de manera clara los conceptos, ideas, sentimientos, hechos y opiniones en forma oral y escrita para comunicarse e interactuar con otras personas en contextos sociales y laborales diversos. (UD)
A31: CE2 Tecnologías de la información.- Manejar herramientas informáticas de las TIC para buscar y analizar información, comunicarse y realizar procedimientos o tareas vinculadas al área profesional, de acuerdo a los requerimientos de su entorno laboral.(UD) | F31: =A31 -> CE2 Tecnologías de la información.- Manejar herramientas informáticas de las TIC para buscar y analizar información, comunicarse y realizar procedimientos o tareas vinculadas al área profesional, de acuerdo a los requerimientos de su entorno laboral.(UD)
A32: CE3 Emprendimiento.- Identificar nuevas oportunidades de proyectos o negocios que generen valor y sean sostenibles, gestionando recursos para su funcionamiento con creatividad y ética, articulando acciones que permitan desarrollar innovaciones en la creación de bienes y/o servicios, así como en procesos o productos ya existentes. (UD) | F32: =A32 -> CE3 Emprendimiento.- Identificar nuevas oportunidades de proyectos o negocios que generen valor y sean sostenibles, gestionando recursos para su funcionamiento con creatividad y ética, articulando acciones que permitan desarrollar innovaciones en la creación de bienes y/o servicios, así como en procesos o productos ya existentes. (UD)
A33: CE4 Ética.-Establecer relaciones con respeto y justicia en los ámbitos personal, colectivo e institucional, contribuyendo a una convivencia democrática, orientada al bien común que considere la diversidad y dignidad de las personas, teniendo en cuenta las consideraciones aplicadas en su contexto laboral.(UD) | F33: =A33 -> CE4 Ética.-Establecer relaciones con respeto y justicia en los ámbitos personal, colectivo e institucional, contribuyendo a una convivencia democrática, orientada al bien común que considere la diversidad y dignidad de las personas, teniendo en cuenta las consideraciones aplicadas en su contexto laboral.(UD)
A34: CE5 Liderazgo personal y profesional.- Articular recursos y potencialidades de cada integrante de su equipo logrando un trabajo comprometido, colaborativo, creativo, ético, sensible a su contexto social y ambiente, en pro del bien común. (T) | F34: =A34 -> CE5 Liderazgo personal y profesional.- Articular recursos y potencialidades de cada integrante de su equipo logrando un trabajo comprometido, colaborativo, creativo, ético, sensible a su contexto social y ambiente, en pro del bien común. (T)
A35: CE6 Cultura ambiental.- Convivir de manera ética, autónoma, responsable y sostenible, previniendo, reduciendo y controlando permanente y progresivamente los impactos ambientales. (T) | F35: =A35 -> CE6 Cultura ambiental.- Convivir de manera ética, autónoma, responsable y sostenible, previniendo, reduciendo y controlando permanente y progresivamente los impactos ambientales. (T)
F36: =A36 -> 0
F37: =A37 -> 0
F38: =A38 -> 0
F39: =A39 -> 0
F40: =A40 -> 0
F41: =A41 -> 0
A42: ÁMBITOS DE DESEMPEÑO | F42: =A42 -> ÁMBITOS DE DESEMPEÑO
A43: Desarrolla su actividad en las siguientes áreas: - Area administrativa. - Área de atención al cliente o usuario. - Área de archivo de documentos. - Area administrativa de Call Center. -Area de información -Area de recepción -Area de lógistica y almacén -Mesa de partes -Area de digitalización | F43: =A43 -> Desarrolla su actividad en las siguientes áreas: - Area administrativa. - Área de atención al cliente o usuario. - Área de archivo de documentos. - Area administrativa de Call Center. -Area de información -Area de recepción -Area de lógistica y almacén -Mesa de partes -Area de digitalización
A44: Pautas Generales: 1. Descripción del perfil de egreso: Descripción general y breve de los desempeños que será capaz de realizar el egresado en el campo laboral, al concluir el programa de estudio en correspondencia con las competencias técnicas y de empleabilidad. 2. Competencias específicas: Transcripción de las unidades de competencia del programa de estudio, establecido en el CNOF. En caso de que el programa no se encuentre en el CNOF se tomarán las Unidades de Competencias definidas mediante el análisis de la actividad económica correspondiente. 3. Las competencias para la empleabilidad: son priorizadas por la institución educativa, en concordancia con los Lineamientos Académicos Generales establecidos por el MINEDU y su modelo educativo. Se debe distinguir los que se abordarán como unidad didáctica (UD), de manera transversal (T) o ambas (UD/T) 4. Ámbitos de desempeño: Listar los campos o áreas laborales en los cuales el egresado del programa de estudio se podrá insertar. *Se considera el código del programa de estudios del CNOF, de ser el caso. ** Indicar sólo en el caso de que sea Dual o En Alternancia, caso contrario dejar la celda en blanco. | F44: =A44 -> Pautas Generales: 1. Descripción del perfil de egreso: Descripción general y breve de los desempeños que será capaz de realizar el egresado en el campo laboral, al concluir el programa de estudio en correspondencia con las competencias técnicas y de empleabilidad. 2. Competencias específicas: Transcripción de las unidades de competencia del programa de estudio, establecido en el CNOF. En caso de que el programa no se encuentre en el CNOF se tomarán las Unidades de Competencias definidas mediante el análisis de la actividad económica correspondiente. 3. Las competencias para la empleabilidad: son priorizadas por la institución educativa, en concordancia con los Lineamientos Académicos Generales establecidos por el MINEDU y su modelo educativo. Se debe distinguir los que se abordarán como unidad didáctica (UD), de manera transversal (T) o ambas (UD/T) 4. Ámbitos de desempeño: Listar los campos o áreas laborales en los cuales el egresado del programa de estudio se podrá insertar. *Se considera el código del programa de estudios del CNOF, de ser el caso. ** Indicar sólo en el caso de que sea Dual o En Alternancia, caso contrario dejar la celda en blanco.

Sheet Programa_Estudio
A1: ANEXO Nº 8 PROGRAMA DE ESTUDIOS CETPRO
A3: =Perfil_Egreso!A3 -> DENOMINACIÓN DE LA INSTITUCIÓN | B3: =Perfil_Egreso!B3 -> CETPRO JUANJUI | D3: =Perfil_Egreso!D3 -> CÓDIGO MODULAR DEL CETPRO | E3: =Perfil_Egreso!E3 -> 0533836
A5: SECTOR ECONÓMICO | B5: =Perfil_Egreso!B5 -> Actividades profesionales, científicas y técnicas | C5: FAMILIA PRODUCTIVA | D5: =Perfil_Egreso!D5 -> Servicios prestados a empresas | E5: ACTIVIDAD ECONÓMICA | F5: =Perfil_Egreso!B7 -> Actividades administrativas y de apoyo de oficina y otras actividades de apoyo a las empresas
A7: DENOMINACIÓN DEL PROGRAMA DE ESTUDIOS SEGÚN CNOF (según corresponda) | B7: =Perfil_Egreso!B10 -> APOYO ADMINISTRATIVO | E7: CÓDIGO DE SER EL CASO * | F7: =Perfil_Egreso!E10 -> M2982-1-002
A9: NIVEL FORMATIVO | B9: =Perfil_Egreso!B14 -> AUXILIAR TÉCNICO | C9: N°. HORAS: | D9: =Itinerario!W17 -> 1072 | E9: N° CRÉDITOS: | F9: =Itinerario!T17 -> 40
A11: FORMACIÓN** | D11: MODALIDAD DEL SERVICIO EDUCATIVO | E11: =Perfil_Egreso!D12 -> PRESENCIAL
A13: COMPETENCIAS ESPECÍFICAS (UNIDAD DE COMPETENCIA)
A14: UNIDAD DE COMPETENCIA | C14: INDICADORES DE LOGRO DE LA COMPETENCIA | G14: Filtro
A15: =CONCATENATE("Unidad de Competencia N° 01 (UC1): ",Perfil_Egreso!A19) -> Unidad de Competencia N° 01 (UC1): UC1. Proveer información, según políticas y procedimientos de la organización, y normativa correspondiente. | C15: 1. Recopila datos o documentación, según políticas, procedimientos, y normativa de la organización. | G15: =C15 -> 1. Recopila datos o documentación, según políticas, procedimientos, y normativa de la organización.
C16: 2. Prepara datos o documentación, según políticas, procedimientos y normativa de la organización. | G16: =C16 -> 2. Prepara datos o documentación, según políticas, procedimientos y normativa de la organización.
C17: 3. Realiza el trámite de datos y documentos, según políticas, procedimientos y normativa de la organización. | G17: =C17 -> 3. Realiza el trámite de datos y documentos, según políticas, procedimientos y normativa de la organización.
G18: =C18 -> 0
G19: =C19 -> 0
G20: =C20 -> 0
G21: =C21 -> 0
G22: =C22 -> 0
G23: =C23 -> 0
G29: =C29 -> 0
A30: =CONCATENATE("Unidad de Competencia N° 02 (UC2): ",Perfil_Egreso!A20) -> Unidad de Competencia N° 02 (UC2): UC2. Procesar la documentación de las distintas áreas de la organización, en función a sus políticas y normativa correspondiente. | C30: 1. Recepciona y atiende los documentos, en función a los objetivos de la organización y procedimientos establecidos. | G30: =C30 -> 1. Recepciona y atiende los documentos, en función a los objetivos de la organización y procedimientos establecidos.
C31: 2. Realiza actividades administrativas de apoyo2, en función de los objetivos de la organización y el área asignada. | G31: =C31 -> 2. Realiza actividades administrativas de apoyo2, en función de los objetivos de la organización y el área asignada.
C32: 3. Atiende las comunicaciones y/o centro de atención virtual, en función a los objetivos de la organización y procedimientos establecidos. | G32: =C32 -> 3. Atiende las comunicaciones y/o centro de atención virtual, en función a los objetivos de la organización y procedimientos establecidos.
C33: 4. Atiende los consultas, según los procedimientos establecidos y normativa correspondiente. | G33: =C33 -> 4. Atiende los consultas, según los procedimientos establecidos y normativa correspondiente.
C34: 5. Revisa la información, en función a los requerimientos de la organización y procedimientos establecidos. | G34: =C34 -> 5. Revisa la información, en función a los requerimientos de la organización y procedimientos establecidos.
G35: =C35 -> 0
G36: =C36 -> 0
G37: =C37 -> 0
G38: =C38 -> 0
G44: =C44 -> 0
A45: =CONCATENATE("Unidad de Competencia N° 03 (UC3): ",Perfil_Egreso!A21) -> Unidad de Competencia N° 03 (UC3): UC3. Custodiar la documentación, según políticas y procedimientos de la organización, y normativa correspondiente. | C45: 1. Cataloga datos de los documentos, según políticas, procedimientos de la organización, y normativa correspondiente. | G45: =C45 -> 1. Cataloga datos de los documentos, según políticas, procedimientos de la organización, y normativa correspondiente.
C46: 2. Archiva los documentos, según políticas y procedimientos de la organización, y normativa correspondiente. | G46: =C46 -> 2. Archiva los documentos, según políticas y procedimientos de la organización, y normativa correspondiente.
G47: =C47 -> 0
G48: =C48 -> 0
G49: =C49 -> 0
G50: =C50 -> 0
G51: =C51 -> 0
G52: =C52 -> 0
G53: =C53 -> 0
G59: =C59 -> 0
A60: =CONCATENATE("Unidad de Competencia N° 04 (UC4): ",Perfil_Egreso!A22) -> Unidad de Competencia N° 04 (UC4): | G60: =C60 -> 0
G61: =C61 -> 0
G62: =C62 -> 0
G63: =C63 -> 0
G64: =C64 -> 0
G65: =C65 -> 0
G66: =C66 -> 0
G67: =C67 -> 0
G68: =C68 -> 0
G74: =C74 -> 0
A75: =CONCATENATE("Unidad de Competencia N° 05 (UC5): ",Perfil_Egreso!A23) -> Unidad de Competencia N° 05 (UC5): | G75: =C75 -> 0
G76: =C76 -> 0
G77: =C77 -> 0
G78: =C78 -> 0
G79: =C79 -> 0
G80: =C80 -> 0
G81: =C81 -> 0
G82: =C82 -> 0
G83: =C83 -> 0
G89: =C89 -> 0
A90: =CONCATENATE("Unidad de Competencia N° 06 (UC6): ",Perfil_Egreso!A24) -> Unidad de Competencia N° 06 (UC6): | G90: =C90 -> 0
G91: =C91 -> 0
G92: =C92 -> 0
G93: =C93 -> 0
G94: =C94 -> 0
G95: =C95 -> 0
G96: =C96 -> 0
G97: =C97 -> 0
G98: =C98 -> 0
G104: =C104 -> 0
A105: =CONCATENATE("Unidad de Competencia N° 07 (UC7): ",Perfil_Egreso!A25) -> Unidad de Competencia N° 07 (UC7): | G105: =C105 -> 0
G106: =C106 -> 0
G107: =C107 -> 0
G108: =C108 -> 0
G109: =C109 -> 0
G110: =C110 -> 0
G111: =C111 -> 0
G112: =C112 -> 0
G113: =C113 -> 0
G119: =C119 -> 0
A120: =CONCATENATE("Unidad de Competencia N° 08 (UC8): ",Perfil_Egreso!A26) -> Unidad de Competencia N° 08 (UC8): | G120: =C120 -> 0
G121: =C121 -> 0
G122: =C122 -> 0
G123: =C123 -> 0
G124: =C124 -> 0
G125: =C125 -> 0
G126: =C126 -> 0
G127: =C127 -> 0
G128: =C128 -> 0
G134: =C134 -> 0
A135: =CONCATENATE("Unidad de Competencia N° 09 (UC9): ",Perfil_Egreso!A27) -> Unidad de Competencia N° 09 (UC9): | G135: =C135 -> 0
G136: =C136 -> 0
G137: =C137 -> 0
G138: =C138 -> 0
G139: =C139 -> 0
G140: =C140 -> 0
G141: =C141 -> 0
G142: =C142 -> 0
G143: =C143 -> 0
G149: =C149 -> 0
A150: =CONCATENATE("Unidad de Competencia N° 10 (UC10): ",Perfil_Egreso!A28) -> Unidad de Competencia N° 10 (UC10): | G150: =C150 -> 0
G151: =C151 -> 0
...

Sheet Capacidades
C1: FORMATO DE PROCESO - FORMULACIÓN DE CAPACIDADES E INDICADORES POR UNIDAD DE COMPETENCIA
C5: Programa de estudios: | E5: =Perfil_Egreso!B10 -> APOYO ADMINISTRATIVO | L5: RESUMEN
D7: Capacidades asociadas a la Unidad de Competencia Específica y de Empleabilidad | H7: Indicadores de la Capacidad
A9: MÓDULOS | B9: Tipo de capacidad | C9: Código Capacidad | D9: Verbo | E9: Objeto | F9: Condición | G9: Código Indicador | H9: Verbo | I9: Objeto | J9: Condición | K9: Observaciones de los facilitadores opcional | L9: Capacidades | M9: Indicadores
A10: Módulo I | B10: Capacidad técnica | C10: UC1 C1 | D10: Organizar | E10: el área de trabajo, equipos y materiales | F10: teniendo en cuenta las normas de seguridad laboral y ambiental. | G10: C1 I1 | H10: Explica | I10: la estructura organizacional de la empresa | J10: de acuerdo a los manuales internos de organización. | L10: =CONCATENATE(C10," ",D10," ",E10," ",F10," ",C11," ",D11," ",E11," ",F11) -> UC1 C1 Organizar el área de trabajo, equipos y materiales teniendo en cuenta las normas de seguridad laboral y ambiental. | M10: =CONCATENATE(G10," ",H10," ",I10," ",J10) -> C1 I1 Explica la estructura organizacional de la empresa de acuerdo a los manuales internos de organización.
G11: C1 I2 | H11: Identifica | I11: los ambientes de trabajo, equipos y materiales | J11: tomando en cuenta sus características y funcionalidad. | M11: =CONCATENATE(G11," ",H11," ",I11," ",J11) -> C1 I2 Identifica los ambientes de trabajo, equipos y materiales tomando en cuenta sus características y funcionalidad.
G12: C1 I3 | H12: Opera | I12: los equipos de oficina | J12: de acuerdo al manual de operaciones. | M12: =CONCATENATE(G12," ",H12," ",I12," ",J12) -> C1 I3 Opera los equipos de oficina de acuerdo al manual de operaciones.
G13: C1 I4 | H13: Realiza | I13: la organización del ambiente de trabajo, equipos y materiales, | J13: teniendo en cuenta las normas de seguridad e higiene y protocolos de bioseguridad | M13: =CONCATENATE(G13," ",H13," ",I13," ",J13) -> C1 I4 Realiza la organización del ambiente de trabajo, equipos y materiales, teniendo en cuenta las normas de seguridad e higiene y protocolos de bioseguridad
M14: =CONCATENATE(G14," ",H14," ",I14," ",J14)
M15: =CONCATENATE(G15," ",H15," ",I15," ",J15)
M16: =CONCATENATE(G16," ",H16," ",I16," ",J16)
M17: =CONCATENATE(G17," ",H17," ",I17," ",J17)
M18: =CONCATENATE(G18," ",H18," ",I18," ",J18)
M19: =CONCATENATE(G19," ",H19," ",I19," ",J19)
A20: Módulo I | B20: Capacidad técnica | C20: UC1 C2 | D20: Elaborar | E20: documentos administrativos y/o mercantiles | F20: de acuerdo a las características y estructuras de las mismas, aplicando técnicas de redacción, reglas ortográficas y gramaticales . | G20: C2 I1 | H20: Identifica | I20: los diverso tipos de documentos administrativos | J20: de acuerdo a las políticas y normativas de la organización. | L20: =CONCATENATE(C20," ",D20," ",E20," ",F20," ",C21," ",D21," ",E21," ",F21) -> UC1 C2 Elaborar documentos administrativos y/o mercantiles de acuerdo a las características y estructuras de las mismas, aplicando técnicas de redacción, reglas ortográficas y gramaticales . | M20: =CONCATENATE(G20," ",H20," ",I20," ",J20) -> C2 I1 Identifica los diverso tipos de documentos administrativos de acuerdo a las políticas y normativas de la organización.
G21: C2 I2 | H21: Redacta | I21: los documentos administrativos | J21: aplicando las técnicas de redacción, reglas ortográficas y gramaticales, de acuerdo a las políticas y normativas de la organización. | M21: =CONCATENATE(G21," ",H21," ",I21," ",J21) -> C2 I2 Redacta los documentos administrativos aplicando las técnicas de redacción, reglas ortográficas y gramaticales, de acuerdo a las políticas y normativas de la organización.
G22: C2 I3 | H22: Realiza | I22: el llenado de los documentos administrativos y/o mercantiles | J22: aplicando reglas ortográficas y gramaticales, de acuerdo a las políticas y normativas de la organización. | M22: =CONCATENATE(G22," ",H22," ",I22," ",J22) -> C2 I3 Realiza el llenado de los documentos administrativos y/o mercantiles aplicando reglas ortográficas y gramaticales, de acuerdo a las políticas y normativas de la organización.
G23: C2 I4 | H23: Verifica | I23: la calidad de los documentos administrativos y/o mercantiles | J23: de acuerdo a la información correspondiente, aplicando reglas ortográficas y gramaticales. | M23: =CONCATENATE(G23," ",H23," ",I23," ",J23) -> C2 I4 Verifica la calidad de los documentos administrativos y/o mercantiles de acuerdo a la información correspondiente, aplicando reglas ortográficas y gramaticales.
M24: =CONCATENATE(G24," ",H24," ",I24," ",J24)
M25: =CONCATENATE(G25," ",H25," ",I25," ",J25)
M26: =CONCATENATE(G26," ",H26," ",I26," ",J26)
M27: =CONCATENATE(G27," ",H27," ",I27," ",J27)
M28: =CONCATENATE(G28," ",H28," ",I28," ",J28)
M29: =CONCATENATE(G29," ",H29," ",I29," ",J29)
A30: Módulo I | B30: Capacidad técnica | C30: UC1 C3 | D30: Realizar | E30: el trámite de datos y documentos, | F30: de acuerdo a los procedimientos, normativa vigente y políticas de la organización. | G30: C3 I1 | H30: Explica | I30: un diagrama de flujo documentario | J30: de acuerdo a los procedimientos, normativa vigente y políticas de la organización. | L30: =CONCATENATE(C30," ",D30," ",E30," ",F30," ",C31," ",D31," ",E31," ",F31) -> UC1 C3 Realizar el trámite de datos y documentos, de acuerdo a los procedimientos, normativa vigente y políticas de la organización. | M30: =CONCATENATE(G30," ",H30," ",I30," ",J30) -> C3 I1 Explica un diagrama de flujo documentario de acuerdo a los procedimientos, normativa vigente y políticas de la organización.
G31: C3 I2 | H31: Organiza | I31: el procedimiento de registro y recepción del flujo documentario | J31: de acuerdo a los procedimientos, normativa vigente y políticas de la organización. | M31: =CONCATENATE(G31," ",H31," ",I31," ",J31) -> C3 I2 Organiza el procedimiento de registro y recepción del flujo documentario de acuerdo a los procedimientos, normativa vigente y políticas de la organización.
G32: C3 I3 | H32: Ejecuta | I32: la organización y traslado de expedientes | J32: de acuerdo a los procedimientos, normativa vigente y políticas de la organización. | M32: =CONCATENATE(G32," ",H32," ",I32," ",J32) -> C3 I3 Ejecuta la organización y traslado de expedientes de acuerdo a los procedimientos, normativa vigente y políticas de la organización.
G33: C3 I4 | H33: Efectúa | I33: el control del traslado de los expedientes y/o documentos | J33: de acuerdo a los procedimientos, normativa vigente y políticas de la organización. | M33: =CONCATENATE(G33," ",H33," ",I33," ",J33) -> C3 I4 Efectúa el control del traslado de los expedientes y/o documentos de acuerdo a los procedimientos, normativa vigente y políticas de la organización.
G34: C3 I5 | H34: Informa | I34: al usuario sobre el trámite documentario | J34: de acuerdo a los procedimientos, normativa vigente y políticas de la organización. | M34: =CONCATENATE(G34," ",H34," ",I34," ",J34) -> C3 I5 Informa al usuario sobre el trámite documentario de acuerdo a los procedimientos, normativa vigente y políticas de la organización.
M35: =CONCATENATE(G35," ",H35," ",I35," ",J35)
M36: =CONCATENATE(G36," ",H36," ",I36," ",J36)
M37: =CONCATENATE(G37," ",H37," ",I37," ",J37)
M38: =CONCATENATE(G38," ",H38," ",I38," ",J38)
M39: =CONCATENATE(G39," ",H39," ",I39," ",J39)
A40: Módulo I | B40: Capacidad técnica | L40: =CONCATENATE(C40," ",D40," ",E40," ",F40," ",C41," ",D41," ",E41," ",F41) | M40: =CONCATENATE(G40," ",H40," ",I40," ",J40)
M41: =CONCATENATE(G41," ",H41," ",I41," ",J41)
M42: =CONCATENATE(G42," ",H42," ",I42," ",J42)
M43: =CONCATENATE(G43," ",H43," ",I43," ",J43)
M44: =CONCATENATE(G44," ",H44," ",I44," ",J44)
M45: =CONCATENATE(G45," ",H45," ",I45," ",J45)
M46: =CONCATENATE(G46," ",H46," ",I46," ",J46)
M47: =CONCATENATE(G47," ",H47," ",I47," ",J47)
M48: =CONCATENATE(G48," ",H48," ",I48," ",J48)
M49: =CONCATENATE(G49," ",H49," ",I49," ",J49)
A50: Módulo I | B50: Capacidad técnica | L50: =CONCATENATE(C50," ",D50," ",E50," ",F50," ",C51," ",D51," ",E51," ",F51) | M50: =CONCATENATE(G50," ",H50," ",I50," ",J50)
M51: =CONCATENATE(G51," ",H51," ",I51," ",J51)
M52: =CONCATENATE(G52," ",H52," ",I52," ",J52)
M53: =CONCATENATE(G53," ",H53," ",I53," ",J53)
M54: =CONCATENATE(G54," ",H54," ",I54," ",J54)
M55: =CONCATENATE(G55," ",H55," ",I55," ",J55)
M56: =CONCATENATE(G56," ",H56," ",I56," ",J56)
M57: =CONCATENATE(G57," ",H57," ",I57," ",J57)
M58: =CONCATENATE(G58," ",H58," ",I58," ",J58)
M59: =CONCATENATE(G59," ",H59," ",I59," ",J59)
A60: Módulo I | B60: Capacidad técnica | L60: =CONCATENATE(C60," ",D60," ",E60," ",F60," ",C61," ",D61," ",E61," ",F61) | M60: =CONCATENATE(G60," ",H60," ",I60," ",J60)
M61: =CONCATENATE(G61," ",H61," ",I61," ",J61)
M62: =CONCATENATE(G62," ",H62," ",I62," ",J62)
M63: =CONCATENATE(G63," ",H63," ",I63," ",J63)
M64: =CONCATENATE(G64," ",H64," ",I64," ",J64)
M65: =CONCATENATE(G65," ",H65," ",I65," ",J65)
M66: =CONCATENATE(G66," ",H66," ",I66," ",J66)
M67: =CONCATENATE(G67," ",H67," ",I67," ",J67)
M68: =CONCATENATE(G68," ",H68," ",I68," ",J68)
M69: =CONCATENATE(G69," ",H69," ",I69," ",J69)
A70: Módulo I | B70: Capacidad técnica | L70: =CONCATENATE(C70," ",D70," ",E70," ",F70," ",C71," ",D71," ",E71," ",F71) | M70: =CONCATENATE(G70," ",H70," ",I70," ",J70)
M71: =CONCATENATE(G71," ",H71," ",I71," ",J71)
M72: =CONCATENATE(G72," ",H72," ",I72," ",J72)
M73: =CONCATENATE(G73," ",H73," ",I73," ",J73)
M74: =CONCATENATE(G74," ",H74," ",I74," ",J74)
M75: =CONCATENATE(G75," ",H75," ",I75," ",J75)
M76: =CONCATENATE(G76," ",H76," ",I76," ",J76)
M77: =CONCATENATE(G77," ",H77," ",I77," ",J77)
M78: =CONCATENATE(G78," ",H78," ",I78," ",J78)
M79: =CONCATENATE(G79," ",H79," ",I79," ",J79)
A80: Módulo I | B80: Capacidad técnica | L80: =CONCATENATE(C80," ",D80," ",E80," ",F80," ",C81," ",D81," ",E81," ",F81) | M80: =CONCATENATE(G80," ",H80," ",I80," ",J80)
M81: =CONCATENATE(G81," ",H81," ",I81," ",J81)
M82: =CONCATENATE(G82," ",H82," ",I82," ",J82)
M83: =CONCATENATE(G83," ",H83," ",I83," ",J83)
M84: =CONCATENATE(G84," ",H84," ",I84," ",J84)
M85: =CONCATENATE(G85," ",H85," ",I85," ",J85)
M86: =CONCATENATE(G86," ",H86," ",I86," ",J86)
M87: =CONCATENATE(G87," ",H87," ",I87," ",J87)
M88: =CONCATENATE(G88," ",H88," ",I88," ",J88)
M89: =CONCATENATE(G89," ",H89," ",I89," ",J89)
A90: Módulo I | B90: Capacidad técnica | L90: =CONCATENATE(C90," ",D90," ",E90," ",F90," ",C91," ",D91," ",E91," ",F91) | M90: =CONCATENATE(G90," ",H90," ",I90," ",J90)
M91: =CONCATENATE(G91," ",H91," ",I91," ",J91)
M92: =CONCATENATE(G92," ",H92," ",I92," ",J92)
M93: =CONCATENATE(G93," ",H93," ",I93," ",J93)
M94: =CONCATENATE(G94," ",H94," ",I94," ",J94)
M95: =CONCATENATE(G95," ",H95," ",I95," ",J95)
M96: =CONCATENATE(G96," ",H96," ",I96," ",J96)
M97: =CONCATENATE(G97," ",H97," ",I97," ",J97)
M98: =CONCATENATE(G98," ",H98," ",I98," ",J98)
M99: =CONCATENATE(G99," ",H99," ",I99," ",J99)
A100: Módulo I | B100: Capacidad técnica | L100: =CONCATENATE(C100," ",D100," ",E100," ",F100," ",C101," ",D101," ",E101," ",F101) | M100: =CONCATENATE(G100," ",H100," ",I100," ",J100)
M101: =CONCATENATE(G101," ",H101," ",I101," ",J101)
M102: =CONCATENATE(G102," ",H102," ",I102," ",J102)
M103: =CONCATENATE(G103," ",H103," ",I103," ",J103)
M104: =CONCATENATE(G104," ",H104," ",I104," ",J104)
M105: =CONCATENATE(G105," ",H105," ",I105," ",J105)
...

Sheet Organización_Modular
A1: ORGANIZACIÓN MODULAR
A3: DENOMINACIÓN DE LA INSTITUCIÓN | C3: =Perfil_Egreso!B3 -> CETPRO JUANJUI | F3: CÓDIGO MODULAR | G3: =Perfil_Egreso!E3 -> 0533836
A5: =Perfil_Egreso!A10 -> DENOMINACIÓN DEL PROGRAMA DE ESTUDIOS SEGÚN CNOF (según corresponda) | C5: =Perfil_Egreso!B10 -> APOYO ADMINISTRATIVO | D5: CÓDIGO * | E5: =Perfil_Egreso!E10 -> M2982-1-002 | F5: NIVEL FORMATIVO | G5: =Perfil_Egreso!B14 -> AUXILIAR TÉCNICO
A7: =Perfil_Egreso!A12 -> FORMACIÓN** | C7: =Perfil_Egreso!B12 -> AUXILIAR TECNICO | E7: MODALIDAD DEL SERVICIO EDUCATIVO | F7: =Perfil_Egreso!D12 -> PRESENCIAL
H8: Información solo de proceso
A9: MÓDULO | B9: DESCRIPCIÓN DE LA COMPETENCIA | D9: CAPACIDADES | F9: UNIDAD DIDÁCTICA | G9: PERIODO ACADÉMICO | H9: Crédito teórico | I9: Crédito práctico | J9: T.créditos (Filtrar)
A10: MÓDULO I: REDACCIÓN Y TRÁMITE DOCUMENTARIO | B10: Competencias técnicas (Unidad de competencia) | C10: UC1 Proveer información, según políticas y procedimientos de la organización, y normativa correspondiente. | D10: =OFFSET(Capacidades!$A$1,(ROW()-9)*10-1,11) -> UC1 C1 Organizar el área de trabajo, equipos y materiales teniendo en cuenta las normas de seguridad laboral y ambiental. | F10: Organización del área de trabajo | G10: I | H10: 1 | I10: 1 | J10: =SUM(H10:I10) -> 2
D11: =OFFSET(Capacidades!$A$1,(ROW()-9)*10-1,11) -> UC1 C2 Elaborar documentos administrativos y/o mercantiles de acuerdo a las características y estructuras de las mismas, aplicando técnicas de redacción, reglas ortográficas y gramaticales . | F11: Redacción de documentos | G11: I | H11: 2 | I11: 2 | J11: =SUM(H11:I11) -> 4
D12: =OFFSET(Capacidades!$A$1,(ROW()-9)*10-1,11) -> UC1 C3 Realizar el trámite de datos y documentos, de acuerdo a los procedimientos, normativa vigente y políticas de la organización. | F12: Trámite documentario | G12: I | H12: 2 | I12: 2 | J12: =SUM(H12:I12) -> 4
D13: =OFFSET(Capacidades!$A$1,(ROW()-9)*10-1,11)
D14: =OFFSET(Capacidades!$A$1,(ROW()-9)*10-1,11) | J14: =SUM(H14:I14) -> 0
D15: =OFFSET(Capacidades!$A$1,(ROW()-9)*10-1,11) | J15: =SUM(H15:I15) -> 0
D16: =OFFSET(Capacidades!$A$1,(ROW()-9)*10-1,11) | J16: =SUM(H16:I16) -> 0
D17: =OFFSET(Capacidades!$A$1,(ROW()-9)*10-1,11) | J17: =SUM(H17:I17) -> 0
D18: =OFFSET(Capacidades!$A$1,(ROW()-9)*10-1,11) | J18: =SUM(H18:I18) -> 0
D19: =OFFSET(Capacidades!$A$1,(ROW()-9)*10-1,11) | J19: =SUM(H19:I19) -> 0
D20: =OFFSET(Capacidades!$A$1,(ROW()-9)*10-1,11) | J20: =SUM(H20:I20) -> 0
D21: =OFFSET(Capacidades!$A$1,(ROW()-9)*10-1,11) | J21: =SUM(H21:I21) -> 0
D22: =OFFSET(Capacidades!$A$1,(ROW()-9)*10-1,11) | J22: =SUM(H22:I22) -> 0
D23: =OFFSET(Capacidades!$A$1,(ROW()-9)*10-1,11) | J23: =SUM(H23:I23) -> 0
D24: =OFFSET(Capacidades!$A$1,(ROW()-9)*10-1,11) | J24: =SUM(H24:I24) -> 0
D25: =OFFSET(Capacidades!$A$1,(ROW()-9)*10-1,11) | J25: =SUM(H25:I25) -> 0
... D29: =OFFSET(Capacidades!$A$1,(ROW()-9)*10-1,11) | J29: =SUM(H29:I29) -> 0
B30: Competencias para la empleabilidad | C30: CE1 Comunicación efectiva. - Expresar de manera clara los conceptos, ideas, sentimientos, hechos y opiniones en forma oral y escrita para comunicarse e interactuar con otras personas en contextos sociales y laborales diversos. (UD) CE2 Tecnologías de la información. - Manejar herramientas informáticas de las TIC para buscar y analizar información, Comunicarse y realizar procedimientos o tareas vinculadas al área profesional, de acuerdo a los requerimientos de su entorno laboral. (UD) | D30: =OFFSET(Capacidades!$A$1,(ROW()-9)*10-1,11) -> CE1 C1 Comunicar conceptos, ideas, opiniones, sentimientos y hechos en forma oral en situaciones relacionadas a su entorno personal y profesional. CE1 C2 Transmitir conceptos, ideas, opiniones, sentimientos y hechos en forma escrita en situaciones relacionadas a su entorno social y laboral. | F30: Comunicación para el desarrollo personal y profesional | G30: I | H30: 1 | I30: 1 | J30: =SUM(H30:I30) -> 2
D31: =OFFSET(Capacidades!$A$1,(ROW()-9)*10-1,11) -> CE2 C1 Utilizar aplicaciones y herramientas informáticas de las TIC de manera responsable y técnica. CE2 C2 Emplear software en la realización de tareas y requerimientos vinculados a su programa de estudios. | F31: Aplicaciones de herramientas informáticas | G31: I | H31: 1 | I31: 1 | J31: =SUM(H31:I31) -> 2
D32: =OFFSET(Capacidades!$A$1,(ROW()-9)*10-1,11) | J32: =SUM(H32:I32) -> 0
D33: =OFFSET(Capacidades!$A$1,(ROW()-9)*10-1,11) | J33: =SUM(H33:I33) -> 0
D34: =OFFSET(Capacidades!$A$1,(ROW()-9)*10-1,11) | J34: =SUM(H34:I34) -> 0
D35: =OFFSET(Capacidades!$A$1,(ROW()-9)*10-1,11) | J35: =SUM(H35:I35) -> 0
D36: =OFFSET(Capacidades!$A$1,(ROW()-9)*10-1,11) | J36: =SUM(H36:I36) -> 0
D37: =OFFSET(Capacidades!$A$1,(ROW()-9)*10-1,11) | J37: =SUM(H37:I37) -> 0
D38: =OFFSET(Capacidades!$A$1,(ROW()-9)*10-1,11) | J38: =SUM(H38:I38) -> 0
D39: =OFFSET(Capacidades!$A$1,(ROW()-9)*10-1,11) | J39: =SUM(H39:I39) -> 0
B40: Experiencias formativas en situaciones reales de trabajo (ESRT) | G40: Taller del programa "Apoyo administrativo" | H40: 0 | I40: 6 | J40: 6
A41: MÓDULO II: PROCESAMIENTO Y ARCHIVO DOCUMENTARIO | B41: =$B$10 -> Competencias técnicas (Unidad de competencia) | C41: UC2 Procesar la documentación de las distintas áreas de la organización, en función a sus políticas y normativa correspondiente. UC3 Custodiar la documentación, según políticas y procedimientos de la organización, y normativa correspondiente. | D41: =OFFSET(Capacidades!$A$302,(ROW()-40)*10-1,11) -> UC2 C1 Realizar el procesamiento y transmisión de la información y/o documentación, teniendo en cuenta los medios adecuados, la confiabilidad, en función a los objetivos de la organización y procedimientos establecidos. | F41: Recepción y procesamiento de la información | G41: II | H41: 1 | I41: 1 | J41: =SUM(H41:I41) -> 2
D42: =OFFSET(Capacidades!$A$302,(ROW()-40)*10-1,11) -> UC2 C2 Ejecutar actividades administrativas de apoyo2, en función de los objetivos de la organización, los procedimientos establecidos y el área asignada. | F42: Actividades administrativas | G42: II | H42: 0 | I42: 1 | J42: =SUM(H42:I42) -> 1
D43: =OFFSET(Capacidades!$A$302,(ROW()-40)*10-1,11) -> UC2 C3 Atender las comunicaciones, consultas, y/o centro de atención virtual, utilizando los medios adecuados y protocolos de la organización. | F43: Atención al público | G43: II | H43: 1 | I43: 1 | J43: =SUM(H43:I43) -> 2
D44: =OFFSET(Capacidades!$A$302,(ROW()-40)*10-1,11) -> UC2 C4 Realiza la revisisón de información y/o documentación en función a los requerimientos de la organización y procedimientos establecidos. | F44: Control y registro documentario | G44: II | H44: 0 | I44: 1 | J44: =SUM(H44:I44) -> 1
D45: =OFFSET(Capacidades!$A$302,(ROW()-40)*10-1,11) -> UC3 C1 Organizar el sistema de gestión de archivos según políticas de la organización y normativa vigente. UC3 C2 Realizar la clasificación de documentos según políticas de la organización y normativa vigente. | F45: Organización del sistema de gestión de archivos | G45: II | H45: 1 | I45: 1 | J45: =SUM(H45:I45) -> 2
D46: =OFFSET(Capacidades!$A$302,(ROW()-40)*10-1,11) -> UC3 C3 Archivar los documentos de gestión según políticas de la organización y normativa vigente. UC3 C4 Realizar el archivo, mantenimiento y conservación de los documentos según políticas de la organización y normativa vigente. | F46: Archivos, mantenimiento y conservación de documentos | G46: II | H46: 1 | I46: 1 | J46: =SUM(H46:I46) -> 2
D47: =OFFSET(Capacidades!$A$302,(ROW()-40)*10-1,11) | J47: =SUM(H47:I47) -> 0
D48: =OFFSET(Capacidades!$A$302,(ROW()-40)*10-1,11) | J48: =SUM(H48:I48) -> 0
D49: =OFFSET(Capacidades!$A$302,(ROW()-40)*10-1,11) | J49: =SUM(H49:I49) -> 0
D50: =OFFSET(Capacidades!$A$302,(ROW()-40)*10-1,11) | J50: =SUM(H50:I50) -> 0
D51: =OFFSET(Capacidades!$A$302,(ROW()-40)*10-1,11) | J51: =SUM(H51:I51) -> 0
D52: =OFFSET(Capacidades!$A$302,(ROW()-40)*10-1,11) | J52: =SUM(H52:I52) -> 0
D53: =OFFSET(Capacidades!$A$302,(ROW()-40)*10-1,11) | J53: =SUM(H53:I53) -> 0
D54: =OFFSET(Capacidades!$A$302,(ROW()-40)*10-1,11) | J54: =SUM(H54:I54) -> 0
D55: =OFFSET(Capacidades!$A$302,(ROW()-40)*10-1,11) | J55: =SUM(H55:I55) -> 0
D56: =OFFSET(Capacidades!$A$302,(ROW()-40)*10-1,11) | J56: =SUM(H56:I56) -> 0
D57: =OFFSET(Capacidades!$A$302,(ROW()-40)*10-1,11) | J57: =SUM(H57:I57) -> 0
D58: =OFFSET(Capacidades!$A$302,(ROW()-40)*10-1,11) | J58: =SUM(H58:I58) -> 0
... D60: =OFFSET(Capacidades!$A$302,(ROW()-40)*10-1,11) | J60: =SUM(H60:I60) -> 0
B61: =$B$30 -> Competencias para la empleabilidad | C61: CE3 Emprendimiento.- Identificar nuevas oportunidades de proyectos o negocios que generen valor y sean sostenibles, gestionando recursos para su funcionamiento con creatividad y ética, articulando acciones que permitan desarrollar innovaciones en la creación de bienes y/o servicios, así como en procesos o productos ya existentes. CE4 Ética.-Establecer relaciones con respeto y justicia en los ámbitos personal, colectivo e institucional, contribuyendo a una convivencia democrática, orientada al bien común que considere la diversidad y dignidad de las personas, teniendo en cuenta las consideraciones aplicadas en su contexto laboral. | D61: =OFFSET(Capacidades!$A$302,(ROW()-40)*10-1,11) -> CE3 C1 Utilizar metodologías para identificar oportunidades de negocio tomando en cuenta el programa de estudios y las necesidades del mercado. CE3 C2 Formular planes de negocio innovadores vinculados al programa de estudio considerando un proceso metodológico que genere valor, sea sostenible y preserve el ambiente. | F61: Plan de Negocios | G61: II | H61: 1 | I61: 1 | J61: =SUM(H61:I61) -> 2
D62: =OFFSET(Capacidades!$A$302,(ROW()-40)*10-1,11) -> CE4 C1 Practicar las relaciones interpersonales democráticas, teniendo en cuenta los principios y valores éticos, la dignidad de las personas, la convivencia social y la gestión efectiva de los conflictos en su contexto social y laboral. CE4 C2 Promover una cultura ética, transparente y de anticorrupción en su contexto social y laboral fomentando el bien común, la diversidad y la dignidad de las personas. | F62: Comportamiento ético | G62: II | H62: 1 | I62: 1 | J62: =SUM(H62:I62) -> 2
D63: =OFFSET(Capacidades!$A$302,(ROW()-40)*10-1,11) | J63: =SUM(H63:I63) -> 0
D64: =OFFSET(Capacidades!$A$302,(ROW()-40)*10-1,11) | J64: =SUM(H64:I64) -> 0
D65: =OFFSET(Capacidades!$A$302,(ROW()-40)*10-1,11) | J65: =SUM(H65:I65) -> 0
D66: =OFFSET(Capacidades!$A$302,(ROW()-40)*10-1,11) | J66: =SUM(H66:I66) -> 0
D67: =OFFSET(Capacidades!$A$302,(ROW()-40)*10-1,11) | J67: =SUM(H67:I67) -> 0
D68: =OFFSET(Capacidades!$A$302,(ROW()-40)*10-1,11) | J68: =SUM(H68:I68) -> 0
D69: =OFFSET(Capacidades!$A$302,(ROW()-40)*10-1,11) | J69: =SUM(H69:I69) -> 0
D70: =OFFSET(Capacidades!$A$302,(ROW()-40)*10-1,11) | J70: =SUM(H70:I70) -> 0
B71: =$B$40 -> Experiencias formativas en situaciones reales de trabajo (ESRT) | G71: Taller del programa "Apoyo administrativo" | H71: 0 | I71: 6 | J71: 6
B72: =$B$10 -> Competencias técnicas (Unidad de competencia) | D72: =OFFSET(Capacidades!$A$603,(ROW()-71)*10-1,11)
D73: =OFFSET(Capacidades!$A$603,(ROW()-71)*10-1,11)
D74: =OFFSET(Capacidades!$A$603,(ROW()-71)*10-1,11)
D75: =OFFSET(Capacidades!$A$603,(ROW()-71)*10-1,11)
D76: =OFFSET(Capacidades!$A$603,(ROW()-71)*10-1,11) | J76: =SUM(H76:I76) -> 0
D77: =OFFSET(Capacidades!$A$603,(ROW()-71)*10-1,11) | J77: =SUM(H77:I77) -> 0
D78: =OFFSET(Capacidades!$A$603,(ROW()-71)*10-1,11) | J78: =SUM(H78:I78) -> 0
D79: =OFFSET(Capacidades!$A$603,(ROW()-71)*10-1,11) | J79: =SUM(H79:I79) -> 0
D80: =OFFSET(Capacidades!$A$603,(ROW()-71)*10-1,11) | J80: =SUM(H80:I80) -> 0
D81: =OFFSET(Capacidades!$A$603,(ROW()-71)*10-1,11) | J81: =SUM(H81:I81) -> 0
D82: =OFFSET(Capacidades!$A$603,(ROW()-71)*10-1,11) | J82: =SUM(H82:I82) -> 0
D83: =OFFSET(Capacidades!$A$603,(ROW()-71)*10-1,11) | J83: =SUM(H83:I83) -> 0
D84: =OFFSET(Capacidades!$A$603,(ROW()-71)*10-1,11) | J84: =SUM(H84:I84) -> 0
D85: =OFFSET(Capacidades!$A$603,(ROW()-71)*10-1,11) | J85: =SUM(H85:I85) -> 0
D86: =OFFSET(Capacidades!$A$603,(ROW()-71)*10-1,11) | J86: =SUM(H86:I86) -> 0
D87: =OFFSET(Capacidades!$A$603,(ROW()-71)*10-1,11) | J87: =SUM(H87:I87) -> 0
... D91: =OFFSET(Capacidades!$A$603,(ROW()-71)*10-1,11) | J91: =SUM(H91:I91) -> 0
B92: =$B$30 -> Competencias para la empleabilidad | D92: =OFFSET(Capacidades!$A$603,(ROW()-71)*10-1,11)
D93: =OFFSET(Capacidades!$A$603,(ROW()-71)*10-1,11) | J93: =SUM(H93:I93) -> 0
D94: =OFFSET(Capacidades!$A$603,(ROW()-71)*10-1,11) | J94: =SUM(H94:I94) -> 0
D95: =OFFSET(Capacidades!$A$603,(ROW()-71)*10-1,11) | J95: =SUM(H95:I95) -> 0
D96: =OFFSET(Capacidades!$A$603,(ROW()-71)*10-1,11) | J96: =SUM(H96:I96) -> 0
D97: =OFFSET(Capacidades!$A$603,(ROW()-71)*10-1,11) | J97: =SUM(H97:I97) -> 0
D98: =OFFSET(Capacidades!$A$603,(ROW()-71)*10-1,11) | J98: =SUM(H98:I98) -> 0
D99: =OFFSET(Capacidades!$A$603,(ROW()-71)*10-1,11) | J99: =SUM(H99:I99) -> 0
D100: =OFFSET(Capacidades!$A$603,(ROW()-71)*10-1,11) | J100: =SUM(H100:I100) -> 0
D101: =OFFSET(Capacidades!$A$603,(ROW()-71)*10-1,11) | J101: =SUM(H101:I101) -> 0
B102: =$B$40 -> Experiencias formativas en situaciones reales de trabajo (ESRT)
A103: MÓDULO II: COCINA NACIONAL E INTERNACIONAL | B103: =$B$10 -> Competencias técnicas (Unidad de competencia) | D103: =OFFSET(Capacidades!$A$904,(ROW()-102)*10-1,11)
D104: =OFFSET(Capacidades!$A$904,(ROW()-102)*10-1,11)
D105: =OFFSET(Capacidades!$A$904,(ROW()-102)*10-1,11)
D106: =OFFSET(Capacidades!$A$904,(ROW()-102)*10-1,11) | J106: =SUM(H106:I106) -> 0
D107: =OFFSET(Capacidades!$A$904,(ROW()-102)*10-1,11) | J107: =SUM(H107:I107) -> 0
D108: =OFFSET(Capacidades!$A$904,(ROW()-102)*10-1,11) | J108: =SUM(H108:I108) -> 0
D109: =OFFSET(Capacidades!$A$904,(ROW()-102)*10-1,11) | J109: =SUM(H109:I109) -> 0
D110: =OFFSET(Capacidades!$A$904,(ROW()-102)*10-1,11) | J110: =SUM(H110:I110) -> 0
...

Sheet M1
A1: ORGANIZACIÓN DE LOS ELEMENTOS DEL MÓDULO
A3: DENOMINACIÓN DE LA INSTITUCIÓN | B3: =Perfil_Egreso!B3 -> CETPRO JUANJUI | F3: CÓDIGO MODULAR DEL INSTITUTO | I3: =Perfil_Egreso!E3 -> 0533836
A5: SECTOR ECONÓMICO | B5: =Perfil_Egreso!B5 -> Actividades profesionales, científicas y técnicas | C5: FAMILIA PRODUCTIVA | D5: =Perfil_Egreso!D5 -> Servicios prestados a empresas | F5: ACTIVIDAD ECONÓMICA | I5: =Perfil_Egreso!B7 -> Actividades administrativas y de apoyo de oficina y otras actividades de apoyo a las empresas
A7: =Perfil_Egreso!A10 -> DENOMINACIÓN DEL PROGRAMA DE ESTUDIOS SEGÚN CNOF (según corresponda) | B7: =Perfil_Egreso!B10 -> APOYO ADMINISTRATIVO | F7: CÓDIGO * | I7: =Perfil_Egreso!E10 -> M2982-1-002
A9: =Perfil_Egreso!A12 -> FORMACIÓN** | B9: =Perfil_Egreso!B12 -> AUXILIAR TECNICO | C9: N°. HORAS: | D9: =Itinerario!W17 -> 1072 | F9: N° CRÉDITOS: | I9: =Itinerario!T17 -> 40
A11: =Perfil_Egreso!C12 -> MODALIDAD DEL SERVICIO EDUCATIVO | B11: =Perfil_Egreso!D12 -> PRESENCIAL | F11: =Perfil_Egreso!A14 -> NIVEL FORMATIVO | I11: =Perfil_Egreso!B14 -> AUXILIAR TÉCNICO
A13: UNIDAD DE COMPETENCIA DEL CATÁLOGO NACIONAL DE LA OFERTA FORMATIVA
A14: =Organización_Modular!C10 -> UC1 Proveer información, según políticas y procedimientos de la organización, y normativa correspondiente.
A15: DENOMINACIÓN DEL MÓDULO | B15: =Organización_Modular!A10 -> MÓDULO I: REDACCIÓN Y TRÁMITE DOCUMENTARIO
A16: CAPACIDADES TÉCNICAS O ESPECÍFICAS | B16: INDICADORES DE LOGRO DE LA CAPACIDAD | C16: CONTENIDOS | D16: UNIDAD DIDÁCTICA | E16: Periodo | F16: CRÉDITOS | H16: CRÉDITOS | I16: HORAS | K16: HORAS | L16: PERFIL DOCENTE | M16: Filtrar
F17: Teórico | G17: Práctica | I17: Teórico | J17: Práctica
A18: =Capacidades!L10 -> UC1 C1 Organizar el área de trabajo, equipos y materiales teniendo en cuenta las normas de seguridad laboral y ambiental. | B18: =Capacidades!M10 -> C1 I1 Explica la estructura organizacional de la empresa de acuerdo a los manuales internos de organización. | C18: Empresa. Tipos de Empresa. Instituciones gubernamentales, no gubernamentales.- Estructura organizacional: - Organigramas, tipos. | D18: =Organización_Modular!F10 -> Organización del área de trabajo | E18: =Organización_Modular!G10 -> I | F18: =Organización_Modular!H10 -> 1 | G18: =Organización_Modular!I10 -> 1 | H18: =SUM(F18:G18) -> 2 | I18: =F18*16 -> 16 | J18: =G18*32 -> 32 | K18: =SUM(I18:J18) -> 48 | L18: TECNICO PROFESIONAL EN ADMINISTRACION DE EMPRESAS, CONTABILIDAD Y PROFESIONAL EN PEDAGOGIA | M18: =B18 -> C1 I1 Explica la estructura organizacional de la empresa de acuerdo a los manuales internos de organización.
B19: =Capacidades!M11 -> C1 I2 Identifica los ambientes de trabajo, equipos y materiales tomando en cuenta sus características y funcionalidad. | C19: - Organización del ambiente, muebles, equipos, herramientas y materiales. - normas de seguridad laboral y ambiental. - La PC, aplicaciones y dispositivos. - Entorno Windows. - Herramientas digitales. | M19: =B19 -> C1 I2 Identifica los ambientes de trabajo, equipos y materiales tomando en cuenta sus características y funcionalidad.
B20: =Capacidades!M12 -> C1 I3 Opera los equipos de oficina de acuerdo al manual de operaciones. | C20: Equipo manuales. Tipos. Características. Funcionalidad. Equipos electrónicos. Tipos. Características. Funcionalidad. | M20: =B20 -> C1 I3 Opera los equipos de oficina de acuerdo al manual de operaciones.
B21: =Capacidades!M13 -> C1 I4 Realiza la organización del ambiente de trabajo, equipos y materiales, teniendo en cuenta las normas de seguridad e higiene y protocolos de bioseguridad | C21: Distribución de equipos, materiales en el ambiente de trabajo Señalización Normas de seguridad e higiene Protocolos de bioseguridad | M21: =B21 -> C1 I4 Realiza la organización del ambiente de trabajo, equipos y materiales, teniendo en cuenta las normas de seguridad e higiene y protocolos de bioseguridad
B22: =Capacidades!M14 | M22: =B22
B23: =Capacidades!M15 | M23: =B23
B24: =Capacidades!M16 | M24: =B24
B25: =Capacidades!M17 | M25: =B25
B26: =Capacidades!M18 | M26: =B26
B27: =Capacidades!M19 | M27: =B27
A28: =Capacidades!L20 -> UC1 C2 Elaborar documentos administrativos y/o mercantiles de acuerdo a las características y estructuras de las mismas, aplicando técnicas de redacción, reglas ortográficas y gramaticales . | B28: =Capacidades!M20 -> C2 I1 Identifica los diverso tipos de documentos administrativos de acuerdo a las políticas y normativas de la organización. | C28: Documentos administrativos. Tipos Estructuras y diseños de documentos administrativos Carta, oficio, certificados, constancias, informes, memorándums, actas, avisos, solicitudes, entre otros. | D28: =Organización_Modular!F11 -> Redacción de documentos | E28: =Organización_Modular!G11 -> I | F28: =Organización_Modular!H11 -> 2 | G28: =Organización_Modular!I11 -> 2 | H28: =SUM(F28:G28) -> 4 | I28: =F28*16 -> 32 | J28: =G28*32 -> 64 | K28: =SUM(I28:J28) -> 96 | L28: TECNICO PROFESIONAL EN ADMINISTRACION DE EMPRESAS, CONTABILIDAD Y PROFESIONAL EN PEDAGOGIA | M28: =B28 -> C2 I1 Identifica los diverso tipos de documentos administrativos de acuerdo a las políticas y normativas de la organización.
B29: =Capacidades!M21 -> C2 I2 Redacta los documentos administrativos aplicando las técnicas de redacción, reglas ortográficas y gramaticales, de acuerdo a las políticas y normativas de la organización. | C29: Técnicas de redacción. Reglas ortográficas y gramaticales Redacción de documentos administrativos Combinar correspondencia. Impresión de documentos | M29: =B29 -> C2 I2 Redacta los documentos administrativos aplicando las técnicas de redacción, reglas ortográficas y gramaticales, de acuerdo a las políticas y normativas de la organización.
B30: =Capacidades!M22 -> C2 I3 Realiza el llenado de los documentos administrativos y/o mercantiles aplicando reglas ortográficas y gramaticales, de acuerdo a las políticas y normativas de la organización. | C30: Documento empresarial. Comprobantes de pago: Boleta, recibo por honorarios profesionales, factura, guías de remisión. Nota de pedido de compra y venta. FUT | M30: =B30 -> C2 I3 Realiza el llenado de los documentos administrativos y/o mercantiles aplicando reglas ortográficas y gramaticales, de acuerdo a las políticas y normativas de la organización.
B31: =Capacidades!M23 -> C2 I4 Verifica la calidad de los documentos administrativos y/o mercantiles de acuerdo a la información correspondiente, aplicando reglas ortográficas y gramaticales. | C31: Técnicas de revisión de documentos Prácticas de revisión de documentos | M31: =B31 -> C2 I4 Verifica la calidad de los documentos administrativos y/o mercantiles de acuerdo a la información correspondiente, aplicando reglas ortográficas y gramaticales.
B32: =Capacidades!M24 | M32: =B32
B33: =Capacidades!M25 | M33: =B33
B34: =Capacidades!M26 | M34: =B34
B35: =Capacidades!M27 | M35: =B35
B36: =Capacidades!M28 | M36: =B36
B37: =Capacidades!M29 | M37: =B37
A38: =Capacidades!L30 -> UC1 C3 Realizar el trámite de datos y documentos, de acuerdo a los procedimientos, normativa vigente y políticas de la organización. | B38: =Capacidades!M30 -> C3 I1 Explica un diagrama de flujo documentario de acuerdo a los procedimientos, normativa vigente y políticas de la organización. | C38: Diagrama de flujo documentario según el tipo de organización Ley 27444, Ley del Procedimiento Administativo General Orientación del sistema de trámite documentario en línea | D38: =Organización_Modular!F12 -> Trámite documentario | E38: =Organización_Modular!G12 -> I | F38: =Organización_Modular!H12 -> 2 | G38: =Organización_Modular!I12 -> 2 | H38: =SUM(F38:G38) -> 4 | I38: =F38*16 -> 32 | J38: =G38*32 -> 64 | K38: =SUM(I38:J38) -> 96 | L38: TECNICO PROFESIONAL EN ADMINISTRACION DE EMPRESAS, CONTABILIDAD Y PROFESIONAL EN PEDAGOGIA | M38: =B38 -> C3 I1 Explica un diagrama de flujo documentario de acuerdo a los procedimientos, normativa vigente y políticas de la organización.
B39: =Capacidades!M31 -> C3 I2 Organiza el procedimiento de registro y recepción del flujo documentario de acuerdo a los procedimientos, normativa vigente y políticas de la organización. | C39: Sistema de gestión administrativa Procedimiento de Recepción documentario Procedimiento de Registro documentario Prodimientos de Tramitación Procedimientos de notificación y entrega del documento. | M39: =B39 -> C3 I2 Organiza el procedimiento de registro y recepción del flujo documentario de acuerdo a los procedimientos, normativa vigente y políticas de la organización.
B40: =Capacidades!M32 -> C3 I3 Ejecuta la organización y traslado de expedientes de acuerdo a los procedimientos, normativa vigente y políticas de la organización. | C40: Registro de ingreso y salida de documentos. Hoja de envío y hoja de ruta | M40: =B40 -> C3 I3 Ejecuta la organización y traslado de expedientes de acuerdo a los procedimientos, normativa vigente y políticas de la organización.
B41: =Capacidades!M33 -> C3 I4 Efectúa el control del traslado de los expedientes y/o documentos de acuerdo a los procedimientos, normativa vigente y políticas de la organización. | C41: Hoja, cuaderno o registro de control de cargo Formato digital de control del traslado documentario | M41: =B41 -> C3 I4 Efectúa el control del traslado de los expedientes y/o documentos de acuerdo a los procedimientos, normativa vigente y políticas de la organización.
M42: =B42 -> 0
B43: =Capacidades!M35 | M43: =B43
B44: =Capacidades!M36 | M44: =B44
B45: =Capacidades!M37 | M45: =B45
B46: =Capacidades!M38 | M46: =B46
B47: =Capacidades!M39 | M47: =B47
A48: =Capacidades!L40 | B48: =Capacidades!M40 | D48: =Organización_Modular!F13 -> 0 | E48: =Organización_Modular!G13 -> 0 | F48: =Organización_Modular!H13 -> 0 | G48: =Organización_Modular!I13 -> 0 | H48: =SUM(F48:G48) -> 0 | I48: =F48*16 -> 0 | J48: =G48*32 -> 0 | K48: =SUM(I48:J48) -> 0 | M48: =B48
B49: =Capacidades!M41 | M49: =B49
B50: =Capacidades!M42 | M50: =B50
B51: =Capacidades!M43 | M51: =B51
B52: =Capacidades!M44 | M52: =B52
B53: =Capacidades!M45 | M53: =B53
B54: =Capacidades!M46 | M54: =B54
B55: =Capacidades!M47 | M55: =B55
B56: =Capacidades!M48 | M56: =B56
B57: =Capacidades!M49 | M57: =B57
A58: =Capacidades!L50 | B58: =Capacidades!M50 | D58: =Organización_Modular!F14 -> 0 | E58: =Organización_Modular!G14 -> 0 | F58: =Organización_Modular!H14 -> 0 | G58: =Organización_Modular!I14 -> 0 | H58: =SUM(F58:G58) -> 0 | I58: =F58*16 -> 0 | J58: =G58*32 -> 0 | K58: =SUM(I58:J58) -> 0 | M58: =B58
B59: =Capacidades!M51 | M59: =B59
B60: =Capacidades!M52 | M60: =B60
B61: =Capacidades!M53 | M61: =B61
B62: =Capacidades!M54 | M62: =B62
B63: =Capacidades!M55 | M63: =B63
B64: =Capacidades!M56 | M64: =B64
B65: =Capacidades!M57 | M65: =B65
B66: =Capacidades!M58 | M66: =B66
B67: =Capacidades!M59 | M67: =B67
A68: =Capacidades!L60 | B68: =Capacidades!M60 | D68: =Organización_Modular!F15 -> 0 | E68: =Organización_Modular!G15 -> 0 | F68: =Organización_Modular!H15 -> 0 | G68: =Organización_Modular!I15 -> 0 | H68: =SUM(F68:G68) -> 0 | I68: =F68*16 -> 0 | J68: =G68*32 -> 0 | K68: =SUM(I68:J68) -> 0 | M68: =B68
B69: =Capacidades!M61 | M69: =B69
B70: =Capacidades!M62 | M70: =B70
B71: =Capacidades!M63 | M71: =B71
B72: =Capacidades!M64 | M72: =B72
B73: =Capacidades!M65 | M73: =B73
B74: =Capacidades!M66 | M74: =B74
B75: =Capacidades!M67 | M75: =B75
B76: =Capacidades!M68 | M76: =B76
B77: =Capacidades!M69 | M77: =B77
A78: =Capacidades!L70 | B78: =Capacidades!M70 | D78: =Organización_Modular!F16 -> 0 | E78: =Organización_Modular!G16 -> 0 | F78: =Organización_Modular!H16 -> 0 | G78: =Organización_Modular!I16 -> 0 | H78: =SUM(F78:G78) -> 0 | I78: =F78*16 -> 0 | J78: =G78*32 -> 0 | K78: =SUM(I78:J78) -> 0 | M78: =B78
B79: =Capacidades!M71 | M79: =B79
B80: =Capacidades!M72 | M80: =B80
B81: =Capacidades!M73 | M81: =B81
B82: =Capacidades!M74 | M82: =B82
B83: =Capacidades!M75 | M83: =B83
B84: =Capacidades!M76 | M84: =B84
B85: =Capacidades!M77 | M85: =B85
B86: =Capacidades!M78 | M86: =B86
B87: =Capacidades!M79 | M87: =B87
A88: =Capacidades!L80 | B88: =Capacidades!M80 | D88: =Organización_Modular!F17 -> 0 | E88: =Organización_Modular!G17 -> 0 | F88: =Organización_Modular!H17 -> 0 | G88: =Organización_Modular!I17 -> 0 | H88: =SUM(F88:G88) -> 0 | I88: =F88*16 -> 0 | J88: =G88*32 -> 0 | K88: =SUM(I88:J88) -> 0 | M88: =B88
B89: =Capacidades!M81 | M89: =B89
B90: =Capacidades!M82 | M90: =B90
B91: =Capacidades!M83 | M91: =B91
B92: =Capacidades!M84 | M92: =B92
B93: =Capacidades!M85 | M93: =B93
B94: =Capacidades!M86 | M94: =B94
B95: =Capacidades!M87 | M95: =B95
B96: =Capacidades!M88 | M96: =B96
B97: =Capacidades!M89 | M97: =B97
A98: =Capacidades!L90 | B98: =Capacidades!M90 | D98: =Organización_Modular!F18 -> 0 | E98: =Organización_Modular!G18 -> 0 | F98: =Organización_Modular!H18 -> 0 | G98: =Organización_Modular!I18 -> 0 | H98: =SUM(F98:G98) -> 0 | I98: =F98*16 -> 0 | J98: =G98*32 -> 0 | K98: =SUM(I98:J98) -> 0 | M98: =B98
B99: =Capacidades!M91 | M99: =B99
B100: =Capacidades!M92 | M100: =B100
B101: =Capacidades!M93 | M101: =B101
B102: =Capacidades!M94 | M102: =B102
B103: =Capacidades!M95 | M103: =B103
B104: =Capacidades!M96 | M104: =B104
B105: =Capacidades!M97 | M105: =B105
B106: =Capacidades!M98 | M106: =B106
...

Sheet M2
A1: ='M1'!A1:L1 -> ORGANIZACIÓN DE LOS ELEMENTOS DEL MÓDULO
A3: DENOMINACIÓN DE LA INSTITUCIÓN | B3: =Perfil_Egreso!B3 -> CETPRO JUANJUI | F3: CÓDIGO MODULAR DEL INSTITUTO | I3: =Perfil_Egreso!E3 -> 0533836
A5: SECTOR ECONÓMICO | B5: =Perfil_Egreso!B5 -> Actividades profesionales, científicas y técnicas | C5: FAMILIA PRODUCTIVA | D5: =Perfil_Egreso!D5 -> Servicios prestados a empresas | F5: ACTIVIDAD ECONÓMICA | I5: =Perfil_Egreso!B7 -> Actividades administrativas y de apoyo de oficina y otras actividades de apoyo a las empresas
A7: =Perfil_Egreso!A10 -> DENOMINACIÓN DEL PROGRAMA DE ESTUDIOS SEGÚN CNOF (según corresponda) | B7: =Perfil_Egreso!B10 -> APOYO ADMINISTRATIVO | F7: CÓDIGO * | I7: =Perfil_Egreso!E10 -> M2982-1-002
A9: =Perfil_Egreso!A12 -> FORMACIÓN** | B9: =Perfil_Egreso!B12 -> AUXILIAR TECNICO | C9: N°. HORAS: | D9: =Itinerario!W17 -> 1072 | F9: N° CRÉDITOS: | I9: =Itinerario!T17 -> 40
A11: =Perfil_Egreso!C12 -> MODALIDAD DEL SERVICIO EDUCATIVO | B11: =Perfil_Egreso!D12 -> PRESENCIAL | F11: =Perfil_Egreso!A14 -> NIVEL FORMATIVO | I11: =Perfil_Egreso!B14 -> AUXILIAR TÉCNICO
A13: UNIDAD DE COMPETENCIA DEL CATÁLOGO NACIONAL DE LA OFERTA FORMATIVA
A14: =Organización_Modular!C41 -> UC2 Procesar la documentación de las distintas áreas de la organización, en función a sus políticas y normativa correspondiente. UC3 Custodiar la documentación, según políticas y procedimientos de la organización, y normativa correspondiente.
A15: DENOMINACIÓN DEL MÓDULO | B15: =Organización_Modular!A41 -> MÓDULO II: PROCESAMIENTO Y ARCHIVO DOCUMENTARIO
A16: CAPACIDADES TÉCNICAS O ESPECÍFICAS | B16: INDICADORES DE LOGRO DE LA CAPACIDAD | C16: CONTENIDOS | D16: UNIDAD DIDÁCTICA | E16: Periodo | F16: CRÉDITOS | H16: CRÉDITOS | I16: HORAS | K16: HORAS | L16: PERFIL DOCENTE | M16: Filtrar
F17: Teórico | G17: Práctica | I17: Teórico | J17: Práctica
A18: =Capacidades!L311 -> UC2 C1 Realizar el procesamiento y transmisión de la información y/o documentación, teniendo en cuenta los medios adecuados, la confiabilidad, en función a los objetivos de la organización y procedimientos establecidos. | B18: =Capacidades!M311 -> C1 I1 Identifica el flujo de información en función a los objetivos de la organización y procedimientos establecidos. | C18: - Flujo de la información - Tratamiento de la información de salida. - Protocolos de bioseguridad. - Confiabilidad -Confidencialidad | D18: =Organización_Modular!F41 -> Recepción y procesamiento de la información | E18: =Organización_Modular!G41 -> II | F18: =Organización_Modular!H41 -> 1 | G18: =Organización_Modular!I41 -> 1 | H18: =SUM(F18:G18) -> 2 | I18: =F18*16 -> 16 | J18: =G18*32 -> 32 | K18: =SUM(I18:J18) -> 48 | L18: TECNICO PROFESIONAL EN ADMINISTRACION DE EMPRESAS, CONTABILIDAD Y PROFESIONAL EN PEDAGOGIA | M18: =B18 -> C1 I1 Identifica el flujo de información en función a los objetivos de la organización y procedimientos establecidos.
B19: =Capacidades!M312 -> C1 I2 Procesa la información utilizando los medios electrónicos y digitales, teniendo en la confiabilidad y procedimientos establecidos. | C19: Procesamiento de documentos Operaciones con el sotfwar especializado. | M19: =B19 -> C1 I2 Procesa la información utilizando los medios electrónicos y digitales, teniendo en la confiabilidad y procedimientos establecidos.
B20: =Capacidades!M313 -> C1 I3 Transmite la información y/o documentación teniendo en cuenta los medios adecuados, la confiabilidad, en función a los objetivos de la organización y procedimientos establecidos. | C20: Distribución interna y externa de las comunicaciones. Formatos de transmisión. Proveido/nota de proveido. Hoja de ruta | M20: =B20 -> C1 I3 Transmite la información y/o documentación teniendo en cuenta los medios adecuados, la confiabilidad, en función a los objetivos de la organización y procedimientos establecidos.
B21: =Capacidades!M314 -> C1 I4 Ejecuta el control de la información teniendo en cuenta los medios adecuados, la confiabilidad, en función a los objetivos de la organización y procedimientos establecidos. | C21: Procedimientos para el control de la información Elaboración de la estructura de almacenamiento. Formatos para la impresión. Comunicación de la información | M21: =B21 -> C1 I4 Ejecuta el control de la información teniendo en cuenta los medios adecuados, la confiabilidad, en función a los objetivos de la organización y procedimientos establecidos.
B22: =Capacidades!M315 | M22: =B22
B23: =Capacidades!M316 | M23: =B23
B24: =Capacidades!M317 | M24: =B24
B25: =Capacidades!M318 | M25: =B25
B26: =Capacidades!M319 | M26: =B26
B27: =Capacidades!M320 | M27: =B27
A28: =Capacidades!L321 -> UC2 C2 Ejecutar actividades administrativas de apoyo2, en función de los objetivos de la organización, los procedimientos establecidos y el área asignada. | B28: =Capacidades!M321 -> C2 I1 Notifica la culminación del trámite documentario en función de los objetivos de la organización, los procedimientos establecidos y el área asignada. | C28: .Notificaciones administrativas. Tipo de notificaciones. .Procedimiento de notificaciones: -Organización de documentación según el lugar de entrega -Registro de la notificación -Entrega de la fichas de notificaciones -Informe diario de noticiaciones -Culminación del trámite | D28: =Organización_Modular!F42 -> Actividades administrativas | E28: =Organización_Modular!G42 -> II | F28: =Organización_Modular!H42 -> 0 | G28: =Organización_Modular!I42 -> 1 | H28: =SUM(F28:G28) -> 1 | I28: =F28*16 -> 0 | J28: =G28*32 -> 32 | K28: =SUM(I28:J28) -> 32 | L28: TECNICO PROFESIONAL EN ADMINISTRACION DE EMPRESAS, CONTABILIDAD Y PROFESIONAL EN PEDAGOGIA | M28: =B28 -> C2 I1 Notifica la culminación del trámite documentario en función de los objetivos de la organización, los procedimientos establecidos y el área asignada.
B29: =Capacidades!M322 -> C2 I2 Digita los documentos administrativos y/o comerciales en función de los objetivos de la organización, los procedimientos establecidos y el área asignada. | C29: Técnicas de digitación. Importancia. Prácticas de digitación. Scaner. Operación de scaner. | M29: =B29 -> C2 I2 Digita los documentos administrativos y/o comerciales en función de los objetivos de la organización, los procedimientos establecidos y el área asignada.
B30: =Capacidades!M323 -> C2 I3 Imprime los documentos administrativos y/o comerciales en función de los objetivos de la organización, los procedimientos establecidos y el área asignada. | C30: Impresiones. Características. funcionalidad. Operaciones de impresiones | M30: =B30 -> C2 I3 Imprime los documentos administrativos y/o comerciales en función de los objetivos de la organización, los procedimientos establecidos y el área asignada.
B31: =Capacidades!M324 -> C2 I4 Realiza el fotocopiado los documentos administrativos y/o comerciales en función de los objetivos de la organización, los procedimientos establecidos y el área asignada. | C31: Fotocopiadoras. Características. funcionalidad. Operaciones de fotocopiado | M31: =B31 -> C2 I4 Realiza el fotocopiado los documentos administrativos y/o comerciales en función de los objetivos de la organización, los procedimientos establecidos y el área asignada.
B32: =Capacidades!M325 -> C2 I5 Realiza el mantenimiento e higienes de los ambientes en función de los objetivos de la organización, los procedimientos establecidos y el área asignada. | C32: Normas de higiene y salud laboral Mantenimineto de los ambientes | M32: =B32 -> C2 I5 Realiza el mantenimiento e higienes de los ambientes en función de los objetivos de la organización, los procedimientos establecidos y el área asignada.
B33: =Capacidades!M326 | M33: =B33
B34: =Capacidades!M327 | M34: =B34
B35: =Capacidades!M328 | M35: =B35
B36: =Capacidades!M329 | M36: =B36
B37: =Capacidades!M330 | M37: =B37
A38: =Capacidades!L331 -> UC2 C3 Atender las comunicaciones, consultas, y/o centro de atención virtual, utilizando los medios adecuados y protocolos de la organización. | B38: =Capacidades!M331 -> C3 I1 Identifica la tipología del cliente considerando las caracteríscas personales y los protocolos de atención la organización | C38: Cliente. Tipología del cliente. Atención al cliente. Características de atención. Importancia. Protocolos de atención al cliente. | D38: =Organización_Modular!F43 -> Atención al público | E38: =Organización_Modular!G43 -> II | F38: =Organización_Modular!H43 -> 1 | G38: =Organización_Modular!I43 -> 1 | H38: =SUM(F38:G38) -> 2 | I38: =F38*16 -> 16 | J38: =G38*32 -> 32 | K38: =SUM(I38:J38) -> 48 | L38: TECNICO PROFESIONAL EN ADMINISTRACION DE EMPRESAS, CONTABILIDAD Y PROFESIONAL EN PEDAGOGIA | M38: =B38 -> C3 I1 Identifica la tipología del cliente considerando las caracteríscas personales y los protocolos de atención la organización
B39: =Capacidades!M332 -> C3 I2 Maneja los protocolos de atención al cliente según las políticas de la organización. | C39: Normas técnicas para la gestión de calidad para el servicio al cliente. Protocolos de la comunicación de la empresa. Aplicación de protocolos. Agendar y confirmar citas. | M39: =B39 -> C3 I2 Maneja los protocolos de atención al cliente según las políticas de la organización.
B40: =Capacidades!M333 -> C3 I3 Recibe las llamadas telefónicas teniendo en cuenta las normas de cortesía. | C40: Uso del teléfono. Atención de llamadas telefónicas. Registro de llamadas. Aplicación de protocolos de la comunicación de la empresa.(Cualidades de la voz. Cortesías telefónicas) Asertividad en el tratamiento de la información vía telefónica. | M40: =B40 -> C3 I3 Recibe las llamadas telefónicas teniendo en cuenta las normas de cortesía.
B41: =Capacidades!M334 -> C3 I4 Realiza la identificación del mensaje recibido y la transmisión del mismo de acuerdo los protocolos establecidos y en función a los objetivos de la organización. | C41: Técnicas de comunicación. Medios de comunicación. | M41: =B41 -> C3 I4 Realiza la identificación del mensaje recibido y la transmisión del mismo de acuerdo los protocolos establecidos y en función a los objetivos de la organización.
B42: =Capacidades!M335 -> C3 I5 Ejecuta la atención al cliente considerando la imagen y protocolos de la organización. | C42: - Resolución de conflictos. - Objeción de los clientes. - Libro de reclamaciones. - Negociación con los clientes. | M42: =B42 -> C3 I5 Ejecuta la atención al cliente considerando la imagen y protocolos de la organización.
B43: =Capacidades!M336 | M43: =B43
B44: =Capacidades!M337 | M44: =B44
B45: =Capacidades!M338 | M45: =B45
B46: =Capacidades!M339 | M46: =B46
B47: =Capacidades!M340 | M47: =B47
A48: =Capacidades!L341 -> UC2 C4 Realiza la revisisón de información y/o documentación en función a los requerimientos de la organización y procedimientos establecidos. | B48: =Capacidades!M341 -> C4 I1 Clasifica la documentación (recibida y remitida) y la atención brindada según los procedimientos y políticas de la organización. | C48: Clasificación de los documentos recepcionados y remitidos. Métodos y técnicas de clasificación. | D48: =Organización_Modular!F44 -> Control y registro documentario | E48: =Organización_Modular!G44 -> II | F48: =Organización_Modular!H44 -> 0 | G48: =Organización_Modular!I44 -> 1 | H48: =SUM(F48:G48) -> 1 | I48: =F48*16 -> 0 | J48: =G48*32 -> 32 | K48: =SUM(I48:J48) -> 32 | L48: TECNICO PROFESIONAL EN ADMINISTRACION DE EMPRESAS, CONTABILIDAD Y PROFESIONAL EN PEDAGOGIA | M48: =B48 -> C4 I1 Clasifica la documentación (recibida y remitida) y la atención brindada según los procedimientos y políticas de la organización.
B49: =Capacidades!M342 -> C4 I2 Revisa la información y/o documentación según los procedimientos y políticas de la organización. | C49: Manual de organización y funciones. Manual de procedimientos administrativos. Flujograma. Reglamento interno de la organización. TUPA | M49: =B49 -> C4 I2 Revisa la información y/o documentación según los procedimientos y políticas de la organización.
B50: =Capacidades!M343 -> C4 I3 Elabora el registro de la atención brindada según los procedimientos y políticas de la organización. | C50: Registro de información. Base de datos. | M50: =B50 -> C4 I3 Elabora el registro de la atención brindada según los procedimientos y políticas de la organización.
B51: =Capacidades!M344 | M51: =B51
B52: =Capacidades!M345 | M52: =B52
B53: =Capacidades!M346 | M53: =B53
B54: =Capacidades!M347 | M54: =B54
B55: =Capacidades!M348 | M55: =B55
B56: =Capacidades!M349 | M56: =B56
B57: =Capacidades!M350 | M57: =B57
A58: =Capacidades!L351 -> UC3 C1 Organizar el sistema de gestión de archivos según políticas de la organización y normativa vigente. UC3 C2 Realizar la clasificación de documentos según políticas de la organización y normativa vigente. | B58: =Capacidades!M351 -> C1 I1 Explica el sistema de gestión de archivos, tipos y características del sistema de archivo y flujo de archivos de gestión según políticas de la organización. | C58: Sistema de gestión de archivos. Características de sistema de gestión de archivo. Flujo de archivos de gestión. Sistema Nacional de Archivos (SNA). | D58: =Organización_Modular!F45 -> Organización del sistema de gestión de archivos | E58: =Organización_Modular!G45 -> II | F58: =Organización_Modular!H45 -> 1 | G58: =Organización_Modular!I45 -> 1 | H58: =SUM(F58:G58) -> 2 | I58: =F58*16 -> 16 | J58: =G58*32 -> 32 | K58: =SUM(I58:J58) -> 48 | L58: TECNICO PROFESIONAL EN ADMINISTRACION DE EMPRESAS, CONTABILIDAD Y PROFESIONAL EN PEDAGOGIA | M58: =B58 -> C1 I1 Explica el sistema de gestión de archivos, tipos y características del sistema de archivo y flujo de archivos de gestión según políticas de la organización.
B59: =Capacidades!M352 -> C1 I2 Identifica los equipos y materiales, elementos de bioseguridad empleados en los sistemas de archivos | C59: Equipos, materiales y herramientas de archivo. Elementos de bioseguridad Métodos de archivo. | M59: =B59 -> C1 I2 Identifica los equipos y materiales, elementos de bioseguridad empleados en los sistemas de archivos
B60: =Capacidades!M353 -> C1 I3 Utiliza los equipos y materiales para un determinado sistema de archivo según los requerimientos de la organización. | C60: Equipos, materiales y herramientas de archivo. Tipos, características y funcionalidad. Seguridad y control de equipos, materiales y herramientas de archivo. | M60: =B60 -> C1 I3 Utiliza los equipos y materiales para un determinado sistema de archivo según los requerimientos de la organización.
B61: =Capacidades!M354 -> C1 I4 Realiza la organización del sistema de gestión de archivo aplicando normas de bioseguridad. | C61: Identificación de agentes noscivos para la salud. Normas de bioseguridad. | M61: =B61 -> C1 I4 Realiza la organización del sistema de gestión de archivo aplicando normas de bioseguridad.
B62: =Capacidades!M355 -> C2 I1 Realiza la identificación y ordenamiento de la documentación según políticas de la organización y normativa vigente. | C62: Clasificación de los archivos por ciclo de vida. Políticas institucionales de conservación de los archivos documentario. | M62: =B62 -> C2 I1 Realiza la identificación y ordenamiento de la documentación según políticas de la organización y normativa vigente.
B63: =Capacidades!M356 -> C2 I2 Realiza la foliación y/o depuración de la documentación según el sistema de archivo de la organización y normativa vigente. | C63: Técnicas de foliación de archivos Técnica de depuración de archivos. | M63: =B63 -> C2 I2 Realiza la foliación y/o depuración de la documentación según el sistema de archivo de la organización y normativa vigente.
B64: =Capacidades!M357 -> C2 I3 Codifica la documentación y/o archivos según el sistema de archivo de la organización y normativa vigente. | C64: Técnicas de codificación de la documentación y/ archivos | M64: =B64 -> C2 I3 Codifica la documentación y/o archivos según el sistema de archivo de la organización y normativa vigente.
B65: =Capacidades!M358 | M65: =B65
B66: =Capacidades!M359 | M66: =B66
B67: =Capacidades!M360 | M67: =B67
A68: =Capacidades!L361 -> UC3 C3 Archivar los documentos de gestión según políticas de la organización y normativa vigente. UC3 C4 Realizar el archivo, mantenimiento y conservación de los documentos según políticas de la organización y normativa vigente. | B68: =Capacidades!M361 -> C3 I1 Rotula la documentación y/o archivos según el sistema de archivo de la organización y normativa vigente. | C68: Técnicas de rotulación de documentos y archivos. Organización de documentos por áreas. Formulario de ingreso y salida de documentos. | D68: =Organización_Modular!F46 -> Archivos, mantenimiento y conservación de documentos | E68: =Organización_Modular!G46 -> II | F68: =Organización_Modular!H46 -> 1 | G68: =Organización_Modular!I46 -> 1 | H68: =SUM(F68:G68) -> 2 | I68: =F68*16 -> 16 | J68: =G68*32 -> 32 | K68: =SUM(I68:J68) -> 48 | L68: TECNICO PROFESIONAL EN ADMINISTRACION DE EMPRESAS, CONTABILIDAD Y PROFESIONAL EN PEDAGOGIA | M68: =B68 -> C3 I1 Rotula la documentación y/o archivos según el sistema de archivo de la organización y normativa vigente.
B69: =Capacidades!M362 -> C3 I2 Realiza el empastado o cocido de achivos documentarios de acuerdo a los procedimientos de la organización. | C69: Técnicas para el empastado y cocido. | M69: =B69 -> C3 I2 Realiza el empastado o cocido de achivos documentarios de acuerdo a los procedimientos de la organización.
B70: =Capacidades!M363 -> C3 I3 Archiva los documentos administrativos y/o comerciales teniendo en cuenta los criterios establecidos en la organización. | C70: Criterios técnicos para el archivo documentario. Archivo documentario. | M70: =B70 -> C3 I3 Archiva los documentos administrativos y/o comerciales teniendo en cuenta los criterios establecidos en la organización.
B71: =Capacidades!M364 -> C3 I4 Realiza la consulta y localización de los documentos teniendo en cuenta la información almacenada. | C71: Búsqueda de los documentos. Registro de préstamo de documentos. Transferencia física y/o digital de documentos. Devolución de archivos documentario | M71: =B71 -> C3 I4 Realiza la consulta y localización de los documentos teniendo en cuenta la información almacenada.
B72: =Capacidades!M365 -> C4 I1 Explica el procedimiento de conservación y mantenimiento de los archivos documentarios según políticas de la organización y normativa vigente. | C72: Técnicas de conservación y mantenimiento de archivos. Normas de seguridad e higiene documentaria. Mantenimiento preventivo de conservación de los archivos. | M72: =B72 -> C4 I1 Explica el procedimiento de conservación y mantenimiento de los archivos documentarios según políticas de la organización y normativa vigente.
B73: =Capacidades!M366 -> C4 I2 Ejecuta el procedimiento de conservación y mantenimiento de los archivos documentarios según políticas de la organización y normativa vigente. | C73: Prácticas de conservación y mantenimiento de los archivos documentarios. | M73: =B73 -> C4 I2 Ejecuta el procedimiento de conservación y mantenimiento de los archivos documentarios según políticas de la organización y normativa vigente.
B74: =Capacidades!M367 | M74: =B74
B75: =Capacidades!M368 | M75: =B75
B76: =Capacidades!M369 | M76: =B76
B77: =Capacidades!M370 | M77: =B77
A78: =Capacidades!L371 | B78: =Capacidades!M371 | D78: =Organización_Modular!F47 -> 0 | E78: =Organización_Modular!G47 -> 0 | F78: =Organización_Modular!H47 -> 0 | G78: =Organización_Modular!I47 -> 0 | H78: =SUM(F78:G78) -> 0 | I78: =F78*16 -> 0 | J78: =G78*32 -> 0 | K78: =SUM(I78:J78) -> 0 | M78: =B78
B79: =Capacidades!M372 | M79: =B79
B80: =Capacidades!M373 | M80: =B80
B81: =Capacidades!M374 | M81: =B81
B82: =Capacidades!M375 | M82: =B82
B83: =Capacidades!M376 | M83: =B83
B84: =Capacidades!M377 | M84: =B84
B85: =Capacidades!M378 | M85: =B85
B86: =Capacidades!M379 | M86: =B86
B87: =Capacidades!M380 | M87: =B87
A88: =Capacidades!L381 | B88: =Capacidades!M381 | D88: =Organización_Modular!F48 -> 0 | E88: =Organización_Modular!G48 -> 0 | F88: =Organización_Modular!H48 -> 0 | G88: =Organización_Modular!I48 -> 0 | H88: =SUM(F88:G88) -> 0 | I88: =F88*16 -> 0 | J88: =G88*32 -> 0 | K88: =SUM(I88:J88) -> 0 | M88: =B88
B89: =Capacidades!M382 | M89: =B89
B90: =Capacidades!M383 | M90: =B90
B91: =Capacidades!M384 | M91: =B91
B92: =Capacidades!M385 | M92: =B92
B93: =Capacidades!M386 | M93: =B93
B94: =Capacidades!M387 | M94: =B94
B95: =Capacidades!M388 | M95: =B95
B96: =Capacidades!M389 | M96: =B96
B97: =Capacidades!M390 | M97: =B97
A98: =Capacidades!L391 | B98: =Capacidades!M391 | D98: =Organización_Modular!F49 -> 0 | E98: =Organización_Modular!G49 -> 0 | F98: =Organización_Modular!H49 -> 0 | G98: =Organización_Modular!I49 -> 0 | H98: =SUM(F98:G98) -> 0 | I98: =F98*16 -> 0 | J98: =G98*32 -> 0 | K98: =SUM(I98:J98) -> 0 | M98: =B98
B99: =Capacidades!M392 | M99: =B99
B100: =Capacidades!M393 | M100: =B100
B101: =Capacidades!M394 | M101: =B101
B102: =Capacidades!M395 | M102: =B102
B103: =Capacidades!M396 | M103: =B103
B104: =Capacidades!M397 | M104: =B104
B105: =Capacidades!M398 | M105: =B105
B106: =Capacidades!M399 | M106: =B106
...

Sheet M3
A1: ='M2'!A1:L1 -> ORGANIZACIÓN DE LOS ELEMENTOS DEL MÓDULO
A3: DENOMINACIÓN DE LA INSTITUCIÓN | B3: =Perfil_Egreso!B3 -> CETPRO JUANJUI | F3: CÓDIGO MODULAR DEL INSTITUTO | I3: =Perfil_Egreso!E3 -> 0533836
A5: SECTOR ECONÓMICO | B5: =Perfil_Egreso!B5 -> Actividades profesionales, científicas y técnicas | C5: FAMILIA PRODUCTIVA | D5: =Perfil_Egreso!D5 -> Servicios prestados a empresas | F5: ACTIVIDAD ECONÓMICA | I5: =Perfil_Egreso!B7 -> Actividades administrativas y de apoyo de oficina y otras actividades de apoyo a las empresas
A7: =Perfil_Egreso!A10 -> DENOMINACIÓN DEL PROGRAMA DE ESTUDIOS SEGÚN CNOF (según corresponda) | B7: =Perfil_Egreso!B10 -> APOYO ADMINISTRATIVO | F7: CÓDIGO * | I7: =Perfil_Egreso!E10 -> M2982-1-002
A9: =Perfil_Egreso!A12 -> FORMACIÓN** | B9: =Perfil_Egreso!B12 -> AUXILIAR TECNICO | C9: N°. HORAS: | D9: =Itinerario!W17 -> 1072 | F9: N° CRÉDITOS: | I9: =Itinerario!T17 -> 40
A11: =Perfil_Egreso!C12 -> MODALIDAD DEL SERVICIO EDUCATIVO | B11: =Perfil_Egreso!D12 -> PRESENCIAL | F11: =Perfil_Egreso!A14 -> NIVEL FORMATIVO | I11: =Perfil_Egreso!B14 -> AUXILIAR TÉCNICO
A13: UNIDAD DE COMPETENCIA DEL CATÁLOGO NACIONAL DE LA OFERTA FORMATIVA
A14: =Organización_Modular!C72 -> 0
A15: DENOMINACIÓN DEL MÓDULO | B15: =Organización_Modular!A72 -> 0
A16: CAPACIDADES TÉCNICAS O ESPECÍFICAS | B16: INDICADORES DE LOGRO DE LA CAPACIDAD | C16: CONTENIDOS | D16: UNIDAD DIDÁCTICA | E16: Periodo | F16: CRÉDITOS | H16: CRÉDITOS | I16: HORAS | K16: HORAS | L16: PERFIL DOCENTE | M16: Filtrar
F17: Teórico | G17: Práctica | I17: Teórico | J17: Práctica
A18: =Capacidades!L612 | B18: =Capacidades!M612 | D18: =Organización_Modular!F72 -> 0 | E18: =Organización_Modular!G72 -> 0 | F18: =Organización_Modular!H72 -> 0 | G18: =Organización_Modular!I72 -> 0 | H18: =SUM(F18:G18) -> 0 | I18: =F18*16 -> 0 | J18: =G18*32 -> 0 | K18: =SUM(I18:J18) -> 0 | M18: =B18
B19: =Capacidades!M613 | M19: =B19
B20: =Capacidades!M614 | M20: =B20
B21: =Capacidades!M615 | M21: =B21
B22: =Capacidades!M616 | M22: =B22
B23: =Capacidades!M617 | M23: =B23
B24: =Capacidades!M618 | M24: =B24
B25: =Capacidades!M619 | M25: =B25
B26: =Capacidades!M620 | M26: =B26
B27: =Capacidades!M621 | M27: =B27
A28: =Capacidades!L622 | B28: =Capacidades!M622 | D28: =Organización_Modular!F73 -> 0 | E28: =Organización_Modular!G73 -> 0 | F28: =Organización_Modular!H73 -> 0 | G28: =Organización_Modular!I73 -> 0 | H28: =SUM(F28:G28) -> 0 | I28: =F28*16 -> 0 | J28: =G28*32 -> 0 | K28: =SUM(I28:J28) -> 0 | M28: =B28
B29: =Capacidades!M623 | M29: =B29
B30: =Capacidades!M624 | M30: =B30
B31: =Capacidades!M625 | M31: =B31
B32: =Capacidades!M626 | M32: =B32
B33: =Capacidades!M627 | M33: =B33
B34: =Capacidades!M628 | M34: =B34
B35: =Capacidades!M629 | M35: =B35
B36: =Capacidades!M630 | M36: =B36
B37: =Capacidades!M631 | M37: =B37
A38: =Capacidades!L632 | B38: =Capacidades!M632 | D38: =Organización_Modular!F74 -> 0 | E38: =Organización_Modular!G74 -> 0 | F38: =Organización_Modular!H74 -> 0 | G38: =Organización_Modular!I74 -> 0 | H38: =SUM(F38:G38) -> 0 | I38: =F38*16 -> 0 | J38: =G38*32 -> 0 | K38: =SUM(I38:J38) -> 0 | M38: =B38
B39: =Capacidades!M633 | M39: =B39
B40: =Capacidades!M634 | M40: =B40
B41: =Capacidades!M635 | M41: =B41
B42: =Capacidades!M636 | M42: =B42
B43: =Capacidades!M637 | M43: =B43
B44: =Capacidades!M638 | M44: =B44
B45: =Capacidades!M639 | M45: =B45
B46: =Capacidades!M640 | M46: =B46
B47: =Capacidades!M641 | M47: =B47
A48: =Capacidades!L642 | B48: =Capacidades!M642 | D48: =Organización_Modular!F75 -> 0 | E48: =Organización_Modular!G75 -> 0 | F48: =Organización_Modular!H75 -> 0 | G48: =Organización_Modular!I75 -> 0 | H48: =SUM(F48:G48) -> 0 | I48: =F48*16 -> 0 | J48: =G48*32 -> 0 | K48: =SUM(I48:J48) -> 0 | M48: =B48
B49: =Capacidades!M643 | M49: =B49
B50: =Capacidades!M644 | M50: =B50
B51: =Capacidades!M645 | M51: =B51
B52: =Capacidades!M646 | M52: =B52
B53: =Capacidades!M647 | M53: =B53
B54: =Capacidades!M648 | M54: =B54
B55: =Capacidades!M649 | M55: =B55
B56: =Capacidades!M650 | M56: =B56
B57: =Capacidades!M651 | M57: =B57
A58: =Capacidades!L652 | B58: =Capacidades!M652 | D58: =Organización_Modular!F76 -> 0 | E58: =Organización_Modular!G76 -> 0 | F58: =Organización_Modular!H76 -> 0 | G58: =Organización_Modular!I76 -> 0 | H58: =SUM(F58:G58) -> 0 | I58: =F58*16 -> 0 | J58: =G58*32 -> 0 | K58: =SUM(I58:J58) -> 0 | M58: =B58
B59: =Capacidades!M653 | M59: =B59
B60: =Capacidades!M654 | M60: =B60
B61: =Capacidades!M655 | M61: =B61
B62: =Capacidades!M656 | M62: =B62
B63: =Capacidades!M657 | M63: =B63
B64: =Capacidades!M658 | M64: =B64
B65: =Capacidades!M659 | M65: =B65
B66: =Capacidades!M660 | M66: =B66
B67: =Capacidades!M661 | M67: =B67
A68: =Capacidades!L662 | B68: =Capacidades!M662 | D68: =Organización_Modular!F77 -> 0 | E68: =Organización_Modular!G77 -> 0 | F68: =Organización_Modular!H77 -> 0 | G68: =Organización_Modular!I77 -> 0 | H68: =SUM(F68:G68) -> 0 | I68: =F68*16 -> 0 | J68: =G68*32 -> 0 | K68: =SUM(I68:J68) -> 0 | M68: =B68
B69: =Capacidades!M663 | M69: =B69
B70: =Capacidades!M664 | M70: =B70
B71: =Capacidades!M665 | M71: =B71
B72: =Capacidades!M666 | M72: =B72
B73: =Capacidades!M667 | M73: =B73
B74: =Capacidades!M668 | M74: =B74
B75: =Capacidades!M669 | M75: =B75
B76: =Capacidades!M670 | M76: =B76
B77: =Capacidades!M671 | M77: =B77
A78: =Capacidades!L672 | B78: =Capacidades!M672 | D78: =Organización_Modular!F78 -> 0 | E78: =Organización_Modular!G78 -> 0 | F78: =Organización_Modular!H78 -> 0 | G78: =Organización_Modular!I78 -> 0 | H78: =SUM(F78:G78) -> 0 | I78: =F78*16 -> 0 | J78: =G78*32 -> 0 | K78: =SUM(I78:J78) -> 0 | M78: =B78
B79: =Capacidades!M673 | M79: =B79
B80: =Capacidades!M674 | M80: =B80
B81: =Capacidades!M675 | M81: =B81
B82: =Capacidades!M676 | M82: =B82
B83: =Capacidades!M677 | M83: =B83
B84: =Capacidades!M678 | M84: =B84
B85: =Capacidades!M679 | M85: =B85
B86: =Capacidades!M680 | M86: =B86
B87: =Capacidades!M681 | M87: =B87
A88: =Capacidades!L682 | B88: =Capacidades!M682 | D88: =Organización_Modular!F79 -> 0 | E88: =Organización_Modular!G79 -> 0 | F88: =Organización_Modular!H79 -> 0 | G88: =Organización_Modular!I79 -> 0 | H88: =SUM(F88:G88) -> 0 | I88: =F88*16 -> 0 | J88: =G88*32 -> 0 | K88: =SUM(I88:J88) -> 0 | M88: =B88
B89: =Capacidades!M683 | M89: =B89
B90: =Capacidades!M684 | M90: =B90
B91: =Capacidades!M685 | M91: =B91
B92: =Capacidades!M686 | M92: =B92
B93: =Capacidades!M687 | M93: =B93
B94: =Capacidades!M688 | M94: =B94
B95: =Capacidades!M689 | M95: =B95
B96: =Capacidades!M690 | M96: =B96
B97: =Capacidades!M691 | M97: =B97
A98: =Capacidades!L692 | B98: =Capacidades!M692 | D98: =Organización_Modular!F80 -> 0 | E98: =Organización_Modular!G80 -> 0 | F98: =Organización_Modular!H80 -> 0 | G98: =Organización_Modular!I80 -> 0 | H98: =SUM(F98:G98) -> 0 | I98: =F98*16 -> 0 | J98: =G98*32 -> 0 | K98: =SUM(I98:J98) -> 0 | M98: =B98
B99: =Capacidades!M693 | M99: =B99
B100: =Capacidades!M694 | M100: =B100
B101: =Capacidades!M695 | M101: =B101
B102: =Capacidades!M696 | M102: =B102
B103: =Capacidades!M697 | M103: =B103
B104: =Capacidades!M698 | M104: =B104
B105: =Capacidades!M699 | M105: =B105
B106: =Capacidades!M700 | M106: =B106
...

Sheet M4
A1: ='M3'!A1:L1 -> ORGANIZACIÓN DE LOS ELEMENTOS DEL MÓDULO
A3: DENOMINACIÓN DE LA INSTITUCIÓN | B3: =Perfil_Egreso!B3 -> CETPRO JUANJUI | F3: CÓDIGO MODULAR DEL INSTITUTO | I3: =Perfil_Egreso!E3 -> 0533836
A5: SECTOR ECONÓMICO | B5: =Perfil_Egreso!B5 -> Actividades profesionales, científicas y técnicas | C5: FAMILIA PRODUCTIVA | D5: =Perfil_Egreso!D5 -> Servicios prestados a empresas | F5: ACTIVIDAD ECONÓMICA | I5: =Perfil_Egreso!B7 -> Actividades administrativas y de apoyo de oficina y otras actividades de apoyo a las empresas
A7: =Perfil_Egreso!A10 -> DENOMINACIÓN DEL PROGRAMA DE ESTUDIOS SEGÚN CNOF (según corresponda) | B7: =Perfil_Egreso!B10 -> APOYO ADMINISTRATIVO | F7: CÓDIGO * | I7: =Perfil_Egreso!E10 -> M2982-1-002
A9: =Perfil_Egreso!A12 -> FORMACIÓN** | B9: =Perfil_Egreso!B12 -> AUXILIAR TECNICO | C9: N°. HORAS: | D9: =Itinerario!W17 -> 1072 | F9: N° CRÉDITOS: | I9: =Itinerario!T17 -> 40
A11: =Perfil_Egreso!C12 -> MODALIDAD DEL SERVICIO EDUCATIVO | B11: =Perfil_Egreso!D12 -> PRESENCIAL | F11: =Perfil_Egreso!A14 -> NIVEL FORMATIVO | I11: =Perfil_Egreso!B14 -> AUXILIAR TÉCNICO
A13: UNIDAD DE COMPETENCIA DEL CATÁLOGO NACIONAL DE LA OFERTA FORMATIVA
A14: =Organización_Modular!C103 -> 0
A15: DENOMINACIÓN DEL MÓDULO | B15: =Organización_Modular!A103 -> MÓDULO II: COCINA NACIONAL E INTERNACIONAL
A16: CAPACIDADES TÉCNICAS O ESPECÍFICAS | B16: INDICADORES DE LOGRO DE LA CAPACIDAD | C16: CONTENIDOS | D16: UNIDAD DIDÁCTICA | E16: Periodo | F16: CRÉDITOS | H16: CRÉDITOS | I16: HORAS | K16: HORAS | L16: PERFIL DOCENTE | M16: Filtrar
F17: Teórico | G17: Práctica | I17: Teórico | J17: Práctica
A18: =Capacidades!L913 | B18: =Capacidades!M913 | D18: =Organización_Modular!F103 -> 0 | E18: =Organización_Modular!G103 -> 0 | F18: =Organización_Modular!H103 -> 0 | G18: =Organización_Modular!I103 -> 0 | H18: =SUM(F18:G18) -> 0 | I18: =F18*16 -> 0 | J18: =G18*32 -> 0 | K18: =SUM(I18:J18) -> 0 | M18: =B18
B19: =Capacidades!M914 | M19: =B19
B20: =Capacidades!M915 | M20: =B20
B21: =Capacidades!M916 | M21: =B21
B22: =Capacidades!M917 | M22: =B22
B23: =Capacidades!M918 | M23: =B23
B24: =Capacidades!M919 | M24: =B24
B25: =Capacidades!M920 | M25: =B25
B26: =Capacidades!M921 | M26: =B26
B27: =Capacidades!M922 | M27: =B27
A28: =Capacidades!L923 | B28: =Capacidades!M923 | D28: =Organización_Modular!F104 -> 0 | E28: =Organización_Modular!G104 -> 0 | F28: =Organización_Modular!H104 -> 0 | G28: =Organización_Modular!I104 -> 0 | H28: =SUM(F28:G28) -> 0 | I28: =F28*16 -> 0 | J28: =G28*32 -> 0 | K28: =SUM(I28:J28) -> 0 | M28: =B28
B29: =Capacidades!M924 | M29: =B29
B30: =Capacidades!M925 | M30: =B30
B31: =Capacidades!M926 | M31: =B31
B32: =Capacidades!M927 | M32: =B32
B33: =Capacidades!M928 | M33: =B33
B34: =Capacidades!M929 | M34: =B34
B35: =Capacidades!M930 | M35: =B35
B36: =Capacidades!M931 | M36: =B36
B37: =Capacidades!M932 | M37: =B37
A38: =Capacidades!L933 | B38: =Capacidades!M933 | D38: =Organización_Modular!F105 -> 0 | E38: =Organización_Modular!G105 -> 0 | F38: =Organización_Modular!H105 -> 0 | G38: =Organización_Modular!I105 -> 0 | H38: =SUM(F38:G38) -> 0 | I38: =F38*16 -> 0 | J38: =G38*32 -> 0 | K38: =SUM(I38:J38) -> 0 | M38: =B38
B39: =Capacidades!M934 | M39: =B39
B40: =Capacidades!M935 | M40: =B40
B41: =Capacidades!M936 | M41: =B41
B42: =Capacidades!M937 | M42: =B42
B43: =Capacidades!M938 | M43: =B43
B44: =Capacidades!M939 | M44: =B44
B45: =Capacidades!M940 | M45: =B45
B46: =Capacidades!M941 | M46: =B46
B47: =Capacidades!M942 | M47: =B47
A48: =Capacidades!L943 | B48: =Capacidades!M943 | D48: =Organización_Modular!F106 -> 0 | E48: =Organización_Modular!G106 -> 0 | F48: =Organización_Modular!H106 -> 0 | G48: =Organización_Modular!I106 -> 0 | H48: =SUM(F48:G48) -> 0 | I48: =F48*16 -> 0 | J48: =G48*32 -> 0 | K48: =SUM(I48:J48) -> 0 | M48: =B48
B49: =Capacidades!M944 | M49: =B49
B50: =Capacidades!M945 | M50: =B50
B51: =Capacidades!M946 | M51: =B51
B52: =Capacidades!M947 | M52: =B52
B53: =Capacidades!M948 | M53: =B53
B54: =Capacidades!M949 | M54: =B54
B55: =Capacidades!M950 | M55: =B55
B56: =Capacidades!M951 | M56: =B56
B57: =Capacidades!M952 | M57: =B57
A58: =Capacidades!L953 | B58: =Capacidades!M953 | D58: =Organización_Modular!F107 -> 0 | E58: =Organización_Modular!G107 -> 0 | F58: =Organización_Modular!H107 -> 0 | G58: =Organización_Modular!I107 -> 0 | H58: =SUM(F58:G58) -> 0 | I58: =F58*16 -> 0 | J58: =G58*32 -> 0 | K58: =SUM(I58:J58) -> 0 | M58: =B58
B59: =Capacidades!M954 | M59: =B59
B60: =Capacidades!M955 | M60: =B60
B61: =Capacidades!M956 | M61: =B61
B62: =Capacidades!M957 | M62: =B62
B63: =Capacidades!M958 | M63: =B63
B64: =Capacidades!M959 | M64: =B64
B65: =Capacidades!M960 | M65: =B65
B66: =Capacidades!M961 | M66: =B66
B67: =Capacidades!M962 | M67: =B67
A68: =Capacidades!L963 | B68: =Capacidades!M963 | D68: =Organización_Modular!F108 -> 0 | E68: =Organización_Modular!G108 -> 0 | F68: =Organización_Modular!H108 -> 0 | G68: =Organización_Modular!I108 -> 0 | H68: =SUM(F68:G68) -> 0 | I68: =F68*16 -> 0 | J68: =G68*32 -> 0 | K68: =SUM(I68:J68) -> 0 | M68: =B68
B69: =Capacidades!M964 | M69: =B69
B70: =Capacidades!M965 | M70: =B70
B71: =Capacidades!M966 | M71: =B71
B72: =Capacidades!M967 | M72: =B72
B73: =Capacidades!M968 | M73: =B73
B74: =Capacidades!M969 | M74: =B74
B75: =Capacidades!M970 | M75: =B75
B76: =Capacidades!M971 | M76: =B76
B77: =Capacidades!M972 | M77: =B77
A78: =Capacidades!L973 | B78: =Capacidades!M973 | D78: =Organización_Modular!F109 -> 0 | E78: =Organización_Modular!G109 -> 0 | F78: =Organización_Modular!H109 -> 0 | G78: =Organización_Modular!I109 -> 0 | H78: =SUM(F78:G78) -> 0 | I78: =F78*16 -> 0 | J78: =G78*32 -> 0 | K78: =SUM(I78:J78) -> 0 | M78: =B78
B79: =Capacidades!M974 | M79: =B79
B80: =Capacidades!M975 | M80: =B80
B81: =Capacidades!M976 | M81: =B81
B82: =Capacidades!M977 | M82: =B82
B83: =Capacidades!M978 | M83: =B83
B84: =Capacidades!M979 | M84: =B84
B85: =Capacidades!M980 | M85: =B85
B86: =Capacidades!M981 | M86: =B86
B87: =Capacidades!M982 | M87: =B87
A88: =Capacidades!L983 | B88: =Capacidades!M983 | D88: =Organización_Modular!F110 -> 0 | E88: =Organización_Modular!G110 -> 0 | F88: =Organización_Modular!H110 -> 0 | G88: =Organización_Modular!I110 -> 0 | H88: =SUM(F88:G88) -> 0 | I88: =F88*16 -> 0 | J88: =G88*32 -> 0 | K88: =SUM(I88:J88) -> 0 | M88: =B88
B89: =Capacidades!M984 | M89: =B89
B90: =Capacidades!M985 | M90: =B90
B91: =Capacidades!M986 | M91: =B91
B92: =Capacidades!M987 | M92: =B92
B93: =Capacidades!M988 | M93: =B93
B94: =Capacidades!M989 | M94: =B94
B95: =Capacidades!M990 | M95: =B95
B96: =Capacidades!M991 | M96: =B96
B97: =Capacidades!M992 | M97: =B97
A98: =Capacidades!L993 | B98: =Capacidades!M993 | D98: =Organización_Modular!F111 -> 0 | E98: =Organización_Modular!G111 -> 0 | F98: =Organización_Modular!H111 -> 0 | G98: =Organización_Modular!I111 -> 0 | H98: =SUM(F98:G98) -> 0 | I98: =F98*16 -> 0 | J98: =G98*32 -> 0 | K98: =SUM(I98:J98) -> 0 | M98: =B98
B99: =Capacidades!M994 | M99: =B99
B100: =Capacidades!M995 | M100: =B100
B101: =Capacidades!M996 | M101: =B101
B102: =Capacidades!M997 | M102: =B102
B103: =Capacidades!M998 | M103: =B103
B104: =Capacidades!M999 | M104: =B104
B105: =Capacidades!M1000 | M105: =B105
B106: =Capacidades!M1001 | M106: =B106
...

Sheet M5
A1: ='M4'!A1:L1 -> ORGANIZACIÓN DE LOS ELEMENTOS DEL MÓDULO
A3: DENOMINACIÓN DE LA INSTITUCIÓN | B3: =Perfil_Egreso!B3 -> CETPRO JUANJUI | F3: CÓDIGO MODULAR DEL INSTITUTO | I3: =Perfil_Egreso!E3 -> 0533836
A5: SECTOR ECONÓMICO | B5: =Perfil_Egreso!B5 -> Actividades profesionales, científicas y técnicas | C5: FAMILIA PRODUCTIVA | D5: =Perfil_Egreso!D5 -> Servicios prestados a empresas | F5: ACTIVIDAD ECONÓMICA | I5: =Perfil_Egreso!B7 -> Actividades administrativas y de apoyo de oficina y otras actividades de apoyo a las empresas
A7: =Perfil_Egreso!A10 -> DENOMINACIÓN DEL PROGRAMA DE ESTUDIOS SEGÚN CNOF (según corresponda) | B7: =Perfil_Egreso!B10 -> APOYO ADMINISTRATIVO | F7: CÓDIGO * | I7: =Perfil_Egreso!E10 -> M2982-1-002
A9: =Perfil_Egreso!A12 -> FORMACIÓN** | B9: =Perfil_Egreso!B12 -> AUXILIAR TECNICO | C9: N°. HORAS: | D9: =Itinerario!W17 -> 1072 | F9: N° CRÉDITOS: | I9: =Itinerario!T17 -> 40
A11: =Perfil_Egreso!C12 -> MODALIDAD DEL SERVICIO EDUCATIVO | B11: =Perfil_Egreso!D12 -> PRESENCIAL | F11: =Perfil_Egreso!A14 -> NIVEL FORMATIVO | I11: =Perfil_Egreso!B14 -> AUXILIAR TÉCNICO
A13: UNIDAD DE COMPETENCIA DEL CATÁLOGO NACIONAL DE LA OFERTA FORMATIVA
A14: =Organización_Modular!C134 -> 0
A15: DENOMINACIÓN DEL MÓDULO | B15: =Organización_Modular!A134 -> 0
A16: CAPACIDADES TÉCNICAS O ESPECÍFICAS | B16: INDICADORES DE LOGRO DE LA CAPACIDAD | C16: CONTENIDOS | D16: UNIDAD DIDÁCTICA | E16: Periodo | F16: CRÉDITOS | H16: CRÉDITOS | I16: HORAS | K16: HORAS | L16: PERFIL DOCENTE | M16: Filtrar
F17: Teórico | G17: Práctica | I17: Teórico | J17: Práctica
A18: =Capacidades!L1214 | B18: =Capacidades!M1214 | D18: =Organización_Modular!F134 -> 0 | E18: =Organización_Modular!G134 -> 0 | F18: =Organización_Modular!H134 -> 0 | G18: =Organización_Modular!I134 -> 0 | H18: =SUM(F18:G18) -> 0 | I18: =F18*16 -> 0 | J18: =G18*32 -> 0 | K18: =SUM(I18:J18) -> 0 | M18: =B18
B19: =Capacidades!M1215 | M19: =B19
B20: =Capacidades!M1216 | M20: =B20
B21: =Capacidades!M1217 | M21: =B21
B22: =Capacidades!M1218 | M22: =B22
B23: =Capacidades!M1219 | M23: =B23
B24: =Capacidades!M1220 | M24: =B24
B25: =Capacidades!M1221 | M25: =B25
B26: =Capacidades!M1222 | M26: =B26
B27: =Capacidades!M1223 | M27: =B27
A28: =Capacidades!L1224 | B28: =Capacidades!M1224 | D28: =Organización_Modular!F135 -> 0 | E28: =Organización_Modular!G135 -> 0 | F28: =Organización_Modular!H135 -> 0 | G28: =Organización_Modular!I135 -> 0 | H28: =SUM(F28:G28) -> 0 | I28: =F28*16 -> 0 | J28: =G28*32 -> 0 | K28: =SUM(I28:J28) -> 0 | M28: =B28
B29: =Capacidades!M1225 | M29: =B29
B30: =Capacidades!M1226 | M30: =B30
B31: =Capacidades!M1227 | M31: =B31
B32: =Capacidades!M1228 | M32: =B32
B33: =Capacidades!M1229 | M33: =B33
B34: =Capacidades!M1230 | M34: =B34
B35: =Capacidades!M1231 | M35: =B35
B36: =Capacidades!M1232 | M36: =B36
B37: =Capacidades!M1233 | M37: =B37
A38: =Capacidades!L1234 | B38: =Capacidades!M1234 | D38: =Organización_Modular!F136 -> 0 | E38: =Organización_Modular!G136 -> 0 | F38: =Organización_Modular!H136 -> 0 | G38: =Organización_Modular!I136 -> 0 | H38: =SUM(F38:G38) -> 0 | I38: =F38*16 -> 0 | J38: =G38*32 -> 0 | K38: =SUM(I38:J38) -> 0 | M38: =B38
B39: =Capacidades!M1235 | M39: =B39
B40: =Capacidades!M1236 | M40: =B40
B41: =Capacidades!M1237 | M41: =B41
B42: =Capacidades!M1238 | M42: =B42
B43: =Capacidades!M1239 | M43: =B43
B44: =Capacidades!M1240 | M44: =B44
B45: =Capacidades!M1241 | M45: =B45
B46: =Capacidades!M1242 | M46: =B46
B47: =Capacidades!M1243 | M47: =B47
A48: =Capacidades!L1244 | B48: =Capacidades!M1244 | D48: =Organización_Modular!F137 -> 0 | E48: =Organización_Modular!G137 -> 0 | F48: =Organización_Modular!H137 -> 0 | G48: =Organización_Modular!I137 -> 0 | H48: =SUM(F48:G48) -> 0 | I48: =F48*16 -> 0 | J48: =G48*32 -> 0 | K48: =SUM(I48:J48) -> 0 | M48: =B48
B49: =Capacidades!M1245 | M49: =B49
B50: =Capacidades!M1246 | M50: =B50
B51: =Capacidades!M1247 | M51: =B51
B52: =Capacidades!M1248 | M52: =B52
B53: =Capacidades!M1249 | M53: =B53
B54: =Capacidades!M1250 | M54: =B54
B55: =Capacidades!M1251 | M55: =B55
B56: =Capacidades!M1252 | M56: =B56
B57: =Capacidades!M1253 | M57: =B57
A58: =Capacidades!L1254 | B58: =Capacidades!M1254 | D58: =Organización_Modular!F138 -> 0 | E58: =Organización_Modular!G138 -> 0 | F58: =Organización_Modular!H138 -> 0 | G58: =Organización_Modular!I138 -> 0 | H58: =SUM(F58:G58) -> 0 | I58: =F58*16 -> 0 | J58: =G58*32 -> 0 | K58: =SUM(I58:J58) -> 0 | M58: =B58
B59: =Capacidades!M1255 | M59: =B59
B60: =Capacidades!M1256 | M60: =B60
B61: =Capacidades!M1257 | M61: =B61
B62: =Capacidades!M1258 | M62: =B62
B63: =Capacidades!M1259 | M63: =B63
B64: =Capacidades!M1260 | M64: =B64
B65: =Capacidades!M1261 | M65: =B65
B66: =Capacidades!M1262 | M66: =B66
B67: =Capacidades!M1263 | M67: =B67
A68: =Capacidades!L1264 | B68: =Capacidades!M1264 | D68: =Organización_Modular!F139 -> 0 | E68: =Organización_Modular!G139 -> 0 | F68: =Organización_Modular!H139 -> 0 | G68: =Organización_Modular!I139 -> 0 | H68: =SUM(F68:G68) -> 0 | I68: =F68*16 -> 0 | J68: =G68*32 -> 0 | K68: =SUM(I68:J68) -> 0 | M68: =B68
B69: =Capacidades!M1265 | M69: =B69
B70: =Capacidades!M1266 | M70: =B70
B71: =Capacidades!M1267 | M71: =B71
B72: =Capacidades!M1268 | M72: =B72
B73: =Capacidades!M1269 | M73: =B73
B74: =Capacidades!M1270 | M74: =B74
B75: =Capacidades!M1271 | M75: =B75
B76: =Capacidades!M1272 | M76: =B76
B77: =Capacidades!M1273 | M77: =B77
A78: =Capacidades!L1274 | B78: =Capacidades!M1274 | D78: =Organización_Modular!F140 -> 0 | E78: =Organización_Modular!G140 -> 0 | F78: =Organización_Modular!H140 -> 0 | G78: =Organización_Modular!I140 -> 0 | H78: =SUM(F78:G78) -> 0 | I78: =F78*16 -> 0 | J78: =G78*32 -> 0 | K78: =SUM(I78:J78) -> 0 | M78: =B78
B79: =Capacidades!M1275 | M79: =B79
B80: =Capacidades!M1276 | M80: =B80
B81: =Capacidades!M1277 | M81: =B81
B82: =Capacidades!M1278 | M82: =B82
B83: =Capacidades!M1279 | M83: =B83
B84: =Capacidades!M1280 | M84: =B84
B85: =Capacidades!M1281 | M85: =B85
B86: =Capacidades!M1282 | M86: =B86
B87: =Capacidades!M1283 | M87: =B87
A88: =Capacidades!L1284 | B88: =Capacidades!M1284 | D88: =Organización_Modular!F141 -> 0 | E88: =Organización_Modular!G141 -> 0 | F88: =Organización_Modular!H141 -> 0 | G88: =Organización_Modular!I141 -> 0 | H88: =SUM(F88:G88) -> 0 | I88: =F88*16 -> 0 | J88: =G88*32 -> 0 | K88: =SUM(I88:J88) -> 0 | M88: =B88
B89: =Capacidades!M1285 | M89: =B89
B90: =Capacidades!M1286 | M90: =B90
B91: =Capacidades!M1287 | M91: =B91
B92: =Capacidades!M1288 | M92: =B92
B93: =Capacidades!M1289 | M93: =B93
B94: =Capacidades!M1290 | M94: =B94
B95: =Capacidades!M1291 | M95: =B95
B96: =Capacidades!M1292 | M96: =B96
B97: =Capacidades!M1293 | M97: =B97
A98: =Capacidades!L1294 | B98: =Capacidades!M1294 | D98: =Organización_Modular!F142 -> 0 | E98: =Organización_Modular!G142 -> 0 | F98: =Organización_Modular!H142 -> 0 | G98: =Organización_Modular!I142 -> 0 | H98: =SUM(F98:G98) -> 0 | I98: =F98*16 -> 0 | J98: =G98*32 -> 0 | K98: =SUM(I98:J98) -> 0 | M98: =B98
B99: =Capacidades!M1295 | M99: =B99
B100: =Capacidades!M1296 | M100: =B100
B101: =Capacidades!M1297 | M101: =B101
B102: =Capacidades!M1298 | M102: =B102
B103: =Capacidades!M1299 | M103: =B103
B104: =Capacidades!M1300 | M104: =B104
B105: =Capacidades!M1301 | M105: =B105
B106: =Capacidades!M1302 | M106: =B106
...

Sheet M6
A1: ='M5'!A1:L1 -> ORGANIZACIÓN DE LOS ELEMENTOS DEL MÓDULO
A3: DENOMINACIÓN DE LA INSTITUCIÓN | B3: =Perfil_Egreso!B3 -> CETPRO JUANJUI | F3: CÓDIGO MODULAR DEL INSTITUTO | I3: =Perfil_Egreso!E3 -> 0533836
A5: SECTOR ECONÓMICO | B5: =Perfil_Egreso!B5 -> Actividades profesionales, científicas y técnicas | C5: FAMILIA PRODUCTIVA | D5: =Perfil_Egreso!D5 -> Servicios prestados a empresas | F5: ACTIVIDAD ECONÓMICA | I5: =Perfil_Egreso!B7 -> Actividades administrativas y de apoyo de oficina y otras actividades de apoyo a las empresas
A7: =Perfil_Egreso!A10 -> DENOMINACIÓN DEL PROGRAMA DE ESTUDIOS SEGÚN CNOF (según corresponda) | B7: =Perfil_Egreso!B10 -> APOYO ADMINISTRATIVO | F7: CÓDIGO * | I7: =Perfil_Egreso!E10 -> M2982-1-002
A9: =Perfil_Egreso!A12 -> FORMACIÓN** | B9: =Perfil_Egreso!B12 -> AUXILIAR TECNICO | C9: N°. HORAS: | D9: =Itinerario!W17 -> 1072 | F9: N° CRÉDITOS: | I9: =Itinerario!T17 -> 40
A11: =Perfil_Egreso!C12 -> MODALIDAD DEL SERVICIO EDUCATIVO | B11: =Perfil_Egreso!D12 -> PRESENCIAL | F11: =Perfil_Egreso!A14 -> NIVEL FORMATIVO | I11: =Perfil_Egreso!B14 -> AUXILIAR TÉCNICO
A13: UNIDAD DE COMPETENCIA DEL CATÁLOGO NACIONAL DE LA OFERTA FORMATIVA
A14: =Organización_Modular!C134 -> 0
A15: DENOMINACIÓN DEL MÓDULO | B15: =Organización_Modular!A134 -> 0
A16: CAPACIDADES TÉCNICAS O ESPECÍFICAS | B16: INDICADORES DE LOGRO DE LA CAPACIDAD | C16: CONTENIDOS | D16: UNIDAD DIDÁCTICA | E16: Periodo | F16: CRÉDITOS | H16: CRÉDITOS | I16: HORAS | K16: HORAS | L16: PERFIL DOCENTE | M16: Filtrar
F17: Teórico | G17: Práctica | I17: Teórico | J17: Práctica
A18: =Capacidades!L1515 | B18: =Capacidades!M1515 | D18: =Organización_Modular!F165 -> 0 | E18: =Organización_Modular!G165 -> 0 | F18: =Organización_Modular!H165 -> 0 | G18: =Organización_Modular!I165 -> 0 | H18: =SUM(F18:G18) -> 0 | I18: =F18*16 -> 0 | J18: =G18*32 -> 0 | K18: =SUM(I18:J18) -> 0 | M18: =B18
B19: =Capacidades!M1516 | M19: =B19
B20: =Capacidades!M1517 | M20: =B20
B21: =Capacidades!M1518 | M21: =B21
B22: =Capacidades!M1519 | M22: =B22
B23: =Capacidades!M1520 | M23: =B23
B24: =Capacidades!M1521 | M24: =B24
B25: =Capacidades!M1522 | M25: =B25
B26: =Capacidades!M1523 | M26: =B26
B27: =Capacidades!M1524 | M27: =B27
A28: =Capacidades!L1525 | B28: =Capacidades!M1525 | D28: =Organización_Modular!F166 -> 0 | E28: =Organización_Modular!G166 -> 0 | F28: =Organización_Modular!H166 -> 0 | G28: =Organización_Modular!I166 -> 0 | H28: =SUM(F28:G28) -> 0 | I28: =F28*16 -> 0 | J28: =G28*32 -> 0 | K28: =SUM(I28:J28) -> 0 | M28: =B28
B29: =Capacidades!M1526 | M29: =B29
B30: =Capacidades!M1527 | M30: =B30
B31: =Capacidades!M1528 | M31: =B31
B32: =Capacidades!M1529 | M32: =B32
B33: =Capacidades!M1530 | M33: =B33
B34: =Capacidades!M1531 | M34: =B34
B35: =Capacidades!M1532 | M35: =B35
B36: =Capacidades!M1533 | M36: =B36
B37: =Capacidades!M1534 | M37: =B37
A38: =Capacidades!L1535 | B38: =Capacidades!M1535 | D38: =Organización_Modular!F167 -> 0 | E38: =Organización_Modular!G167 -> 0 | F38: =Organización_Modular!H167 -> 0 | G38: =Organización_Modular!I167 -> 0 | H38: =SUM(F38:G38) -> 0 | I38: =F38*16 -> 0 | J38: =G38*32 -> 0 | K38: =SUM(I38:J38) -> 0 | M38: =B38
B39: =Capacidades!M1536 | M39: =B39
B40: =Capacidades!M1537 | M40: =B40
B41: =Capacidades!M1538 | M41: =B41
B42: =Capacidades!M1539 | M42: =B42
B43: =Capacidades!M1540 | M43: =B43
B44: =Capacidades!M1541 | M44: =B44
B45: =Capacidades!M1542 | M45: =B45
B46: =Capacidades!M1543 | M46: =B46
B47: =Capacidades!M1544 | M47: =B47
A48: =Capacidades!L1545 | B48: =Capacidades!M1545 | D48: =Organización_Modular!F168 -> 0 | E48: =Organización_Modular!G168 -> 0 | F48: =Organización_Modular!H168 -> 0 | G48: =Organización_Modular!I168 -> 0 | H48: =SUM(F48:G48) -> 0 | I48: =F48*16 -> 0 | J48: =G48*32 -> 0 | K48: =SUM(I48:J48) -> 0 | M48: =B48
B49: =Capacidades!M1546 | M49: =B49
B50: =Capacidades!M1547 | M50: =B50
B51: =Capacidades!M1548 | M51: =B51
B52: =Capacidades!M1549 | M52: =B52
B53: =Capacidades!M1550 | M53: =B53
B54: =Capacidades!M1551 | M54: =B54
B55: =Capacidades!M1552 | M55: =B55
B56: =Capacidades!M1553 | M56: =B56
B57: =Capacidades!M1554 | M57: =B57
A58: =Capacidades!L1555 | B58: =Capacidades!M1555 | D58: =Organización_Modular!F169 -> 0 | E58: =Organización_Modular!G169 -> 0 | F58: =Organización_Modular!H169 -> 0 | G58: =Organización_Modular!I169 -> 0 | H58: =SUM(F58:G58) -> 0 | I58: =F58*16 -> 0 | J58: =G58*32 -> 0 | K58: =SUM(I58:J58) -> 0 | M58: =B58
B59: =Capacidades!M1556 | M59: =B59
B60: =Capacidades!M1557 | M60: =B60
B61: =Capacidades!M1558 | M61: =B61
B62: =Capacidades!M1559 | M62: =B62
B63: =Capacidades!M1560 | M63: =B63
B64: =Capacidades!M1561 | M64: =B64
B65: =Capacidades!M1562 | M65: =B65
B66: =Capacidades!M1563 | M66: =B66
B67: =Capacidades!M1564 | M67: =B67
A68: =Capacidades!L1565 | B68: =Capacidades!M1565 | D68: =Organización_Modular!F170 -> 0 | E68: =Organización_Modular!G170 -> 0 | F68: =Organización_Modular!H170 -> 0 | G68: =Organización_Modular!I170 -> 0 | H68: =SUM(F68:G68) -> 0 | I68: =F68*16 -> 0 | J68: =G68*32 -> 0 | K68: =SUM(I68:J68) -> 0 | M68: =B68
B69: =Capacidades!M1566 | M69: =B69
B70: =Capacidades!M1567 | M70: =B70
B71: =Capacidades!M1568 | M71: =B71
B72: =Capacidades!M1569 | M72: =B72
B73: =Capacidades!M1570 | M73: =B73
B74: =Capacidades!M1571 | M74: =B74
B75: =Capacidades!M1572 | M75: =B75
B76: =Capacidades!M1573 | M76: =B76
B77: =Capacidades!M1574 | M77: =B77
A78: =Capacidades!L1575 | B78: =Capacidades!M1575 | D78: =Organización_Modular!F171 -> 0 | E78: =Organización_Modular!G171 -> 0 | F78: =Organización_Modular!H171 -> 0 | G78: =Organización_Modular!I171 -> 0 | H78: =SUM(F78:G78) -> 0 | I78: =F78*16 -> 0 | J78: =G78*32 -> 0 | K78: =SUM(I78:J78) -> 0 | M78: =B78
B79: =Capacidades!M1576 | M79: =B79
B80: =Capacidades!M1577 | M80: =B80
B81: =Capacidades!M1578 | M81: =B81
B82: =Capacidades!M1579 | M82: =B82
B83: =Capacidades!M1580 | M83: =B83
B84: =Capacidades!M1581 | M84: =B84
B85: =Capacidades!M1582 | M85: =B85
B86: =Capacidades!M1583 | M86: =B86
B87: =Capacidades!M1584 | M87: =B87
A88: =Capacidades!L1585 | B88: =Capacidades!M1585 | D88: =Organización_Modular!F172 -> 0 | E88: =Organización_Modular!G172 -> 0 | F88: =Organización_Modular!H172 -> 0 | G88: =Organización_Modular!I172 -> 0 | H88: =SUM(F88:G88) -> 0 | I88: =F88*16 -> 0 | J88: =G88*32 -> 0 | K88: =SUM(I88:J88) -> 0 | M88: =B88
B89: =Capacidades!M1586 | M89: =B89
B90: =Capacidades!M1587 | M90: =B90
B91: =Capacidades!M1588 | M91: =B91
B92: =Capacidades!M1589 | M92: =B92
B93: =Capacidades!M1590 | M93: =B93
B94: =Capacidades!M1591 | M94: =B94
B95: =Capacidades!M1592 | M95: =B95
B96: =Capacidades!M1593 | M96: =B96
B97: =Capacidades!M1594 | M97: =B97
A98: =Capacidades!L1595 | B98: =Capacidades!M1595 | D98: =Organización_Modular!F173 -> 0 | E98: =Organización_Modular!G173 -> 0 | F98: =Organización_Modular!H173 -> 0 | G98: =Organización_Modular!I173 -> 0 | H98: =SUM(F98:G98) -> 0 | I98: =F98*16 -> 0 | J98: =G98*32 -> 0 | K98: =SUM(I98:J98) -> 0 | M98: =B98
B99: =Capacidades!M1596 | M99: =B99
B100: =Capacidades!M1597 | M100: =B100
B101: =Capacidades!M1598 | M101: =B101
B102: =Capacidades!M1599 | M102: =B102
B103: =Capacidades!M1600 | M103: =B103
B104: =Capacidades!M1601 | M104: =B104
B105: =Capacidades!M1602 | M105: =B105
B106: =Capacidades!M1603 | M106: =B106
...

Sheet Itinerario
A1: ANEXO Nº10A ITINERARIO FORMATIVO IES
A3: DENOMINACIÓN DE LA INSTITUCIÓN EDUCATIVA | C3: =Perfil_Egreso!B3 -> CETPRO JUANJUI | L3: CÓDIGO MODULAR DEL CETPRO | S3: =Perfil_Egreso!E3 -> 0533836
A5: SECTOR ECONÓMICO | C5: =Perfil_Egreso!B5 -> Actividades profesionales, científicas y técnicas | E5: FAMILIA PRODUCTIVA | G5: =Perfil_Egreso!D5 -> Servicios prestados a empresas | P5: ACTIVIDAD ECONÓMICA | T5: =Perfil_Egreso!B7 -> Actividades administrativas y de apoyo de oficina y otras actividades de apoyo a las empresas
A7: DENOMINACIÓN DEL PROGRAMA DE ESTUDIOS SEGÚN CNOF (según corresponda) | C7: =Perfil_Egreso!B10 -> APOYO ADMINISTRATIVO
A9: CÓDIGO DE SER EL CASO * | C9: =Perfil_Egreso!E10 -> M2982-1-002 | E9: NIVEL FORMATIVO | G9: =Perfil_Egreso!B14 -> AUXILIAR TÉCNICO | M9: N° HORAS: | P9: =W17 -> 1072 | S9: N° CRÉDITOS: | U9: =T17 -> 40
A11: MODALIDAD DEL SERVICIO EDUCATIVO | C11: =Perfil_Egreso!D12 -> PRESENCIAL
A13: N° de créditos en forma virtual (**) | G13: COMPONENTES CURRICULARES | R13: Créd. T | S13: Créd. P | T13: Total créditos | U13: HT | V13: HP | W13: Total horas | Y13: Ayuda para verificar - f(x) criterios
G14: Competencias técnicas o específicas | R14: =SUM(R24:R43,R55:R74,R86:R105,R117:R136,R148:R167,R179:R198) -> 9 | S14: =SUM(S24:S43,S55:S74,S86:S105,S117:S136,S148:S167,S179:S198) -> 11 | T14: =SUM(R14:S14) -> 20 | U14: =R14*$S$19 -> 144 | V14: =S14*$U$19 -> 352 | W14: =SUM(U14:V14) -> 496 | Y14: Total horas (UD) | AD14: =SUM(W14:W15) -> 688
A15: % de créditos en forma virtual (**) | G15: Competencias para la empleabilidad | R15: =SUM(R44:R53,R75:R84,R106:R115,R137:R146,R168:R177,R199:R208) -> 4 | S15: =SUM(S44:S53,S75:S84,S106:S115,S137:S146,S168:S177,S199:S208) -> 4 | T15: =SUM(R15:S15) -> 8 | U15: =R15*$S$19 -> 64 | V15: =S15*$U$19 -> 128 | W15: =SUM(U15:V15) -> 192 | Y15: c | Z15: h | AA15: c | AB15: h | AC15: c | AD15: h | AE15: c | AF15: h | AG15: c | AH15: h | AI15: c | AJ15: h
G16: EFSRT | S16: =SUM(S54,S209) -> 12 | T16: =SUM(R16:S16) -> 12 | V16: =S16*$U$19 -> 384 | W16: =SUM(U16:V16) -> 384 | Y16: I | Z16: I | AA16: II | AB16: II | AC16: III | AD16: III | AE16: IV | AF16: IV | AG16: V | AH16: V | AI16: VI | AJ16: VI
A17: % de créditos prácticos respecto del total de créditos: | C17: =$S$17/$T$17 -> 0.675 | G17: TOTALES | R17: =SUM(R14:R16) -> 13 | S17: =SUM(S14:S16) -> 27 | T17: =SUM(T14:T16) -> 40 | U17: =SUM(U14:U16) -> 208 | V17: =SUM(V14:V16) -> 864 | W17: =SUM(U17:V17) -> 1072 | Y17: =SUM(F24:F54,F55:F84,F86:F115,F117:F146,F148:F177,F179:F208) -> 20 | Z17: =SUM(G24:G54,G55:G84,G86:G115,G117:G146,G148:G177,G179:G208) -> 528 | AA17: =SUM(H24:H53,H55:H85,H86:H115,H117:H146,H148:H177,H179:H208) -> 20 | AB17: =SUM(I24:I53,I55:I85,I86:I115,I117:I146,I148:I177,I179:I208) -> 544 | AC17: =SUM(J24:J53,J55:J84,J86:J116,J117:J146,J148:J177,J179:J208) -> 0 | AD17: =SUM(K24:K53,K55:K84,K86:K116,K117:K146,K148:K177,K179:K208) -> 0 | AE17: =SUM(L24:L53,L55:L84,L86:L115,L117:L147,L148:L177,L179:L208) -> 0 | AF17: =SUM(M24:M53,M55:M84,M86:M115,M117:M147,M148:M177,M179:M208) -> 0 | AG17: =SUM(N24:N53,N55:N84,N86:N115,N117:N146,N148:N177,N179:N208) -> 0 | AH17: =SUM(O24:O53,O55:O84,O86:O115,O117:O146,O148:O177,O179:O208) -> 0 | AI17: =SUM(P24:P53,P55:P84,P86:P115,P117:P146,P148:P177,P179:P208) -> 0 | AJ17: =SUM(Q24:Q53,Q55:Q84,Q86:Q115,Q117:Q146,Q148:Q177,Q179:Q208) -> 0
G19: Equivalencia de un (1) crédito:(4) | R19: HT | S19: 16 | T19: HP | U19: 32
A21: MÓDULO | B21: DESCRIPCION DE LA COMPETENCIA | D21: UNIDAD DIDÁCTICA | F21: Periodos Académicos (créditos y horas) | R21: Créditos Académicos | U21: Horas | X21: Filtro
F22: I(c) | G22: I(h) | H22: II (c) | I22: II (h) | J22: III (c) | K22: III (h) | L22: IV (c) | M22: IV (h) | N22: V (c) | O22: V (h) | P22: VI (c) | Q22: VI (h) | R22: Teóricos | S22: Prácticos | T22: Total | U22: De teoría | V22: Prácticas | W22: Total | X22: =W22 -> Total
F23: I | G23: I | H23: II | I23: II | J23: III | K23: III | L23: IV | M23: IV | N23: V | O23: V | P23: VI | Q23: VI | W23: 0 | X23: =W23 -> 0
A24: =Organización_Modular!A10 -> MÓDULO I: REDACCIÓN Y TRÁMITE DOCUMENTARIO | B24: =Organización_Modular!B10 -> Competencias técnicas (Unidad de competencia) | C24: =Organización_Modular!C10 -> UC1 Proveer información, según políticas y procedimientos de la organización, y normativa correspondiente. | D24: =Organización_Modular!F10 -> Organización del área de trabajo | F24: =_xlfn.IFNA(IF(VLOOKUP($D24,Organización_Modular!$F$10:$G$195,2,FALSE)=F$23,Itinerario!T24," ")," ") -> 2 | G24: =_xlfn.IFNA(IF(VLOOKUP($D24,Organización_Modular!$F$10:$G$195,2,FALSE)=G$23,Itinerario!W24," ")," ") -> 48 | H24: =_xlfn.IFNA(IF(VLOOKUP($D24,Organización_Modular!$F$10:$G$195,2,FALSE)=H$23,Itinerario!T24," ")," ") | I24: =_xlfn.IFNA(IF(VLOOKUP($D24,Organización_Modular!$F$10:$G$195,2,FALSE)=I$23,Itinerario!W24," ")," ") | J24: =_xlfn.IFNA(IF(VLOOKUP($D24,Organización_Modular!$F$10:$G$195,2,FALSE)=J$23,Itinerario!T24," ")," ") | K24: =_xlfn.IFNA(IF(VLOOKUP($D24,Organización_Modular!$F$10:$G$195,2,FALSE)=K$23,Itinerario!W24," ")," ") | L24: =_xlfn.IFNA(IF(VLOOKUP($D24,Organización_Modular!$F$10:$G$195,2,FALSE)=L$23,Itinerario!T24," ")," ") | M24: =_xlfn.IFNA(IF(VLOOKUP($D24,Organización_Modular!$F$10:$G$195,2,FALSE)=M$23,Itinerario!W24," ")," ") | N24: =_xlfn.IFNA(IF(VLOOKUP($D24,Organización_Modular!$F$10:$G$195,2,FALSE)=N$23,Itinerario!T24," ")," ") | O24: =_xlfn.IFNA(IF(VLOOKUP($D24,Organización_Modular!$F$10:$G$195,2,FALSE)=O$23,Itinerario!W24," ")," ") | P24: =_xlfn.IFNA(IF(VLOOKUP($D24,Organización_Modular!$F$10:$G$195,2,FALSE)=P$23,Itinerario!T24," ")," ") | Q24: =_xlfn.IFNA(IF(VLOOKUP($D24,Organización_Modular!$F$10:$G$195,2,FALSE)=Q$23,Itinerario!W24," ")," ") | R24: =Organización_Modular!H10 -> 1 | S24: =Organización_Modular!I10 -> 1 | T24: =SUM(R24:S24) -> 2 | U24: =+R24*$S$19 -> 16 | V24: =+S24*$U$19 -> 32 | W24: =SUM(U24:V24) -> 48 | X24: =W24 -> 48
D25: =Organización_Modular!F11 -> Redacción de documentos | F25: =_xlfn.IFNA(IF(VLOOKUP($D25,Organización_Modular!$F$10:$G$195,2,FALSE)=F$23,Itinerario!T25," ")," ") -> 4 | G25: =_xlfn.IFNA(IF(VLOOKUP($D25,Organización_Modular!$F$10:$G$195,2,FALSE)=G$23,Itinerario!W25," ")," ") -> 96 | H25: =_xlfn.IFNA(IF(VLOOKUP($D25,Organización_Modular!$F$10:$G$195,2,FALSE)=H$23,Itinerario!T25," ")," ") | I25: =_xlfn.IFNA(IF(VLOOKUP($D25,Organización_Modular!$F$10:$G$195,2,FALSE)=I$23,Itinerario!W25," ")," ") | J25: =_xlfn.IFNA(IF(VLOOKUP($D25,Organización_Modular!$F$10:$G$195,2,FALSE)=J$23,Itinerario!T25," ")," ") | K25: =_xlfn.IFNA(IF(VLOOKUP($D25,Organización_Modular!$F$10:$G$195,2,FALSE)=K$23,Itinerario!W25," ")," ") | L25: =_xlfn.IFNA(IF(VLOOKUP($D25,Organización_Modular!$F$10:$G$195,2,FALSE)=L$23,Itinerario!T25," ")," ") | M25: =_xlfn.IFNA(IF(VLOOKUP($D25,Organización_Modular!$F$10:$G$195,2,FALSE)=M$23,Itinerario!W25," ")," ") | N25: =_xlfn.IFNA(IF(VLOOKUP($D25,Organización_Modular!$F$10:$G$195,2,FALSE)=N$23,Itinerario!T25," ")," ") | O25: =_xlfn.IFNA(IF(VLOOKUP($D25,Organización_Modular!$F$10:$G$195,2,FALSE)=O$23,Itinerario!W25," ")," ") | P25: =_xlfn.IFNA(IF(VLOOKUP($D25,Organización_Modular!$F$10:$G$195,2,FALSE)=P$23,Itinerario!T25," ")," ") | Q25: =_xlfn.IFNA(IF(VLOOKUP($D25,Organización_Modular!$F$10:$G$195,2,FALSE)=Q$23,Itinerario!W25," ")," ") | R25: =Organización_Modular!H11 -> 2 | S25: =Organización_Modular!I11 -> 2 | T25: =SUM(R25:S25) -> 4 | U25: =+R25*$S$19 -> 32 | V25: =+S25*$U$19 -> 64 | W25: =SUM(U25:V25) -> 96 | X25: =W25 -> 96
D26: =Organización_Modular!F12 -> Trámite documentario | F26: =_xlfn.IFNA(IF(VLOOKUP($D26,Organización_Modular!$F$10:$G$195,2,FALSE)=F$23,Itinerario!T26," ")," ") -> 4 | G26: =_xlfn.IFNA(IF(VLOOKUP($D26,Organización_Modular!$F$10:$G$195,2,FALSE)=G$23,Itinerario!W26," ")," ") -> 96 | H26: =_xlfn.IFNA(IF(VLOOKUP($D26,Organización_Modular!$F$10:$G$195,2,FALSE)=H$23,Itinerario!T26," ")," ") | I26: =_xlfn.IFNA(IF(VLOOKUP($D26,Organización_Modular!$F$10:$G$195,2,FALSE)=I$23,Itinerario!W26," ")," ") | J26: =_xlfn.IFNA(IF(VLOOKUP($D26,Organización_Modular!$F$10:$G$195,2,FALSE)=J$23,Itinerario!T26," ")," ") | K26: =_xlfn.IFNA(IF(VLOOKUP($D26,Organización_Modular!$F$10:$G$195,2,FALSE)=K$23,Itinerario!W26," ")," ") | L26: =_xlfn.IFNA(IF(VLOOKUP($D26,Organización_Modular!$F$10:$G$195,2,FALSE)=L$23,Itinerario!T26," ")," ") | M26: =_xlfn.IFNA(IF(VLOOKUP($D26,Organización_Modular!$F$10:$G$195,2,FALSE)=M$23,Itinerario!W26," ")," ") | N26: =_xlfn.IFNA(IF(VLOOKUP($D26,Organización_Modular!$F$10:$G$195,2,FALSE)=N$23,Itinerario!T26," ")," ") | O26: =_xlfn.IFNA(IF(VLOOKUP($D26,Organización_Modular!$F$10:$G$195,2,FALSE)=O$23,Itinerario!W26," ")," ") | P26: =_xlfn.IFNA(IF(VLOOKUP($D26,Organización_Modular!$F$10:$G$195,2,FALSE)=P$23,Itinerario!T26," ")," ") | Q26: =_xlfn.IFNA(IF(VLOOKUP($D26,Organización_Modular!$F$10:$G$195,2,FALSE)=Q$23,Itinerario!W26," ")," ") | R26: =Organización_Modular!H12 -> 2 | S26: =Organización_Modular!I12 -> 2 | T26: =SUM(R26:S26) -> 4 | U26: =+R26*$S$19 -> 32 | V26: =+S26*$U$19 -> 64 | W26: =SUM(U26:V26) -> 96 | X26: =W26 -> 96
D27: =Organización_Modular!F13 -> 0 | F27: =_xlfn.IFNA(IF(VLOOKUP($D27,Organización_Modular!$F$10:$G$195,2,FALSE)=F$23,Itinerario!T27," ")," ") | G27: =_xlfn.IFNA(IF(VLOOKUP($D27,Organización_Modular!$F$10:$G$195,2,FALSE)=G$23,Itinerario!W27," ")," ") | H27: =_xlfn.IFNA(IF(VLOOKUP($D27,Organización_Modular!$F$10:$G$195,2,FALSE)=H$23,Itinerario!T27," ")," ") | I27: =_xlfn.IFNA(IF(VLOOKUP($D27,Organización_Modular!$F$10:$G$195,2,FALSE)=I$23,Itinerario!W27," ")," ") | J27: =_xlfn.IFNA(IF(VLOOKUP($D27,Organización_Modular!$F$10:$G$195,2,FALSE)=J$23,Itinerario!T27," ")," ") | K27: =_xlfn.IFNA(IF(VLOOKUP($D27,Organización_Modular!$F$10:$G$195,2,FALSE)=K$23,Itinerario!W27," ")," ") | L27: =_xlfn.IFNA(IF(VLOOKUP($D27,Organización_Modular!$F$10:$G$195,2,FALSE)=L$23,Itinerario!T27," ")," ") | M27: =_xlfn.IFNA(IF(VLOOKUP($D27,Organización_Modular!$F$10:$G$195,2,FALSE)=M$23,Itinerario!W27," ")," ") | N27: =_xlfn.IFNA(IF(VLOOKUP($D27,Organización_Modular!$F$10:$G$195,2,FALSE)=N$23,Itinerario!T27," ")," ") | O27: =_xlfn.IFNA(IF(VLOOKUP($D27,Organización_Modular!$F$10:$G$195,2,FALSE)=O$23,Itinerario!W27," ")," ") | P27: =_xlfn.IFNA(IF(VLOOKUP($D27,Organización_Modular!$F$10:$G$195,2,FALSE)=P$23,Itinerario!T27," ")," ") | Q27: =_xlfn.IFNA(IF(VLOOKUP($D27,Organización_Modular!$F$10:$G$195,2,FALSE)=Q$23,Itinerario!W27," ")," ") | R27: =Organización_Modular!H13 -> 0 | S27: =Organización_Modular!I13 -> 0 | T27: =SUM(R27:S27) -> 0 | U27: =+R27*$S$19 -> 0 | V27: =+S27*$U$19 -> 0 | W27: =SUM(U27:V27) -> 0 | X27: =W27 -> 0
D28: =Organización_Modular!F14 -> 0 | F28: =_xlfn.IFNA(IF(VLOOKUP($D28,Organización_Modular!$F$10:$G$195,2,FALSE)=F$23,Itinerario!T28," ")," ") | G28: =_xlfn.IFNA(IF(VLOOKUP($D28,Organización_Modular!$F$10:$G$195,2,FALSE)=G$23,Itinerario!W28," ")," ") | H28: =_xlfn.IFNA(IF(VLOOKUP($D28,Organización_Modular!$F$10:$G$195,2,FALSE)=H$23,Itinerario!T28," ")," ") | I28: =_xlfn.IFNA(IF(VLOOKUP($D28,Organización_Modular!$F$10:$G$195,2,FALSE)=I$23,Itinerario!W28," ")," ") | J28: =_xlfn.IFNA(IF(VLOOKUP($D28,Organización_Modular!$F$10:$G$195,2,FALSE)=J$23,Itinerario!T28," ")," ") | K28: =_xlfn.IFNA(IF(VLOOKUP($D28,Organización_Modular!$F$10:$G$195,2,FALSE)=K$23,Itinerario!W28," ")," ") | L28: =_xlfn.IFNA(IF(VLOOKUP($D28,Organización_Modular!$F$10:$G$195,2,FALSE)=L$23,Itinerario!T28," ")," ") | M28: =_xlfn.IFNA(IF(VLOOKUP($D28,Organización_Modular!$F$10:$G$195,2,FALSE)=M$23,Itinerario!W28," ")," ") | N28: =_xlfn.IFNA(IF(VLOOKUP($D28,Organización_Modular!$F$10:$G$195,2,FALSE)=N$23,Itinerario!T28," ")," ") | O28: =_xlfn.IFNA(IF(VLOOKUP($D28,Organización_Modular!$F$10:$G$195,2,FALSE)=O$23,Itinerario!W28," ")," ") | P28: =_xlfn.IFNA(IF(VLOOKUP($D28,Organización_Modular!$F$10:$G$195,2,FALSE)=P$23,Itinerario!T28," ")," ") | Q28: =_xlfn.IFNA(IF(VLOOKUP($D28,Organización_Modular!$F$10:$G$195,2,FALSE)=Q$23,Itinerario!W28," ")," ") | R28: =Organización_Modular!H14 -> 0 | S28: =Organización_Modular!I14 -> 0 | T28: =SUM(R28:S28) -> 0 | U28: =+R28*$S$19 -> 0 | V28: =+S28*$U$19 -> 0 | W28: =SUM(U28:V28) -> 0 | X28: =W28 -> 0
D29: =Organización_Modular!F15 -> 0 | F29: =_xlfn.IFNA(IF(VLOOKUP($D29,Organización_Modular!$F$10:$G$195,2,FALSE)=F$23,Itinerario!T29," ")," ") | G29: =_xlfn.IFNA(IF(VLOOKUP($D29,Organización_Modular!$F$10:$G$195,2,FALSE)=G$23,Itinerario!W29," ")," ") | H29: =_xlfn.IFNA(IF(VLOOKUP($D29,Organización_Modular!$F$10:$G$195,2,FALSE)=H$23,Itinerario!T29," ")," ") | I29: =_xlfn.IFNA(IF(VLOOKUP($D29,Organización_Modular!$F$10:$G$195,2,FALSE)=I$23,Itinerario!W29," ")," ") | J29: =_xlfn.IFNA(IF(VLOOKUP($D29,Organización_Modular!$F$10:$G$195,2,FALSE)=J$23,Itinerario!T29," ")," ") | K29: =_xlfn.IFNA(IF(VLOOKUP($D29,Organización_Modular!$F$10:$G$195,2,FALSE)=K$23,Itinerario!W29," ")," ") | L29: =_xlfn.IFNA(IF(VLOOKUP($D29,Organización_Modular!$F$10:$G$195,2,FALSE)=L$23,Itinerario!T29," ")," ") | M29: =_xlfn.IFNA(IF(VLOOKUP($D29,Organización_Modular!$F$10:$G$195,2,FALSE)=M$23,Itinerario!W29," ")," ") | N29: =_xlfn.IFNA(IF(VLOOKUP($D29,Organización_Modular!$F$10:$G$195,2,FALSE)=N$23,Itinerario!T29," ")," ") | O29: =_xlfn.IFNA(IF(VLOOKUP($D29,Organización_Modular!$F$10:$G$195,2,FALSE)=O$23,Itinerario!W29," ")," ") | P29: =_xlfn.IFNA(IF(VLOOKUP($D29,Organización_Modular!$F$10:$G$195,2,FALSE)=P$23,Itinerario!T29," ")," ") | Q29: =_xlfn.IFNA(IF(VLOOKUP($D29,Organización_Modular!$F$10:$G$195,2,FALSE)=Q$23,Itinerario!W29," ")," ") | R29: =Organización_Modular!H15 -> 0 | S29: =Organización_Modular!I15 -> 0 | T29: =SUM(R29:S29) -> 0 | U29: =+R29*$S$19 -> 0 | V29: =+S29*$U$19 -> 0 | W29: =SUM(U29:V29) -> 0 | X29: =W29 -> 0
D30: =Organización_Modular!F16 -> 0 | F30: =_xlfn.IFNA(IF(VLOOKUP($D30,Organización_Modular!$F$10:$G$195,2,FALSE)=F$23,Itinerario!T30," ")," ") | G30: =_xlfn.IFNA(IF(VLOOKUP($D30,Organización_Modular!$F$10:$G$195,2,FALSE)=G$23,Itinerario!W30," ")," ") | H30: =_xlfn.IFNA(IF(VLOOKUP($D30,Organización_Modular!$F$10:$G$195,2,FALSE)=H$23,Itinerario!T30," ")," ") | I30: =_xlfn.IFNA(IF(VLOOKUP($D30,Organización_Modular!$F$10:$G$195,2,FALSE)=I$23,Itinerario!W30," ")," ") | J30: =_xlfn.IFNA(IF(VLOOKUP($D30,Organización_Modular!$F$10:$G$195,2,FALSE)=J$23,Itinerario!T30," ")," ") | K30: =_xlfn.IFNA(IF(VLOOKUP($D30,Organización_Modular!$F$10:$G$195,2,FALSE)=K$23,Itinerario!W30," ")," ") | L30: =_xlfn.IFNA(IF(VLOOKUP($D30,Organización_Modular!$F$10:$G$195,2,FALSE)=L$23,Itinerario!T30," ")," ") | M30: =_xlfn.IFNA(IF(VLOOKUP($D30,Organización_Modular!$F$10:$G$195,2,FALSE)=M$23,Itinerario!W30," ")," ") | N30: =_xlfn.IFNA(IF(VLOOKUP($D30,Organización_Modular!$F$10:$G$195,2,FALSE)=N$23,Itinerario!T30," ")," ") | O30: =_xlfn.IFNA(IF(VLOOKUP($D30,Organización_Modular!$F$10:$G$195,2,FALSE)=O$23,Itinerario!W30," ")," ") | P30: =_xlfn.IFNA(IF(VLOOKUP($D30,Organización_Modular!$F$10:$G$195,2,FALSE)=P$23,Itinerario!T30," ")," ") | Q30: =_xlfn.IFNA(IF(VLOOKUP($D30,Organización_Modular!$F$10:$G$195,2,FALSE)=Q$23,Itinerario!W30," ")," ") | R30: =Organización_Modular!H16 -> 0 | S30: =Organización_Modular!I16 -> 0 | T30: =SUM(R30:S30) -> 0 | U30: =+R30*$S$19 -> 0 | V30: =+S30*$U$19 -> 0 | W30: =SUM(U30:V30) -> 0 | X30: =W30 -> 0
D31: =Organización_Modular!F17 -> 0 | F31: =_xlfn.IFNA(IF(VLOOKUP($D31,Organización_Modular!$F$10:$G$195,2,FALSE)=F$23,Itinerario!T31," ")," ") | G31: =_xlfn.IFNA(IF(VLOOKUP($D31,Organización_Modular!$F$10:$G$195,2,FALSE)=G$23,Itinerario!W31," ")," ") | H31: =_xlfn.IFNA(IF(VLOOKUP($D31,Organización_Modular!$F$10:$G$195,2,FALSE)=H$23,Itinerario!T31," ")," ") | I31: =_xlfn.IFNA(IF(VLOOKUP($D31,Organización_Modular!$F$10:$G$195,2,FALSE)=I$23,Itinerario!W31," ")," ") | J31: =_xlfn.IFNA(IF(VLOOKUP($D31,Organización_Modular!$F$10:$G$195,2,FALSE)=J$23,Itinerario!T31," ")," ") | K31: =_xlfn.IFNA(IF(VLOOKUP($D31,Organización_Modular!$F$10:$G$195,2,FALSE)=K$23,Itinerario!W31," ")," ") | L31: =_xlfn.IFNA(IF(VLOOKUP($D31,Organización_Modular!$F$10:$G$195,2,FALSE)=L$23,Itinerario!T31," ")," ") | M31: =_xlfn.IFNA(IF(VLOOKUP($D31,Organización_Modular!$F$10:$G$195,2,FALSE)=M$23,Itinerario!W31," ")," ") | N31: =_xlfn.IFNA(IF(VLOOKUP($D31,Organización_Modular!$F$10:$G$195,2,FALSE)=N$23,Itinerario!T31," ")," ") | O31: =_xlfn.IFNA(IF(VLOOKUP($D31,Organización_Modular!$F$10:$G$195,2,FALSE)=O$23,Itinerario!W31," ")," ") | P31: =_xlfn.IFNA(IF(VLOOKUP($D31,Organización_Modular!$F$10:$G$195,2,FALSE)=P$23,Itinerario!T31," ")," ") | Q31: =_xlfn.IFNA(IF(VLOOKUP($D31,Organización_Modular!$F$10:$G$195,2,FALSE)=Q$23,Itinerario!W31," ")," ") | R31: =Organización_Modular!H17 -> 0 | S31: =Organización_Modular!I17 -> 0 | T31: =SUM(R31:S31) -> 0 | U31: =+R31*$S$19 -> 0 | V31: =+S31*$U$19 -> 0 | W31: =SUM(U31:V31) -> 0 | X31: =W31 -> 0
D32: =Organización_Modular!F18 -> 0 | F32: =_xlfn.IFNA(IF(VLOOKUP($D32,Organización_Modular!$F$10:$G$195,2,FALSE)=F$23,Itinerario!T32," ")," ") | G32: =_xlfn.IFNA(IF(VLOOKUP($D32,Organización_Modular!$F$10:$G$195,2,FALSE)=G$23,Itinerario!W32," ")," ") | H32: =_xlfn.IFNA(IF(VLOOKUP($D32,Organización_Modular!$F$10:$G$195,2,FALSE)=H$23,Itinerario!T32," ")," ") | I32: =_xlfn.IFNA(IF(VLOOKUP($D32,Organización_Modular!$F$10:$G$195,2,FALSE)=I$23,Itinerario!W32," ")," ") | J32: =_xlfn.IFNA(IF(VLOOKUP($D32,Organización_Modular!$F$10:$G$195,2,FALSE)=J$23,Itinerario!T32," ")," ") | K32: =_xlfn.IFNA(IF(VLOOKUP($D32,Organización_Modular!$F$10:$G$195,2,FALSE)=K$23,Itinerario!W32," ")," ") | L32: =_xlfn.IFNA(IF(VLOOKUP($D32,Organización_Modular!$F$10:$G$195,2,FALSE)=L$23,Itinerario!T32," ")," ") | M32: =_xlfn.IFNA(IF(VLOOKUP($D32,Organización_Modular!$F$10:$G$195,2,FALSE)=M$23,Itinerario!W32," ")," ") | N32: =_xlfn.IFNA(IF(VLOOKUP($D32,Organización_Modular!$F$10:$G$195,2,FALSE)=N$23,Itinerario!T32," ")," ") | O32: =_xlfn.IFNA(IF(VLOOKUP($D32,Organización_Modular!$F$10:$G$195,2,FALSE)=O$23,Itinerario!W32," ")," ") | P32: =_xlfn.IFNA(IF(VLOOKUP($D32,Organización_Modular!$F$10:$G$195,2,FALSE)=P$23,Itinerario!T32," ")," ") | Q32: =_xlfn.IFNA(IF(VLOOKUP($D32,Organización_Modular!$F$10:$G$195,2,FALSE)=Q$23,Itinerario!W32," ")," ") | R32: =Organización_Modular!H18 -> 0 | S32: =Organización_Modular!I18 -> 0 | T32: =SUM(R32:S32) -> 0 | U32: =+R32*$S$19 -> 0 | V32: =+S32*$U$19 -> 0 | W32: =SUM(U32:V32) -> 0 | X32: =W32 -> 0
D33: =Organización_Modular!F19 -> 0 | F33: =_xlfn.IFNA(IF(VLOOKUP($D33,Organización_Modular!$F$10:$G$195,2,FALSE)=F$23,Itinerario!T33," ")," ") | G33: =_xlfn.IFNA(IF(VLOOKUP($D33,Organización_Modular!$F$10:$G$195,2,FALSE)=G$23,Itinerario!W33," ")," ") | H33: =_xlfn.IFNA(IF(VLOOKUP($D33,Organización_Modular!$F$10:$G$195,2,FALSE)=H$23,Itinerario!T33," ")," ") | I33: =_xlfn.IFNA(IF(VLOOKUP($D33,Organización_Modular!$F$10:$G$195,2,FALSE)=I$23,Itinerario!W33," ")," ") | J33: =_xlfn.IFNA(IF(VLOOKUP($D33,Organización_Modular!$F$10:$G$195,2,FALSE)=J$23,Itinerario!T33," ")," ") | K33: =_xlfn.IFNA(IF(VLOOKUP($D33,Organización_Modular!$F$10:$G$195,2,FALSE)=K$23,Itinerario!W33," ")," ") | L33: =_xlfn.IFNA(IF(VLOOKUP($D33,Organización_Modular!$F$10:$G$195,2,FALSE)=L$23,Itinerario!T33," ")," ") | M33: =_xlfn.IFNA(IF(VLOOKUP($D33,Organización_Modular!$F$10:$G$195,2,FALSE)=M$23,Itinerario!W33," ")," ") | N33: =_xlfn.IFNA(IF(VLOOKUP($D33,Organización_Modular!$F$10:$G$195,2,FALSE)=N$23,Itinerario!T33," ")," ") | O33: =_xlfn.IFNA(IF(VLOOKUP($D33,Organización_Modular!$F$10:$G$195,2,FALSE)=O$23,Itinerario!W33," ")," ") | P33: =_xlfn.IFNA(IF(VLOOKUP($D33,Organización_Modular!$F$10:$G$195,2,FALSE)=P$23,Itinerario!T33," ")," ") | Q33: =_xlfn.IFNA(IF(VLOOKUP($D33,Organización_Modular!$F$10:$G$195,2,FALSE)=Q$23,Itinerario!W33," ")," ") | R33: =Organización_Modular!H19 -> 0 | S33: =Organización_Modular!I19 -> 0 | T33: =SUM(R33:S33) -> 0 | U33: =+R33*$S$19 -> 0 | V33: =+S33*$U$19 -> 0 | W33: =SUM(U33:V33) -> 0 | X33: =W33 -> 0
D34: =Organización_Modular!F20 -> 0 | F34: =_xlfn.IFNA(IF(VLOOKUP($D34,Organización_Modular!$F$10:$G$195,2,FALSE)=F$23,Itinerario!T34," ")," ") | G34: =_xlfn.IFNA(IF(VLOOKUP($D34,Organización_Modular!$F$10:$G$195,2,FALSE)=G$23,Itinerario!W34," ")," ") | H34: =_xlfn.IFNA(IF(VLOOKUP($D34,Organización_Modular!$F$10:$G$195,2,FALSE)=H$23,Itinerario!T34," ")," ") | I34: =_xlfn.IFNA(IF(VLOOKUP($D34,Organización_Modular!$F$10:$G$195,2,FALSE)=I$23,Itinerario!W34," ")," ") | J34: =_xlfn.IFNA(IF(VLOOKUP($D34,Organización_Modular!$F$10:$G$195,2,FALSE)=J$23,Itinerario!T34," ")," ") | K34: =_xlfn.IFNA(IF(VLOOKUP($D34,Organización_Modular!$F$10:$G$195,2,FALSE)=K$23,Itinerario!W34," ")," ") | L34: =_xlfn.IFNA(IF(VLOOKUP($D34,Organización_Modular!$F$10:$G$195,2,FALSE)=L$23,Itinerario!T34," ")," ") | M34: =_xlfn.IFNA(IF(VLOOKUP($D34,Organización_Modular!$F$10:$G$195,2,FALSE)=M$23,Itinerario!W34," ")," ") | N34: =_xlfn.IFNA(IF(VLOOKUP($D34,Organización_Modular!$F$10:$G$195,2,FALSE)=N$23,Itinerario!T34," ")," ") | O34: =_xlfn.IFNA(IF(VLOOKUP($D34,Organización_Modular!$F$10:$G$195,2,FALSE)=O$23,Itinerario!W34," ")," ") | P34: =_xlfn.IFNA(IF(VLOOKUP($D34,Organización_Modular!$F$10:$G$195,2,FALSE)=P$23,Itinerario!T34," ")," ") | Q34: =_xlfn.IFNA(IF(VLOOKUP($D34,Organización_Modular!$F$10:$G$195,2,FALSE)=Q$23,Itinerario!W34," ")," ") | R34: =Organización_Modular!H20 -> 0 | S34: =Organización_Modular!I20 -> 0 | T34: =SUM(R34:S34) -> 0 | U34: =+R34*$S$19 -> 0 | V34: =+S34*$U$19 -> 0 | W34: =SUM(U34:V34) -> 0 | X34: =W34 -> 0
D35: =Organización_Modular!F21 -> 0 | F35: =_xlfn.IFNA(IF(VLOOKUP($D35,Organización_Modular!$F$10:$G$195,2,FALSE)=F$23,Itinerario!T35," ")," ") | G35: =_xlfn.IFNA(IF(VLOOKUP($D35,Organización_Modular!$F$10:$G$195,2,FALSE)=G$23,Itinerario!W35," ")," ") | H35: =_xlfn.IFNA(IF(VLOOKUP($D35,Organización_Modular!$F$10:$G$195,2,FALSE)=H$23,Itinerario!T35," ")," ") | I35: =_xlfn.IFNA(IF(VLOOKUP($D35,Organización_Modular!$F$10:$G$195,2,FALSE)=I$23,Itinerario!W35," ")," ") | J35: =_xlfn.IFNA(IF(VLOOKUP($D35,Organización_Modular!$F$10:$G$195,2,FALSE)=J$23,Itinerario!T35," ")," ") | K35: =_xlfn.IFNA(IF(VLOOKUP($D35,Organización_Modular!$F$10:$G$195,2,FALSE)=K$23,Itinerario!W35," ")," ") | L35: =_xlfn.IFNA(IF(VLOOKUP($D35,Organización_Modular!$F$10:$G$195,2,FALSE)=L$23,Itinerario!T35," ")," ") | M35: =_xlfn.IFNA(IF(VLOOKUP($D35,Organización_Modular!$F$10:$G$195,2,FALSE)=M$23,Itinerario!W35," ")," ") | N35: =_xlfn.IFNA(IF(VLOOKUP($D35,Organización_Modular!$F$10:$G$195,2,FALSE)=N$23,Itinerario!T35," ")," ") | O35: =_xlfn.IFNA(IF(VLOOKUP($D35,Organización_Modular!$F$10:$G$195,2,FALSE)=O$23,Itinerario!W35," ")," ") | P35: =_xlfn.IFNA(IF(VLOOKUP($D35,Organización_Modular!$F$10:$G$195,2,FALSE)=P$23,Itinerario!T35," ")," ") | Q35: =_xlfn.IFNA(IF(VLOOKUP($D35,Organización_Modular!$F$10:$G$195,2,FALSE)=Q$23,Itinerario!W35," ")," ") | R35: =Organización_Modular!H21 -> 0 | S35: =Organización_Modular!I21 -> 0 | T35: =SUM(R35:S35) -> 0 | U35: =+R35*$S$19 -> 0 | V35: =+S35*$U$19 -> 0 | W35: =SUM(U35:V35) -> 0 | X35: =W35 -> 0
D36: =Organización_Modular!F22 -> 0 | F36: =_xlfn.IFNA(IF(VLOOKUP($D36,Organización_Modular!$F$10:$G$195,2,FALSE)=F$23,Itinerario!T36," ")," ") | G36: =_xlfn.IFNA(IF(VLOOKUP($D36,Organización_Modular!$F$10:$G$195,2,FALSE)=G$23,Itinerario!W36," ")," ") | H36: =_xlfn.IFNA(IF(VLOOKUP($D36,Organización_Modular!$F$10:$G$195,2,FALSE)=H$23,Itinerario!T36," ")," ") | I36: =_xlfn.IFNA(IF(VLOOKUP($D36,Organización_Modular!$F$10:$G$195,2,FALSE)=I$23,Itinerario!W36," ")," ") | J36: =_xlfn.IFNA(IF(VLOOKUP($D36,Organización_Modular!$F$10:$G$195,2,FALSE)=J$23,Itinerario!T36," ")," ") | K36: =_xlfn.IFNA(IF(VLOOKUP($D36,Organización_Modular!$F$10:$G$195,2,FALSE)=K$23,Itinerario!W36," ")," ") | L36: =_xlfn.IFNA(IF(VLOOKUP($D36,Organización_Modular!$F$10:$G$195,2,FALSE)=L$23,Itinerario!T36," ")," ") | M36: =_xlfn.IFNA(IF(VLOOKUP($D36,Organización_Modular!$F$10:$G$195,2,FALSE)=M$23,Itinerario!W36," ")," ") | N36: =_xlfn.IFNA(IF(VLOOKUP($D36,Organización_Modular!$F$10:$G$195,2,FALSE)=N$23,Itinerario!T36," ")," ") | O36: =_xlfn.IFNA(IF(VLOOKUP($D36,Organización_Modular!$F$10:$G$195,2,FALSE)=O$23,Itinerario!W36," ")," ") | P36: =_xlfn.IFNA(IF(VLOOKUP($D36,Organización_Modular!$F$10:$G$195,2,FALSE)=P$23,Itinerario!T36," ")," ") | Q36: =_xlfn.IFNA(IF(VLOOKUP($D36,Organización_Modular!$F$10:$G$195,2,FALSE)=Q$23,Itinerario!W36," ")," ") | R36: =Organización_Modular!H22 -> 0 | S36: =Organización_Modular!I22 -> 0 | T36: =SUM(R36:S36) -> 0 | U36: =+R36*$S$19 -> 0 | V36: =+S36*$U$19 -> 0 | W36: =SUM(U36:V36) -> 0 | X36: =W36 -> 0
... D43: =Organización_Modular!F29 -> 0 | F43: =_xlfn.IFNA(IF(VLOOKUP($D43,Organización_Modular!$F$10:$G$195,2,FALSE)=F$23,Itinerario!T43," ")," ") | G43: =_xlfn.IFNA(IF(VLOOKUP($D43,Organización_Modular!$F$10:$G$195,2,FALSE)=G$23,Itinerario!W43," ")," ") | H43: =_xlfn.IFNA(IF(VLOOKUP($D43,Organización_Modular!$F$10:$G$195,2,FALSE)=H$23,Itinerario!T43," ")," ") | I43: =_xlfn.IFNA(IF(VLOOKUP($D43,Organización_Modular!$F$10:$G$195,2,FALSE)=I$23,Itinerario!W43," ")," ") | J43: =_xlfn.IFNA(IF(VLOOKUP($D43,Organización_Modular!$F$10:$G$195,2,FALSE)=J$23,Itinerario!T43," ")," ") | K43: =_xlfn.IFNA(IF(VLOOKUP($D43,Organización_Modular!$F$10:$G$195,2,FALSE)=K$23,Itinerario!W43," ")," ") | L43: =_xlfn.IFNA(IF(VLOOKUP($D43,Organización_Modular!$F$10:$G$195,2,FALSE)=L$23,Itinerario!T43," ")," ") | M43: =_xlfn.IFNA(IF(VLOOKUP($D43,Organización_Modular!$F$10:$G$195,2,FALSE)=M$23,Itinerario!W43," ")," ") | N43: =_xlfn.IFNA(IF(VLOOKUP($D43,Organización_Modular!$F$10:$G$195,2,FALSE)=N$23,Itinerario!T43," ")," ") | O43: =_xlfn.IFNA(IF(VLOOKUP($D43,Organización_Modular!$F$10:$G$195,2,FALSE)=O$23,Itinerario!W43," ")," ") | P43: =_xlfn.IFNA(IF(VLOOKUP($D43,Organización_Modular!$F$10:$G$195,2,FALSE)=P$23,Itinerario!T43," ")," ") | Q43: =_xlfn.IFNA(IF(VLOOKUP($D43,Organización_Modular!$F$10:$G$195,2,FALSE)=Q$23,Itinerario!W43," ")," ") | R43: =Organización_Modular!H29 -> 0 | S43: =Organización_Modular!I29 -> 0 | T43: =SUM(R43:S43) -> 0 | U43: =+R43*$S$19 -> 0 | V43: =+S43*$U$19 -> 0 | W43: =SUM(U43:V43) -> 0 | X43: =W43 -> 0
B44: =Organización_Modular!B30 -> Competencias para la empleabilidad | C44: =Organización_Modular!C30 -> CE1 Comunicación efectiva. - Expresar de manera clara los conceptos, ideas, sentimientos, hechos y opiniones en forma oral y escrita para comunicarse e interactuar con otras personas en contextos sociales y laborales diversos. (UD) CE2 Tecnologías de la información. - Manejar herramientas informáticas de las TIC para buscar y analizar información, Comunicarse y realizar procedimientos o tareas vinculadas al área profesional, de acuerdo a los requerimientos de su entorno laboral. (UD) | D44: =Organización_Modular!F30 -> Comunicación para el desarrollo personal y profesional | F44: =_xlfn.IFNA(IF(VLOOKUP($D44,Organización_Modular!$F$10:$G$195,2,FALSE)=F$23,Itinerario!T44," ")," ") -> 2 | G44: =_xlfn.IFNA(IF(VLOOKUP($D44,Organización_Modular!$F$10:$G$195,2,FALSE)=G$23,Itinerario!W44," ")," ") -> 48 | H44: =_xlfn.IFNA(IF(VLOOKUP($D44,Organización_Modular!$F$10:$G$195,2,FALSE)=H$23,Itinerario!T44," ")," ") | I44: =_xlfn.IFNA(IF(VLOOKUP($D44,Organización_Modular!$F$10:$G$195,2,FALSE)=I$23,Itinerario!W44," ")," ") | J44: =_xlfn.IFNA(IF(VLOOKUP($D44,Organización_Modular!$F$10:$G$195,2,FALSE)=J$23,Itinerario!T44," ")," ") | K44: =_xlfn.IFNA(IF(VLOOKUP($D44,Organización_Modular!$F$10:$G$195,2,FALSE)=K$23,Itinerario!W44," ")," ") | L44: =_xlfn.IFNA(IF(VLOOKUP($D44,Organización_Modular!$F$10:$G$195,2,FALSE)=L$23,Itinerario!T44," ")," ") | M44: =_xlfn.IFNA(IF(VLOOKUP($D44,Organización_Modular!$F$10:$G$195,2,FALSE)=M$23,Itinerario!W44," ")," ") | N44: =_xlfn.IFNA(IF(VLOOKUP($D44,Organización_Modular!$F$10:$G$195,2,FALSE)=N$23,Itinerario!T44," ")," ") | O44: =_xlfn.IFNA(IF(VLOOKUP($D44,Organización_Modular!$F$10:$G$195,2,FALSE)=O$23,Itinerario!W44," ")," ") | P44: =_xlfn.IFNA(IF(VLOOKUP($D44,Organización_Modular!$F$10:$G$195,2,FALSE)=P$23,Itinerario!T44," ")," ") | Q44: =_xlfn.IFNA(IF(VLOOKUP($D44,Organización_Modular!$F$10:$G$195,2,FALSE)=Q$23,Itinerario!W44," ")," ") | R44: =Organización_Modular!H30 -> 1 | S44: =Organización_Modular!I30 -> 1 | T44: =SUM(R44:S44) -> 2 | U44: =+R44*$S$19 -> 16 | V44: =+S44*$U$19 -> 32 | W44: =SUM(U44:V44) -> 48 | X44: =W44 -> 48
D45: =Organización_Modular!F31 -> Aplicaciones de herramientas informáticas | F45: =_xlfn.IFNA(IF(VLOOKUP($D45,Organización_Modular!$F$10:$G$195,2,FALSE)=F$23,Itinerario!T45," ")," ") -> 2 | G45: =_xlfn.IFNA(IF(VLOOKUP($D45,Organización_Modular!$F$10:$G$195,2,FALSE)=G$23,Itinerario!W45," ")," ") -> 48 | H45: =_xlfn.IFNA(IF(VLOOKUP($D45,Organización_Modular!$F$10:$G$195,2,FALSE)=H$23,Itinerario!T45," ")," ") | I45: =_xlfn.IFNA(IF(VLOOKUP($D45,Organización_Modular!$F$10:$G$195,2,FALSE)=I$23,Itinerario!W45," ")," ") | J45: =_xlfn.IFNA(IF(VLOOKUP($D45,Organización_Modular!$F$10:$G$195,2,FALSE)=J$23,Itinerario!T45," ")," ") | K45: =_xlfn.IFNA(IF(VLOOKUP($D45,Organización_Modular!$F$10:$G$195,2,FALSE)=K$23,Itinerario!W45," ")," ") | L45: =_xlfn.IFNA(IF(VLOOKUP($D45,Organización_Modular!$F$10:$G$195,2,FALSE)=L$23,Itinerario!T45," ")," ") | M45: =_xlfn.IFNA(IF(VLOOKUP($D45,Organización_Modular!$F$10:$G$195,2,FALSE)=M$23,Itinerario!W45," ")," ") | N45: =_xlfn.IFNA(IF(VLOOKUP($D45,Organización_Modular!$F$10:$G$195,2,FALSE)=N$23,Itinerario!T45," ")," ") | O45: =_xlfn.IFNA(IF(VLOOKUP($D45,Organización_Modular!$F$10:$G$195,2,FALSE)=O$23,Itinerario!W45," ")," ") | P45: =_xlfn.IFNA(IF(VLOOKUP($D45,Organización_Modular!$F$10:$G$195,2,FALSE)=P$23,Itinerario!T45," ")," ") | Q45: =_xlfn.IFNA(IF(VLOOKUP($D45,Organización_Modular!$F$10:$G$195,2,FALSE)=Q$23,Itinerario!W45," ")," ") | R45: =Organización_Modular!H31 -> 1 | S45: =Organización_Modular!I31 -> 1 | T45: =SUM(R45:S45) -> 2 | U45: =+R45*$S$19 -> 16 | V45: =+S45*$U$19 -> 32 | W45: =SUM(U45:V45) -> 48 | X45: =W45 -> 48
D46: =Organización_Modular!F32 -> 0 | F46: =_xlfn.IFNA(IF(VLOOKUP($D46,Organización_Modular!$F$10:$G$195,2,FALSE)=F$23,Itinerario!T46," ")," ") | G46: =_xlfn.IFNA(IF(VLOOKUP($D46,Organización_Modular!$F$10:$G$195,2,FALSE)=G$23,Itinerario!W46," ")," ") | H46: =_xlfn.IFNA(IF(VLOOKUP($D46,Organización_Modular!$F$10:$G$195,2,FALSE)=H$23,Itinerario!T46," ")," ") | I46: =_xlfn.IFNA(IF(VLOOKUP($D46,Organización_Modular!$F$10:$G$195,2,FALSE)=I$23,Itinerario!W46," ")," ") | J46: =_xlfn.IFNA(IF(VLOOKUP($D46,Organización_Modular!$F$10:$G$195,2,FALSE)=J$23,Itinerario!T46," ")," ") | K46: =_xlfn.IFNA(IF(VLOOKUP($D46,Organización_Modular!$F$10:$G$195,2,FALSE)=K$23,Itinerario!W46," ")," ") | L46: =_xlfn.IFNA(IF(VLOOKUP($D46,Organización_Modular!$F$10:$G$195,2,FALSE)=L$23,Itinerario!T46," ")," ") | M46: =_xlfn.IFNA(IF(VLOOKUP($D46,Organización_Modular!$F$10:$G$195,2,FALSE)=M$23,Itinerario!W46," ")," ") | N46: =_xlfn.IFNA(IF(VLOOKUP($D46,Organización_Modular!$F$10:$G$195,2,FALSE)=N$23,Itinerario!T46," ")," ") | O46: =_xlfn.IFNA(IF(VLOOKUP($D46,Organización_Modular!$F$10:$G$195,2,FALSE)=O$23,Itinerario!W46," ")," ") | P46: =_xlfn.IFNA(IF(VLOOKUP($D46,Organización_Modular!$F$10:$G$195,2,FALSE)=P$23,Itinerario!T46," ")," ") | Q46: =_xlfn.IFNA(IF(VLOOKUP($D46,Organización_Modular!$F$10:$G$195,2,FALSE)=Q$23,Itinerario!W46," ")," ") | R46: =Organización_Modular!H32 -> 0 | S46: =Organización_Modular!I32 -> 0 | T46: =SUM(R46:S46) -> 0 | U46: =+R46*$S$19 -> 0 | V46: =+S46*$U$19 -> 0 | W46: =SUM(U46:V46) -> 0 | X46: =W46 -> 0
D47: =Organización_Modular!F33 -> 0 | F47: =_xlfn.IFNA(IF(VLOOKUP($D47,Organización_Modular!$F$10:$G$195,2,FALSE)=F$23,Itinerario!T47," ")," ") | G47: =_xlfn.IFNA(IF(VLOOKUP($D47,Organización_Modular!$F$10:$G$195,2,FALSE)=G$23,Itinerario!W47," ")," ") | H47: =_xlfn.IFNA(IF(VLOOKUP($D47,Organización_Modular!$F$10:$G$195,2,FALSE)=H$23,Itinerario!T47," ")," ") | I47: =_xlfn.IFNA(IF(VLOOKUP($D47,Organización_Modular!$F$10:$G$195,2,FALSE)=I$23,Itinerario!W47," ")," ") | J47: =_xlfn.IFNA(IF(VLOOKUP($D47,Organización_Modular!$F$10:$G$195,2,FALSE)=J$23,Itinerario!T47," ")," ") | K47: =_xlfn.IFNA(IF(VLOOKUP($D47,Organización_Modular!$F$10:$G$195,2,FALSE)=K$23,Itinerario!W47," ")," ") | L47: =_xlfn.IFNA(IF(VLOOKUP($D47,Organización_Modular!$F$10:$G$195,2,FALSE)=L$23,Itinerario!T47," ")," ") | M47: =_xlfn.IFNA(IF(VLOOKUP($D47,Organización_Modular!$F$10:$G$195,2,FALSE)=M$23,Itinerario!W47," ")," ") | N47: =_xlfn.IFNA(IF(VLOOKUP($D47,Organización_Modular!$F$10:$G$195,2,FALSE)=N$23,Itinerario!T47," ")," ") | O47: =_xlfn.IFNA(IF(VLOOKUP($D47,Organización_Modular!$F$10:$G$195,2,FALSE)=O$23,Itinerario!W47," ")," ") | P47: =_xlfn.IFNA(IF(VLOOKUP($D47,Organización_Modular!$F$10:$G$195,2,FALSE)=P$23,Itinerario!T47," ")," ") | Q47: =_xlfn.IFNA(IF(VLOOKUP($D47,Organización_Modular!$F$10:$G$195,2,FALSE)=Q$23,Itinerario!W47," ")," ") | R47: =Organización_Modular!H33 -> 0 | S47: =Organización_Modular!I33 -> 0 | T47: =SUM(R47:S47) -> 0 | U47: =+R47*$S$19 -> 0 | V47: =+S47*$U$19 -> 0 | W47: =SUM(U47:V47) -> 0 | X47: =W47 -> 0
D48: =Organización_Modular!F34 -> 0 | F48: =_xlfn.IFNA(IF(VLOOKUP($D48,Organización_Modular!$F$10:$G$195,2,FALSE)=F$23,Itinerario!T48," ")," ") | G48: =_xlfn.IFNA(IF(VLOOKUP($D48,Organización_Modular!$F$10:$G$195,2,FALSE)=G$23,Itinerario!W48," ")," ") | H48: =_xlfn.IFNA(IF(VLOOKUP($D48,Organización_Modular!$F$10:$G$195,2,FALSE)=H$23,Itinerario!T48," ")," ") | I48: =_xlfn.IFNA(IF(VLOOKUP($D48,Organización_Modular!$F$10:$G$195,2,FALSE)=I$23,Itinerario!W48," ")," ") | J48: =_xlfn.IFNA(IF(VLOOKUP($D48,Organización_Modular!$F$10:$G$195,2,FALSE)=J$23,Itinerario!T48," ")," ") | K48: =_xlfn.IFNA(IF(VLOOKUP($D48,Organización_Modular!$F$10:$G$195,2,FALSE)=K$23,Itinerario!W48," ")," ") | L48: =_xlfn.IFNA(IF(VLOOKUP($D48,Organización_Modular!$F$10:$G$195,2,FALSE)=L$23,Itinerario!T48," ")," ") | M48: =_xlfn.IFNA(IF(VLOOKUP($D48,Organización_Modular!$F$10:$G$195,2,FALSE)=M$23,Itinerario!W48," ")," ") | N48: =_xlfn.IFNA(IF(VLOOKUP($D48,Organización_Modular!$F$10:$G$195,2,FALSE)=N$23,Itinerario!T48," ")," ") | O48: =_xlfn.IFNA(IF(VLOOKUP($D48,Organización_Modular!$F$10:$G$195,2,FALSE)=O$23,Itinerario!W48," ")," ") | P48: =_xlfn.IFNA(IF(VLOOKUP($D48,Organización_Modular!$F$10:$G$195,2,FALSE)=P$23,Itinerario!T48," ")," ") | Q48: =_xlfn.IFNA(IF(VLOOKUP($D48,Organización_Modular!$F$10:$G$195,2,FALSE)=Q$23,Itinerario!W48," ")," ") | R48: =Organización_Modular!H34 -> 0 | S48: =Organización_Modular!I34 -> 0 | T48: =SUM(R48:S48) -> 0 | U48: =+R48*$S$19 -> 0 | V48: =+S48*$U$19 -> 0 | W48: =SUM(U48:V48) -> 0 | X48: =W48 -> 0
D49: =Organización_Modular!F35 -> 0 | F49: =_xlfn.IFNA(IF(VLOOKUP($D49,Organización_Modular!$F$10:$G$195,2,FALSE)=F$23,Itinerario!T49," ")," ") | G49: =_xlfn.IFNA(IF(VLOOKUP($D49,Organización_Modular!$F$10:$G$195,2,FALSE)=G$23,Itinerario!W49," ")," ") | H49: =_xlfn.IFNA(IF(VLOOKUP($D49,Organización_Modular!$F$10:$G$195,2,FALSE)=H$23,Itinerario!T49," ")," ") | I49: =_xlfn.IFNA(IF(VLOOKUP($D49,Organización_Modular!$F$10:$G$195,2,FALSE)=I$23,Itinerario!W49," ")," ") | J49: =_xlfn.IFNA(IF(VLOOKUP($D49,Organización_Modular!$F$10:$G$195,2,FALSE)=J$23,Itinerario!T49," ")," ") | K49: =_xlfn.IFNA(IF(VLOOKUP($D49,Organización_Modular!$F$10:$G$195,2,FALSE)=K$23,Itinerario!W49," ")," ") | L49: =_xlfn.IFNA(IF(VLOOKUP($D49,Organización_Modular!$F$10:$G$195,2,FALSE)=L$23,Itinerario!T49," ")," ") | M49: =_xlfn.IFNA(IF(VLOOKUP($D49,Organización_Modular!$F$10:$G$195,2,FALSE)=M$23,Itinerario!W49," ")," ") | N49: =_xlfn.IFNA(IF(VLOOKUP($D49,Organización_Modular!$F$10:$G$195,2,FALSE)=N$23,Itinerario!T49," ")," ") | O49: =_xlfn.IFNA(IF(VLOOKUP($D49,Organización_Modular!$F$10:$G$195,2,FALSE)=O$23,Itinerario!W49," ")," ") | P49: =_xlfn.IFNA(IF(VLOOKUP($D49,Organización_Modular!$F$10:$G$195,2,FALSE)=P$23,Itinerario!T49," ")," ") | Q49: =_xlfn.IFNA(IF(VLOOKUP($D49,Organización_Modular!$F$10:$G$195,2,FALSE)=Q$23,Itinerario!W49," ")," ") | R49: =Organización_Modular!H35 -> 0 | S49: =Organización_Modular!I35 -> 0 | T49: =SUM(R49:S49) -> 0 | U49: =+R49*$S$19 -> 0 | V49: =+S49*$U$19 -> 0 | W49: =SUM(U49:V49) -> 0 | X49: =W49 -> 0
D50: =Organización_Modular!F36 -> 0 | F50: =_xlfn.IFNA(IF(VLOOKUP($D50,Organización_Modular!$F$10:$G$195,2,FALSE)=F$23,Itinerario!T50," ")," ") | G50: =_xlfn.IFNA(IF(VLOOKUP($D50,Organización_Modular!$F$10:$G$195,2,FALSE)=G$23,Itinerario!W50," ")," ") | H50: =_xlfn.IFNA(IF(VLOOKUP($D50,Organización_Modular!$F$10:$G$195,2,FALSE)=H$23,Itinerario!T50," ")," ") | I50: =_xlfn.IFNA(IF(VLOOKUP($D50,Organización_Modular!$F$10:$G$195,2,FALSE)=I$23,Itinerario!W50," ")," ") | J50: =_xlfn.IFNA(IF(VLOOKUP($D50,Organización_Modular!$F$10:$G$195,2,FALSE)=J$23,Itinerario!T50," ")," ") | K50: =_xlfn.IFNA(IF(VLOOKUP($D50,Organización_Modular!$F$10:$G$195,2,FALSE)=K$23,Itinerario!W50," ")," ") | L50: =_xlfn.IFNA(IF(VLOOKUP($D50,Organización_Modular!$F$10:$G$195,2,FALSE)=L$23,Itinerario!T50," ")," ") | M50: =_xlfn.IFNA(IF(VLOOKUP($D50,Organización_Modular!$F$10:$G$195,2,FALSE)=M$23,Itinerario!W50," ")," ") | N50: =_xlfn.IFNA(IF(VLOOKUP($D50,Organización_Modular!$F$10:$G$195,2,FALSE)=N$23,Itinerario!T50," ")," ") | O50: =_xlfn.IFNA(IF(VLOOKUP($D50,Organización_Modular!$F$10:$G$195,2,FALSE)=O$23,Itinerario!W50," ")," ") | P50: =_xlfn.IFNA(IF(VLOOKUP($D50,Organización_Modular!$F$10:$G$195,2,FALSE)=P$23,Itinerario!T50," ")," ") | Q50: =_xlfn.IFNA(IF(VLOOKUP($D50,Organización_Modular!$F$10:$G$195,2,FALSE)=Q$23,Itinerario!W50," ")," ") | R50: =Organización_Modular!H36 -> 0 | S50: =Organización_Modular!I36 -> 0 | T50: =SUM(R50:S50) -> 0 | U50: =+R50*$S$19 -> 0 | V50: =+S50*$U$19 -> 0 | W50: =SUM(U50:V50) -> 0 | X50: =W50 -> 0
D51: =Organización_Modular!F37 -> 0 | F51: =_xlfn.IFNA(IF(VLOOKUP($D51,Organización_Modular!$F$10:$G$195,2,FALSE)=F$23,Itinerario!T51," ")," ") | G51: =_xlfn.IFNA(IF(VLOOKUP($D51,Organización_Modular!$F$10:$G$195,2,FALSE)=G$23,Itinerario!W51," ")," ") | H51: =_xlfn.IFNA(IF(VLOOKUP($D51,Organización_Modular!$F$10:$G$195,2,FALSE)=H$23,Itinerario!T51," ")," ") | I51: =_xlfn.IFNA(IF(VLOOKUP($D51,Organización_Modular!$F$10:$G$195,2,FALSE)=I$23,Itinerario!W51," ")," ") | J51: =_xlfn.IFNA(IF(VLOOKUP($D51,Organización_Modular!$F$10:$G$195,2,FALSE)=J$23,Itinerario!T51," ")," ") | K51: =_xlfn.IFNA(IF(VLOOKUP($D51,Organización_Modular!$F$10:$G$195,2,FALSE)=K$23,Itinerario!W51," ")," ") | L51: =_xlfn.IFNA(IF(VLOOKUP($D51,Organización_Modular!$F$10:$G$195,2,FALSE)=L$23,Itinerario!T51," ")," ") | M51: =_xlfn.IFNA(IF(VLOOKUP($D51,Organización_Modular!$F$10:$G$195,2,FALSE)=M$23,Itinerario!W51," ")," ") | N51: =_xlfn.IFNA(IF(VLOOKUP($D51,Organización_Modular!$F$10:$G$195,2,FALSE)=N$23,Itinerario!T51," ")," ") | O51: =_xlfn.IFNA(IF(VLOOKUP($D51,Organización_Modular!$F$10:$G$195,2,FALSE)=O$23,Itinerario!W51," ")," ") | P51: =_xlfn.IFNA(IF(VLOOKUP($D51,Organización_Modular!$F$10:$G$195,2,FALSE)=P$23,Itinerario!T51," ")," ") | Q51: =_xlfn.IFNA(IF(VLOOKUP($D51,Organización_Modular!$F$10:$G$195,2,FALSE)=Q$23,Itinerario!W51," ")," ") | R51: =Organización_Modular!H37 -> 0 | S51: =Organización_Modular!I37 -> 0 | T51: =SUM(R51:S51) -> 0 | U51: =+R51*$S$19 -> 0 | V51: =+S51*$U$19 -> 0 | W51: =SUM(U51:V51) -> 0 | X51: =W51 -> 0
D52: =Organización_Modular!F38 -> 0 | F52: =_xlfn.IFNA(IF(VLOOKUP($D52,Organización_Modular!$F$10:$G$195,2,FALSE)=F$23,Itinerario!T52," ")," ") | G52: =_xlfn.IFNA(IF(VLOOKUP($D52,Organización_Modular!$F$10:$G$195,2,FALSE)=G$23,Itinerario!W52," ")," ") | H52: =_xlfn.IFNA(IF(VLOOKUP($D52,Organización_Modular!$F$10:$G$195,2,FALSE)=H$23,Itinerario!T52," ")," ") | I52: =_xlfn.IFNA(IF(VLOOKUP($D52,Organización_Modular!$F$10:$G$195,2,FALSE)=I$23,Itinerario!W52," ")," ") | J52: =_xlfn.IFNA(IF(VLOOKUP($D52,Organización_Modular!$F$10:$G$195,2,FALSE)=J$23,Itinerario!T52," ")," ") | K52: =_xlfn.IFNA(IF(VLOOKUP($D52,Organización_Modular!$F$10:$G$195,2,FALSE)=K$23,Itinerario!W52," ")," ") | L52: =_xlfn.IFNA(IF(VLOOKUP($D52,Organización_Modular!$F$10:$G$195,2,FALSE)=L$23,Itinerario!T52," ")," ") | M52: =_xlfn.IFNA(IF(VLOOKUP($D52,Organización_Modular!$F$10:$G$195,2,FALSE)=M$23,Itinerario!W52," ")," ") | N52: =_xlfn.IFNA(IF(VLOOKUP($D52,Organización_Modular!$F$10:$G$195,2,FALSE)=N$23,Itinerario!T52," ")," ") | O52: =_xlfn.IFNA(IF(VLOOKUP($D52,Organización_Modular!$F$10:$G$195,2,FALSE)=O$23,Itinerario!W52," ")," ") | P52: =_xlfn.IFNA(IF(VLOOKUP($D52,Organización_Modular!$F$10:$G$195,2,FALSE)=P$23,Itinerario!T52," ")," ") | Q52: =_xlfn.IFNA(IF(VLOOKUP($D52,Organización_Modular!$F$10:$G$195,2,FALSE)=Q$23,Itinerario!W52," ")," ") | R52: =Organización_Modular!H38 -> 0 | S52: =Organización_Modular!I38 -> 0 | T52: =SUM(R52:S52) -> 0 | U52: =+R52*$S$19 -> 0 | V52: =+S52*$U$19 -> 0 | W52: =SUM(U52:V52) -> 0 | X52: =W52 -> 0
D53: =Organización_Modular!F39 -> 0 | F53: =_xlfn.IFNA(IF(VLOOKUP($D53,Organización_Modular!$F$10:$G$195,2,FALSE)=F$23,Itinerario!T53," ")," ") | G53: =_xlfn.IFNA(IF(VLOOKUP($D53,Organización_Modular!$F$10:$G$195,2,FALSE)=G$23,Itinerario!W53," ")," ") | H53: =_xlfn.IFNA(IF(VLOOKUP($D53,Organización_Modular!$F$10:$G$195,2,FALSE)=H$23,Itinerario!T53," ")," ") | I53: =_xlfn.IFNA(IF(VLOOKUP($D53,Organización_Modular!$F$10:$G$195,2,FALSE)=I$23,Itinerario!W53," ")," ") | J53: =_xlfn.IFNA(IF(VLOOKUP($D53,Organización_Modular!$F$10:$G$195,2,FALSE)=J$23,Itinerario!T53," ")," ") | K53: =_xlfn.IFNA(IF(VLOOKUP($D53,Organización_Modular!$F$10:$G$195,2,FALSE)=K$23,Itinerario!W53," ")," ") | L53: =_xlfn.IFNA(IF(VLOOKUP($D53,Organización_Modular!$F$10:$G$195,2,FALSE)=L$23,Itinerario!T53," ")," ") | M53: =_xlfn.IFNA(IF(VLOOKUP($D53,Organización_Modular!$F$10:$G$195,2,FALSE)=M$23,Itinerario!W53," ")," ") | N53: =_xlfn.IFNA(IF(VLOOKUP($D53,Organización_Modular!$F$10:$G$195,2,FALSE)=N$23,Itinerario!T53," ")," ") | O53: =_xlfn.IFNA(IF(VLOOKUP($D53,Organización_Modular!$F$10:$G$195,2,FALSE)=O$23,Itinerario!W53," ")," ") | P53: =_xlfn.IFNA(IF(VLOOKUP($D53,Organización_Modular!$F$10:$G$195,2,FALSE)=P$23,Itinerario!T53," ")," ") | Q53: =_xlfn.IFNA(IF(VLOOKUP($D53,Organización_Modular!$F$10:$G$195,2,FALSE)=Q$23,Itinerario!W53," ")," ") | R53: =Organización_Modular!H39 -> 0 | S53: =Organización_Modular!I39 -> 0 | T53: =SUM(R53:S53) -> 0 | U53: =+R53*$S$19 -> 0 | V53: =+S53*$U$19 -> 0 | W53: =SUM(U53:V53) -> 0 | X53: =W53 -> 0
B54: =Organización_Modular!B40 -> Experiencias formativas en situaciones reales de trabajo (ESRT) | F54: =Organización_Modular!I40 -> 6 | G54: =F54*32 -> 192 | R54: =Organización_Modular!H40 -> 0 | S54: =Organización_Modular!I40 -> 6 | T54: =SUM(R54:S54) -> 6 | U54: =+R54*$S$19 -> 0 | V54: =+S54*$U$19 -> 192 | W54: =SUM(U54:V54) -> 192 | X54: =W54 -> 192
A55: =Organización_Modular!A41 -> MÓDULO II: PROCESAMIENTO Y ARCHIVO DOCUMENTARIO | B55: =B24 -> Competencias técnicas (Unidad de competencia) | C55: =Organización_Modular!C41 -> UC2 Procesar la documentación de las distintas áreas de la organización, en función a sus políticas y normativa correspondiente. UC3 Custodiar la documentación, según políticas y procedimientos de la organización, y normativa correspondiente. | D55: =Organización_Modular!F41 -> Recepción y procesamiento de la información | F55: =_xlfn.IFNA(IF(VLOOKUP($D55,Organización_Modular!$F$10:$G$195,2,FALSE)=F$23,Itinerario!T55," ")," ") | G55: =_xlfn.IFNA(IF(VLOOKUP($D55,Organización_Modular!$F$10:$G$195,2,FALSE)=G$23,Itinerario!W55," ")," ") | H55: =_xlfn.IFNA(IF(VLOOKUP($D55,Organización_Modular!$F$10:$G$195,2,FALSE)=H$23,Itinerario!T55," ")," ") -> 2 | I55: =_xlfn.IFNA(IF(VLOOKUP($D55,Organización_Modular!$F$10:$G$195,2,FALSE)=I$23,Itinerario!W55," ")," ") -> 48 | J55: =_xlfn.IFNA(IF(VLOOKUP($D55,Organización_Modular!$F$10:$G$195,2,FALSE)=J$23,Itinerario!T55," ")," ") | K55: =_xlfn.IFNA(IF(VLOOKUP($D55,Organización_Modular!$F$10:$G$195,2,FALSE)=K$23,Itinerario!W55," ")," ") | L55: =_xlfn.IFNA(IF(VLOOKUP($D55,Organización_Modular!$F$10:$G$195,2,FALSE)=L$23,Itinerario!T55," ")," ") | M55: =_xlfn.IFNA(IF(VLOOKUP($D55,Organización_Modular!$F$10:$G$195,2,FALSE)=M$23,Itinerario!W55," ")," ") | N55: =_xlfn.IFNA(IF(VLOOKUP($D55,Organización_Modular!$F$10:$G$195,2,FALSE)=N$23,Itinerario!T55," ")," ") | O55: =_xlfn.IFNA(IF(VLOOKUP($D55,Organización_Modular!$F$10:$G$195,2,FALSE)=O$23,Itinerario!W55," ")," ") | P55: =_xlfn.IFNA(IF(VLOOKUP($D55,Organización_Modular!$F$10:$G$195,2,FALSE)=P$23,Itinerario!T55," ")," ") | Q55: =_xlfn.IFNA(IF(VLOOKUP($D55,Organización_Modular!$F$10:$G$195,2,FALSE)=Q$23,Itinerario!W55," ")," ") | R55: =Organización_Modular!H41 -> 1 | S55: =Organización_Modular!I41 -> 1 | T55: =SUM(R55:S55) -> 2 | U55: =+R55*$S$19 -> 16 | V55: =+S55*$U$19 -> 32 | W55: =SUM(U55:V55) -> 48 | X55: =W55 -> 48
D56: =Organización_Modular!F42 -> Actividades administrativas | F56: =_xlfn.IFNA(IF(VLOOKUP($D56,Organización_Modular!$F$10:$G$195,2,FALSE)=F$23,Itinerario!T56," ")," ") | G56: =_xlfn.IFNA(IF(VLOOKUP($D56,Organización_Modular!$F$10:$G$195,2,FALSE)=G$23,Itinerario!W56," ")," ") | H56: =_xlfn.IFNA(IF(VLOOKUP($D56,Organización_Modular!$F$10:$G$195,2,FALSE)=H$23,Itinerario!T56," ")," ") -> 1 | I56: =_xlfn.IFNA(IF(VLOOKUP($D56,Organización_Modular!$F$10:$G$195,2,FALSE)=I$23,Itinerario!W56," ")," ") -> 32 | J56: =_xlfn.IFNA(IF(VLOOKUP($D56,Organización_Modular!$F$10:$G$195,2,FALSE)=J$23,Itinerario!T56," ")," ") | K56: =_xlfn.IFNA(IF(VLOOKUP($D56,Organización_Modular!$F$10:$G$195,2,FALSE)=K$23,Itinerario!W56," ")," ") | L56: =_xlfn.IFNA(IF(VLOOKUP($D56,Organización_Modular!$F$10:$G$195,2,FALSE)=L$23,Itinerario!T56," ")," ") | M56: =_xlfn.IFNA(IF(VLOOKUP($D56,Organización_Modular!$F$10:$G$195,2,FALSE)=M$23,Itinerario!W56," ")," ") | N56: =_xlfn.IFNA(IF(VLOOKUP($D56,Organización_Modular!$F$10:$G$195,2,FALSE)=N$23,Itinerario!T56," ")," ") | O56: =_xlfn.IFNA(IF(VLOOKUP($D56,Organización_Modular!$F$10:$G$195,2,FALSE)=O$23,Itinerario!W56," ")," ") | P56: =_xlfn.IFNA(IF(VLOOKUP($D56,Organización_Modular!$F$10:$G$195,2,FALSE)=P$23,Itinerario!T56," ")," ") | Q56: =_xlfn.IFNA(IF(VLOOKUP($D56,Organización_Modular!$F$10:$G$195,2,FALSE)=Q$23,Itinerario!W56," ")," ") | R56: =Organización_Modular!H42 -> 0 | S56: =Organización_Modular!I42 -> 1 | T56: =SUM(R56:S56) -> 1 | U56: =+R56*$S$19 -> 0 | V56: =+S56*$U$19 -> 32 | W56: =SUM(U56:V56) -> 32 | X56: =W56 -> 32
D57: =Organización_Modular!F43 -> Atención al público | F57: =_xlfn.IFNA(IF(VLOOKUP($D57,Organización_Modular!$F$10:$G$195,2,FALSE)=F$23,Itinerario!T57," ")," ") | G57: =_xlfn.IFNA(IF(VLOOKUP($D57,Organización_Modular!$F$10:$G$195,2,FALSE)=G$23,Itinerario!W57," ")," ") | H57: =_xlfn.IFNA(IF(VLOOKUP($D57,Organización_Modular!$F$10:$G$195,2,FALSE)=H$23,Itinerario!T57," ")," ") -> 2 | I57: =_xlfn.IFNA(IF(VLOOKUP($D57,Organización_Modular!$F$10:$G$195,2,FALSE)=I$23,Itinerario!W57," ")," ") -> 48 | J57: =_xlfn.IFNA(IF(VLOOKUP($D57,Organización_Modular!$F$10:$G$195,2,FALSE)=J$23,Itinerario!T57," ")," ") | K57: =_xlfn.IFNA(IF(VLOOKUP($D57,Organización_Modular!$F$10:$G$195,2,FALSE)=K$23,Itinerario!W57," ")," ") | L57: =_xlfn.IFNA(IF(VLOOKUP($D57,Organización_Modular!$F$10:$G$195,2,FALSE)=L$23,Itinerario!T57," ")," ") | M57: =_xlfn.IFNA(IF(VLOOKUP($D57,Organización_Modular!$F$10:$G$195,2,FALSE)=M$23,Itinerario!W57," ")," ") | N57: =_xlfn.IFNA(IF(VLOOKUP($D57,Organización_Modular!$F$10:$G$195,2,FALSE)=N$23,Itinerario!T57," ")," ") | O57: =_xlfn.IFNA(IF(VLOOKUP($D57,Organización_Modular!$F$10:$G$195,2,FALSE)=O$23,Itinerario!W57," ")," ") | P57: =_xlfn.IFNA(IF(VLOOKUP($D57,Organización_Modular!$F$10:$G$195,2,FALSE)=P$23,Itinerario!T57," ")," ") | Q57: =_xlfn.IFNA(IF(VLOOKUP($D57,Organización_Modular!$F$10:$G$195,2,FALSE)=Q$23,Itinerario!W57," ")," ") | R57: =Organización_Modular!H43 -> 1 | S57: =Organización_Modular!I43 -> 1 | T57: =SUM(R57:S57) -> 2 | U57: =+R57*$S$19 -> 16 | V57: =+S57*$U$19 -> 32 | W57: =SUM(U57:V57) -> 48 | X57: =W57 -> 48
D58: =Organización_Modular!F44 -> Control y registro documentario | F58: =_xlfn.IFNA(IF(VLOOKUP($D58,Organización_Modular!$F$10:$G$195,2,FALSE)=F$23,Itinerario!T58," ")," ") | G58: =_xlfn.IFNA(IF(VLOOKUP($D58,Organización_Modular!$F$10:$G$195,2,FALSE)=G$23,Itinerario!W58," ")," ") | H58: =_xlfn.IFNA(IF(VLOOKUP($D58,Organización_Modular!$F$10:$G$195,2,FALSE)=H$23,Itinerario!T58," ")," ") -> 1 | I58: =_xlfn.IFNA(IF(VLOOKUP($D58,Organización_Modular!$F$10:$G$195,2,FALSE)=I$23,Itinerario!W58," ")," ") -> 32 | J58: =_xlfn.IFNA(IF(VLOOKUP($D58,Organización_Modular!$F$10:$G$195,2,FALSE)=J$23,Itinerario!T58," ")," ") | K58: =_xlfn.IFNA(IF(VLOOKUP($D58,Organización_Modular!$F$10:$G$195,2,FALSE)=K$23,Itinerario!W58," ")," ") | L58: =_xlfn.IFNA(IF(VLOOKUP($D58,Organización_Modular!$F$10:$G$195,2,FALSE)=L$23,Itinerario!T58," ")," ") | M58: =_xlfn.IFNA(IF(VLOOKUP($D58,Organización_Modular!$F$10:$G$195,2,FALSE)=M$23,Itinerario!W58," ")," ") | N58: =_xlfn.IFNA(IF(VLOOKUP($D58,Organización_Modular!$F$10:$G$195,2,FALSE)=N$23,Itinerario!T58," ")," ") | O58: =_xlfn.IFNA(IF(VLOOKUP($D58,Organización_Modular!$F$10:$G$195,2,FALSE)=O$23,Itinerario!W58," ")," ") | P58: =_xlfn.IFNA(IF(VLOOKUP($D58,Organización_Modular!$F$10:$G$195,2,FALSE)=P$23,Itinerario!T58," ")," ") | Q58: =_xlfn.IFNA(IF(VLOOKUP($D58,Organización_Modular!$F$10:$G$195,2,FALSE)=Q$23,Itinerario!W58," ")," ") | R58: =Organización_Modular!H44 -> 0 | S58: =Organización_Modular!I44 -> 1 | T58: =SUM(R58:S58) -> 1 | U58: =+R58*$S$19 -> 0 | V58: =+S58*$U$19 -> 32 | W58: =SUM(U58:V58) -> 32 | X58: =W58 -> 32
D59: =Organización_Modular!F45 -> Organización del sistema de gestión de archivos | F59: =_xlfn.IFNA(IF(VLOOKUP($D59,Organización_Modular!$F$10:$G$195,2,FALSE)=F$23,Itinerario!T59," ")," ") | G59: =_xlfn.IFNA(IF(VLOOKUP($D59,Organización_Modular!$F$10:$G$195,2,FALSE)=G$23,Itinerario!W59," ")," ") | H59: =_xlfn.IFNA(IF(VLOOKUP($D59,Organización_Modular!$F$10:$G$195,2,FALSE)=H$23,Itinerario!T59," ")," ") -> 2 | I59: =_xlfn.IFNA(IF(VLOOKUP($D59,Organización_Modular!$F$10:$G$195,2,FALSE)=I$23,Itinerario!W59," ")," ") -> 48 | J59: =_xlfn.IFNA(IF(VLOOKUP($D59,Organización_Modular!$F$10:$G$195,2,FALSE)=J$23,Itinerario!T59," ")," ") | K59: =_xlfn.IFNA(IF(VLOOKUP($D59,Organización_Modular!$F$10:$G$195,2,FALSE)=K$23,Itinerario!W59," ")," ") | L59: =_xlfn.IFNA(IF(VLOOKUP($D59,Organización_Modular!$F$10:$G$195,2,FALSE)=L$23,Itinerario!T59," ")," ") | M59: =_xlfn.IFNA(IF(VLOOKUP($D59,Organización_Modular!$F$10:$G$195,2,FALSE)=M$23,Itinerario!W59," ")," ") | N59: =_xlfn.IFNA(IF(VLOOKUP($D59,Organización_Modular!$F$10:$G$195,2,FALSE)=N$23,Itinerario!T59," ")," ") | O59: =_xlfn.IFNA(IF(VLOOKUP($D59,Organización_Modular!$F$10:$G$195,2,FALSE)=O$23,Itinerario!W59," ")," ") | P59: =_xlfn.IFNA(IF(VLOOKUP($D59,Organización_Modular!$F$10:$G$195,2,FALSE)=P$23,Itinerario!T59," ")," ") | Q59: =_xlfn.IFNA(IF(VLOOKUP($D59,Organización_Modular!$F$10:$G$195,2,FALSE)=Q$23,Itinerario!W59," ")," ") | R59: =Organización_Modular!H45 -> 1 | S59: =Organización_Modular!I45 -> 1 | T59: =SUM(R59:S59) -> 2 | U59: =+R59*$S$19 -> 16 | V59: =+S59*$U$19 -> 32 | W59: =SUM(U59:V59) -> 48 | X59: =W59 -> 48
D60: =Organización_Modular!F46 -> Archivos, mantenimiento y conservación de documentos | F60: =_xlfn.IFNA(IF(VLOOKUP($D60,Organización_Modular!$F$10:$G$195,2,FALSE)=F$23,Itinerario!T60," ")," ") | G60: =_xlfn.IFNA(IF(VLOOKUP($D60,Organización_Modular!$F$10:$G$195,2,FALSE)=G$23,Itinerario!W60," ")," ") | H60: =_xlfn.IFNA(IF(VLOOKUP($D60,Organización_Modular!$F$10:$G$195,2,FALSE)=H$23,Itinerario!T60," ")," ") -> 2 | I60: =_xlfn.IFNA(IF(VLOOKUP($D60,Organización_Modular!$F$10:$G$195,2,FALSE)=I$23,Itinerario!W60," ")," ") -> 48 | J60: =_xlfn.IFNA(IF(VLOOKUP($D60,Organización_Modular!$F$10:$G$195,2,FALSE)=J$23,Itinerario!T60," ")," ") | K60: =_xlfn.IFNA(IF(VLOOKUP($D60,Organización_Modular!$F$10:$G$195,2,FALSE)=K$23,Itinerario!W60," ")," ") | L60: =_xlfn.IFNA(IF(VLOOKUP($D60,Organización_Modular!$F$10:$G$195,2,FALSE)=L$23,Itinerario!T60," ")," ") | M60: =_xlfn.IFNA(IF(VLOOKUP($D60,Organización_Modular!$F$10:$G$195,2,FALSE)=M$23,Itinerario!W60," ")," ") | N60: =_xlfn.IFNA(IF(VLOOKUP($D60,Organización_Modular!$F$10:$G$195,2,FALSE)=N$23,Itinerario!T60," ")," ") | O60: =_xlfn.IFNA(IF(VLOOKUP($D60,Organización_Modular!$F$10:$G$195,2,FALSE)=O$23,Itinerario!W60," ")," ") | P60: =_xlfn.IFNA(IF(VLOOKUP($D60,Organización_Modular!$F$10:$G$195,2,FALSE)=P$23,Itinerario!T60," ")," ") | Q60: =_xlfn.IFNA(IF(VLOOKUP($D60,Organización_Modular!$F$10:$G$195,2,FALSE)=Q$23,Itinerario!W60," ")," ") | R60: =Organización_Modular!H46 -> 1 | S60: =Organización_Modular!I46 -> 1 | T60: =SUM(R60:S60) -> 2 | U60: =+R60*$S$19 -> 16 | V60: =+S60*$U$19 -> 32 | W60: =SUM(U60:V60) -> 48 | X60: =W60 -> 48
F61: =_xlfn.IFNA(IF(VLOOKUP($D61,Organización_Modular!$F$10:$G$195,2,FALSE)=F$23,Itinerario!T61," ")," ") | G61: =_xlfn.IFNA(IF(VLOOKUP($D61,Organización_Modular!$F$10:$G$195,2,FALSE)=G$23,Itinerario!W61," ")," ") | H61: =_xlfn.IFNA(IF(VLOOKUP($D61,Organización_Modular!$F$10:$G$195,2,FALSE)=H$23,Itinerario!T61," ")," ") | I61: =_xlfn.IFNA(IF(VLOOKUP($D61,Organización_Modular!$F$10:$G$195,2,FALSE)=I$23,Itinerario!W61," ")," ") | J61: =_xlfn.IFNA(IF(VLOOKUP($D61,Organización_Modular!$F$10:$G$195,2,FALSE)=J$23,Itinerario!T61," ")," ") | K61: =_xlfn.IFNA(IF(VLOOKUP($D61,Organización_Modular!$F$10:$G$195,2,FALSE)=K$23,Itinerario!W61," ")," ") | L61: =_xlfn.IFNA(IF(VLOOKUP($D61,Organización_Modular!$F$10:$G$195,2,FALSE)=L$23,Itinerario!T61," ")," ") | M61: =_xlfn.IFNA(IF(VLOOKUP($D61,Organización_Modular!$F$10:$G$195,2,FALSE)=M$23,Itinerario!W61," ")," ") | N61: =_xlfn.IFNA(IF(VLOOKUP($D61,Organización_Modular!$F$10:$G$195,2,FALSE)=N$23,Itinerario!T61," ")," ") | O61: =_xlfn.IFNA(IF(VLOOKUP($D61,Organización_Modular!$F$10:$G$195,2,FALSE)=O$23,Itinerario!W61," ")," ") | P61: =_xlfn.IFNA(IF(VLOOKUP($D61,Organización_Modular!$F$10:$G$195,2,FALSE)=P$23,Itinerario!T61," ")," ") | Q61: =_xlfn.IFNA(IF(VLOOKUP($D61,Organización_Modular!$F$10:$G$195,2,FALSE)=Q$23,Itinerario!W61," ")," ") | X61: =W61 -> 0
D62: =Organización_Modular!F48 -> 0 | F62: =_xlfn.IFNA(IF(VLOOKUP($D62,Organización_Modular!$F$10:$G$195,2,FALSE)=F$23,Itinerario!T62," ")," ") | G62: =_xlfn.IFNA(IF(VLOOKUP($D62,Organización_Modular!$F$10:$G$195,2,FALSE)=G$23,Itinerario!W62," ")," ") | H62: =_xlfn.IFNA(IF(VLOOKUP($D62,Organización_Modular!$F$10:$G$195,2,FALSE)=H$23,Itinerario!T62," ")," ") | I62: =_xlfn.IFNA(IF(VLOOKUP($D62,Organización_Modular!$F$10:$G$195,2,FALSE)=I$23,Itinerario!W62," ")," ") | J62: =_xlfn.IFNA(IF(VLOOKUP($D62,Organización_Modular!$F$10:$G$195,2,FALSE)=J$23,Itinerario!T62," ")," ") | K62: =_xlfn.IFNA(IF(VLOOKUP($D62,Organización_Modular!$F$10:$G$195,2,FALSE)=K$23,Itinerario!W62," ")," ") | L62: =_xlfn.IFNA(IF(VLOOKUP($D62,Organización_Modular!$F$10:$G$195,2,FALSE)=L$23,Itinerario!T62," ")," ") | M62: =_xlfn.IFNA(IF(VLOOKUP($D62,Organización_Modular!$F$10:$G$195,2,FALSE)=M$23,Itinerario!W62," ")," ") | N62: =_xlfn.IFNA(IF(VLOOKUP($D62,Organización_Modular!$F$10:$G$195,2,FALSE)=N$23,Itinerario!T62," ")," ") | O62: =_xlfn.IFNA(IF(VLOOKUP($D62,Organización_Modular!$F$10:$G$195,2,FALSE)=O$23,Itinerario!W62," ")," ") | P62: =_xlfn.IFNA(IF(VLOOKUP($D62,Organización_Modular!$F$10:$G$195,2,FALSE)=P$23,Itinerario!T62," ")," ") | Q62: =_xlfn.IFNA(IF(VLOOKUP($D62,Organización_Modular!$F$10:$G$195,2,FALSE)=Q$23,Itinerario!W62," ")," ") | R62: =Organización_Modular!H48 -> 0 | S62: =Organización_Modular!I48 -> 0 | T62: =SUM(R62:S62) -> 0 | U62: =+R62*$S$19 -> 0 | V62: =+S62*$U$19 -> 0 | W62: =SUM(U62:V62) -> 0 | X62: =W62 -> 0
D63: =Organización_Modular!F49 -> 0 | F63: =_xlfn.IFNA(IF(VLOOKUP($D63,Organización_Modular!$F$10:$G$195,2,FALSE)=F$23,Itinerario!T63," ")," ") | G63: =_xlfn.IFNA(IF(VLOOKUP($D63,Organización_Modular!$F$10:$G$195,2,FALSE)=G$23,Itinerario!W63," ")," ") | H63: =_xlfn.IFNA(IF(VLOOKUP($D63,Organización_Modular!$F$10:$G$195,2,FALSE)=H$23,Itinerario!T63," ")," ") | I63: =_xlfn.IFNA(IF(VLOOKUP($D63,Organización_Modular!$F$10:$G$195,2,FALSE)=I$23,Itinerario!W63," ")," ") | J63: =_xlfn.IFNA(IF(VLOOKUP($D63,Organización_Modular!$F$10:$G$195,2,FALSE)=J$23,Itinerario!T63," ")," ") | K63: =_xlfn.IFNA(IF(VLOOKUP($D63,Organización_Modular!$F$10:$G$195,2,FALSE)=K$23,Itinerario!W63," ")," ") | L63: =_xlfn.IFNA(IF(VLOOKUP($D63,Organización_Modular!$F$10:$G$195,2,FALSE)=L$23,Itinerario!T63," ")," ") | M63: =_xlfn.IFNA(IF(VLOOKUP($D63,Organización_Modular!$F$10:$G$195,2,FALSE)=M$23,Itinerario!W63," ")," ") | N63: =_xlfn.IFNA(IF(VLOOKUP($D63,Organización_Modular!$F$10:$G$195,2,FALSE)=N$23,Itinerario!T63," ")," ") | O63: =_xlfn.IFNA(IF(VLOOKUP($D63,Organización_Modular!$F$10:$G$195,2,FALSE)=O$23,Itinerario!W63," ")," ") | P63: =_xlfn.IFNA(IF(VLOOKUP($D63,Organización_Modular!$F$10:$G$195,2,FALSE)=P$23,Itinerario!T63," ")," ") | Q63: =_xlfn.IFNA(IF(VLOOKUP($D63,Organización_Modular!$F$10:$G$195,2,FALSE)=Q$23,Itinerario!W63," ")," ") | R63: =Organización_Modular!H49 -> 0 | S63: =Organización_Modular!I49 -> 0 | T63: =SUM(R63:S63) -> 0 | U63: =+R63*$S$19 -> 0 | V63: =+S63*$U$19 -> 0 | W63: =SUM(U63:V63) -> 0 | X63: =W63 -> 0
D64: =Organización_Modular!F50 -> 0 | F64: =_xlfn.IFNA(IF(VLOOKUP($D64,Organización_Modular!$F$10:$G$195,2,FALSE)=F$23,Itinerario!T64," ")," ") | G64: =_xlfn.IFNA(IF(VLOOKUP($D64,Organización_Modular!$F$10:$G$195,2,FALSE)=G$23,Itinerario!W64," ")," ") | H64: =_xlfn.IFNA(IF(VLOOKUP($D64,Organización_Modular!$F$10:$G$195,2,FALSE)=H$23,Itinerario!T64," ")," ") | I64: =_xlfn.IFNA(IF(VLOOKUP($D64,Organización_Modular!$F$10:$G$195,2,FALSE)=I$23,Itinerario!W64," ")," ") | J64: =_xlfn.IFNA(IF(VLOOKUP($D64,Organización_Modular!$F$10:$G$195,2,FALSE)=J$23,Itinerario!T64," ")," ") | K64: =_xlfn.IFNA(IF(VLOOKUP($D64,Organización_Modular!$F$10:$G$195,2,FALSE)=K$23,Itinerario!W64," ")," ") | L64: =_xlfn.IFNA(IF(VLOOKUP($D64,Organización_Modular!$F$10:$G$195,2,FALSE)=L$23,Itinerario!T64," ")," ") | M64: =_xlfn.IFNA(IF(VLOOKUP($D64,Organización_Modular!$F$10:$G$195,2,FALSE)=M$23,Itinerario!W64," ")," ") | N64: =_xlfn.IFNA(IF(VLOOKUP($D64,Organización_Modular!$F$10:$G$195,2,FALSE)=N$23,Itinerario!T64," ")," ") | O64: =_xlfn.IFNA(IF(VLOOKUP($D64,Organización_Modular!$F$10:$G$195,2,FALSE)=O$23,Itinerario!W64," ")," ") | P64: =_xlfn.IFNA(IF(VLOOKUP($D64,Organización_Modular!$F$10:$G$195,2,FALSE)=P$23,Itinerario!T64," ")," ") | Q64: =_xlfn.IFNA(IF(VLOOKUP($D64,Organización_Modular!$F$10:$G$195,2,FALSE)=Q$23,Itinerario!W64," ")," ") | R64: =Organización_Modular!H50 -> 0 | S64: =Organización_Modular!I50 -> 0 | T64: =SUM(R64:S64) -> 0 | U64: =+R64*$S$19 -> 0 | V64: =+S64*$U$19 -> 0 | W64: =SUM(U64:V64) -> 0 | X64: =W64 -> 0
D65: =Organización_Modular!F51 -> 0 | F65: =_xlfn.IFNA(IF(VLOOKUP($D65,Organización_Modular!$F$10:$G$195,2,FALSE)=F$23,Itinerario!T65," ")," ") | G65: =_xlfn.IFNA(IF(VLOOKUP($D65,Organización_Modular!$F$10:$G$195,2,FALSE)=G$23,Itinerario!W65," ")," ") | H65: =_xlfn.IFNA(IF(VLOOKUP($D65,Organización_Modular!$F$10:$G$195,2,FALSE)=H$23,Itinerario!T65," ")," ") | I65: =_xlfn.IFNA(IF(VLOOKUP($D65,Organización_Modular!$F$10:$G$195,2,FALSE)=I$23,Itinerario!W65," ")," ") | J65: =_xlfn.IFNA(IF(VLOOKUP($D65,Organización_Modular!$F$10:$G$195,2,FALSE)=J$23,Itinerario!T65," ")," ") | K65: =_xlfn.IFNA(IF(VLOOKUP($D65,Organización_Modular!$F$10:$G$195,2,FALSE)=K$23,Itinerario!W65," ")," ") | L65: =_xlfn.IFNA(IF(VLOOKUP($D65,Organización_Modular!$F$10:$G$195,2,FALSE)=L$23,Itinerario!T65," ")," ") | M65: =_xlfn.IFNA(IF(VLOOKUP($D65,Organización_Modular!$F$10:$G$195,2,FALSE)=M$23,Itinerario!W65," ")," ") | N65: =_xlfn.IFNA(IF(VLOOKUP($D65,Organización_Modular!$F$10:$G$195,2,FALSE)=N$23,Itinerario!T65," ")," ") | O65: =_xlfn.IFNA(IF(VLOOKUP($D65,Organización_Modular!$F$10:$G$195,2,FALSE)=O$23,Itinerario!W65," ")," ") | P65: =_xlfn.IFNA(IF(VLOOKUP($D65,Organización_Modular!$F$10:$G$195,2,FALSE)=P$23,Itinerario!T65," ")," ") | Q65: =_xlfn.IFNA(IF(VLOOKUP($D65,Organización_Modular!$F$10:$G$195,2,FALSE)=Q$23,Itinerario!W65," ")," ") | R65: =Organización_Modular!H51 -> 0 | S65: =Organización_Modular!I51 -> 0 | T65: =SUM(R65:S65) -> 0 | U65: =+R65*$S$19 -> 0 | V65: =+S65*$U$19 -> 0 | W65: =SUM(U65:V65) -> 0 | X65: =W65 -> 0
D66: =Organización_Modular!F52 -> 0 | F66: =_xlfn.IFNA(IF(VLOOKUP($D66,Organización_Modular!$F$10:$G$195,2,FALSE)=F$23,Itinerario!T66," ")," ") | G66: =_xlfn.IFNA(IF(VLOOKUP($D66,Organización_Modular!$F$10:$G$195,2,FALSE)=G$23,Itinerario!W66," ")," ") | H66: =_xlfn.IFNA(IF(VLOOKUP($D66,Organización_Modular!$F$10:$G$195,2,FALSE)=H$23,Itinerario!T66," ")," ") | I66: =_xlfn.IFNA(IF(VLOOKUP($D66,Organización_Modular!$F$10:$G$195,2,FALSE)=I$23,Itinerario!W66," ")," ") | J66: =_xlfn.IFNA(IF(VLOOKUP($D66,Organización_Modular!$F$10:$G$195,2,FALSE)=J$23,Itinerario!T66," ")," ") | K66: =_xlfn.IFNA(IF(VLOOKUP($D66,Organización_Modular!$F$10:$G$195,2,FALSE)=K$23,Itinerario!W66," ")," ") | L66: =_xlfn.IFNA(IF(VLOOKUP($D66,Organización_Modular!$F$10:$G$195,2,FALSE)=L$23,Itinerario!T66," ")," ") | M66: =_xlfn.IFNA(IF(VLOOKUP($D66,Organización_Modular!$F$10:$G$195,2,FALSE)=M$23,Itinerario!W66," ")," ") | N66: =_xlfn.IFNA(IF(VLOOKUP($D66,Organización_Modular!$F$10:$G$195,2,FALSE)=N$23,Itinerario!T66," ")," ") | O66: =_xlfn.IFNA(IF(VLOOKUP($D66,Organización_Modular!$F$10:$G$195,2,FALSE)=O$23,Itinerario!W66," ")," ") | P66: =_xlfn.IFNA(IF(VLOOKUP($D66,Organización_Modular!$F$10:$G$195,2,FALSE)=P$23,Itinerario!T66," ")," ") | Q66: =_xlfn.IFNA(IF(VLOOKUP($D66,Organización_Modular!$F$10:$G$195,2,FALSE)=Q$23,Itinerario!W66," ")," ") | R66: =Organización_Modular!H52 -> 0 | S66: =Organización_Modular!I52 -> 0 | T66: =SUM(R66:S66) -> 0 | U66: =+R66*$S$19 -> 0 | V66: =+S66*$U$19 -> 0 | W66: =SUM(U66:V66) -> 0 | X66: =W66 -> 0
D67: =Organización_Modular!F53 -> 0 | F67: =_xlfn.IFNA(IF(VLOOKUP($D67,Organización_Modular!$F$10:$G$195,2,FALSE)=F$23,Itinerario!T67," ")," ") | G67: =_xlfn.IFNA(IF(VLOOKUP($D67,Organización_Modular!$F$10:$G$195,2,FALSE)=G$23,Itinerario!W67," ")," ") | H67: =_xlfn.IFNA(IF(VLOOKUP($D67,Organización_Modular!$F$10:$G$195,2,FALSE)=H$23,Itinerario!T67," ")," ") | I67: =_xlfn.IFNA(IF(VLOOKUP($D67,Organización_Modular!$F$10:$G$195,2,FALSE)=I$23,Itinerario!W67," ")," ") | J67: =_xlfn.IFNA(IF(VLOOKUP($D67,Organización_Modular!$F$10:$G$195,2,FALSE)=J$23,Itinerario!T67," ")," ") | K67: =_xlfn.IFNA(IF(VLOOKUP($D67,Organización_Modular!$F$10:$G$195,2,FALSE)=K$23,Itinerario!W67," ")," ") | L67: =_xlfn.IFNA(IF(VLOOKUP($D67,Organización_Modular!$F$10:$G$195,2,FALSE)=L$23,Itinerario!T67," ")," ") | M67: =_xlfn.IFNA(IF(VLOOKUP($D67,Organización_Modular!$F$10:$G$195,2,FALSE)=M$23,Itinerario!W67," ")," ") | N67: =_xlfn.IFNA(IF(VLOOKUP($D67,Organización_Modular!$F$10:$G$195,2,FALSE)=N$23,Itinerario!T67," ")," ") | O67: =_xlfn.IFNA(IF(VLOOKUP($D67,Organización_Modular!$F$10:$G$195,2,FALSE)=O$23,Itinerario!W67," ")," ") | P67: =_xlfn.IFNA(IF(VLOOKUP($D67,Organización_Modular!$F$10:$G$195,2,FALSE)=P$23,Itinerario!T67," ")," ") | Q67: =_xlfn.IFNA(IF(VLOOKUP($D67,Organización_Modular!$F$10:$G$195,2,FALSE)=Q$23,Itinerario!W67," ")," ") | R67: =Organización_Modular!H53 -> 0 | S67: =Organización_Modular!I53 -> 0 | T67: =SUM(R67:S67) -> 0 | U67: =+R67*$S$19 -> 0 | V67: =+S67*$U$19 -> 0 | W67: =SUM(U67:V67) -> 0 | X67: =W67 -> 0
D68: =Organización_Modular!F54 -> 0 | F68: =_xlfn.IFNA(IF(VLOOKUP($D68,Organización_Modular!$F$10:$G$195,2,FALSE)=F$23,Itinerario!T68," ")," ") | G68: =_xlfn.IFNA(IF(VLOOKUP($D68,Organización_Modular!$F$10:$G$195,2,FALSE)=G$23,Itinerario!W68," ")," ") | H68: =_xlfn.IFNA(IF(VLOOKUP($D68,Organización_Modular!$F$10:$G$195,2,FALSE)=H$23,Itinerario!T68," ")," ") | I68: =_xlfn.IFNA(IF(VLOOKUP($D68,Organización_Modular!$F$10:$G$195,2,FALSE)=I$23,Itinerario!W68," ")," ") | J68: =_xlfn.IFNA(IF(VLOOKUP($D68,Organización_Modular!$F$10:$G$195,2,FALSE)=J$23,Itinerario!T68," ")," ") | K68: =_xlfn.IFNA(IF(VLOOKUP($D68,Organización_Modular!$F$10:$G$195,2,FALSE)=K$23,Itinerario!W68," ")," ") | L68: =_xlfn.IFNA(IF(VLOOKUP($D68,Organización_Modular!$F$10:$G$195,2,FALSE)=L$23,Itinerario!T68," ")," ") | M68: =_xlfn.IFNA(IF(VLOOKUP($D68,Organización_Modular!$F$10:$G$195,2,FALSE)=M$23,Itinerario!W68," ")," ") | N68: =_xlfn.IFNA(IF(VLOOKUP($D68,Organización_Modular!$F$10:$G$195,2,FALSE)=N$23,Itinerario!T68," ")," ") | O68: =_xlfn.IFNA(IF(VLOOKUP($D68,Organización_Modular!$F$10:$G$195,2,FALSE)=O$23,Itinerario!W68," ")," ") | P68: =_xlfn.IFNA(IF(VLOOKUP($D68,Organización_Modular!$F$10:$G$195,2,FALSE)=P$23,Itinerario!T68," ")," ") | Q68: =_xlfn.IFNA(IF(VLOOKUP($D68,Organización_Modular!$F$10:$G$195,2,FALSE)=Q$23,Itinerario!W68," ")," ") | R68: =Organización_Modular!H54 -> 0 | S68: =Organización_Modular!I54 -> 0 | T68: =SUM(R68:S68) -> 0 | U68: =+R68*$S$19 -> 0 | V68: =+S68*$U$19 -> 0 | W68: =SUM(U68:V68) -> 0 | X68: =W68 -> 0
D69: =Organización_Modular!F55 -> 0 | F69: =_xlfn.IFNA(IF(VLOOKUP($D69,Organización_Modular!$F$10:$G$195,2,FALSE)=F$23,Itinerario!T69," ")," ") | G69: =_xlfn.IFNA(IF(VLOOKUP($D69,Organización_Modular!$F$10:$G$195,2,FALSE)=G$23,Itinerario!W69," ")," ") | H69: =_xlfn.IFNA(IF(VLOOKUP($D69,Organización_Modular!$F$10:$G$195,2,FALSE)=H$23,Itinerario!T69," ")," ") | I69: =_xlfn.IFNA(IF(VLOOKUP($D69,Organización_Modular!$F$10:$G$195,2,FALSE)=I$23,Itinerario!W69," ")," ") | J69: =_xlfn.IFNA(IF(VLOOKUP($D69,Organización_Modular!$F$10:$G$195,2,FALSE)=J$23,Itinerario!T69," ")," ") | K69: =_xlfn.IFNA(IF(VLOOKUP($D69,Organización_Modular!$F$10:$G$195,2,FALSE)=K$23,Itinerario!W69," ")," ") | L69: =_xlfn.IFNA(IF(VLOOKUP($D69,Organización_Modular!$F$10:$G$195,2,FALSE)=L$23,Itinerario!T69," ")," ") | M69: =_xlfn.IFNA(IF(VLOOKUP($D69,Organización_Modular!$F$10:$G$195,2,FALSE)=M$23,Itinerario!W69," ")," ") | N69: =_xlfn.IFNA(IF(VLOOKUP($D69,Organización_Modular!$F$10:$G$195,2,FALSE)=N$23,Itinerario!T69," ")," ") | O69: =_xlfn.IFNA(IF(VLOOKUP($D69,Organización_Modular!$F$10:$G$195,2,FALSE)=O$23,Itinerario!W69," ")," ") | P69: =_xlfn.IFNA(IF(VLOOKUP($D69,Organización_Modular!$F$10:$G$195,2,FALSE)=P$23,Itinerario!T69," ")," ") | Q69: =_xlfn.IFNA(IF(VLOOKUP($D69,Organización_Modular!$F$10:$G$195,2,FALSE)=Q$23,Itinerario!W69," ")," ") | R69: =Organización_Modular!H55 -> 0 | S69: =Organización_Modular!I55 -> 0 | T69: =SUM(R69:S69) -> 0 | U69: =+R69*$S$19 -> 0 | V69: =+S69*$U$19 -> 0 | W69: =SUM(U69:V69) -> 0 | X69: =W69 -> 0
D70: =Organización_Modular!F56 -> 0 | F70: =_xlfn.IFNA(IF(VLOOKUP($D70,Organización_Modular!$F$10:$G$195,2,FALSE)=F$23,Itinerario!T70," ")," ") | G70: =_xlfn.IFNA(IF(VLOOKUP($D70,Organización_Modular!$F$10:$G$195,2,FALSE)=G$23,Itinerario!W70," ")," ") | H70: =_xlfn.IFNA(IF(VLOOKUP($D70,Organización_Modular!$F$10:$G$195,2,FALSE)=H$23,Itinerario!T70," ")," ") | I70: =_xlfn.IFNA(IF(VLOOKUP($D70,Organización_Modular!$F$10:$G$195,2,FALSE)=I$23,Itinerario!W70," ")," ") | J70: =_xlfn.IFNA(IF(VLOOKUP($D70,Organización_Modular!$F$10:$G$195,2,FALSE)=J$23,Itinerario!T70," ")," ") | K70: =_xlfn.IFNA(IF(VLOOKUP($D70,Organización_Modular!$F$10:$G$195,2,FALSE)=K$23,Itinerario!W70," ")," ") | L70: =_xlfn.IFNA(IF(VLOOKUP($D70,Organización_Modular!$F$10:$G$195,2,FALSE)=L$23,Itinerario!T70," ")," ") | M70: =_xlfn.IFNA(IF(VLOOKUP($D70,Organización_Modular!$F$10:$G$195,2,FALSE)=M$23,Itinerario!W70," ")," ") | N70: =_xlfn.IFNA(IF(VLOOKUP($D70,Organización_Modular!$F$10:$G$195,2,FALSE)=N$23,Itinerario!T70," ")," ") | O70: =_xlfn.IFNA(IF(VLOOKUP($D70,Organización_Modular!$F$10:$G$195,2,FALSE)=O$23,Itinerario!W70," ")," ") | P70: =_xlfn.IFNA(IF(VLOOKUP($D70,Organización_Modular!$F$10:$G$195,2,FALSE)=P$23,Itinerario!T70," ")," ") | Q70: =_xlfn.IFNA(IF(VLOOKUP($D70,Organización_Modular!$F$10:$G$195,2,FALSE)=Q$23,Itinerario!W70," ")," ") | R70: =Organización_Modular!H56 -> 0 | S70: =Organización_Modular!I56 -> 0 | T70: =SUM(R70:S70) -> 0 | U70: =+R70*$S$19 -> 0 | V70: =+S70*$U$19 -> 0 | W70: =SUM(U70:V70) -> 0 | X70: =W70 -> 0
D71: =Organización_Modular!F57 -> 0 | F71: =_xlfn.IFNA(IF(VLOOKUP($D71,Organización_Modular!$F$10:$G$195,2,FALSE)=F$23,Itinerario!T71," ")," ") | G71: =_xlfn.IFNA(IF(VLOOKUP($D71,Organización_Modular!$F$10:$G$195,2,FALSE)=G$23,Itinerario!W71," ")," ") | H71: =_xlfn.IFNA(IF(VLOOKUP($D71,Organización_Modular!$F$10:$G$195,2,FALSE)=H$23,Itinerario!T71," ")," ") | I71: =_xlfn.IFNA(IF(VLOOKUP($D71,Organización_Modular!$F$10:$G$195,2,FALSE)=I$23,Itinerario!W71," ")," ") | J71: =_xlfn.IFNA(IF(VLOOKUP($D71,Organización_Modular!$F$10:$G$195,2,FALSE)=J$23,Itinerario!T71," ")," ") | K71: =_xlfn.IFNA(IF(VLOOKUP($D71,Organización_Modular!$F$10:$G$195,2,FALSE)=K$23,Itinerario!W71," ")," ") | L71: =_xlfn.IFNA(IF(VLOOKUP($D71,Organización_Modular!$F$10:$G$195,2,FALSE)=L$23,Itinerario!T71," ")," ") | M71: =_xlfn.IFNA(IF(VLOOKUP($D71,Organización_Modular!$F$10:$G$195,2,FALSE)=M$23,Itinerario!W71," ")," ") | N71: =_xlfn.IFNA(IF(VLOOKUP($D71,Organización_Modular!$F$10:$G$195,2,FALSE)=N$23,Itinerario!T71," ")," ") | O71: =_xlfn.IFNA(IF(VLOOKUP($D71,Organización_Modular!$F$10:$G$195,2,FALSE)=O$23,Itinerario!W71," ")," ") | P71: =_xlfn.IFNA(IF(VLOOKUP($D71,Organización_Modular!$F$10:$G$195,2,FALSE)=P$23,Itinerario!T71," ")," ") | Q71: =_xlfn.IFNA(IF(VLOOKUP($D71,Organización_Modular!$F$10:$G$195,2,FALSE)=Q$23,Itinerario!W71," ")," ") | R71: =Organización_Modular!H57 -> 0 | S71: =Organización_Modular!I57 -> 0 | T71: =SUM(R71:S71) -> 0 | U71: =+R71*$S$19 -> 0 | V71: =+S71*$U$19 -> 0 | W71: =SUM(U71:V71) -> 0 | X71: =W71 -> 0
D72: =Organización_Modular!F58 -> 0 | F72: =_xlfn.IFNA(IF(VLOOKUP($D72,Organización_Modular!$F$10:$G$195,2,FALSE)=F$23,Itinerario!T72," ")," ") | G72: =_xlfn.IFNA(IF(VLOOKUP($D72,Organización_Modular!$F$10:$G$195,2,FALSE)=G$23,Itinerario!W72," ")," ") | H72: =_xlfn.IFNA(IF(VLOOKUP($D72,Organización_Modular!$F$10:$G$195,2,FALSE)=H$23,Itinerario!T72," ")," ") | I72: =_xlfn.IFNA(IF(VLOOKUP($D72,Organización_Modular!$F$10:$G$195,2,FALSE)=I$23,Itinerario!W72," ")," ") | J72: =_xlfn.IFNA(IF(VLOOKUP($D72,Organización_Modular!$F$10:$G$195,2,FALSE)=J$23,Itinerario!T72," ")," ") | K72: =_xlfn.IFNA(IF(VLOOKUP($D72,Organización_Modular!$F$10:$G$195,2,FALSE)=K$23,Itinerario!W72," ")," ") | L72: =_xlfn.IFNA(IF(VLOOKUP($D72,Organización_Modular!$F$10:$G$195,2,FALSE)=L$23,Itinerario!T72," ")," ") | M72: =_xlfn.IFNA(IF(VLOOKUP($D72,Organización_Modular!$F$10:$G$195,2,FALSE)=M$23,Itinerario!W72," ")," ") | N72: =_xlfn.IFNA(IF(VLOOKUP($D72,Organización_Modular!$F$10:$G$195,2,FALSE)=N$23,Itinerario!T72," ")," ") | O72: =_xlfn.IFNA(IF(VLOOKUP($D72,Organización_Modular!$F$10:$G$195,2,FALSE)=O$23,Itinerario!W72," ")," ") | P72: =_xlfn.IFNA(IF(VLOOKUP($D72,Organización_Modular!$F$10:$G$195,2,FALSE)=P$23,Itinerario!T72," ")," ") | Q72: =_xlfn.IFNA(IF(VLOOKUP($D72,Organización_Modular!$F$10:$G$195,2,FALSE)=Q$23,Itinerario!W72," ")," ") | R72: =Organización_Modular!H58 -> 0 | S72: =Organización_Modular!I58 -> 0 | T72: =SUM(R72:S72) -> 0 | U72: =+R72*$S$19 -> 0 | V72: =+S72*$U$19 -> 0 | W72: =SUM(U72:V72) -> 0 | X72: =W72 -> 0
D73: =Organización_Modular!F59 -> 0 | F73: =_xlfn.IFNA(IF(VLOOKUP($D73,Organización_Modular!$F$10:$G$195,2,FALSE)=F$23,Itinerario!T73," ")," ") | G73: =_xlfn.IFNA(IF(VLOOKUP($D73,Organización_Modular!$F$10:$G$195,2,FALSE)=G$23,Itinerario!W73," ")," ") | H73: =_xlfn.IFNA(IF(VLOOKUP($D73,Organización_Modular!$F$10:$G$195,2,FALSE)=H$23,Itinerario!T73," ")," ") | I73: =_xlfn.IFNA(IF(VLOOKUP($D73,Organización_Modular!$F$10:$G$195,2,FALSE)=I$23,Itinerario!W73," ")," ") | J73: =_xlfn.IFNA(IF(VLOOKUP($D73,Organización_Modular!$F$10:$G$195,2,FALSE)=J$23,Itinerario!T73," ")," ") | K73: =_xlfn.IFNA(IF(VLOOKUP($D73,Organización_Modular!$F$10:$G$195,2,FALSE)=K$23,Itinerario!W73," ")," ") | L73: =_xlfn.IFNA(IF(VLOOKUP($D73,Organización_Modular!$F$10:$G$195,2,FALSE)=L$23,Itinerario!T73," ")," ") | M73: =_xlfn.IFNA(IF(VLOOKUP($D73,Organización_Modular!$F$10:$G$195,2,FALSE)=M$23,Itinerario!W73," ")," ") | N73: =_xlfn.IFNA(IF(VLOOKUP($D73,Organización_Modular!$F$10:$G$195,2,FALSE)=N$23,Itinerario!T73," ")," ") | O73: =_xlfn.IFNA(IF(VLOOKUP($D73,Organización_Modular!$F$10:$G$195,2,FALSE)=O$23,Itinerario!W73," ")," ") | P73: =_xlfn.IFNA(IF(VLOOKUP($D73,Organización_Modular!$F$10:$G$195,2,FALSE)=P$23,Itinerario!T73," ")," ") | Q73: =_xlfn.IFNA(IF(VLOOKUP($D73,Organización_Modular!$F$10:$G$195,2,FALSE)=Q$23,Itinerario!W73," ")," ") | R73: =Organización_Modular!H59 -> 0 | S73: =Organización_Modular!I59 -> 0 | T73: =SUM(R73:S73) -> 0 | U73: =+R73*$S$19 -> 0 | V73: =+S73*$U$19 -> 0 | W73: =SUM(U73:V73) -> 0 | X73: =W73 -> 0
D74: =Organización_Modular!F60 -> 0 | F74: =_xlfn.IFNA(IF(VLOOKUP($D74,Organización_Modular!$F$10:$G$195,2,FALSE)=F$23,Itinerario!T74," ")," ") | G74: =_xlfn.IFNA(IF(VLOOKUP($D74,Organización_Modular!$F$10:$G$195,2,FALSE)=G$23,Itinerario!W74," ")," ") | H74: =_xlfn.IFNA(IF(VLOOKUP($D74,Organización_Modular!$F$10:$G$195,2,FALSE)=H$23,Itinerario!T74," ")," ") | I74: =_xlfn.IFNA(IF(VLOOKUP($D74,Organización_Modular!$F$10:$G$195,2,FALSE)=I$23,Itinerario!W74," ")," ") | J74: =_xlfn.IFNA(IF(VLOOKUP($D74,Organización_Modular!$F$10:$G$195,2,FALSE)=J$23,Itinerario!T74," ")," ") | K74: =_xlfn.IFNA(IF(VLOOKUP($D74,Organización_Modular!$F$10:$G$195,2,FALSE)=K$23,Itinerario!W74," ")," ") | L74: =_xlfn.IFNA(IF(VLOOKUP($D74,Organización_Modular!$F$10:$G$195,2,FALSE)=L$23,Itinerario!T74," ")," ") | M74: =_xlfn.IFNA(IF(VLOOKUP($D74,Organización_Modular!$F$10:$G$195,2,FALSE)=M$23,Itinerario!W74," ")," ") | N74: =_xlfn.IFNA(IF(VLOOKUP($D74,Organización_Modular!$F$10:$G$195,2,FALSE)=N$23,Itinerario!T74," ")," ") | O74: =_xlfn.IFNA(IF(VLOOKUP($D74,Organización_Modular!$F$10:$G$195,2,FALSE)=O$23,Itinerario!W74," ")," ") | P74: =_xlfn.IFNA(IF(VLOOKUP($D74,Organización_Modular!$F$10:$G$195,2,FALSE)=P$23,Itinerario!T74," ")," ") | Q74: =_xlfn.IFNA(IF(VLOOKUP($D74,Organización_Modular!$F$10:$G$195,2,FALSE)=Q$23,Itinerario!W74," ")," ") | R74: =Organización_Modular!H60 -> 0 | S74: =Organización_Modular!I60 -> 0 | T74: =SUM(R74:S74) -> 0 | U74: =+R74*$S$19 -> 0 | V74: =+S74*$U$19 -> 0 | W74: =SUM(U74:V74) -> 0 | X74: =W74 -> 0
B75: =B44 -> Competencias para la empleabilidad | C75: =Organización_Modular!C61 -> CE3 Emprendimiento.- Identificar nuevas oportunidades de proyectos o negocios que generen valor y sean sostenibles, gestionando recursos para su funcionamiento con creatividad y ética, articulando acciones que permitan desarrollar innovaciones en la creación de bienes y/o servicios, así como en procesos o productos ya existentes. CE4 Ética.-Establecer relaciones con respeto y justicia en los ámbitos personal, colectivo e institucional, contribuyendo a una convivencia democrática, orientada al bien común que considere la diversidad y dignidad de las personas, teniendo en cuenta las consideraciones aplicadas en su contexto laboral. | D75: =Organización_Modular!F61 -> Plan de Negocios | F75: =_xlfn.IFNA(IF(VLOOKUP($D75,Organización_Modular!$F$10:$G$195,2,FALSE)=F$23,Itinerario!T75," ")," ") | G75: =_xlfn.IFNA(IF(VLOOKUP($D75,Organización_Modular!$F$10:$G$195,2,FALSE)=G$23,Itinerario!W75," ")," ") | H75: =_xlfn.IFNA(IF(VLOOKUP($D75,Organización_Modular!$F$10:$G$195,2,FALSE)=H$23,Itinerario!T75," ")," ") -> 2 | I75: =_xlfn.IFNA(IF(VLOOKUP($D75,Organización_Modular!$F$10:$G$195,2,FALSE)=I$23,Itinerario!W75," ")," ") -> 48 | J75: =_xlfn.IFNA(IF(VLOOKUP($D75,Organización_Modular!$F$10:$G$195,2,FALSE)=J$23,Itinerario!T75," ")," ") | K75: =_xlfn.IFNA(IF(VLOOKUP($D75,Organización_Modular!$F$10:$G$195,2,FALSE)=K$23,Itinerario!W75," ")," ") | L75: =_xlfn.IFNA(IF(VLOOKUP($D75,Organización_Modular!$F$10:$G$195,2,FALSE)=L$23,Itinerario!T75," ")," ") | M75: =_xlfn.IFNA(IF(VLOOKUP($D75,Organización_Modular!$F$10:$G$195,2,FALSE)=M$23,Itinerario!W75," ")," ") | N75: =_xlfn.IFNA(IF(VLOOKUP($D75,Organización_Modular!$F$10:$G$195,2,FALSE)=N$23,Itinerario!T75," ")," ") | O75: =_xlfn.IFNA(IF(VLOOKUP($D75,Organización_Modular!$F$10:$G$195,2,FALSE)=O$23,Itinerario!W75," ")," ") | P75: =_xlfn.IFNA(IF(VLOOKUP($D75,Organización_Modular!$F$10:$G$195,2,FALSE)=P$23,Itinerario!T75," ")," ") | Q75: =_xlfn.IFNA(IF(VLOOKUP($D75,Organización_Modular!$F$10:$G$195,2,FALSE)=Q$23,Itinerario!W75," ")," ") | R75: =Organización_Modular!H61 -> 1 | S75: =Organización_Modular!I61 -> 1 | T75: =SUM(R75:S75) -> 2 | U75: =+R75*$S$19 -> 16 | V75: =+S75*$U$19 -> 32 | W75: =SUM(U75:V75) -> 48 | X75: =W75 -> 48
D76: =Organización_Modular!F62 -> Comportamiento ético | F76: =_xlfn.IFNA(IF(VLOOKUP($D76,Organización_Modular!$F$10:$G$195,2,FALSE)=F$23,Itinerario!T76," ")," ") | G76: =_xlfn.IFNA(IF(VLOOKUP($D76,Organización_Modular!$F$10:$G$195,2,FALSE)=G$23,Itinerario!W76," ")," ") | H76: =_xlfn.IFNA(IF(VLOOKUP($D76,Organización_Modular!$F$10:$G$195,2,FALSE)=H$23,Itinerario!T76," ")," ") -> 2 | I76: =_xlfn.IFNA(IF(VLOOKUP($D76,Organización_Modular!$F$10:$G$195,2,FALSE)=I$23,Itinerario!W76," ")," ") -> 48 | J76: =_xlfn.IFNA(IF(VLOOKUP($D76,Organización_Modular!$F$10:$G$195,2,FALSE)=J$23,Itinerario!T76," ")," ") | K76: =_xlfn.IFNA(IF(VLOOKUP($D76,Organización_Modular!$F$10:$G$195,2,FALSE)=K$23,Itinerario!W76," ")," ") | L76: =_xlfn.IFNA(IF(VLOOKUP($D76,Organización_Modular!$F$10:$G$195,2,FALSE)=L$23,Itinerario!T76," ")," ") | M76: =_xlfn.IFNA(IF(VLOOKUP($D76,Organización_Modular!$F$10:$G$195,2,FALSE)=M$23,Itinerario!W76," ")," ") | N76: =_xlfn.IFNA(IF(VLOOKUP($D76,Organización_Modular!$F$10:$G$195,2,FALSE)=N$23,Itinerario!T76," ")," ") | O76: =_xlfn.IFNA(IF(VLOOKUP($D76,Organización_Modular!$F$10:$G$195,2,FALSE)=O$23,Itinerario!W76," ")," ") | P76: =_xlfn.IFNA(IF(VLOOKUP($D76,Organización_Modular!$F$10:$G$195,2,FALSE)=P$23,Itinerario!T76," ")," ") | Q76: =_xlfn.IFNA(IF(VLOOKUP($D76,Organización_Modular!$F$10:$G$195,2,FALSE)=Q$23,Itinerario!W76," ")," ") | R76: =Organización_Modular!H62 -> 1 | S76: =Organización_Modular!I62 -> 1 | T76: =SUM(R76:S76) -> 2 | U76: =+R76*$S$19 -> 16 | V76: =+S76*$U$19 -> 32 | W76: =SUM(U76:V76) -> 48 | X76: =W76 -> 48
F77: =_xlfn.IFNA(IF(VLOOKUP($D77,Organización_Modular!$F$10:$G$195,2,FALSE)=F$23,Itinerario!T77," ")," ") | G77: =_xlfn.IFNA(IF(VLOOKUP($D77,Organización_Modular!$F$10:$G$195,2,FALSE)=G$23,Itinerario!W77," ")," ") | H77: =_xlfn.IFNA(IF(VLOOKUP($D77,Organización_Modular!$F$10:$G$195,2,FALSE)=H$23,Itinerario!T77," ")," ") | I77: =_xlfn.IFNA(IF(VLOOKUP($D77,Organización_Modular!$F$10:$G$195,2,FALSE)=I$23,Itinerario!W77," ")," ") | J77: =_xlfn.IFNA(IF(VLOOKUP($D77,Organización_Modular!$F$10:$G$195,2,FALSE)=J$23,Itinerario!T77," ")," ") | K77: =_xlfn.IFNA(IF(VLOOKUP($D77,Organización_Modular!$F$10:$G$195,2,FALSE)=K$23,Itinerario!W77," ")," ") | L77: =_xlfn.IFNA(IF(VLOOKUP($D77,Organización_Modular!$F$10:$G$195,2,FALSE)=L$23,Itinerario!T77," ")," ") | M77: =_xlfn.IFNA(IF(VLOOKUP($D77,Organización_Modular!$F$10:$G$195,2,FALSE)=M$23,Itinerario!W77," ")," ") | N77: =_xlfn.IFNA(IF(VLOOKUP($D77,Organización_Modular!$F$10:$G$195,2,FALSE)=N$23,Itinerario!T77," ")," ") | O77: =_xlfn.IFNA(IF(VLOOKUP($D77,Organización_Modular!$F$10:$G$195,2,FALSE)=O$23,Itinerario!W77," ")," ") | P77: =_xlfn.IFNA(IF(VLOOKUP($D77,Organización_Modular!$F$10:$G$195,2,FALSE)=P$23,Itinerario!T77," ")," ") | Q77: =_xlfn.IFNA(IF(VLOOKUP($D77,Organización_Modular!$F$10:$G$195,2,FALSE)=Q$23,Itinerario!W77," ")," ") | X77: =W77 -> 0
D78: =Organización_Modular!F64 -> 0 | F78: =_xlfn.IFNA(IF(VLOOKUP($D78,Organización_Modular!$F$10:$G$195,2,FALSE)=F$23,Itinerario!T78," ")," ") | G78: =_xlfn.IFNA(IF(VLOOKUP($D78,Organización_Modular!$F$10:$G$195,2,FALSE)=G$23,Itinerario!W78," ")," ") | H78: =_xlfn.IFNA(IF(VLOOKUP($D78,Organización_Modular!$F$10:$G$195,2,FALSE)=H$23,Itinerario!T78," ")," ") | I78: =_xlfn.IFNA(IF(VLOOKUP($D78,Organización_Modular!$F$10:$G$195,2,FALSE)=I$23,Itinerario!W78," ")," ") | J78: =_xlfn.IFNA(IF(VLOOKUP($D78,Organización_Modular!$F$10:$G$195,2,FALSE)=J$23,Itinerario!T78," ")," ") | K78: =_xlfn.IFNA(IF(VLOOKUP($D78,Organización_Modular!$F$10:$G$195,2,FALSE)=K$23,Itinerario!W78," ")," ") | L78: =_xlfn.IFNA(IF(VLOOKUP($D78,Organización_Modular!$F$10:$G$195,2,FALSE)=L$23,Itinerario!T78," ")," ") | M78: =_xlfn.IFNA(IF(VLOOKUP($D78,Organización_Modular!$F$10:$G$195,2,FALSE)=M$23,Itinerario!W78," ")," ") | N78: =_xlfn.IFNA(IF(VLOOKUP($D78,Organización_Modular!$F$10:$G$195,2,FALSE)=N$23,Itinerario!T78," ")," ") | O78: =_xlfn.IFNA(IF(VLOOKUP($D78,Organización_Modular!$F$10:$G$195,2,FALSE)=O$23,Itinerario!W78," ")," ") | P78: =_xlfn.IFNA(IF(VLOOKUP($D78,Organización_Modular!$F$10:$G$195,2,FALSE)=P$23,Itinerario!T78," ")," ") | Q78: =_xlfn.IFNA(IF(VLOOKUP($D78,Organización_Modular!$F$10:$G$195,2,FALSE)=Q$23,Itinerario!W78," ")," ") | R78: =Organización_Modular!H64 -> 0 | S78: =Organización_Modular!I64 -> 0 | T78: =SUM(R78:S78) -> 0 | U78: =+R78*$S$19 -> 0 | V78: =+S78*$U$19 -> 0 | W78: =SUM(U78:V78) -> 0 | X78: =W78 -> 0
D79: =Organización_Modular!F65 -> 0 | F79: =_xlfn.IFNA(IF(VLOOKUP($D79,Organización_Modular!$F$10:$G$195,2,FALSE)=F$23,Itinerario!T79," ")," ") | G79: =_xlfn.IFNA(IF(VLOOKUP($D79,Organización_Modular!$F$10:$G$195,2,FALSE)=G$23,Itinerario!W79," ")," ") | H79: =_xlfn.IFNA(IF(VLOOKUP($D79,Organización_Modular!$F$10:$G$195,2,FALSE)=H$23,Itinerario!T79," ")," ") | I79: =_xlfn.IFNA(IF(VLOOKUP($D79,Organización_Modular!$F$10:$G$195,2,FALSE)=I$23,Itinerario!W79," ")," ") | J79: =_xlfn.IFNA(IF(VLOOKUP($D79,Organización_Modular!$F$10:$G$195,2,FALSE)=J$23,Itinerario!T79," ")," ") | K79: =_xlfn.IFNA(IF(VLOOKUP($D79,Organización_Modular!$F$10:$G$195,2,FALSE)=K$23,Itinerario!W79," ")," ") | L79: =_xlfn.IFNA(IF(VLOOKUP($D79,Organización_Modular!$F$10:$G$195,2,FALSE)=L$23,Itinerario!T79," ")," ") | M79: =_xlfn.IFNA(IF(VLOOKUP($D79,Organización_Modular!$F$10:$G$195,2,FALSE)=M$23,Itinerario!W79," ")," ") | N79: =_xlfn.IFNA(IF(VLOOKUP($D79,Organización_Modular!$F$10:$G$195,2,FALSE)=N$23,Itinerario!T79," ")," ") | O79: =_xlfn.IFNA(IF(VLOOKUP($D79,Organización_Modular!$F$10:$G$195,2,FALSE)=O$23,Itinerario!W79," ")," ") | P79: =_xlfn.IFNA(IF(VLOOKUP($D79,Organización_Modular!$F$10:$G$195,2,FALSE)=P$23,Itinerario!T79," ")," ") | Q79: =_xlfn.IFNA(IF(VLOOKUP($D79,Organización_Modular!$F$10:$G$195,2,FALSE)=Q$23,Itinerario!W79," ")," ") | R79: =Organización_Modular!H65 -> 0 | S79: =Organización_Modular!I65 -> 0 | T79: =SUM(R79:S79) -> 0 | U79: =+R79*$S$19 -> 0 | V79: =+S79*$U$19 -> 0 | W79: =SUM(U79:V79) -> 0 | X79: =W79 -> 0
D80: =Organización_Modular!F66 -> 0 | F80: =_xlfn.IFNA(IF(VLOOKUP($D80,Organización_Modular!$F$10:$G$195,2,FALSE)=F$23,Itinerario!T80," ")," ") | G80: =_xlfn.IFNA(IF(VLOOKUP($D80,Organización_Modular!$F$10:$G$195,2,FALSE)=G$23,Itinerario!W80," ")," ") | H80: =_xlfn.IFNA(IF(VLOOKUP($D80,Organización_Modular!$F$10:$G$195,2,FALSE)=H$23,Itinerario!T80," ")," ") | I80: =_xlfn.IFNA(IF(VLOOKUP($D80,Organización_Modular!$F$10:$G$195,2,FALSE)=I$23,Itinerario!W80," ")," ") | J80: =_xlfn.IFNA(IF(VLOOKUP($D80,Organización_Modular!$F$10:$G$195,2,FALSE)=J$23,Itinerario!T80," ")," ") | K80: =_xlfn.IFNA(IF(VLOOKUP($D80,Organización_Modular!$F$10:$G$195,2,FALSE)=K$23,Itinerario!W80," ")," ") | L80: =_xlfn.IFNA(IF(VLOOKUP($D80,Organización_Modular!$F$10:$G$195,2,FALSE)=L$23,Itinerario!T80," ")," ") | M80: =_xlfn.IFNA(IF(VLOOKUP($D80,Organización_Modular!$F$10:$G$195,2,FALSE)=M$23,Itinerario!W80," ")," ") | N80: =_xlfn.IFNA(IF(VLOOKUP($D80,Organización_Modular!$F$10:$G$195,2,FALSE)=N$23,Itinerario!T80," ")," ") | O80: =_xlfn.IFNA(IF(VLOOKUP($D80,Organización_Modular!$F$10:$G$195,2,FALSE)=O$23,Itinerario!W80," ")," ") | P80: =_xlfn.IFNA(IF(VLOOKUP($D80,Organización_Modular!$F$10:$G$195,2,FALSE)=P$23,Itinerario!T80," ")," ") | Q80: =_xlfn.IFNA(IF(VLOOKUP($D80,Organización_Modular!$F$10:$G$195,2,FALSE)=Q$23,Itinerario!W80," ")," ") | R80: =Organización_Modular!H66 -> 0 | S80: =Organización_Modular!I66 -> 0 | T80: =SUM(R80:S80) -> 0 | U80: =+R80*$S$19 -> 0 | V80: =+S80*$U$19 -> 0 | W80: =SUM(U80:V80) -> 0 | X80: =W80 -> 0
D81: =Organización_Modular!F67 -> 0 | F81: =_xlfn.IFNA(IF(VLOOKUP($D81,Organización_Modular!$F$10:$G$195,2,FALSE)=F$23,Itinerario!T81," ")," ") | G81: =_xlfn.IFNA(IF(VLOOKUP($D81,Organización_Modular!$F$10:$G$195,2,FALSE)=G$23,Itinerario!W81," ")," ") | H81: =_xlfn.IFNA(IF(VLOOKUP($D81,Organización_Modular!$F$10:$G$195,2,FALSE)=H$23,Itinerario!T81," ")," ") | I81: =_xlfn.IFNA(IF(VLOOKUP($D81,Organización_Modular!$F$10:$G$195,2,FALSE)=I$23,Itinerario!W81," ")," ") | J81: =_xlfn.IFNA(IF(VLOOKUP($D81,Organización_Modular!$F$10:$G$195,2,FALSE)=J$23,Itinerario!T81," ")," ") | K81: =_xlfn.IFNA(IF(VLOOKUP($D81,Organización_Modular!$F$10:$G$195,2,FALSE)=K$23,Itinerario!W81," ")," ") | L81: =_xlfn.IFNA(IF(VLOOKUP($D81,Organización_Modular!$F$10:$G$195,2,FALSE)=L$23,Itinerario!T81," ")," ") | M81: =_xlfn.IFNA(IF(VLOOKUP($D81,Organización_Modular!$F$10:$G$195,2,FALSE)=M$23,Itinerario!W81," ")," ") | N81: =_xlfn.IFNA(IF(VLOOKUP($D81,Organización_Modular!$F$10:$G$195,2,FALSE)=N$23,Itinerario!T81," ")," ") | O81: =_xlfn.IFNA(IF(VLOOKUP($D81,Organización_Modular!$F$10:$G$195,2,FALSE)=O$23,Itinerario!W81," ")," ") | P81: =_xlfn.IFNA(IF(VLOOKUP($D81,Organización_Modular!$F$10:$G$195,2,FALSE)=P$23,Itinerario!T81," ")," ") | Q81: =_xlfn.IFNA(IF(VLOOKUP($D81,Organización_Modular!$F$10:$G$195,2,FALSE)=Q$23,Itinerario!W81," ")," ") | R81: =Organización_Modular!H67 -> 0 | S81: =Organización_Modular!I67 -> 0 | T81: =SUM(R81:S81) -> 0 | U81: =+R81*$S$19 -> 0 | V81: =+S81*$U$19 -> 0 | W81: =SUM(U81:V81) -> 0 | X81: =W81 -> 0
D82: =Organización_Modular!F68 -> 0 | F82: =_xlfn.IFNA(IF(VLOOKUP($D82,Organización_Modular!$F$10:$G$195,2,FALSE)=F$23,Itinerario!T82," ")," ") | G82: =_xlfn.IFNA(IF(VLOOKUP($D82,Organización_Modular!$F$10:$G$195,2,FALSE)=G$23,Itinerario!W82," ")," ") | H82: =_xlfn.IFNA(IF(VLOOKUP($D82,Organización_Modular!$F$10:$G$195,2,FALSE)=H$23,Itinerario!T82," ")," ") | I82: =_xlfn.IFNA(IF(VLOOKUP($D82,Organización_Modular!$F$10:$G$195,2,FALSE)=I$23,Itinerario!W82," ")," ") | J82: =_xlfn.IFNA(IF(VLOOKUP($D82,Organización_Modular!$F$10:$G$195,2,FALSE)=J$23,Itinerario!T82," ")," ") | K82: =_xlfn.IFNA(IF(VLOOKUP($D82,Organización_Modular!$F$10:$G$195,2,FALSE)=K$23,Itinerario!W82," ")," ") | L82: =_xlfn.IFNA(IF(VLOOKUP($D82,Organización_Modular!$F$10:$G$195,2,FALSE)=L$23,Itinerario!T82," ")," ") | M82: =_xlfn.IFNA(IF(VLOOKUP($D82,Organización_Modular!$F$10:$G$195,2,FALSE)=M$23,Itinerario!W82," ")," ") | N82: =_xlfn.IFNA(IF(VLOOKUP($D82,Organización_Modular!$F$10:$G$195,2,FALSE)=N$23,Itinerario!T82," ")," ") | O82: =_xlfn.IFNA(IF(VLOOKUP($D82,Organización_Modular!$F$10:$G$195,2,FALSE)=O$23,Itinerario!W82," ")," ") | P82: =_xlfn.IFNA(IF(VLOOKUP($D82,Organización_Modular!$F$10:$G$195,2,FALSE)=P$23,Itinerario!T82," ")," ") | Q82: =_xlfn.IFNA(IF(VLOOKUP($D82,Organización_Modular!$F$10:$G$195,2,FALSE)=Q$23,Itinerario!W82," ")," ") | R82: =Organización_Modular!H68 -> 0 | S82: =Organización_Modular!I68 -> 0 | T82: =SUM(R82:S82) -> 0 | U82: =+R82*$S$19 -> 0 | V82: =+S82*$U$19 -> 0 | W82: =SUM(U82:V82) -> 0 | X82: =W82 -> 0
D83: =Organización_Modular!F69 -> 0 | F83: =_xlfn.IFNA(IF(VLOOKUP($D83,Organización_Modular!$F$10:$G$195,2,FALSE)=F$23,Itinerario!T83," ")," ") | G83: =_xlfn.IFNA(IF(VLOOKUP($D83,Organización_Modular!$F$10:$G$195,2,FALSE)=G$23,Itinerario!W83," ")," ") | H83: =_xlfn.IFNA(IF(VLOOKUP($D83,Organización_Modular!$F$10:$G$195,2,FALSE)=H$23,Itinerario!T83," ")," ") | I83: =_xlfn.IFNA(IF(VLOOKUP($D83,Organización_Modular!$F$10:$G$195,2,FALSE)=I$23,Itinerario!W83," ")," ") | J83: =_xlfn.IFNA(IF(VLOOKUP($D83,Organización_Modular!$F$10:$G$195,2,FALSE)=J$23,Itinerario!T83," ")," ") | K83: =_xlfn.IFNA(IF(VLOOKUP($D83,Organización_Modular!$F$10:$G$195,2,FALSE)=K$23,Itinerario!W83," ")," ") | L83: =_xlfn.IFNA(IF(VLOOKUP($D83,Organización_Modular!$F$10:$G$195,2,FALSE)=L$23,Itinerario!T83," ")," ") | M83: =_xlfn.IFNA(IF(VLOOKUP($D83,Organización_Modular!$F$10:$G$195,2,FALSE)=M$23,Itinerario!W83," ")," ") | N83: =_xlfn.IFNA(IF(VLOOKUP($D83,Organización_Modular!$F$10:$G$195,2,FALSE)=N$23,Itinerario!T83," ")," ") | O83: =_xlfn.IFNA(IF(VLOOKUP($D83,Organización_Modular!$F$10:$G$195,2,FALSE)=O$23,Itinerario!W83," ")," ") | P83: =_xlfn.IFNA(IF(VLOOKUP($D83,Organización_Modular!$F$10:$G$195,2,FALSE)=P$23,Itinerario!T83," ")," ") | Q83: =_xlfn.IFNA(IF(VLOOKUP($D83,Organización_Modular!$F$10:$G$195,2,FALSE)=Q$23,Itinerario!W83," ")," ") | R83: =Organización_Modular!H69 -> 0 | S83: =Organización_Modular!I69 -> 0 | T83: =SUM(R83:S83) -> 0 | U83: =+R83*$S$19 -> 0 | V83: =+S83*$U$19 -> 0 | W83: =SUM(U83:V83) -> 0 | X83: =W83 -> 0
X84: =W84 -> 0
B85: =B54 -> Experiencias formativas en situaciones reales de trabajo (ESRT) | H85: =Organización_Modular!I71 -> 6 | I85: =H85*32 -> 192 | R85: =Organización_Modular!H71 -> 0 | S85: =Organización_Modular!I71 -> 6 | T85: =SUM(R85:S85) -> 6 | U85: =+R85*$S$19 -> 0 | V85: =+S85*$U$19 -> 192 | W85: =SUM(U85:V85) -> 192 | X85: =W85 -> 192
A86: =Organización_Modular!A72 -> 0 | B86: =B24 -> Competencias técnicas (Unidad de competencia) | C86: =Organización_Modular!C72 -> 0 | D86: =Organización_Modular!F72 -> 0 | F86: =_xlfn.IFNA(IF(VLOOKUP($D86,Organización_Modular!$F$10:$G$195,2,FALSE)=F$23,Itinerario!T86," ")," ") | G86: =_xlfn.IFNA(IF(VLOOKUP($D86,Organización_Modular!$F$10:$G$195,2,FALSE)=G$23,Itinerario!W86," ")," ") | H86: =_xlfn.IFNA(IF(VLOOKUP($D86,Organización_Modular!$F$10:$G$195,2,FALSE)=H$23,Itinerario!T86," ")," ") | I86: =_xlfn.IFNA(IF(VLOOKUP($D86,Organización_Modular!$F$10:$G$195,2,FALSE)=I$23,Itinerario!W86," ")," ") | J86: =_xlfn.IFNA(IF(VLOOKUP($D86,Organización_Modular!$F$10:$G$195,2,FALSE)=J$23,Itinerario!T86," ")," ") | K86: =_xlfn.IFNA(IF(VLOOKUP($D86,Organización_Modular!$F$10:$G$195,2,FALSE)=K$23,Itinerario!W86," ")," ") | L86: =_xlfn.IFNA(IF(VLOOKUP($D86,Organización_Modular!$F$10:$G$195,2,FALSE)=L$23,Itinerario!T86," ")," ") | M86: =_xlfn.IFNA(IF(VLOOKUP($D86,Organización_Modular!$F$10:$G$195,2,FALSE)=M$23,Itinerario!W86," ")," ") | N86: =_xlfn.IFNA(IF(VLOOKUP($D86,Organización_Modular!$F$10:$G$195,2,FALSE)=N$23,Itinerario!T86," ")," ") | O86: =_xlfn.IFNA(IF(VLOOKUP($D86,Organización_Modular!$F$10:$G$195,2,FALSE)=O$23,Itinerario!W86," ")," ") | P86: =_xlfn.IFNA(IF(VLOOKUP($D86,Organización_Modular!$F$10:$G$195,2,FALSE)=P$23,Itinerario!T86," ")," ") | Q86: =_xlfn.IFNA(IF(VLOOKUP($D86,Organización_Modular!$F$10:$G$195,2,FALSE)=Q$23,Itinerario!W86," ")," ") | R86: =Organización_Modular!H72 -> 0 | S86: =Organización_Modular!I72 -> 0 | T86: =SUM(R86:S86) -> 0 | U86: =+R86*$S$19 -> 0 | V86: =+S86*$U$19 -> 0 | W86: =SUM(U86:V86) -> 0 | X86: =W86 -> 0
D87: =Organización_Modular!F73 -> 0 | F87: =_xlfn.IFNA(IF(VLOOKUP($D87,Organización_Modular!$F$10:$G$195,2,FALSE)=F$23,Itinerario!T87," ")," ") | G87: =_xlfn.IFNA(IF(VLOOKUP($D87,Organización_Modular!$F$10:$G$195,2,FALSE)=G$23,Itinerario!W87," ")," ") | H87: =_xlfn.IFNA(IF(VLOOKUP($D87,Organización_Modular!$F$10:$G$195,2,FALSE)=H$23,Itinerario!T87," ")," ") | I87: =_xlfn.IFNA(IF(VLOOKUP($D87,Organización_Modular!$F$10:$G$195,2,FALSE)=I$23,Itinerario!W87," ")," ") | J87: =_xlfn.IFNA(IF(VLOOKUP($D87,Organización_Modular!$F$10:$G$195,2,FALSE)=J$23,Itinerario!T87," ")," ") | K87: =_xlfn.IFNA(IF(VLOOKUP($D87,Organización_Modular!$F$10:$G$195,2,FALSE)=K$23,Itinerario!W87," ")," ") | L87: =_xlfn.IFNA(IF(VLOOKUP($D87,Organización_Modular!$F$10:$G$195,2,FALSE)=L$23,Itinerario!T87," ")," ") | M87: =_xlfn.IFNA(IF(VLOOKUP($D87,Organización_Modular!$F$10:$G$195,2,FALSE)=M$23,Itinerario!W87," ")," ") | N87: =_xlfn.IFNA(IF(VLOOKUP($D87,Organización_Modular!$F$10:$G$195,2,FALSE)=N$23,Itinerario!T87," ")," ") | O87: =_xlfn.IFNA(IF(VLOOKUP($D87,Organización_Modular!$F$10:$G$195,2,FALSE)=O$23,Itinerario!W87," ")," ") | P87: =_xlfn.IFNA(IF(VLOOKUP($D87,Organización_Modular!$F$10:$G$195,2,FALSE)=P$23,Itinerario!T87," ")," ") | Q87: =_xlfn.IFNA(IF(VLOOKUP($D87,Organización_Modular!$F$10:$G$195,2,FALSE)=Q$23,Itinerario!W87," ")," ") | R87: =Organización_Modular!H73 -> 0 | S87: =Organización_Modular!I73 -> 0 | T87: =SUM(R87:S87) -> 0 | U87: =+R87*$S$19 -> 0 | V87: =+S87*$U$19 -> 0 | W87: =SUM(U87:V87) -> 0 | X87: =W87 -> 0
D88: =Organización_Modular!F74 -> 0 | F88: =_xlfn.IFNA(IF(VLOOKUP($D88,Organización_Modular!$F$10:$G$195,2,FALSE)=F$23,Itinerario!T88," ")," ") | G88: =_xlfn.IFNA(IF(VLOOKUP($D88,Organización_Modular!$F$10:$G$195,2,FALSE)=G$23,Itinerario!W88," ")," ") | H88: =_xlfn.IFNA(IF(VLOOKUP($D88,Organización_Modular!$F$10:$G$195,2,FALSE)=H$23,Itinerario!T88," ")," ") | I88: =_xlfn.IFNA(IF(VLOOKUP($D88,Organización_Modular!$F$10:$G$195,2,FALSE)=I$23,Itinerario!W88," ")," ") | J88: =_xlfn.IFNA(IF(VLOOKUP($D88,Organización_Modular!$F$10:$G$195,2,FALSE)=J$23,Itinerario!T88," ")," ") | K88: =_xlfn.IFNA(IF(VLOOKUP($D88,Organización_Modular!$F$10:$G$195,2,FALSE)=K$23,Itinerario!W88," ")," ") | L88: =_xlfn.IFNA(IF(VLOOKUP($D88,Organización_Modular!$F$10:$G$195,2,FALSE)=L$23,Itinerario!T88," ")," ") | M88: =_xlfn.IFNA(IF(VLOOKUP($D88,Organización_Modular!$F$10:$G$195,2,FALSE)=M$23,Itinerario!W88," ")," ") | N88: =_xlfn.IFNA(IF(VLOOKUP($D88,Organización_Modular!$F$10:$G$195,2,FALSE)=N$23,Itinerario!T88," ")," ") | O88: =_xlfn.IFNA(IF(VLOOKUP($D88,Organización_Modular!$F$10:$G$195,2,FALSE)=O$23,Itinerario!W88," ")," ") | P88: =_xlfn.IFNA(IF(VLOOKUP($D88,Organización_Modular!$F$10:$G$195,2,FALSE)=P$23,Itinerario!T88," ")," ") | Q88: =_xlfn.IFNA(IF(VLOOKUP($D88,Organización_Modular!$F$10:$G$195,2,FALSE)=Q$23,Itinerario!W88," ")," ") | R88: =Organización_Modular!H74 -> 0 | S88: =Organización_Modular!I74 -> 0 | T88: =SUM(R88:S88) -> 0 | U88: =+R88*$S$19 -> 0 | V88: =+S88*$U$19 -> 0 | W88: =SUM(U88:V88) -> 0 | X88: =W88 -> 0
D89: =Organización_Modular!F75 -> 0 | F89: =_xlfn.IFNA(IF(VLOOKUP($D89,Organización_Modular!$F$10:$G$195,2,FALSE)=F$23,Itinerario!T89," ")," ") | G89: =_xlfn.IFNA(IF(VLOOKUP($D89,Organización_Modular!$F$10:$G$195,2,FALSE)=G$23,Itinerario!W89," ")," ") | H89: =_xlfn.IFNA(IF(VLOOKUP($D89,Organización_Modular!$F$10:$G$195,2,FALSE)=H$23,Itinerario!T89," ")," ") | I89: =_xlfn.IFNA(IF(VLOOKUP($D89,Organización_Modular!$F$10:$G$195,2,FALSE)=I$23,Itinerario!W89," ")," ") | J89: =_xlfn.IFNA(IF(VLOOKUP($D89,Organización_Modular!$F$10:$G$195,2,FALSE)=J$23,Itinerario!T89," ")," ") | K89: =_xlfn.IFNA(IF(VLOOKUP($D89,Organización_Modular!$F$10:$G$195,2,FALSE)=K$23,Itinerario!W89," ")," ") | L89: =_xlfn.IFNA(IF(VLOOKUP($D89,Organización_Modular!$F$10:$G$195,2,FALSE)=L$23,Itinerario!T89," ")," ") | M89: =_xlfn.IFNA(IF(VLOOKUP($D89,Organización_Modular!$F$10:$G$195,2,FALSE)=M$23,Itinerario!W89," ")," ") | N89: =_xlfn.IFNA(IF(VLOOKUP($D89,Organización_Modular!$F$10:$G$195,2,FALSE)=N$23,Itinerario!T89," ")," ") | O89: =_xlfn.IFNA(IF(VLOOKUP($D89,Organización_Modular!$F$10:$G$195,2,FALSE)=O$23,Itinerario!W89," ")," ") | P89: =_xlfn.IFNA(IF(VLOOKUP($D89,Organización_Modular!$F$10:$G$195,2,FALSE)=P$23,Itinerario!T89," ")," ") | Q89: =_xlfn.IFNA(IF(VLOOKUP($D89,Organización_Modular!$F$10:$G$195,2,FALSE)=Q$23,Itinerario!W89," ")," ") | R89: =Organización_Modular!H75 -> 0 | S89: =Organización_Modular!I75 -> 0 | T89: =SUM(R89:S89) -> 0 | U89: =+R89*$S$19 -> 0 | V89: =+S89*$U$19 -> 0 | W89: =SUM(U89:V89) -> 0 | X89: =W89 -> 0
D90: =Organización_Modular!F76 -> 0 | F90: =_xlfn.IFNA(IF(VLOOKUP($D90,Organización_Modular!$F$10:$G$195,2,FALSE)=F$23,Itinerario!T90," ")," ") | G90: =_xlfn.IFNA(IF(VLOOKUP($D90,Organización_Modular!$F$10:$G$195,2,FALSE)=G$23,Itinerario!W90," ")," ") | H90: =_xlfn.IFNA(IF(VLOOKUP($D90,Organización_Modular!$F$10:$G$195,2,FALSE)=H$23,Itinerario!T90," ")," ") | I90: =_xlfn.IFNA(IF(VLOOKUP($D90,Organización_Modular!$F$10:$G$195,2,FALSE)=I$23,Itinerario!W90," ")," ") | J90: =_xlfn.IFNA(IF(VLOOKUP($D90,Organización_Modular!$F$10:$G$195,2,FALSE)=J$23,Itinerario!T90," ")," ") | K90: =_xlfn.IFNA(IF(VLOOKUP($D90,Organización_Modular!$F$10:$G$195,2,FALSE)=K$23,Itinerario!W90," ")," ") | L90: =_xlfn.IFNA(IF(VLOOKUP($D90,Organización_Modular!$F$10:$G$195,2,FALSE)=L$23,Itinerario!T90," ")," ") | M90: =_xlfn.IFNA(IF(VLOOKUP($D90,Organización_Modular!$F$10:$G$195,2,FALSE)=M$23,Itinerario!W90," ")," ") | N90: =_xlfn.IFNA(IF(VLOOKUP($D90,Organización_Modular!$F$10:$G$195,2,FALSE)=N$23,Itinerario!T90," ")," ") | O90: =_xlfn.IFNA(IF(VLOOKUP($D90,Organización_Modular!$F$10:$G$195,2,FALSE)=O$23,Itinerario!W90," ")," ") | P90: =_xlfn.IFNA(IF(VLOOKUP($D90,Organización_Modular!$F$10:$G$195,2,FALSE)=P$23,Itinerario!T90," ")," ") | Q90: =_xlfn.IFNA(IF(VLOOKUP($D90,Organización_Modular!$F$10:$G$195,2,FALSE)=Q$23,Itinerario!W90," ")," ") | R90: =Organización_Modular!H76 -> 0 | S90: =Organización_Modular!I76 -> 0 | T90: =SUM(R90:S90) -> 0 | U90: =+R90*$S$19 -> 0 | V90: =+S90*$U$19 -> 0 | W90: =SUM(U90:V90) -> 0 | X90: =W90 -> 0
