Workbook

Sheet Perfil_Egreso
A1: ANEXO Nº 9 PERFIL DE EGRESO (PARA CICLOS FORMATIVOS: TÉCNICO Y AUXILIAR TÉCNICO)
A3: DENOMINACIÓN DE LA INSTITUCIÓN | B3: CETPRO JUANJUI | D3: CÓDIGO MODULAR DEL CETPRO | E3: 533836
A5: SECTOR ECONÓMICO | B5: OTRAS ACTIVIDADES DE SERVICIO | C5: FAMILIA PRODUCTIVA | D5: SERVICIOS PERSONALES Y DE HOGARES
A7: ACTIVIDAD ECONÓMICA | B7: OTRAS ACTIVIDADES DE SERVICIOS PERSONALES
A9: DENOMINACIÓN VARIANTE
A11: DENOMINACIÓN DEL PROGRAMA DE ESTUDIOS | B11: ESTILISMO | D11: CÓDIGO * | E11: S3496-2-001
A13: FORMACIÓN** | B13: 0 | C13: MODALIDAD DEL SERVICIO EDUCATIVO *** | D13: PRESENCIAL
A15: CICLO FORMATIVO | B15: TÉCNICO
A17: DESCRIPCIÓN DEL PERFIL DE EGRESO | F17: Filtrar
A18: El egresado en estilismo será capaz de ejecutar el servicio de peluquería y barbería, realizar procedimientos técnicos capilares, maquillaje de belleza y de caracterizacion, estética en manos y pies, de acuerdo con los requerimientos del cliente, criterios técnicos, estéticos y de bioseguridad e higiene. Asimismo, utiliza de manera adecuada las diversas herramientas de las TICs; busca y analiza la información; se comunica con otros en forma efectiva, liderando emprendimientos con nuevas oportunidades de negocios y proyectos sostenibles; planteando soluciones a diversos problemas, promoviendo una cultura ambiental en su entorno; estableciendo relaciones de respeto y justicia con los demás. | F18: d
A19: COMPETENCIAS ESPECÍFICAS (UNIDAD DE COMPETENCIA) | F19: =A19 -> COMPETENCIAS ESPECÍFICAS (UNIDAD DE COMPETENCIA)
A20: UC1. Ejecutar el servicio de peluquería y barbería, teniendo en cuenta el diagnóstico capilar, requerimientos del cliente, procedimientos del establecimiento, criterios técnicos, estéticos y de bioseguridad e higiene. | F20: =A20 -> UC1. Ejecutar el servicio de peluquería y barbería, teniendo en cuenta el diagnóstico capilar, requerimientos del cliente, procedimientos del establecimiento, criterios técnicos, estéticos y de bioseguridad e higiene.
A21: UC2. Realizar procedimientos técnicos capilares, tomando en cuenta su diagnóstico, requerimientos del cliente, y de bioseguridad e higiene. | F21: =A21 -> UC2. Realizar procedimientos técnicos capilares, tomando en cuenta su diagnóstico, requerimientos del cliente, y de bioseguridad e higiene.
A22: UC3. Efectuar el servicio de maquillaje de belleza de acuerdo con los requerimientos del cliente, criterios técnicos, estéticos y de bioseguridad e higiene. | F22: =A22 -> UC3. Efectuar el servicio de maquillaje de belleza de acuerdo con los requerimientos del cliente, criterios técnicos, estéticos y de bioseguridad e higiene.
A23: UC4. Efectuar el servicio de maquillaje de caracterización aplicando materiales para efectos especiales, de acuerdo con los requerimientos del cliente, criterios técnicos, estéticos, estéticos éticos y de bioseguridad e higiene. | F23: =A23 -> UC4. Efectuar el servicio de maquillaje de caracterización aplicando materiales para efectos especiales, de acuerdo con los requerimientos del cliente, criterios técnicos, estéticos, estéticos éticos y de bioseguridad e higiene.
A24: UC5. Ejecutar el servicio de estética en manos y pies teniendo en cuenta los requerimientos del cliente, los procedimientos del establecimiento, criterios técnicos, estéticos y de bioseguridad e higiene. | F24: =A24 -> UC5. Ejecutar el servicio de estética en manos y pies teniendo en cuenta los requerimientos del cliente, los procedimientos del establecimiento, criterios técnicos, estéticos y de bioseguridad e higiene.
F25: =A25 -> 0
F26: =A26 -> 0
F27: =A27 -> 0
A28: COMPETENCIAS PARA LA EMPLEABILIDAD | F28: =A28 -> COMPETENCIAS PARA LA EMPLEABILIDAD
A29: CE1 Comunicación efectiva.- expresar y comprender de manera clara conceptos, ideas, sentimientos, hechos y opiniones en forma oral y escrita para comunicarse e interactuar con otras personas en contextos sociales y laborales diversos. (UD) | F29: =A29 -> CE1 Comunicación efectiva.- expresar y comprender de manera clara conceptos, ideas, sentimientos, hechos y opiniones en forma oral y escrita para comunicarse e interactuar con otras personas en contextos sociales y laborales diversos. (UD)
A30: CE2. Tecnologías de la información. - Manejar herramientas informáticas de las TICs para buscar y analizar información, comunicarse y realizar procedimientos o tareas vinculadas al área profesional, de acuerdo con los requerimientos de su entorno laboral. (UD) | F30: =A30 -> CE2. Tecnologías de la información. - Manejar herramientas informáticas de las TICs para buscar y analizar información, comunicarse y realizar procedimientos o tareas vinculadas al área profesional, de acuerdo con los requerimientos de su entorno laboral. (UD)
A31: CE3. Emprendimiento.- identificar nuevas oportunidades de proyectos o negocios que generen valor y sean sostenibles, organizando y distribuyendo los recursos para su funcionamiento con creatividad, liderazgo y ética permanente, articulando acciones que permitan desarrollar innovaciones en la creación de bienes y servicios, así como en procesos de productos ya existentes (UD). | F31: =A31 -> CE3. Emprendimiento.- identificar nuevas oportunidades de proyectos o negocios que generen valor y sean sostenibles, organizando y distribuyendo los recursos para su funcionamiento con creatividad, liderazgo y ética permanente, articulando acciones que permitan desarrollar innovaciones en la creación de bienes y servicios, así como en procesos de productos ya existentes (UD).
A32: CE4. Ética.-Establecer relaciones con respeto y justicia en los ámbitos personal, colectivo e institucional, contribuyendo a una convivencia democrática orientada al bien común, que considere la diversidad y dignidad de las personas, teniendo en cuenta las consideraciones aplicadas en su contexto laboral. (UD) | F32: =A32 -> CE4. Ética.-Establecer relaciones con respeto y justicia en los ámbitos personal, colectivo e institucional, contribuyendo a una convivencia democrática orientada al bien común, que considere la diversidad y dignidad de las personas, teniendo en cuenta las consideraciones aplicadas en su contexto laboral. (UD)
A33: CE5. Solución de problemas, identificar situaciones complejas para evaluar posibles soluciones, aplicando un conjunto de herramienta flexibles que conlleve a la atención de una necesidad. (UD) | F33: =A33 -> CE5. Solución de problemas, identificar situaciones complejas para evaluar posibles soluciones, aplicando un conjunto de herramienta flexibles que conlleve a la atención de una necesidad. (UD)
A34: CE6. Cultura Ambiental.- Interactuar con el entorno de forma ética, autonoma responsable y sostenible preservando y cuidando el ambiente natural y social, contrarestando los efectos negativos generados por la acción humana evitando otros daños. (T) | F34: =A34 -> CE6. Cultura Ambiental.- Interactuar con el entorno de forma ética, autonoma responsable y sostenible preservando y cuidando el ambiente natural y social, contrarestando los efectos negativos generados por la acción humana evitando otros daños. (T)
A35: CE 7. Liderazgo personal y profesional .- Articular recursos y potencialidades de cada integrante de su equipo logrando un trabajo comprometido, colaborativo, creativo, ético, sensible a su contexto social y ambiente, en pro del bien común. (T) | F35: =A35 -> CE 7. Liderazgo personal y profesional .- Articular recursos y potencialidades de cada integrante de su equipo logrando un trabajo comprometido, colaborativo, creativo, ético, sensible a su contexto social y ambiente, en pro del bien común. (T)
F36: =A36 -> 0
F37: =A37 -> 0
F38: =A38 -> 0
F39: =A39 -> 0
F40: =A40 -> 0
A41: ÁMBITOS DE DESEMPEÑO | F41: =A41 -> ÁMBITOS DE DESEMPEÑO
A42: El egresado de este programa de estudios podra desempeñarse en las siguientes áreas o espacios laborales: - Corte de cabellos para damas, caballeros y niños. - Extensiones y postizos. - Peinados. - Tratamiento Capilar - Manicure y Pedicure. - Cortes y diseños para barbería. - Maquillajes para diferentes eventos y de caracterización. - Tinturación - Laceados y ondulaciones temporales y permanentes. - Depilaciones corporales. - O su propio Salón de belleza y/o barbería. | F42: =A42 -> El egresado de este programa de estudios podra desempeñarse en las siguientes áreas o espacios laborales: - Corte de cabellos para damas, caballeros y niños. - Extensiones y postizos. - Peinados. - Tratamiento Capilar - Manicure y Pedicure. - Cortes y diseños para barbería. - Maquillajes para diferentes eventos y de caracterización. - Tinturación - Laceados y ondulaciones temporales y permanentes. - Depilaciones corporales. - O su propio Salón de belleza y/o barbería.
A43: Pautas Generales: 1. Descripción del perfil de egreso: Descripción general y breve de los desempeños que será capaz de realizar el egresado en el campo laboral, al concluir el programa de estudio en correspondencia con las competencias técnicas y de empleabilidad. 2. Competencias específicas: Transcripción de las unidades de competencia del programa de estudio, establecido en el CNOF. En caso de que el programa no se encuentre en el CNOF se tomarán las Unidades de Competencias definidas mediante el análisis de la actividad económica correspondiente. 3. Las competencias para la empleabilidad: son priorizadas por la institución educativa, en concordancia con los Lineamientos Académicos Generales establecidos por el MINEDU y su modelo educativo. Se debe distinguir los que se abordarán como unidad didáctica (UD), de manera transversal (T) o ambas (UD/T) 4. Ámbitos de desempeño: Listar los campos o áreas laborales en los cuales el egresado del programa de estudio se podrá insertar. *Se considera el código del programa de estudios del CNOF, de ser el caso. ** Indicar sólo en el caso de que sea Dual o En Alternancia, caso contrario dejar la celda en blanco. | F43: =A43 -> Pautas Generales: 1. Descripción del perfil de egreso: Descripción general y breve de los desempeños que será capaz de realizar el egresado en el campo laboral, al concluir el programa de estudio en correspondencia con las competencias técnicas y de empleabilidad. 2. Competencias específicas: Transcripción de las unidades de competencia del programa de estudio, establecido en el CNOF. En caso de que el programa no se encuentre en el CNOF se tomarán las Unidades de Competencias definidas mediante el análisis de la actividad económica correspondiente. 3. Las competencias para la empleabilidad: son priorizadas por la institución educativa, en concordancia con los Lineamientos Académicos Generales establecidos por el MINEDU y su modelo educativo. Se debe distinguir los que se abordarán como unidad didáctica (UD), de manera transversal (T) o ambas (UD/T) 4. Ámbitos de desempeño: Listar los campos o áreas laborales en los cuales el egresado del programa de estudio se podrá insertar. *Se considera el código del programa de estudios del CNOF, de ser el caso. ** Indicar sólo en el caso de que sea Dual o En Alternancia, caso contrario dejar la celda en blanco.

Sheet Programa_Estudio
A1: ANEXO Nº 8 PROGRAMA DE ESTUDIO (PARA CICLOS FORMATIVOS: TÉCNICO Y AUXILIAR TÉCNICO)
A3: =Perfil_Egreso!A3 -> DENOMINACIÓN DE LA INSTITUCIÓN | B3: =Perfil_Egreso!B3 -> CETPRO JUANJUI | D3: =Perfil_Egreso!D3 -> CÓDIGO MODULAR DEL CETPRO | E3: =Perfil_Egreso!E3 -> 533836
A5: SECTOR ECONÓMICO | B5: =Perfil_Egreso!B5 -> OTRAS ACTIVIDADES DE SERVICIO | C5: FAMILIA PRODUCTIVA | D5: =Perfil_Egreso!D5 -> SERVICIOS PERSONALES Y DE HOGARES | E5: ACTIVIDAD ECONÓMICA | F5: =Perfil_Egreso!B7 -> OTRAS ACTIVIDADES DE SERVICIOS PERSONALES
A7: DENOMINACIÓN DEL PROGRAMA DE ESTUDIOS | B7: =Perfil_Egreso!B11 -> ESTILISMO | C7: CÓDIGO DE SER EL CASO * | D7: =Perfil_Egreso!E11 -> S3496-2-001
A9: CICLO FORMATIVO | B9: =Perfil_Egreso!B15 -> TÉCNICO | C9: N°. HORAS: | D9: =Itinerario!W17 -> 2272 | E9: N° CRÉDITOS: | F9: =Itinerario!T17 -> 83
A11: FORMACIÓN** | B11: =Perfil_Egreso!B13 -> 0 | D11: MODALIDAD DEL SERVICIO EDUCATIVO *** | E11: =Perfil_Egreso!D13 -> PRESENCIAL
A13: COMPETENCIAS ESPECÍFICAS O TECNICAS (UNIDAD DE COMPETENCIA)
A14: UNIDAD DE COMPETENCIA | C14: INDICADORES DE LOGRO DE LA COMPETENCIA | G14: Filtro
A15: =CONCATENATE("Unidad de Competencia N° 01 (UC1): ",Perfil_Egreso!A20) -> Unidad de Competencia N° 01 (UC1): UC1. Ejecutar el servicio de peluquería y barbería, teniendo en cuenta el diagnóstico capilar, requerimientos del cliente, procedimientos del establecimiento, criterios técnicos, estéticos y de bioseguridad e higiene. | C15: 1. Prepara al cliente, teniendo en cuenta los procedimientos del establecimiento y según el servicio a realizar. | G15: =C15 -> 1. Prepara al cliente, teniendo en cuenta los procedimientos del establecimiento y según el servicio a realizar. | H15: 1 | I15: =CONCATENATE(H15,". ",C15) -> 1. 1. Prepara al cliente, teniendo en cuenta los procedimientos del establecimiento y según el servicio a realizar.
C16: 2. Propone estilos de estética de cabello, tomando en cuenta tendencias y criterios estéticos, así como las diferentes morfologías y requerimientos del cliente | G16: =C16 -> 2. Propone estilos de estética de cabello, tomando en cuenta tendencias y criterios estéticos, así como las diferentes morfologías y requerimientos del cliente | H16: 2 | I16: =CONCATENATE(H16,". ",C16) -> 2. 2. Propone estilos de estética de cabello, tomando en cuenta tendencias y criterios estéticos, así como las diferentes morfologías y requerimientos del cliente
C17: 3. Realiza cortes de cabello según el estilo determinado, aplicando técnicas y utilizando equipamiento de la especialidad. | G17: =C17 -> 3. Realiza cortes de cabello según el estilo determinado, aplicando técnicas y utilizando equipamiento de la especialidad. | H17: 3 | I17: =CONCATENATE(H17,". ",C17) -> 3. 3. Realiza cortes de cabello según el estilo determinado, aplicando técnicas y utilizando equipamiento de la especialidad.
C18: 4. Realiza peinados según estilo determinado, aplicando técnicas y utilizando equipamiento de la especialidad. | G18: =C18 -> 4. Realiza peinados según estilo determinado, aplicando técnicas y utilizando equipamiento de la especialidad. | H18: 4 | I18: =CONCATENATE(H18,". ",C18) -> 4. 4. Realiza peinados según estilo determinado, aplicando técnicas y utilizando equipamiento de la especialidad.
C19: 5. Coloca postizos y/o extensiones según estilo determinado, aplicando criterios técnicos, estéticos y de bioseguridad e higiene. | G19: =C19 -> 5. Coloca postizos y/o extensiones según estilo determinado, aplicando criterios técnicos, estéticos y de bioseguridad e higiene. | H19: 5 | I19: =CONCATENATE(H19,". ",C19) -> 5. 5. Coloca postizos y/o extensiones según estilo determinado, aplicando criterios técnicos, estéticos y de bioseguridad e higiene.
C20: 6. Propone estilos o diseños de estética de barba, tomando en cuenta tendencias y criterios estéticos, así como las diferentes morfologías y requerimientos del cliente. | G20: =C20 -> 6. Propone estilos o diseños de estética de barba, tomando en cuenta tendencias y criterios estéticos, así como las diferentes morfologías y requerimientos del cliente. | H20: 6 | I20: =CONCATENATE(H20,". ",C20) -> 6. 6. Propone estilos o diseños de estética de barba, tomando en cuenta tendencias y criterios estéticos, así como las diferentes morfologías y requerimientos del cliente.
C21: 7. Realiza cortes de barbas según el estilo o diseño determinado, aplicando técnicas y utilizando equipamiento de la especialidad. | G21: =C21 -> 7. Realiza cortes de barbas según el estilo o diseño determinado, aplicando técnicas y utilizando equipamiento de la especialidad. | H21: 7 | I21: =CONCATENATE(H21,". ",C21) -> 7. 7. Realiza cortes de barbas según el estilo o diseño determinado, aplicando técnicas y utilizando equipamiento de la especialidad.
C22: 8. Brinda recomendaciones post servicio realizado, según la técnica y tratamiento empleado. | G22: =C22 -> 8. Brinda recomendaciones post servicio realizado, según la técnica y tratamiento empleado. | H22: 8 | I22: =CONCATENATE(H22,". ",C22) -> 8. 8. Brinda recomendaciones post servicio realizado, según la técnica y tratamiento empleado.
G23: =C23 -> 0 | H23: 9 | I23: =CONCATENATE(H23,". ",C23) -> 9.
G24: =C24 -> 0 | H24: 10 | I24: =CONCATENATE(H24,". ",C24) -> 10.
G25: =C25 -> 0 | H25: 11 | I25: =CONCATENATE(H25,". ",C25) -> 11.
G26: =C26 -> 0 | H26: 12 | I26: =CONCATENATE(H26,". ",C26) -> 12.
G27: =C27 -> 0 | H27: 13 | I27: =CONCATENATE(H27,". ",C27) -> 13.
G28: =C28 -> 0 | H28: 14 | I28: =CONCATENATE(H28,". ",C28) -> 14.
G29: =C29 -> 0 | H29: 15 | I29: =CONCATENATE(H29,". ",C29) -> 15.
A30: =CONCATENATE("Unidad de Competencia N° 02 (UC2): ",Perfil_Egreso!A21) -> Unidad de Competencia N° 02 (UC2): UC2. Realizar procedimientos técnicos capilares, tomando en cuenta su diagnóstico, requerimientos del cliente, y de bioseguridad e higiene. | C30: 1. Realiza el diagnóstico del cuero cabelludo, tomando en cuenta la condición de la hebra capilar, sus alteraciones, características y propiedades. | G30: =C30 -> 1. Realiza el diagnóstico del cuero cabelludo, tomando en cuenta la condición de la hebra capilar, sus alteraciones, características y propiedades. | H30: 1 | I30: =CONCATENATE(H30,". ",C30) -> 1. 1. Realiza el diagnóstico del cuero cabelludo, tomando en cuenta la condición de la hebra capilar, sus alteraciones, características y propiedades.
C31: 2. Verifica las condiciones del producto o productos a utilizar, siguiendo procedimientos del establecimiento y criterios de bioseguridad e higiene. | G31: =C31 -> 2. Verifica las condiciones del producto o productos a utilizar, siguiendo procedimientos del establecimiento y criterios de bioseguridad e higiene. | H31: 2 | I31: =CONCATENATE(H31,". ",C31) -> 2. 2. Verifica las condiciones del producto o productos a utilizar, siguiendo procedimientos del establecimiento y criterios de bioseguridad e higiene.
C32: 3. Realiza tratamiento capilar aplicando productos cosméticos y tomando en cuenta criterios técnicos, estéticos y de bioseguridad e higiene. | G32: =C32 -> 3. Realiza tratamiento capilar aplicando productos cosméticos y tomando en cuenta criterios técnicos, estéticos y de bioseguridad e higiene. | H32: 3 | I32: =CONCATENATE(H32,". ",C32) -> 3. 3. Realiza tratamiento capilar aplicando productos cosméticos y tomando en cuenta criterios técnicos, estéticos y de bioseguridad e higiene.
C33: 4. Realiza la decoloración y/o coloración del cabello, según incluye la morfología del rostro, cabeza, cuello, cuerpo, entre otras que correspondan. | G33: =C33 -> 4. Realiza la decoloración y/o coloración del cabello, según incluye la morfología del rostro, cabeza, cuello, cuerpo, entre otras que correspondan. | H33: 4 | I33: =CONCATENATE(H33,". ",C33) -> 4. 4. Realiza la decoloración y/o coloración del cabello, según incluye la morfología del rostro, cabeza, cuello, cuerpo, entre otras que correspondan.
C34: 5. Realiza cambios permanentes o temporales en el cabello, según requerimientos del cliente, criterios técnicos, y de bioseguridad e higiene. | G34: =C34 -> 5. Realiza cambios permanentes o temporales en el cabello, según requerimientos del cliente, criterios técnicos, y de bioseguridad e higiene. | H34: 5 | I34: =CONCATENATE(H34,". ",C34) -> 5. 5. Realiza cambios permanentes o temporales en el cabello, según requerimientos del cliente, criterios técnicos, y de bioseguridad e higiene.
C35: 6. Brinda recomendaciones post servicio realizado, según procedimiento o tratamiento realizado | G35: =C35 -> 6. Brinda recomendaciones post servicio realizado, según procedimiento o tratamiento realizado | H35: 6 | I35: =CONCATENATE(H35,". ",C35) -> 6. 6. Brinda recomendaciones post servicio realizado, según procedimiento o tratamiento realizado
G36: =C36 -> 0 | H36: 7 | I36: =CONCATENATE(H36,". ",C36) -> 7.
G37: =C37 -> 0 | H37: 8 | I37: =CONCATENATE(H37,". ",C37) -> 8.
G38: =C38 -> 0 | H38: 9 | I38: =CONCATENATE(H38,". ",C38) -> 9.
G39: =C39 -> 0 | H39: 10 | I39: =CONCATENATE(H39,". ",C39) -> 10.
G40: =C40 -> 0 | H40: 11 | I40: =CONCATENATE(H40,". ",C40) -> 11.
G41: =C41 -> 0 | H41: 12 | I41: =CONCATENATE(H41,". ",C41) -> 12.
G42: =C42 -> 0 | H42: 13 | I42: =CONCATENATE(H42,". ",C42) -> 13.
G43: =C43 -> 0 | H43: 14 | I43: =CONCATENATE(H43,". ",C43) -> 14.
G44: =C44 -> 0 | H44: 15 | I44: =CONCATENATE(H44,". ",C44) -> 15.
A45: =CONCATENATE("Unidad de Competencia N° 03 (UC3): ",Perfil_Egreso!A22) -> Unidad de Competencia N° 03 (UC3): UC3. Efectuar el servicio de maquillaje de belleza de acuerdo con los requerimientos del cliente, criterios técnicos, estéticos y de bioseguridad e higiene. | C45: 1. Identifica el biotipo cutáneo, teniendo en cuenta sus características (graso, alípico, mixto) y sus condiciones (color, alteraciones, rasgos y morfología facial). | G45: =C45 -> 1. Identifica el biotipo cutáneo, teniendo en cuenta sus características (graso, alípico, mixto) y sus condiciones (color, alteraciones, rasgos y morfología facial). | H45: 1 | I45: =CONCATENATE(H45,". ",C45) -> 1. 1. Identifica el biotipo cutáneo, teniendo en cuenta sus características (graso, alípico, mixto) y sus condiciones (color, alteraciones, rasgos y morfología facial).
C46: 2. Propone estilos de maquillaje, tomando en cuenta la ocasión, criterios estéticos, así como la morfología facial y requerimientos del cliente. | G46: =C46 -> 2. Propone estilos de maquillaje, tomando en cuenta la ocasión, criterios estéticos, así como la morfología facial y requerimientos del cliente. | H46: 2 | I46: =CONCATENATE(H46,". ",C46) -> 2. 2. Propone estilos de maquillaje, tomando en cuenta la ocasión, criterios estéticos, así como la morfología facial y requerimientos del cliente.
C47: 3. Verifica las condiciones del producto cosmético a utilizar, siguiendo procedimientos del establecimiento y criterios de bioseguridad e higiene. | G47: =C47 -> 3. Verifica las condiciones del producto cosmético a utilizar, siguiendo procedimientos del establecimiento y criterios de bioseguridad e higiene. | H47: 3 | I47: =CONCATENATE(H47,". ",C47) -> 3. 3. Verifica las condiciones del producto cosmético a utilizar, siguiendo procedimientos del establecimiento y criterios de bioseguridad e higiene.
C48: 4. Selecciona instrumentos y equipos, según las técnicas de maquillaje a emplear. | G48: =C48 -> 4. Selecciona instrumentos y equipos, según las técnicas de maquillaje a emplear. | H48: 4 | I48: =CONCATENATE(H48,". ",C48) -> 4. 4. Selecciona instrumentos y equipos, según las técnicas de maquillaje a emplear.
C49: 5. Realiza la preparación de la piel, según sus características, criterios técnicos, estéticos y de bioseguridad e higiene. | G49: =C49 -> 5. Realiza la preparación de la piel, según sus características, criterios técnicos, estéticos y de bioseguridad e higiene. | H49: 5 | I49: =CONCATENATE(H49,". ",C49) -> 5. 5. Realiza la preparación de la piel, según sus características, criterios técnicos, estéticos y de bioseguridad e higiene.
C50: 6. Realiza el proceso de maquillaje de belleza aplicando criterios técnicos, estéticos y de bioseguridad e higiene. | G50: =C50 -> 6. Realiza el proceso de maquillaje de belleza aplicando criterios técnicos, estéticos y de bioseguridad e higiene. | H50: 6 | I50: =CONCATENATE(H50,". ",C50) -> 6. 6. Realiza el proceso de maquillaje de belleza aplicando criterios técnicos, estéticos y de bioseguridad e higiene.
C51: 7. Realiza depilaciones básicas en el rostro, aplicando técnicas mecánicas y tomando en cuenta criterios estéticos y de bioseguridad e higiene. | G51: =C51 -> 7. Realiza depilaciones básicas en el rostro, aplicando técnicas mecánicas y tomando en cuenta criterios estéticos y de bioseguridad e higiene. | H51: 7 | I51: =CONCATENATE(H51,". ",C51) -> 7. 7. Realiza depilaciones básicas en el rostro, aplicando técnicas mecánicas y tomando en cuenta criterios estéticos y de bioseguridad e higiene.
C52: 8. Brinda recomendaciones post servicio, de acuerdo con el tipo de maquillaje realizado. | G52: =C52 -> 8. Brinda recomendaciones post servicio, de acuerdo con el tipo de maquillaje realizado. | H52: 8 | I52: =CONCATENATE(H52,". ",C52) -> 8. 8. Brinda recomendaciones post servicio, de acuerdo con el tipo de maquillaje realizado.
G53: =C53 -> 0 | H53: 9 | I53: =CONCATENATE(H53,". ",C53) -> 9.
G54: =C54 -> 0 | H54: 10 | I54: =CONCATENATE(H54,". ",C54) -> 10.
G55: =C55 -> 0 | H55: 11 | I55: =CONCATENATE(H55,". ",C55) -> 11.
G56: =C56 -> 0 | H56: 12 | I56: =CONCATENATE(H56,". ",C56) -> 12.
G57: =C57 -> 0 | H57: 13 | I57: =CONCATENATE(H57,". ",C57) -> 13.
G58: =C58 -> 0 | H58: 14 | I58: =CONCATENATE(H58,". ",C58) -> 14.
G59: =C59 -> 0 | H59: 15 | I59: =CONCATENATE(H59,". ",C59) -> 15.
A60: =CONCATENATE("Unidad de Competencia N° 04 (UC4): ",Perfil_Egreso!A23) -> Unidad de Competencia N° 04 (UC4): UC4. Efectuar el servicio de maquillaje de caracterización aplicando materiales para efectos especiales, de acuerdo con los requerimientos del cliente, criterios técnicos, estéticos, estéticos éticos y de bioseguridad e higiene. | C60: 1. Identifica los rasgos del personaje a representar, según el requerimiento de caracterización. | G60: =C60 -> 1. Identifica los rasgos del personaje a representar, según el requerimiento de caracterización. | H60: 1 | I60: =CONCATENATE(H60,". ",C60) -> 1. 1. Identifica los rasgos del personaje a representar, según el requerimiento de caracterización.
C61: 2. Identifica las necesidades de posticería, según el personaje a interpretar, tomando en cuenta sus características (tipo, forma, color, tamaño, entro otros). | G61: =C61 -> 2. Identifica las necesidades de posticería, según el personaje a interpretar, tomando en cuenta sus características (tipo, forma, color, tamaño, entro otros). | H61: 2 | I61: =CONCATENATE(H61,". ",C61) -> 2. 2. Identifica las necesidades de posticería, según el personaje a interpretar, tomando en cuenta sus características (tipo, forma, color, tamaño, entro otros).
C62: 3. Identifica el biotipo cutáneo, teniendo en cuenta sus características (graso, alípico, mixto) y sus condiciones (color, alteraciones, rasgos y morfología facial). | G62: =C62 -> 3. Identifica el biotipo cutáneo, teniendo en cuenta sus características (graso, alípico, mixto) y sus condiciones (color, alteraciones, rasgos y morfología facial). | H62: 3 | I62: =CONCATENATE(H62,". ",C62) -> 3. 3. Identifica el biotipo cutáneo, teniendo en cuenta sus características (graso, alípico, mixto) y sus condiciones (color, alteraciones, rasgos y morfología facial).
C63: 4. Realizar pruebas alérgicas, siguiendo protocolos establecidos. | G63: =C63 -> 4. Realizar pruebas alérgicas, siguiendo protocolos establecidos. | H63: 4 | I63: =CONCATENATE(H63,". ",C63) -> 4. 4. Realizar pruebas alérgicas, siguiendo protocolos establecidos.
C64: 5. Selecciona los productos cosméticos, accesorios, materiales y equipos a emplear, en función al requerimiento de caracterización. | G64: =C64 -> 5. Selecciona los productos cosméticos, accesorios, materiales y equipos a emplear, en función al requerimiento de caracterización. | H64: 5 | I64: =CONCATENATE(H64,". ",C64) -> 5. 5. Selecciona los productos cosméticos, accesorios, materiales y equipos a emplear, en función al requerimiento de caracterización.
C65: 6. Elabora postizos faciales y/o corporales, en función al requerimiento de caracterización, utilizando materiales y técnicas especializadas. | G65: =C65 -> 6. Elabora postizos faciales y/o corporales, en función al requerimiento de caracterización, utilizando materiales y técnicas especializadas. | H65: 6 | I65: =CONCATENATE(H65,". ",C65) -> 6. 6. Elabora postizos faciales y/o corporales, en función al requerimiento de caracterización, utilizando materiales y técnicas especializadas.
C66: . Realiza el proceso de aplicación de posticería al cliente, según el personaje a interpretar, con criterios técnicos, éticos, estéticos y de bioseguridad e higiene. | G66: =C66 -> . Realiza el proceso de aplicación de posticería al cliente, según el personaje a interpretar, con criterios técnicos, éticos, estéticos y de bioseguridad e higiene. | H66: 7 | I66: =CONCATENATE(H66,". ",C66) -> 7. . Realiza el proceso de aplicación de posticería al cliente, según el personaje a interpretar, con criterios técnicos, éticos, estéticos y de bioseguridad e higiene.
C67: 8. Realiza el proceso de maquillaje de caracterización , aplicando diversas técnicas, estéticos y de bioseguridad e higiene. | G67: =C67 -> 8. Realiza el proceso de maquillaje de caracterización , aplicando diversas técnicas, estéticos y de bioseguridad e higiene. | H67: 8 | I67: =CONCATENATE(H67,". ",C67) -> 8. 8. Realiza el proceso de maquillaje de caracterización , aplicando diversas técnicas, estéticos y de bioseguridad e higiene.
C68: 9. Brinda recomendaciones post servicio, de acuerdo con el tipo de maquillaje realizado. | G68: =C68 -> 9. Brinda recomendaciones post servicio, de acuerdo con el tipo de maquillaje realizado. | H68: 9 | I68: =CONCATENATE(H68,". ",C68) -> 9. 9. Brinda recomendaciones post servicio, de acuerdo con el tipo de maquillaje realizado.
G69: =C69 -> 0 | H69: 10 | I69: =CONCATENATE(H69,". ",C69) -> 10.
G70: =C70 -> 0 | H70: 11 | I70: =CONCATENATE(H70,". ",C70) -> 11.
G71: =C71 -> 0 | H71: 12 | I71: =CONCATENATE(H71,". ",C71) -> 12.
G72: =C72 -> 0 | H72: 13 | I72: =CONCATENATE(H72,". ",C72) -> 13.
G73: =C73 -> 0 | H73: 14 | I73: =CONCATENATE(H73,". ",C73) -> 14.
G74: =C74 -> 0 | H74: 15 | I74: =CONCATENATE(H74,". ",C74) -> 15.
A75: =CONCATENATE("Unidad de Competencia N° 05 (UC5): ",Perfil_Egreso!A24) -> Unidad de Competencia N° 05 (UC5): UC5. Ejecutar el servicio de estética en manos y pies teniendo en cuenta los requerimientos del cliente, los procedimientos del establecimiento, criterios técnicos, estéticos y de bioseguridad e higiene. | C75: 1. Verifica el estado de la piel, la morfología de manos, pies y/o uñas, de acuerdo con sus características y alteraciones. | G75: =C75 -> 1. Verifica el estado de la piel, la morfología de manos, pies y/o uñas, de acuerdo con sus características y alteraciones. | H75: 1 | I75: =CONCATENATE(H75,". ",C75) -> 1. 1. Verifica el estado de la piel, la morfología de manos, pies y/o uñas, de acuerdo con sus características y alteraciones.
C76: 2. Selecciona técnicas de estética de uñas y estilos decorativos, según tendencias y requerimientos del cliente. | G76: =C76 -> 2. Selecciona técnicas de estética de uñas y estilos decorativos, según tendencias y requerimientos del cliente. | H76: 2 | I76: =CONCATENATE(H76,". ",C76) -> 2. 2. Selecciona técnicas de estética de uñas y estilos decorativos, según tendencias y requerimientos del cliente.
C77: 3. Selecciona instrumentos, equipos, aparatología y cosméticos, según técnica a realizar. | G77: =C77 -> 3. Selecciona instrumentos, equipos, aparatología y cosméticos, según técnica a realizar. | H77: 3 | I77: =CONCATENATE(H77,". ",C77) -> 3. 3. Selecciona instrumentos, equipos, aparatología y cosméticos, según técnica a realizar.
C78: 4. Prepara al cliente, teniendo en cuenta los procedimientos del establecimiento y según el servicio a realizar. | G78: =C78 -> 4. Prepara al cliente, teniendo en cuenta los procedimientos del establecimiento y según el servicio a realizar. | H78: 4 | I78: =CONCATENATE(H78,". ",C78) -> 4. 4. Prepara al cliente, teniendo en cuenta los procedimientos del establecimiento y según el servicio a realizar.
C79: 5. Realiza la manicure, aplicando diversas técnicas, criterios técnicos, estéticos y normas de bioseguridad e higiene. | G79: =C79 -> 5. Realiza la manicure, aplicando diversas técnicas, criterios técnicos, estéticos y normas de bioseguridad e higiene. | H79: 5 | I79: =CONCATENATE(H79,". ",C79) -> 5. 5. Realiza la manicure, aplicando diversas técnicas, criterios técnicos, estéticos y normas de bioseguridad e higiene.
C80: 6. Realiza la pedicure, aplicando diversas técnicas, criterios técnicos, estéticos y de bioseguridad e higiene. | G80: =C80 -> 6. Realiza la pedicure, aplicando diversas técnicas, criterios técnicos, estéticos y de bioseguridad e higiene. | H80: 6 | I80: =CONCATENATE(H80,". ",C80) -> 6. 6. Realiza la pedicure, aplicando diversas técnicas, criterios técnicos, estéticos y de bioseguridad e higiene.
G81: =C81 -> 0 | H81: 7 | I81: =CONCATENATE(H81,". ",C81) -> 7.
G82: =C82 -> 0 | H82: 8 | I82: =CONCATENATE(H82,". ",C82) -> 8.
G83: =C83 -> 0 | H83: 9 | I83: =CONCATENATE(H83,". ",C83) -> 9.
G84: =C84 -> 0 | H84: 10 | I84: =CONCATENATE(H84,". ",C84) -> 10.
G85: =C85 -> 0 | H85: 11 | I85: =CONCATENATE(H85,". ",C85) -> 11.
G86: =C86 -> 0 | H86: 12 | I86: =CONCATENATE(H86,". ",C86) -> 12.
G87: =C87 -> 0 | H87: 13 | I87: =CONCATENATE(H87,". ",C87) -> 13.
G88: =C88 -> 0 | H88: 14 | I88: =CONCATENATE(H88,". ",C88) -> 14.
G89: =C89 -> 0 | H89: 15 | I89: =CONCATENATE(H89,". ",C89) -> 15.
A90: =CONCATENATE("Unidad de Competencia N° 06 (UC6): ",Perfil_Egreso!A25) -> Unidad de Competencia N° 06 (UC6): | G90: =C90 -> 0 | H90: 1 | I90: =CONCATENATE(H90,". ",C90) -> 1.
G91: =C91 -> 0 | H91: 2 | I91: =CONCATENATE(H91,". ",C91) -> 2.
G92: =C92 -> 0 | H92: 3 | I92: =CONCATENATE(H92,". ",C92) -> 3.
G93: =C93 -> 0 | H93: 4 | I93: =CONCATENATE(H93,". ",C93) -> 4.
G94: =C94 -> 0 | H94: 5 | I94: =CONCATENATE(H94,". ",C94) -> 5.
G95: =C95 -> 0 | H95: 6 | I95: =CONCATENATE(H95,". ",C95) -> 6.
G96: =C96 -> 0 | H96: 7 | I96: =CONCATENATE(H96,". ",C96) -> 7.
G97: =C97 -> 0 | H97: 8 | I97: =CONCATENATE(H97,". ",C97) -> 8.
G98: =C98 -> 0 | H98: 9 | I98: =CONCATENATE(H98,". ",C98) -> 9.
G99: =C99 -> 0 | H99: 10 | I99: =CONCATENATE(H99,". ",C99) -> 10.
G100: =C100 -> 0 | H100: 11 | I100: =CONCATENATE(H100,". ",C100) -> 11.
G101: =C101 -> 0 | H101: 12 | I101: =CONCATENATE(H101,". ",C101) -> 12.
G102: =C102 -> 0 | H102: 13 | I102: =CONCATENATE(H102,". ",C102) -> 13.
... G104: =C104 -> 0 | H104: 15 | I104: =CONCATENATE(H104,". ",C104) -> 15.
A105: =CONCATENATE("Unidad de Competencia N° 07 (UC7): ",Perfil_Egreso!A26) -> Unidad de Competencia N° 07 (UC7): | G105: =C105 -> 0 | H105: 1 | I105: =CONCATENATE(H105,". ",C105) -> 1.
G106: =C106 -> 0 | H106: 2 | I106: =CONCATENATE(H106,". ",C106) -> 2.
G107: =C107 -> 0 | H107: 3 | I107: =CONCATENATE(H107,". ",C107) -> 3.
...

Sheet Capacidades
A1: FORMATO DE PROCESO - FORMULACIÓN DE CAPACIDADES E INDICADORES POR UNIDAD DE COMPETENCIA
A5: Programa de estudios: | E5: =Perfil_Egreso!B11 -> ESTILISMO | L5: RESUMEN
D7: Capacidades asociadas a la Unidad de Competencia Específica y de Empleabilidad | H7: Indicadores de la Capacidad
A9: MÓDULOS | B9: Tipo de capacidad | C9: Código Capacidad | D9: Verbo | E9: Objeto | F9: Condición | G9: Código Indicador | H9: Verbo | I9: Objeto | J9: Condición | K9: Observaciones de los facilitadores opcional | L9: Capacidades | M9: Indicadores
A10: Módulo I | B10: Capacidad técnica | C10: UC1C1 | D10: Ejecutar | E10: cortes de cabello | F10: tomando en cuenta tendencias y criterios estéticos, así como las diferentes morfologías y requerimientos del cliente. | G10: C1I1 | H10: Acondiciona | I10: su zona de trabajo, herramientas, materiales, presupuesto y control de calidad para el corte de cabello | J10: teniendo en cuenta las condiciones de seguridad y salubridad | L10: =CONCATENATE(C10," ",D10," ",E10," ",F10," ",C11," ",D11," ",E11," ",F11) -> UC1C1 Ejecutar cortes de cabello tomando en cuenta tendencias y criterios estéticos, así como las diferentes morfologías y requerimientos del cliente. | M10: =CONCATENATE(G10," ",H10," ",I10," ",J10) -> C1I1 Acondiciona su zona de trabajo, herramientas, materiales, presupuesto y control de calidad para el corte de cabello teniendo en cuenta las condiciones de seguridad y salubridad
G11: C1I2 | H11: Realiza | I11: el servicio de atenciòn al cliente | J11: teniendo en cuenta los protocolos y requerimientos del cliente | L11: =CONCATENATE(C11," ",D11," ",E11," ",F11," ",C12," ",D12," ",E12," ",F12) | M11: =CONCATENATE(G11," ",H11," ",I11," ",J11) -> C1I2 Realiza el servicio de atenciòn al cliente teniendo en cuenta los protocolos y requerimientos del cliente
G12: C1I3 | H12: Realiza | I12: el diagnóstico tricológico, dermatológico y morfológico al cliente | J12: tomando en cuenta tendencia y estilos de corte de cabello | L12: =CONCATENATE(C12," ",D12," ",E12," ",F12," ",C13," ",D13," ",E13," ",F13) | M12: =CONCATENATE(G12," ",H12," ",I12," ",J12) -> C1I3 Realiza el diagnóstico tricológico, dermatológico y morfológico al cliente tomando en cuenta tendencia y estilos de corte de cabello
G13: C1I4 | H13: Propone | I13: estilos de cortes de cabello, | J13: tomando en cuenta el diagnostico, tendencias, estilos y requerimientos del cliente. | L13: =CONCATENATE(C13," ",D13," ",E13," ",F13," ",C14," ",D14," ",E14," ",F14) | M13: =CONCATENATE(G13," ",H13," ",I13," ",J13) -> C1I4 Propone estilos de cortes de cabello, tomando en cuenta el diagnostico, tendencias, estilos y requerimientos del cliente.
G14: C1I5 | H14: Aplica | I14: técnicas de cortes de cabello | J14: tomando en cuenta la ficha de servicio y requerimiento del cliente | L14: =CONCATENATE(C14," ",D14," ",E14," ",F14," ",C15," ",D15," ",E15," ",F15) | M14: =CONCATENATE(G14," ",H14," ",I14," ",J14) -> C1I5 Aplica técnicas de cortes de cabello tomando en cuenta la ficha de servicio y requerimiento del cliente
L15: =CONCATENATE(C15," ",D15," ",E15," ",F15," ",C16," ",D16," ",E16," ",F16) | M15: =CONCATENATE(G15," ",H15," ",I15," ",J15)
L16: =CONCATENATE(C16," ",D16," ",E16," ",F16," ",C17," ",D17," ",E17," ",F17) | M16: =CONCATENATE(G16," ",H16," ",I16," ",J16)
L17: =CONCATENATE(C17," ",D17," ",E17," ",F17," ",C18," ",D18," ",E18," ",F18) | M17: =CONCATENATE(G17," ",H17," ",I17," ",J17)
L18: =CONCATENATE(C18," ",D18," ",E18," ",F18," ",C19," ",D19," ",E19," ",F19) | M18: =CONCATENATE(G18," ",H18," ",I18," ",J18)
L19: =CONCATENATE(C19," ",D19," ",E19," ",F19) | M19: =CONCATENATE(G19," ",H19," ",I19," ",J19)
A20: Módulo I | B20: Capacidad técnica | C20: UC1C2 | D20: Ejecutar | E20: cortes y diseño de barba y bigote | F20: tomando en cuenta tendencias y criterios estéticos, así como las diferentes morfologías y requerimientos del cliente. | G20: C2I1 | H20: Acondiciona | I20: su zona de trabajo, herramientas, materiales, presupuesto y control de calidad para cortes de barberia | J20: según estilo determinado, aplicando criterios técnicos, estéticos y de bioseguridad e higiene. | L20: =CONCATENATE(C20," ",D20," ",E20," ",F20," ",C21," ",D21," ",E21," ",F21) -> UC1C2 Ejecutar cortes y diseño de barba y bigote tomando en cuenta tendencias y criterios estéticos, así como las diferentes morfologías y requerimientos del cliente. | M20: =CONCATENATE(G20," ",H20," ",I20," ",J20) -> C2I1 Acondiciona su zona de trabajo, herramientas, materiales, presupuesto y control de calidad para cortes de barberia según estilo determinado, aplicando criterios técnicos, estéticos y de bioseguridad e higiene.
G21: C2I2 | H21: Realiza | I21: el diagnóstico dermatológico y morfológico al cliente | J21: tomando en cuenta tendencia y estilos de corte de barba y bigote | L21: =CONCATENATE(C21," ",D21," ",E21," ",F21," ",C22," ",D22," ",E22," ",F22) | M21: =CONCATENATE(G21," ",H21," ",I21," ",J21) -> C2I2 Realiza el diagnóstico dermatológico y morfológico al cliente tomando en cuenta tendencia y estilos de corte de barba y bigote
G22: C2I3 | H22: Realiza | I22: rasurado de barba con o sin diseño | J22: tomando en cuenta tendencias y criterios estéticos y aplicando procedimientos técnicos establecidos. | L22: =CONCATENATE(C22," ",D22," ",E22," ",F22," ",C23," ",D23," ",E23," ",F23) | M22: =CONCATENATE(G22," ",H22," ",I22," ",J22) -> C2I3 Realiza rasurado de barba con o sin diseño tomando en cuenta tendencias y criterios estéticos y aplicando procedimientos técnicos establecidos.
G23: C2I4 | H23: Realiza | I23: cortes con o sin diseño de bigote | J23: teniendo en cuenta las características morfologías y requerimientos del cliente y aplicando procedimientos técnicos establecidos. | L23: =CONCATENATE(C23," ",D23," ",E23," ",F23," ",C24," ",D24," ",E24," ",F24) | M23: =CONCATENATE(G23," ",H23," ",I23," ",J23) -> C2I4 Realiza cortes con o sin diseño de bigote teniendo en cuenta las características morfologías y requerimientos del cliente y aplicando procedimientos técnicos establecidos.
G24: C2I5 | H24: Verifica | I24: el acabado del corte realizado | J24: considerando los criterios estéticos, procedimientos tecnicos establecidos y de bioseguridad e higiene personal. | L24: =CONCATENATE(C24," ",D24," ",E24," ",F24," ",C25," ",D25," ",E25," ",F25) | M24: =CONCATENATE(G24," ",H24," ",I24," ",J24) -> C2I5 Verifica el acabado del corte realizado considerando los criterios estéticos, procedimientos tecnicos establecidos y de bioseguridad e higiene personal.
L25: =CONCATENATE(C25," ",D25," ",E25," ",F25," ",C26," ",D26," ",E26," ",F26) | M25: =CONCATENATE(G25," ",H25," ",I25," ",J25)
L26: =CONCATENATE(C26," ",D26," ",E26," ",F26," ",C27," ",D27," ",E27," ",F27) | M26: =CONCATENATE(G26," ",H26," ",I26," ",J26)
L27: =CONCATENATE(C27," ",D27," ",E27," ",F27," ",C28," ",D28," ",E28," ",F28) | M27: =CONCATENATE(G27," ",H27," ",I27," ",J27)
L28: =CONCATENATE(C28," ",D28," ",E28," ",F28," ",C29," ",D29," ",E29," ",F29) | M28: =CONCATENATE(G28," ",H28," ",I28," ",J28)
L29: =CONCATENATE(C29," ",D29," ",E29," ",F29) | M29: =CONCATENATE(G29," ",H29," ",I29," ",J29)
A30: Módulo I | B30: Capacidad técnica | C30: UC1C3 | D30: Ejecutar | E30: peinados | F30: según procedimientos tècnicos, creatividad y normas de bioseguridad e higiene. | G30: C3I1 | H30: Acondiciona | I30: su zona de trabajo, herramientas y productos para peinados | J30: teniendo en cuenta las condiciones de bioseguridad e higiene | L30: =CONCATENATE(C30," ",D30," ",E30," ",F30," ",C31," ",D31," ",E31," ",F31) -> UC1C3 Ejecutar peinados según procedimientos tècnicos, creatividad y normas de bioseguridad e higiene. | M30: =CONCATENATE(G30," ",H30," ",I30," ",J30) -> C3I1 Acondiciona su zona de trabajo, herramientas y productos para peinados teniendo en cuenta las condiciones de bioseguridad e higiene
G31: C3I2 | H31: Prepara | I31: el cabello para el peinado, | J31: considerando el diagnostico, aplicando técnicas y utilizando equipos térmicos. | L31: =CONCATENATE(C31," ",D31," ",E31," ",F31," ",C32," ",D32," ",E32," ",F32) | M31: =CONCATENATE(G31," ",H31," ",I31," ",J31) -> C3I2 Prepara el cabello para el peinado, considerando el diagnostico, aplicando técnicas y utilizando equipos térmicos.
G32: C3I3 | H32: Realiza | I32: diversos peinados | J32: tomando en cuenta tendencias y criterios estéticos, diagnostico y requerimientos del cliente. | L32: =CONCATENATE(C32," ",D32," ",E32," ",F32," ",C33," ",D33," ",E33," ",F33) | M32: =CONCATENATE(G32," ",H32," ",I32," ",J32) -> C3I3 Realiza diversos peinados tomando en cuenta tendencias y criterios estéticos, diagnostico y requerimientos del cliente.
G33: C3I4 | H33: Aplica | I33: postizos y/o extensiones en los peinados | J33: considerando técnicas, criterios estéticos y requerimientos del cliente. | L33: =CONCATENATE(C33," ",D33," ",E33," ",F33," ",C34," ",D34," ",E34," ",F34) | M33: =CONCATENATE(G33," ",H33," ",I33," ",J33) -> C3I4 Aplica postizos y/o extensiones en los peinados considerando técnicas, criterios estéticos y requerimientos del cliente.
G34: C3I5 | H34: Verifica | I34: el acabado del peinado | J34: considerando los criterios estéticos, procedimientos tecnicos establecidos y de bioseguridad e higiene personal. | L34: =CONCATENATE(C34," ",D34," ",E34," ",F34," ",C35," ",D35," ",E35," ",F35) | M34: =CONCATENATE(G34," ",H34," ",I34," ",J34) -> C3I5 Verifica el acabado del peinado considerando los criterios estéticos, procedimientos tecnicos establecidos y de bioseguridad e higiene personal.
L35: =CONCATENATE(C35," ",D35," ",E35," ",F35," ",C36," ",D36," ",E36," ",F36) | M35: =CONCATENATE(G35," ",H35," ",I35," ",J35)
L36: =CONCATENATE(C36," ",D36," ",E36," ",F36," ",C37," ",D37," ",E37," ",F37) | M36: =CONCATENATE(G36," ",H36," ",I36," ",J36)
L37: =CONCATENATE(C37," ",D37," ",E37," ",F37," ",C38," ",D38," ",E38," ",F38) | M37: =CONCATENATE(G37," ",H37," ",I37," ",J37)
L38: =CONCATENATE(C38," ",D38," ",E38," ",F38," ",C39," ",D39," ",E39," ",F39) | M38: =CONCATENATE(G38," ",H38," ",I38," ",J38)
L39: =CONCATENATE(C39," ",D39," ",E39," ",F39) | M39: =CONCATENATE(G39," ",H39," ",I39," ",J39)
A40: Módulo I | B40: Capacidad técnica | L40: =CONCATENATE(C40," ",D40," ",E40," ",F40," ",C41," ",D41," ",E41," ",F41) | M40: =CONCATENATE(G40," ",H40," ",I40," ",J40)
L41: =CONCATENATE(C41," ",D41," ",E41," ",F41," ",C42," ",D42," ",E42," ",F42) | M41: =CONCATENATE(G41," ",H41," ",I41," ",J41)
L42: =CONCATENATE(C42," ",D42," ",E42," ",F42," ",C43," ",D43," ",E43," ",F43) | M42: =CONCATENATE(G42," ",H42," ",I42," ",J42)
L43: =CONCATENATE(C43," ",D43," ",E43," ",F43," ",C44," ",D44," ",E44," ",F44) | M43: =CONCATENATE(G43," ",H43," ",I43," ",J43)
L44: =CONCATENATE(C44," ",D44," ",E44," ",F44," ",C45," ",D45," ",E45," ",F45) | M44: =CONCATENATE(G44," ",H44," ",I44," ",J44)
L45: =CONCATENATE(C45," ",D45," ",E45," ",F45," ",C46," ",D46," ",E46," ",F46) | M45: =CONCATENATE(G45," ",H45," ",I45," ",J45)
L46: =CONCATENATE(C46," ",D46," ",E46," ",F46," ",C47," ",D47," ",E47," ",F47) | M46: =CONCATENATE(G46," ",H46," ",I46," ",J46)
L47: =CONCATENATE(C47," ",D47," ",E47," ",F47," ",C48," ",D48," ",E48," ",F48) | M47: =CONCATENATE(G47," ",H47," ",I47," ",J47)
L48: =CONCATENATE(C48," ",D48," ",E48," ",F48," ",C49," ",D49," ",E49," ",F49) | M48: =CONCATENATE(G48," ",H48," ",I48," ",J48)
L49: =CONCATENATE(C49," ",D49," ",E49," ",F49) | M49: =CONCATENATE(G49," ",H49," ",I49," ",J49)
A50: Módulo I | B50: Capacidad técnica | L50: =CONCATENATE(C50," ",D50," ",E50," ",F50," ",C51," ",D51," ",E51," ",F51) | M50: =CONCATENATE(G50," ",H50," ",I50," ",J50)
L51: =CONCATENATE(C51," ",D51," ",E51," ",F51," ",C52," ",D52," ",E52," ",F52) | M51: =CONCATENATE(G51," ",H51," ",I51," ",J51)
L52: =CONCATENATE(C52," ",D52," ",E52," ",F52," ",C53," ",D53," ",E53," ",F53) | M52: =CONCATENATE(G52," ",H52," ",I52," ",J52)
L53: =CONCATENATE(C53," ",D53," ",E53," ",F53," ",C54," ",D54," ",E54," ",F54) | M53: =CONCATENATE(G53," ",H53," ",I53," ",J53)
L54: =CONCATENATE(C54," ",D54," ",E54," ",F54," ",C55," ",D55," ",E55," ",F55) | M54: =CONCATENATE(G54," ",H54," ",I54," ",J54)
L55: =CONCATENATE(C55," ",D55," ",E55," ",F55," ",C56," ",D56," ",E56," ",F56) | M55: =CONCATENATE(G55," ",H55," ",I55," ",J55)
L56: =CONCATENATE(C56," ",D56," ",E56," ",F56," ",C57," ",D57," ",E57," ",F57) | M56: =CONCATENATE(G56," ",H56," ",I56," ",J56)
L57: =CONCATENATE(C57," ",D57," ",E57," ",F57," ",C58," ",D58," ",E58," ",F58) | M57: =CONCATENATE(G57," ",H57," ",I57," ",J57)
L58: =CONCATENATE(C58," ",D58," ",E58," ",F58," ",C59," ",D59," ",E59," ",F59) | M58: =CONCATENATE(G58," ",H58," ",I58," ",J58)
L59: =CONCATENATE(C59," ",D59," ",E59," ",F59) | M59: =CONCATENATE(G59," ",H59," ",I59," ",J59)
A60: Módulo I | B60: Capacidad técnica | L60: =CONCATENATE(C60," ",D60," ",E60," ",F60," ",C61," ",D61," ",E61," ",F61) | M60: =CONCATENATE(G60," ",H60," ",I60," ",J60)
L61: =CONCATENATE(C61," ",D61," ",E61," ",F61," ",C62," ",D62," ",E62," ",F62) | M61: =CONCATENATE(G61," ",H61," ",I61," ",J61)
L62: =CONCATENATE(C62," ",D62," ",E62," ",F62," ",C63," ",D63," ",E63," ",F63) | M62: =CONCATENATE(G62," ",H62," ",I62," ",J62)
L63: =CONCATENATE(C63," ",D63," ",E63," ",F63," ",C64," ",D64," ",E64," ",F64) | M63: =CONCATENATE(G63," ",H63," ",I63," ",J63)
L64: =CONCATENATE(C64," ",D64," ",E64," ",F64," ",C65," ",D65," ",E65," ",F65) | M64: =CONCATENATE(G64," ",H64," ",I64," ",J64)
L65: =CONCATENATE(C65," ",D65," ",E65," ",F65," ",C66," ",D66," ",E66," ",F66) | M65: =CONCATENATE(G65," ",H65," ",I65," ",J65)
L66: =CONCATENATE(C66," ",D66," ",E66," ",F66," ",C67," ",D67," ",E67," ",F67) | M66: =CONCATENATE(G66," ",H66," ",I66," ",J66)
L67: =CONCATENATE(C67," ",D67," ",E67," ",F67," ",C68," ",D68," ",E68," ",F68) | M67: =CONCATENATE(G67," ",H67," ",I67," ",J67)
L68: =CONCATENATE(C68," ",D68," ",E68," ",F68," ",C69," ",D69," ",E69," ",F69) | M68: =CONCATENATE(G68," ",H68," ",I68," ",J68)
L69: =CONCATENATE(C69," ",D69," ",E69," ",F69) | M69: =CONCATENATE(G69," ",H69," ",I69," ",J69)
A70: Módulo I | B70: Capacidad técnica | L70: =CONCATENATE(C70," ",D70," ",E70," ",F70," ",C71," ",D71," ",E71," ",F71) | M70: =CONCATENATE(G70," ",H70," ",I70," ",J70)
L71: =CONCATENATE(C71," ",D71," ",E71," ",F71," ",C72," ",D72," ",E72," ",F72) | M71: =CONCATENATE(G71," ",H71," ",I71," ",J71)
L72: =CONCATENATE(C72," ",D72," ",E72," ",F72," ",C73," ",D73," ",E73," ",F73) | M72: =CONCATENATE(G72," ",H72," ",I72," ",J72)
L73: =CONCATENATE(C73," ",D73," ",E73," ",F73," ",C74," ",D74," ",E74," ",F74) | M73: =CONCATENATE(G73," ",H73," ",I73," ",J73)
L74: =CONCATENATE(C74," ",D74," ",E74," ",F74," ",C75," ",D75," ",E75," ",F75) | M74: =CONCATENATE(G74," ",H74," ",I74," ",J74)
L75: =CONCATENATE(C75," ",D75," ",E75," ",F75," ",C76," ",D76," ",E76," ",F76) | M75: =CONCATENATE(G75," ",H75," ",I75," ",J75)
L76: =CONCATENATE(C76," ",D76," ",E76," ",F76," ",C77," ",D77," ",E77," ",F77) | M76: =CONCATENATE(G76," ",H76," ",I76," ",J76)
L77: =CONCATENATE(C77," ",D77," ",E77," ",F77," ",C78," ",D78," ",E78," ",F78) | M77: =CONCATENATE(G77," ",H77," ",I77," ",J77)
L78: =CONCATENATE(C78," ",D78," ",E78," ",F78," ",C79," ",D79," ",E79," ",F79) | M78: =CONCATENATE(G78," ",H78," ",I78," ",J78)
L79: =CONCATENATE(C79," ",D79," ",E79," ",F79) | M79: =CONCATENATE(G79," ",H79," ",I79," ",J79)
A80: Módulo I | B80: Capacidad técnica | L80: =CONCATENATE(C80," ",D80," ",E80," ",F80," ",C81," ",D81," ",E81," ",F81) | M80: =CONCATENATE(G80," ",H80," ",I80," ",J80)
L81: =CONCATENATE(C81," ",D81," ",E81," ",F81," ",C82," ",D82," ",E82," ",F82) | M81: =CONCATENATE(G81," ",H81," ",I81," ",J81)
L82: =CONCATENATE(C82," ",D82," ",E82," ",F82," ",C83," ",D83," ",E83," ",F83) | M82: =CONCATENATE(G82," ",H82," ",I82," ",J82)
L83: =CONCATENATE(C83," ",D83," ",E83," ",F83," ",C84," ",D84," ",E84," ",F84) | M83: =CONCATENATE(G83," ",H83," ",I83," ",J83)
L84: =CONCATENATE(C84," ",D84," ",E84," ",F84," ",C85," ",D85," ",E85," ",F85) | M84: =CONCATENATE(G84," ",H84," ",I84," ",J84)
L85: =CONCATENATE(C85," ",D85," ",E85," ",F85," ",C86," ",D86," ",E86," ",F86) | M85: =CONCATENATE(G85," ",H85," ",I85," ",J85)
L86: =CONCATENATE(C86," ",D86," ",E86," ",F86," ",C87," ",D87," ",E87," ",F87) | M86: =CONCATENATE(G86," ",H86," ",I86," ",J86)
L87: =CONCATENATE(C87," ",D87," ",E87," ",F87," ",C88," ",D88," ",E88," ",F88) | M87: =CONCATENATE(G87," ",H87," ",I87," ",J87)
L88: =CONCATENATE(C88," ",D88," ",E88," ",F88," ",C89," ",D89," ",E89," ",F89) | M88: =CONCATENATE(G88," ",H88," ",I88," ",J88)
L89: =CONCATENATE(C89," ",D89," ",E89," ",F89) | M89: =CONCATENATE(G89," ",H89," ",I89," ",J89)
A90: Módulo I | B90: Capacidad técnica | L90: =CONCATENATE(C90," ",D90," ",E90," ",F90," ",C91," ",D91," ",E91," ",F91) | M90: =CONCATENATE(G90," ",H90," ",I90," ",J90)
L91: =CONCATENATE(C91," ",D91," ",E91," ",F91," ",C92," ",D92," ",E92," ",F92) | M91: =CONCATENATE(G91," ",H91," ",I91," ",J91)
L92: =CONCATENATE(C92," ",D92," ",E92," ",F92," ",C93," ",D93," ",E93," ",F93) | M92: =CONCATENATE(G92," ",H92," ",I92," ",J92)
L93: =CONCATENATE(C93," ",D93," ",E93," ",F93," ",C94," ",D94," ",E94," ",F94) | M93: =CONCATENATE(G93," ",H93," ",I93," ",J93)
L94: =CONCATENATE(C94," ",D94," ",E94," ",F94," ",C95," ",D95," ",E95," ",F95) | M94: =CONCATENATE(G94," ",H94," ",I94," ",J94)
L95: =CONCATENATE(C95," ",D95," ",E95," ",F95," ",C96," ",D96," ",E96," ",F96) | M95: =CONCATENATE(G95," ",H95," ",I95," ",J95)
L96: =CONCATENATE(C96," ",D96," ",E96," ",F96," ",C97," ",D97," ",E97," ",F97) | M96: =CONCATENATE(G96," ",H96," ",I96," ",J96)
L97: =CONCATENATE(C97," ",D97," ",E97," ",F97," ",C98," ",D98," ",E98," ",F98) | M97: =CONCATENATE(G97," ",H97," ",I97," ",J97)
L98: =CONCATENATE(C98," ",D98," ",E98," ",F98," ",C99," ",D99," ",E99," ",F99) | M98: =CONCATENATE(G98," ",H98," ",I98," ",J98)
L99: =CONCATENATE(C99," ",D99," ",E99," ",F99) | M99: =CONCATENATE(G99," ",H99," ",I99," ",J99)
A100: Módulo I | B100: Capacidad técnica | L100: =CONCATENATE(C100," ",D100," ",E100," ",F100," ",C101," ",D101," ",E101," ",F101) | M100: =CONCATENATE(G100," ",H100," ",I100," ",J100)
L101: =CONCATENATE(C101," ",D101," ",E101," ",F101," ",C102," ",D102," ",E102," ",F102) | M101: =CONCATENATE(G101," ",H101," ",I101," ",J101)
L102: =CONCATENATE(C102," ",D102," ",E102," ",F102," ",C103," ",D103," ",E103," ",F103) | M102: =CONCATENATE(G102," ",H102," ",I102," ",J102)
L103: =CONCATENATE(C103," ",D103," ",E103," ",F103," ",C104," ",D104," ",E104," ",F104) | M103: =CONCATENATE(G103," ",H103," ",I103," ",J103)
L104: =CONCATENATE(C104," ",D104," ",E104," ",F104," ",C105," ",D105," ",E105," ",F105) | M104: =CONCATENATE(G104," ",H104," ",I104," ",J104)
L105: =CONCATENATE(C105," ",D105," ",E105," ",F105," ",C106," ",D106," ",E106," ",F106) | M105: =CONCATENATE(G105," ",H105," ",I105," ",J105)
...

Sheet Organización_Modular
A1: ORGANIZACIÓN MODULAR
A3: DENOMINACIÓN DE LA INSTITUCIÓN | C3: =Perfil_Egreso!B3 -> CETPRO JUANJUI | F3: CÓDIGO MODULAR | G3: =Perfil_Egreso!E3 -> 533836
A5: =Perfil_Egreso!A11 -> DENOMINACIÓN DEL PROGRAMA DE ESTUDIOS | C5: =Perfil_Egreso!B11 -> ESTILISMO | D5: CÓDIGO * | E5: =Perfil_Egreso!E11 -> S3496-2-001 | F5: NIVEL FORMATIVO | G5: =Perfil_Egreso!B15 -> TÉCNICO
A7: =Perfil_Egreso!A13 -> FORMACIÓN** | C7: =Perfil_Egreso!B13 -> 0 | E7: MODALIDAD DEL SERVICIO EDUCATIVO | F7: =Perfil_Egreso!D13 -> PRESENCIAL
H8: Información solo de proceso
A9: MÓDULO | B9: DESCRIPCIÓN DE LA COMPETENCIA | D9: CAPACIDADES | F9: UNIDAD DIDÁCTICA | G9: PERIODO ACADÉMICO | H9: Crédito teórico | I9: Crédito práctico | J9: T.créditos (Filtrar)
A10: M1. PELUQUERIA, BARBERÍA Y PEINADOS | B10: Competencias técnicas (Unidad de competencia) | C10: UC1. Ejecutar el servicio de peluquería y barbería, teniendo en cuenta el diagnóstico capilar, requerimientos del cliente, procedimientos del establecimiento, criterios técnicos, estéticos y de bioseguridad e higiene. . | D10: =OFFSET(Capacidades!$A$1,(ROW()-9)*10-1,11) -> UC1C1 Ejecutar cortes de cabello tomando en cuenta tendencias y criterios estéticos, así como las diferentes morfologías y requerimientos del cliente. | F10: CORTE DE CABELLO | G10: I | H10: 2 | I10: 5 | J10: =SUM(H10:I10) -> 7 | L10: UC1 C3 Ejecutar peinados según procedimientos tecnicos, creatividad y normas de bioseguridad e higiene
D11: =OFFSET(Capacidades!$A$1,(ROW()-9)*10-1,11) -> UC1C2 Ejecutar cortes y diseño de barba y bigote tomando en cuenta tendencias y criterios estéticos, así como las diferentes morfologías y requerimientos del cliente. | F11: CORTE Y DISEÑO DE BARBA | G11: I | H11: 1 | I11: 2 | J11: =SUM(H11:I11) -> 3
D12: =OFFSET(Capacidades!$A$1,(ROW()-9)*10-1,11) -> UC1C3 Ejecutar peinados según procedimientos tècnicos, creatividad y normas de bioseguridad e higiene. | F12: PEINADOS | G12: I | H12: 1 | I12: 2 | J12: =SUM(H12:I12) -> 3
D13: =OFFSET(Capacidades!$A$1,(ROW()-9)*10-1,11) | J13: =SUM(H13:I13) -> 0 | M13: 1 | N13: 1
D14: =OFFSET(Capacidades!$A$1,(ROW()-9)*10-1,11) | J14: =SUM(H14:I14) -> 0 | M14: 0 | N14: 1
D15: =OFFSET(Capacidades!$A$1,(ROW()-9)*10-1,11) | J15: =SUM(H15:I15) -> 0
D16: =OFFSET(Capacidades!$A$1,(ROW()-9)*10-1,11) | J16: =SUM(H16:I16) -> 0
D17: =OFFSET(Capacidades!$A$1,(ROW()-9)*10-1,11) | J17: =SUM(H17:I17) -> 0
D18: =OFFSET(Capacidades!$A$1,(ROW()-9)*10-1,11) | J18: =SUM(H18:I18) -> 0
D19: =OFFSET(Capacidades!$A$1,(ROW()-9)*10-1,11) | J19: =SUM(H19:I19) -> 0
D20: =OFFSET(Capacidades!$A$1,(ROW()-9)*10-1,11) | J20: =SUM(H20:I20) -> 0
D21: =OFFSET(Capacidades!$A$1,(ROW()-9)*10-1,11) | J21: =SUM(H21:I21) -> 0
D22: =OFFSET(Capacidades!$A$1,(ROW()-9)*10-1,11) | J22: =SUM(H22:I22) -> 0
D23: =OFFSET(Capacidades!$A$1,(ROW()-9)*10-1,11) | J23: =SUM(H23:I23) -> 0
D24: =OFFSET(Capacidades!$A$1,(ROW()-9)*10-1,11) | J24: =SUM(H24:I24) -> 0
D25: =OFFSET(Capacidades!$A$1,(ROW()-9)*10-1,11) | J25: =SUM(H25:I25) -> 0
D26: =OFFSET(Capacidades!$A$1,(ROW()-9)*10-1,11) | J26: =SUM(H26:I26) -> 0
... D29: =OFFSET(Capacidades!$A$1,(ROW()-9)*10-1,11) | J29: =SUM(H29:I29) -> 0
B30: Competencias para la empleabilidad | C30: CE1 Comunicación efectiva.- expresar y comprender de manera clara conceptos, ideas, sentimientos, hechos y opiniones en forma oral y escrita para comunicarse e interactuar con otras personas en contextos sociales y laborales diversos. | D30: =OFFSET(Capacidades!$A$1,(ROW()-9)*10-1,11) -> CE1. C1 Expresar conceptos, ideas, sentimientos y hechos en la forma oral en la interacción con otras personas en diferentes contextos. | F30: COMUNICACIÓN VERBAL EFECTIVA | G30: I | H30: 1 | I30: 1 | J30: =SUM(H30:I30) -> 2
D31: =OFFSET(Capacidades!$A$1,(ROW()-9)*10-1,11) -> CE1. C2 Interpretar conceptos, ideas y hechos expresados de manera escrita en diferentes contextos. | F31: COMUNICACIÓN ESCRITA | G31: I | H31: 0 | I31: 1 | J31: =SUM(H31:I31) -> 1
D32: =OFFSET(Capacidades!$A$1,(ROW()-9)*10-1,11) | J32: =SUM(H32:I32) -> 0
D33: =OFFSET(Capacidades!$A$1,(ROW()-9)*10-1,11) | J33: =SUM(H33:I33) -> 0
D34: =OFFSET(Capacidades!$A$1,(ROW()-9)*10-1,11) | J34: =SUM(H34:I34) -> 0
D35: =OFFSET(Capacidades!$A$1,(ROW()-9)*10-1,11) | J35: =SUM(H35:I35) -> 0
D36: =OFFSET(Capacidades!$A$1,(ROW()-9)*10-1,11) | J36: =SUM(H36:I36) -> 0
D37: =OFFSET(Capacidades!$A$1,(ROW()-9)*10-1,11) | J37: =SUM(H37:I37) -> 0
D38: =OFFSET(Capacidades!$A$1,(ROW()-9)*10-1,11) | J38: =SUM(H38:I38) -> 0
D39: =OFFSET(Capacidades!$A$1,(ROW()-9)*10-1,11) | J39: =SUM(H39:I39) -> 0
B40: Experiencias formativas en situaciones reales de trabajo (EFSRT) | G40: I | H40: 0 | I40: 4 | J40: =SUM(H40:I40) -> 4
A41: M2. ONDULACIÓN, LACEADO Y TINTURACIÓN DEL CABELLO | B41: =$B$10 -> Competencias técnicas (Unidad de competencia) | C41: UC2. Realizar procedimientos técnicos capilares, tomando en cuenta su diagnóstico, requerimientos del cliente, y de bioseguridad e higiene técnicos capilares, tomando en cuenta su diagnóstico, requerimientos del cliente, y de bioseguridad e higiene. | D41: =OFFSET(Capacidades!$A$302,(ROW()-40)*10-1,11) -> UC2C1 Ejecutar el tratamiento capilar tomando en cuenta el diagnostico tricologico y dermatologico | F41: TRATAMIENTO CAPILAR | G41: II | H41: 2 | I41: 3 | J41: =SUM(H41:I41) -> 5
D42: =OFFSET(Capacidades!$A$302,(ROW()-40)*10-1,11) -> UC2C2 Ejecutar cambios permanentes o temporales del cabello según requerimientos del cliente, criterios técnicos, esteticos y de bioseguridad e higiene. | F42: ONDULACIÓN Y LACEADO | G42: II | H42: 2 | I42: 4 | J42: =SUM(H42:I42) -> 6
D43: =OFFSET(Capacidades!$A$302,(ROW()-40)*10-1,11) -> UC2C3 Ejecutar cambios en la decoloración y/o coloración del cabello con tecnicas directas e indirectas aplicando criterios técnicos, estéticos y de bioseguridad e higiene.. | F43: TINTURACIÓN Y DECOLORACION DEL CABELLO | G43: II | H43: 2 | I43: 2 | J43: =SUM(H43:I43) -> 4
D44: =OFFSET(Capacidades!$A$302,(ROW()-40)*10-1,11) | J44: =SUM(H44:I44) -> 0
D45: =OFFSET(Capacidades!$A$302,(ROW()-40)*10-1,11) | J45: =SUM(H45:I45) -> 0
D46: =OFFSET(Capacidades!$A$302,(ROW()-40)*10-1,11) | J46: =SUM(H46:I46) -> 0
D47: =OFFSET(Capacidades!$A$302,(ROW()-40)*10-1,11) | J47: =SUM(H47:I47) -> 0
D48: =OFFSET(Capacidades!$A$302,(ROW()-40)*10-1,11) | J48: =SUM(H48:I48) -> 0
D49: =OFFSET(Capacidades!$A$302,(ROW()-40)*10-1,11) | J49: =SUM(H49:I49) -> 0
D50: =OFFSET(Capacidades!$A$302,(ROW()-40)*10-1,11) | J50: =SUM(H50:I50) -> 0
D51: =OFFSET(Capacidades!$A$302,(ROW()-40)*10-1,11) | J51: =SUM(H51:I51) -> 0
D52: =OFFSET(Capacidades!$A$302,(ROW()-40)*10-1,11) | J52: =SUM(H52:I52) -> 0
D53: =OFFSET(Capacidades!$A$302,(ROW()-40)*10-1,11) | J53: =SUM(H53:I53) -> 0
D54: =OFFSET(Capacidades!$A$302,(ROW()-40)*10-1,11) | J54: =SUM(H54:I54) -> 0
D55: =OFFSET(Capacidades!$A$302,(ROW()-40)*10-1,11) | J55: =SUM(H55:I55) -> 0
... D60: =OFFSET(Capacidades!$A$302,(ROW()-40)*10-1,11) | J60: =SUM(H60:I60) -> 0
B61: =$B$30 -> Competencias para la empleabilidad | C61: CE4. Ética.-Establecer relaciones con respeto y justicia en los ámbitos personal, colectivo e institucional, contribuyendo a una convivencia democrática orientada al bien común, que considere la diversidad y dignidad de las personas, teniendo en cuenta las consideraciones aplicadas en su contexto laboral. | D61: =OFFSET(Capacidades!$A$302,(ROW()-40)*10-1,11) -> CE4. C1 Practicar las relaciones interpersonales democráticas considerando los principios y valores éticos. | F61: RELACIONES INTERPERSONALES | G61: II | H61: 1 | I61: 1 | J61: =SUM(H61:I61) -> 2
D62: =OFFSET(Capacidades!$A$302,(ROW()-40)*10-1,11) -> CE4. C2 Fortalecer una cultura ética, transparente y de anticorrupción en su contexto social y laboral fomentando el bien común, la diversidad y la dignidad de las personas. | F62: ÉTICA Y VALORES | G62: II | H62: 0 | I62: 1 | J62: =SUM(H62:I62) -> 1
D63: =OFFSET(Capacidades!$A$302,(ROW()-40)*10-1,11) | J63: =SUM(H63:I63) -> 0
D64: =OFFSET(Capacidades!$A$302,(ROW()-40)*10-1,11) | J64: =SUM(H64:I64) -> 0
D65: =OFFSET(Capacidades!$A$302,(ROW()-40)*10-1,11) | J65: =SUM(H65:I65) -> 0
D66: =OFFSET(Capacidades!$A$302,(ROW()-40)*10-1,11) | J66: =SUM(H66:I66) -> 0
D67: =OFFSET(Capacidades!$A$302,(ROW()-40)*10-1,11) | J67: =SUM(H67:I67) -> 0
D68: =OFFSET(Capacidades!$A$302,(ROW()-40)*10-1,11) | J68: =SUM(H68:I68) -> 0
D69: =OFFSET(Capacidades!$A$302,(ROW()-40)*10-1,11) | J69: =SUM(H69:I69) -> 0
D70: =OFFSET(Capacidades!$A$302,(ROW()-40)*10-1,11) | J70: =SUM(H70:I70) -> 0
B71: =$B$40 -> Experiencias formativas en situaciones reales de trabajo (EFSRT) | G71: II | H71: 0 | I71: 3 | J71: =SUM(H71:I71) -> 3
A72: M3. MAQUILLAJE DE BELLEZA Y CARACTERIZACIÓN | B72: =$B$10 -> Competencias técnicas (Unidad de competencia) | C72: UC3 Efectuar el servicio de maquillaje de belleza de acuerdo con los requerimientos del cliente, criterios técnicos, estéticos y de bioseguridad e higiene. UC4 Efectuar el servicio de maquillaje de caracterización aplicando materiales para efectos especiales, de acuerdo con los requerimientos del cliente, criterios técnicos, estéticos, de acuerdo con los requerimientos del cliente, criterios técnicos, estéticos éticos y de bioseguridad e higiene. | D72: =OFFSET(Capacidades!$A$603,(ROW()-71)*10-1,11) -> UC3 C1 Realizar la preparación de la piel de acuerdo a las especificaciones tecnicas y requerimientos del cliente. | F72: PREPARACION FACIAL | G72: III | H72: 1 | I72: 2 | J72: =SUM(H72:I72) -> 3
D73: =OFFSET(Capacidades!$A$603,(ROW()-71)*10-1,11) -> UC3 C2 Ejecutar maquillajes de belleza tomando en cuenta la ocasión, criterios estéticos, así como la morfología facial y requerimientos del cliente. | F73: MAQUILLAJES DE BELLEZA | G73: III | H73: 1 | I73: 3 | J73: =SUM(H73:I73) -> 4
D74: =OFFSET(Capacidades!$A$603,(ROW()-71)*10-1,11) -> UC3 C3 Ejecutar depilaciones de la piel del rostro aplicando técnicas mecánicas y tomando en cuenta criterios estéticos y de bioseguridad e higiene. | F74: DEPILACIÓN Y EPILACIÓN | G74: III | H74: 1 | I74: 2 | J74: =SUM(H74:I74) -> 3
D75: =OFFSET(Capacidades!$A$603,(ROW()-71)*10-1,11) -> UC4 C1 Realizar la preparación de la piel y postizos faciales de acuerdo a las especificaciones tecnicas y requerimientos del cliente. UC4 C2 Ejecutar maquillajes de caracterización usando técnicas de posticería, según el personaje a interpretar, tomando en cuenta sus características. | F75: MAQUILLAJES DE CARACTERIZACIÓN | G75: III | H75: 1 | I75: 2 | J75: =SUM(H75:I75) -> 3
D76: =OFFSET(Capacidades!$A$603,(ROW()-71)*10-1,11) | J76: =SUM(H76:I76) -> 0
D77: =OFFSET(Capacidades!$A$603,(ROW()-71)*10-1,11) | J77: =SUM(H77:I77) -> 0
D78: =OFFSET(Capacidades!$A$603,(ROW()-71)*10-1,11) | J78: =SUM(H78:I78) -> 0
D79: =OFFSET(Capacidades!$A$603,(ROW()-71)*10-1,11) | J79: =SUM(H79:I79) -> 0
D80: =OFFSET(Capacidades!$A$603,(ROW()-71)*10-1,11) | J80: =SUM(H80:I80) -> 0
D81: =OFFSET(Capacidades!$A$603,(ROW()-71)*10-1,11) | J81: =SUM(H81:I81) -> 0
D82: =OFFSET(Capacidades!$A$603,(ROW()-71)*10-1,11) | J82: =SUM(H82:I82) -> 0
D83: =OFFSET(Capacidades!$A$603,(ROW()-71)*10-1,11) | J83: =SUM(H83:I83) -> 0
D84: =OFFSET(Capacidades!$A$603,(ROW()-71)*10-1,11) | J84: =SUM(H84:I84) -> 0
D85: =OFFSET(Capacidades!$A$603,(ROW()-71)*10-1,11) | J85: =SUM(H85:I85) -> 0
D86: =OFFSET(Capacidades!$A$603,(ROW()-71)*10-1,11) | J86: =SUM(H86:I86) -> 0
D87: =OFFSET(Capacidades!$A$603,(ROW()-71)*10-1,11) | J87: =SUM(H87:I87) -> 0
... D91: =OFFSET(Capacidades!$A$603,(ROW()-71)*10-1,11) | J91: =SUM(H91:I91) -> 0
B92: =$B$30 -> Competencias para la empleabilidad | C92: CE2. Tecnologías de la información. - Manejar herramientas informáticas de las TICs para buscar y analizar información, comunicarse y realizar procedimientos o tareas vinculadas al área profesional, de acuerdo con los requerimientos de su entorno laboral. | D92: =OFFSET(Capacidades!$A$603,(ROW()-71)*10-1,11) -> CE2. C1 Utilizar aplicaciones y herramienats informáticas de las TIC de manera responsable y técnica. | F92: APLICACIONES DE HERRAMIENTAS INFORMÁTICAS | G92: III | H92: 1 | I92: 1 | J92: =SUM(H92:I92) -> 2
D93: =OFFSET(Capacidades!$A$603,(ROW()-71)*10-1,11) -> CE2. C2 Utilizar software en la realización de tareas y requerimientos vinculados a su programa de estudios. | F93: OFIMÁTICA Y REDES SOCIALES | G93: III | H93: 1 | I93: 1 | J93: =SUM(H93:I93) -> 2
D94: =OFFSET(Capacidades!$A$603,(ROW()-71)*10-1,11) | J94: =SUM(H94:I94) -> 0
D95: =OFFSET(Capacidades!$A$603,(ROW()-71)*10-1,11) | J95: =SUM(H95:I95) -> 0
D96: =OFFSET(Capacidades!$A$603,(ROW()-71)*10-1,11) | J96: =SUM(H96:I96) -> 0
D97: =OFFSET(Capacidades!$A$603,(ROW()-71)*10-1,11) | J97: =SUM(H97:I97) -> 0
D98: =OFFSET(Capacidades!$A$603,(ROW()-71)*10-1,11) | J98: =SUM(H98:I98) -> 0
D99: =OFFSET(Capacidades!$A$603,(ROW()-71)*10-1,11) | J99: =SUM(H99:I99) -> 0
D100: =OFFSET(Capacidades!$A$603,(ROW()-71)*10-1,11) | J100: =SUM(H100:I100) -> 0
D101: =OFFSET(Capacidades!$A$603,(ROW()-71)*10-1,11) | J101: =SUM(H101:I101) -> 0
B102: =$B$40 -> Experiencias formativas en situaciones reales de trabajo (EFSRT) | G102: III | H102: 0 | I102: 4 | J102: =SUM(H102:I102) -> 4
A103: M4. MANICURE Y PEDICURE | B103: =$B$10 -> Competencias técnicas (Unidad de competencia) | C103: UC5 Ejecutar el servicio de estética en manos y pies teniendo en cuenta los requerimientos del cliente, los procedimientos del establecimiento, criterios técnicos, estéticos y de bioseguridad e higiene. | D103: =OFFSET(Capacidades!$A$904,(ROW()-102)*10-1,11) -> UC5 C1 Ejecutar procedimientos de limpieza, desinfección y preparación de manos y pies teniendo en cuenta los requerimientos del cliente, los procedimientos del establecimiento, criterios técnicos y normas de bioseguridad e higiene. | F103: PREPARACION DE MANOS Y PIES | G103: IV | H103: 1 | I103: 3 | J103: =SUM(H103:I103) -> 4
D104: =OFFSET(Capacidades!$A$904,(ROW()-102)*10-1,11) -> UC5 C2 Realizar técnicas de manicure teniendo en cuenta los requerimientos del cliente, criterios técnicos, estéticos y de bioseguridad e higiene. | F104: MANICURE | G104: IV | H104: 1 | I104: 3 | J104: =SUM(H104:I104) -> 4
D105: =OFFSET(Capacidades!$A$904,(ROW()-102)*10-1,11) -> UC5 C3 Ejecutar técnicas de pedicure teniendo en cuenta los requerimientos del cliente, criterios técnicos, estéticos y de bioseguridad e higiene. | F105: PEDICURE | G105: IV | H105: 1 | I105: 3 | J105: =SUM(H105:I105) -> 4
D106: =OFFSET(Capacidades!$A$904,(ROW()-102)*10-1,11) | J106: =SUM(H106:I106) -> 0
D107: =OFFSET(Capacidades!$A$904,(ROW()-102)*10-1,11) | J107: =SUM(H107:I107) -> 0
D108: =OFFSET(Capacidades!$A$904,(ROW()-102)*10-1,11) | J108: =SUM(H108:I108) -> 0
D109: =OFFSET(Capacidades!$A$904,(ROW()-102)*10-1,11) | J109: =SUM(H109:I109) -> 0
D110: =OFFSET(Capacidades!$A$904,(ROW()-102)*10-1,11) | J110: =SUM(H110:I110) -> 0
D111: =OFFSET(Capacidades!$A$904,(ROW()-102)*10-1,11) | J111: =SUM(H111:I111) -> 0
D112: =OFFSET(Capacidades!$A$904,(ROW()-102)*10-1,11) | J112: =SUM(H112:I112) -> 0
...

Sheet M1
A1: ORGANIZACIÓN DE LOS ELEMENTOS DEL MÓDULO
A3: DENOMINACIÓN DE LA INSTITUCIÓN | B3: =Perfil_Egreso!B3 -> CETPRO JUANJUI | F3: CÓDIGO MODULAR DEL INSTITUTO | I3: =Perfil_Egreso!E3 -> 533836
A5: SECTOR ECONÓMICO | B5: =Perfil_Egreso!B5 -> OTRAS ACTIVIDADES DE SERVICIO | C5: FAMILIA PRODUCTIVA | D5: =Perfil_Egreso!D5 -> SERVICIOS PERSONALES Y DE HOGARES | F5: ACTIVIDAD ECONÓMICA | I5: =Perfil_Egreso!B7 -> OTRAS ACTIVIDADES DE SERVICIOS PERSONALES
A7: =Perfil_Egreso!A11 -> DENOMINACIÓN DEL PROGRAMA DE ESTUDIOS | B7: =Perfil_Egreso!B11 -> ESTILISMO | C7: CÓDIGO * | D7: =Perfil_Egreso!E11 -> S3496-2-001
A9: =Perfil_Egreso!A13 -> FORMACIÓN** | B9: =Perfil_Egreso!B13 -> 0 | C9: N°. HORAS: | D9: =Itinerario!W17 -> 2272 | F9: N° CRÉDITOS: | I9: =Itinerario!T17 -> 83
A11: =Perfil_Egreso!C13 -> MODALIDAD DEL SERVICIO EDUCATIVO *** | B11: =Perfil_Egreso!D13 -> PRESENCIAL | F11: =Perfil_Egreso!A15 -> CICLO FORMATIVO | I11: =Perfil_Egreso!B15 -> TÉCNICO
A13: UNIDAD DE COMPETENCIA DEL CATÁLOGO NACIONAL DE LA OFERTA FORMATIVA
A14: =Organización_Modular!C10 -> UC1. Ejecutar el servicio de peluquería y barbería, teniendo en cuenta el diagnóstico capilar, requerimientos del cliente, procedimientos del establecimiento, criterios técnicos, estéticos y de bioseguridad e higiene. .
A15: DENOMINACIÓN DEL MÓDULO | B15: =Organización_Modular!A10 -> M1. PELUQUERIA, BARBERÍA Y PEINADOS
A16: CAPACIDADES TÉCNICAS O ESPECÍFICAS | B16: INDICADORES DE LOGRO DE LA CAPACIDAD | C16: CONTENIDOS | D16: UNIDAD DIDÁCTICA | E16: Periodo | F16: CRÉDITOS | H16: CRÉDITOS | I16: HORAS | K16: HORAS | L16: PERFIL DOCENTE | M16: Filtrar
F17: Teórico | G17: Práctica | I17: Teórico | J17: Práctica
A18: =Capacidades!L10 -> UC1C1 Ejecutar cortes de cabello tomando en cuenta tendencias y criterios estéticos, así como las diferentes morfologías y requerimientos del cliente. | B18: =Capacidades!M10 -> C1I1 Acondiciona su zona de trabajo, herramientas, materiales, presupuesto y control de calidad para el corte de cabello teniendo en cuenta las condiciones de seguridad y salubridad | C18: •Organizacion del taller - tipos - señalizacion- normas de seguridad e higiene •Tecnologia de los equipos de peluqueria- tipos- Caracteristicas - usos. mantenimiento preventivo •Normas de Bioseguridad •Costos y presupuesto •Control de calidad | D18: =Organización_Modular!F10 -> CORTE DE CABELLO | E18: =Organización_Modular!G10 -> I | F18: =Organización_Modular!H10 -> 2 | G18: =Organización_Modular!I10 -> 5 | H18: =SUM(F18:G18) -> 7 | I18: =F18*16 -> 32 | J18: =G18*32 -> 160 | K18: =SUM(I18:J18) -> 192 | L18: Docente de Educación Técnica con especialidad en en Peluqueria y/o Cosmetología | M18: =B18 -> C1I1 Acondiciona su zona de trabajo, herramientas, materiales, presupuesto y control de calidad para el corte de cabello teniendo en cuenta las condiciones de seguridad y salubridad
B19: =Capacidades!M11 -> C1I2 Realiza el servicio de atenciòn al cliente teniendo en cuenta los protocolos y requerimientos del cliente | C19: • Cliente - Atención al cliente- caracteristicas -protocolos Tecnologia de los materiales - tipos- marcas-caracteristicas- uso- conservación | M19: =B19 -> C1I2 Realiza el servicio de atenciòn al cliente teniendo en cuenta los protocolos y requerimientos del cliente
B20: =Capacidades!M12 -> C1I3 Realiza el diagnóstico tricológico, dermatológico y morfológico al cliente tomando en cuenta tendencia y estilos de corte de cabello | C20: • Historia de Corte de Cabello - tipos • El cabello - caracteristicas - Alteraciones - Lavado de cabello- procedimientos- frecuencia •Cuero cabelludo - alteraciones • Morfologia (Rostro - Caracteristicas - Perfil - craneo, etc) •Diagnóstico - importancia- estructura - Ficha Diagnòstica del cliente - Recomendaciones | M20: =B20 -> C1I3 Realiza el diagnóstico tricológico, dermatológico y morfológico al cliente tomando en cuenta tendencia y estilos de corte de cabello
B21: =Capacidades!M13 -> C1I4 Propone estilos de cortes de cabello, tomando en cuenta el diagnostico, tendencias, estilos y requerimientos del cliente. | C21: • La Tijera : partes y tipos. uso- mantenimiento. •La Maquina Cliper: uso .clasificacion -mantenimiento. •La Navaja:tipos- uso - mantenimiento •Productos de Limpieza . Productos de Pre y post tratamiento del Corte de cabello - Recomendaciones •Corte de cabello - Técnicas - Angulos y grados de elevaciòn: 0º, 45º,90º, 135º y 180º - lineas de corte • Técnicas de rasurado de cuello y patilla Tipos de corte (tijera, maquina clipper, navaja)- Estilos de corte -Formas de corte: (Texturizado -degradado, encapado uniforme . encapado incrementado, desgrafilado). | M21: =B21 -> C1I4 Propone estilos de cortes de cabello, tomando en cuenta el diagnostico, tendencias, estilos y requerimientos del cliente.
M22: =B22
B23: =Capacidades!M15 | M23: =B23
B24: =Capacidades!M16 | M24: =B24
B25: =Capacidades!M17 | M25: =B25
B26: =Capacidades!M18 | M26: =B26
B27: =Capacidades!M19 | M27: =B27
A28: =Capacidades!L20 -> UC1C2 Ejecutar cortes y diseño de barba y bigote tomando en cuenta tendencias y criterios estéticos, así como las diferentes morfologías y requerimientos del cliente. | B28: =Capacidades!M20 -> C2I1 Acondiciona su zona de trabajo, herramientas, materiales, presupuesto y control de calidad para cortes de barberia según estilo determinado, aplicando criterios técnicos, estéticos y de bioseguridad e higiene. | C28: • Organización del área de trabajo - señalizacion- normas de seguridad e higiene •Tecnologia de los equipos de peluqueria- tipos- Caracteristicas - usos. mantenimiento preventivo - Normas de bioseguridad- desinfeccion, esterilizacion • Tecnología de los materiales - tipos- marcas- caractetristicas- conservaciòn. • Manejo de presupuestos, Control de calidad | D28: =Organización_Modular!F11 -> CORTE Y DISEÑO DE BARBA | E28: =Organización_Modular!G11 -> I | F28: =Organización_Modular!H11 -> 1 | G28: =Organización_Modular!I11 -> 2 | H28: =SUM(F28:G28) -> 3 | I28: =F28*16 -> 16 | J28: =G28*32 -> 64 | K28: =SUM(I28:J28) -> 80 | L28: Docente de Educación Técnica con especialidad en en Peluqueria y/o Cosmetología | M28: =B28 -> C2I1 Acondiciona su zona de trabajo, herramientas, materiales, presupuesto y control de calidad para cortes de barberia según estilo determinado, aplicando criterios técnicos, estéticos y de bioseguridad e higiene.
B29: =Capacidades!M21 -> C2I2 Realiza el diagnóstico dermatológico y morfológico al cliente tomando en cuenta tendencia y estilos de corte de barba y bigote | C29: • Estudio dermatologico - Morfológico Tendencias . Estilos | M29: =B29 -> C2I2 Realiza el diagnóstico dermatológico y morfológico al cliente tomando en cuenta tendencia y estilos de corte de barba y bigote
B30: =Capacidades!M22 -> C2I3 Realiza rasurado de barba con o sin diseño tomando en cuenta tendencias y criterios estéticos y aplicando procedimientos técnicos establecidos. | C30: Técnicas de rasurado tendencias | M30: =B30 -> C2I3 Realiza rasurado de barba con o sin diseño tomando en cuenta tendencias y criterios estéticos y aplicando procedimientos técnicos establecidos.
B31: =Capacidades!M23 -> C2I4 Realiza cortes con o sin diseño de bigote teniendo en cuenta las características morfologías y requerimientos del cliente y aplicando procedimientos técnicos establecidos. | C31: • Técnica de corte y diseño de barba • Técnica de corte y diseños de bigotes | M31: =B31 -> C2I4 Realiza cortes con o sin diseño de bigote teniendo en cuenta las características morfologías y requerimientos del cliente y aplicando procedimientos técnicos establecidos.
B32: =Capacidades!M24 -> C2I5 Verifica el acabado del corte realizado considerando los criterios estéticos, procedimientos tecnicos establecidos y de bioseguridad e higiene personal. | C32: • Técnicas de acabados. Control de calidad - Recomendaciones post servicio | M32: =B32 -> C2I5 Verifica el acabado del corte realizado considerando los criterios estéticos, procedimientos tecnicos establecidos y de bioseguridad e higiene personal.
B33: =Capacidades!M25 | M33: =B33
B34: =Capacidades!M26 | M34: =B34
B35: =Capacidades!M27 | M35: =B35
B36: =Capacidades!M28 | M36: =B36
B37: =Capacidades!M29 | M37: =B37
A38: =Capacidades!L30 -> UC1C3 Ejecutar peinados según procedimientos tècnicos, creatividad y normas de bioseguridad e higiene. | B38: =Capacidades!M30 -> C3I1 Acondiciona su zona de trabajo, herramientas y productos para peinados teniendo en cuenta las condiciones de bioseguridad e higiene | C38: • Organización del área de trabajo - señalización- normas de seguridad e higiene •Tecnología de los equipos de peluqueria- tipos- Características - usos. mantenimiento preventivo - Normas de bioseguridad- desinfección, esterilizacion • Manejo de presupuestos, Control de calidad y bioseguridad | D38: =Organización_Modular!F12 -> PEINADOS | E38: =Organización_Modular!G12 -> I | F38: =Organización_Modular!H12 -> 1 | G38: =Organización_Modular!I12 -> 2 | H38: =SUM(F38:G38) -> 3 | I38: =F38*16 -> 16 | J38: =G38*32 -> 64 | K38: =SUM(I38:J38) -> 80 | M38: =B38 -> C3I1 Acondiciona su zona de trabajo, herramientas y productos para peinados teniendo en cuenta las condiciones de bioseguridad e higiene
B39: =Capacidades!M31 -> C3I2 Prepara el cabello para el peinado, considerando el diagnostico, aplicando técnicas y utilizando equipos térmicos. | C39: •Peinado - tipos - estilos- • Ficha diagnóstica •Tecnología de los materiales, - tipos- marcas- características-usos • Limpieza - secado del cabello | M39: =B39 -> C3I2 Prepara el cabello para el peinado, considerando el diagnostico, aplicando técnicas y utilizando equipos térmicos.
B40: =Capacidades!M32 -> C3I3 Realiza diversos peinados tomando en cuenta tendencias y criterios estéticos, diagnostico y requerimientos del cliente. | C40: • Peinado - tipos - estilos- • Técnicas de Trenzado • Técnicas de cepillado • Técnicas de Moños • Técnicas de Cepillado • Técnicas de planchado y rizado • Técnicass de peinados recogidos • Tecnicas de peinados de fantasia | M40: =B40 -> C3I3 Realiza diversos peinados tomando en cuenta tendencias y criterios estéticos, diagnostico y requerimientos del cliente.
B41: =Capacidades!M33 -> C3I4 Aplica postizos y/o extensiones en los peinados considerando técnicas, criterios estéticos y requerimientos del cliente. | C41: • Técnicas de peinados con postizos • Técnicas de peinados con extensiones | M41: =B41 -> C3I4 Aplica postizos y/o extensiones en los peinados considerando técnicas, criterios estéticos y requerimientos del cliente.
B42: =Capacidades!M34 -> C3I5 Verifica el acabado del peinado considerando los criterios estéticos, procedimientos tecnicos establecidos y de bioseguridad e higiene personal. | C42: Técnicas de Acabados Recomendaciones post servicio | M42: =B42 -> C3I5 Verifica el acabado del peinado considerando los criterios estéticos, procedimientos tecnicos establecidos y de bioseguridad e higiene personal.
B43: =Capacidades!M35 | M43: =B43
B44: =Capacidades!M36 | M44: =B44
B45: =Capacidades!M37 | M45: =B45
B46: =Capacidades!M38 | M46: =B46
B47: =Capacidades!M39 | M47: =B47
A48: =Capacidades!L40 | B48: =Capacidades!M40 | D48: =Organización_Modular!F13 -> 0 | E48: =Organización_Modular!G13 -> 0 | F48: =Organización_Modular!H13 -> 0 | G48: =Organización_Modular!I13 -> 0 | H48: =SUM(F48:G48) -> 0 | I48: =F48*16 -> 0 | J48: =G48*32 -> 0 | K48: =SUM(I48:J48) -> 0 | M48: =B48
B49: =Capacidades!M41 | M49: =B49
B50: =Capacidades!M42 | M50: =B50
B51: =Capacidades!M43 | M51: =B51
B52: =Capacidades!M44 | M52: =B52
B53: =Capacidades!M45 | M53: =B53
B54: =Capacidades!M46 | M54: =B54
B55: =Capacidades!M47 | M55: =B55
B56: =Capacidades!M48 | M56: =B56
B57: =Capacidades!M49 | M57: =B57
A58: =Capacidades!L50 | B58: =Capacidades!M50 | D58: =Organización_Modular!F14 -> 0 | E58: =Organización_Modular!G14 -> 0 | F58: =Organización_Modular!H14 -> 0 | G58: =Organización_Modular!I14 -> 0 | H58: =SUM(F58:G58) -> 0 | I58: =F58*16 -> 0 | J58: =G58*32 -> 0 | K58: =SUM(I58:J58) -> 0 | M58: =B58
B59: =Capacidades!M51 | M59: =B59
B60: =Capacidades!M52 | M60: =B60
B61: =Capacidades!M53 | M61: =B61
B62: =Capacidades!M54 | M62: =B62
B63: =Capacidades!M55 | M63: =B63
B64: =Capacidades!M56 | M64: =B64
B65: =Capacidades!M57 | M65: =B65
B66: =Capacidades!M58 | M66: =B66
B67: =Capacidades!M59 | M67: =B67
A68: =Capacidades!L60 | B68: =Capacidades!M60 | D68: =Organización_Modular!F15 -> 0 | E68: =Organización_Modular!G15 -> 0 | F68: =Organización_Modular!H15 -> 0 | G68: =Organización_Modular!I15 -> 0 | H68: =SUM(F68:G68) -> 0 | I68: =F68*16 -> 0 | J68: =G68*32 -> 0 | K68: =SUM(I68:J68) -> 0 | M68: =B68
B69: =Capacidades!M61 | M69: =B69
B70: =Capacidades!M62 | M70: =B70
B71: =Capacidades!M63 | M71: =B71
B72: =Capacidades!M64 | M72: =B72
B73: =Capacidades!M65 | M73: =B73
B74: =Capacidades!M66 | M74: =B74
B75: =Capacidades!M67 | M75: =B75
B76: =Capacidades!M68 | M76: =B76
B77: =Capacidades!M69 | M77: =B77
A78: =Capacidades!L70 | B78: =Capacidades!M70 | D78: =Organización_Modular!F16 -> 0 | E78: =Organización_Modular!G16 -> 0 | F78: =Organización_Modular!H16 -> 0 | G78: =Organización_Modular!I16 -> 0 | H78: =SUM(F78:G78) -> 0 | I78: =F78*16 -> 0 | J78: =G78*32 -> 0 | K78: =SUM(I78:J78) -> 0 | M78: =B78
B79: =Capacidades!M71 | M79: =B79
B80: =Capacidades!M72 | M80: =B80
B81: =Capacidades!M73 | M81: =B81
B82: =Capacidades!M74 | M82: =B82
B83: =Capacidades!M75 | M83: =B83
B84: =Capacidades!M76 | M84: =B84
B85: =Capacidades!M77 | M85: =B85
B86: =Capacidades!M78 | M86: =B86
B87: =Capacidades!M79 | M87: =B87
A88: =Capacidades!L80 | B88: =Capacidades!M80 | D88: =Organización_Modular!F17 -> 0 | E88: =Organización_Modular!G17 -> 0 | F88: =Organización_Modular!H17 -> 0 | G88: =Organización_Modular!I17 -> 0 | H88: =SUM(F88:G88) -> 0 | I88: =F88*16 -> 0 | J88: =G88*32 -> 0 | K88: =SUM(I88:J88) -> 0 | M88: =B88
B89: =Capacidades!M81 | M89: =B89
B90: =Capacidades!M82 | M90: =B90
B91: =Capacidades!M83 | M91: =B91
B92: =Capacidades!M84 | M92: =B92
B93: =Capacidades!M85 | M93: =B93
B94: =Capacidades!M86 | M94: =B94
B95: =Capacidades!M87 | M95: =B95
B96: =Capacidades!M88 | M96: =B96
B97: =Capacidades!M89 | M97: =B97
A98: =Capacidades!L90 | B98: =Capacidades!M90 | D98: =Organización_Modular!F18 -> 0 | E98: =Organización_Modular!G18 -> 0 | F98: =Organización_Modular!H18 -> 0 | G98: =Organización_Modular!I18 -> 0 | H98: =SUM(F98:G98) -> 0 | I98: =F98*16 -> 0 | J98: =G98*32 -> 0 | K98: =SUM(I98:J98) -> 0 | M98: =B98
B99: =Capacidades!M91 | M99: =B99
B100: =Capacidades!M92 | M100: =B100
B101: =Capacidades!M93 | M101: =B101
B102: =Capacidades!M94 | M102: =B102
B103: =Capacidades!M95 | M103: =B103
B104: =Capacidades!M96 | M104: =B104
B105: =Capacidades!M97 | M105: =B105
B106: =Capacidades!M98 | M106: =B106
...

Sheet M2
A1: ='M1'!A1:L1 -> ORGANIZACIÓN DE LOS ELEMENTOS DEL MÓDULO
A3: DENOMINACIÓN DE LA INSTITUCIÓN | B3: =Perfil_Egreso!B3 -> CETPRO JUANJUI | F3: CÓDIGO MODULAR DEL INSTITUTO | I3: =Perfil_Egreso!E3 -> 533836
A5: SECTOR ECONÓMICO | B5: =Perfil_Egreso!B5 -> OTRAS ACTIVIDADES DE SERVICIO | C5: FAMILIA PRODUCTIVA | D5: =Perfil_Egreso!D5 -> SERVICIOS PERSONALES Y DE HOGARES | F5: ACTIVIDAD ECONÓMICA | I5: =Perfil_Egreso!B7 -> OTRAS ACTIVIDADES DE SERVICIOS PERSONALES
A7: =Perfil_Egreso!A11 -> DENOMINACIÓN DEL PROGRAMA DE ESTUDIOS | B7: =Perfil_Egreso!B11 -> ESTILISMO | C7: CÓDIGO * | D7: =Perfil_Egreso!E11 -> S3496-2-001 | F7: =Perfil_Egreso!A9 -> DENOMINACIÓN VARIANTE | I7: =Perfil_Egreso!B9 -> 0
A9: =Perfil_Egreso!A13 -> FORMACIÓN** | B9: =Perfil_Egreso!B13 -> 0 | C9: N°. HORAS: | D9: =Itinerario!W17 -> 2272 | F9: N° CRÉDITOS: | I9: =Itinerario!T17 -> 83
A11: =Perfil_Egreso!C13 -> MODALIDAD DEL SERVICIO EDUCATIVO *** | B11: =Perfil_Egreso!D13 -> PRESENCIAL | F11: =Perfil_Egreso!A15 -> CICLO FORMATIVO | I11: =Perfil_Egreso!B15 -> TÉCNICO
A13: UNIDAD DE COMPETENCIA DEL CATÁLOGO NACIONAL DE LA OFERTA FORMATIVA
A14: =Organización_Modular!C41 -> UC2. Realizar procedimientos técnicos capilares, tomando en cuenta su diagnóstico, requerimientos del cliente, y de bioseguridad e higiene técnicos capilares, tomando en cuenta su diagnóstico, requerimientos del cliente, y de bioseguridad e higiene.
A15: DENOMINACIÓN DEL MÓDULO | B15: =Organización_Modular!A41 -> M2. ONDULACIÓN, LACEADO Y TINTURACIÓN DEL CABELLO
A16: CAPACIDADES TÉCNICAS O ESPECÍFICAS | B16: INDICADORES DE LOGRO DE LA CAPACIDAD | C16: CONTENIDOS | D16: UNIDAD DIDÁCTICA | E16: Periodo | F16: CRÉDITOS | H16: CRÉDITOS | I16: HORAS | K16: HORAS | L16: PERFIL DOCENTE | M16: Filtrar
F17: Teórico | G17: Práctica | I17: Teórico | J17: Práctica
A18: =Capacidades!L311 -> UC2C1 Ejecutar el tratamiento capilar tomando en cuenta el diagnostico tricologico y dermatologico | B18: =Capacidades!M311 -> C1I1 Acondiciona su zona de trabajo, herramientas, materiales para el tratamiento capilar teniendo en cuenta los procedimientos del establecimiento, estandares de calidad según el servicio a realizar. | C18: • Organización del área de trabajo, Manejo y mantenimiento de herramientas para el tratamiento capilar • Manejo de presupuestos, Control de calidad • Normas de bioseguridad e higiene. | D18: =Organización_Modular!F41 -> TRATAMIENTO CAPILAR | E18: =Organización_Modular!G41 -> II | F18: =Organización_Modular!H41 -> 2 | G18: =Organización_Modular!I41 -> 3 | H18: =SUM(F18:G18) -> 5 | I18: =F18*16 -> 32 | J18: =G18*32 -> 96 | K18: =SUM(I18:J18) -> 128 | L18: Docente de Educación Técnica con especialidad en en Peluqueria y/o Cosmetología | M18: =B18 -> C1I1 Acondiciona su zona de trabajo, herramientas, materiales para el tratamiento capilar teniendo en cuenta los procedimientos del establecimiento, estandares de calidad según el servicio a realizar.
B19: =Capacidades!M312 -> C1I2 Diagnostica el cuero cabelludo y la hebra capilar siguiendo los criterios técnicos establecidos y de bioseguridad e higiene. | C19: • Estructura del cuero cabelludo y la hebra capilar. • Diagnóstico Tricológico: Alteraciones, caracteristicas del cuero cabelludo y de la hebra capilar. . | M19: =B19 -> C1I2 Diagnostica el cuero cabelludo y la hebra capilar siguiendo los criterios técnicos establecidos y de bioseguridad e higiene.
B20: =Capacidades!M313 -> C1I3 Verifica los productos a utilizar siguiendo los procedimientos establecidos | C20: • Aplicación de ficha técnica de diagnóstico. • Tecnología de los equipos, materiales y productos cosméticos capilares. Importancia del pH en el cabello. Mascarillas naturales para cabellos no tratados/tratados. | M20: =B20 -> C1I3 Verifica los productos a utilizar siguiendo los procedimientos establecidos
B21: =Capacidades!M314 -> C1I4 Aplica el tratamiento capilar con productos naturales verificando las condiciones del producto natural a utilizar siguiendo criterios de bioseguridad e higiene. | C21: •Tipos de productos y tratamientos • Acondicionador. Ampolletas, Cremas. Mascarillas. Lociones capilares Tratamiento con keratina y recomendaciones post servicio • Tratamiento con botox y recomendaciones post servicio | M21: =B21 -> C1I4 Aplica el tratamiento capilar con productos naturales verificando las condiciones del producto natural a utilizar siguiendo criterios de bioseguridad e higiene.
B22: =Capacidades!M315 -> C1I5 Aplica el tratamiento capilar con productos quimicos verificando las condiciones del producto o productos quimicos a utilizar siguiendo criterios de bioseguridad e higiene. | C22: •Tratamiento capilar con Productos naturales. Mascarillas, tónicos, lociones naturales para cabellos no tratados /tratados. | M22: =B22 -> C1I5 Aplica el tratamiento capilar con productos quimicos verificando las condiciones del producto o productos quimicos a utilizar siguiendo criterios de bioseguridad e higiene.
B23: =Capacidades!M316 -> C1I6 Elabora el presupuesto teniendo en cuenta el servicio a realizar | C23: Costos- Presupuesto Costos directos e indirectos- costo total | M23: =B23 -> C1I6 Elabora el presupuesto teniendo en cuenta el servicio a realizar
M24: =B24 -> 0
B25: =Capacidades!M318 | M25: =B25
B26: =Capacidades!M319 | M26: =B26
B27: =Capacidades!M320 | M27: =B27
A28: =Capacidades!L321 -> UC2C2 Ejecutar cambios permanentes o temporales del cabello según requerimientos del cliente, criterios técnicos, esteticos y de bioseguridad e higiene. | B28: =Capacidades!M321 -> C2I1 Acondiciona su zona de trabajo, herramientas y materiales, teniendo en cuenta los procedimientos técnicos establecidos y según el servicio a realizar. | C28: • Organización del área de trabajo, manejo de presupuestos, control de calidad y bioseguridad • Tecnología de los equipos - tipos- caracteristicas- usos- mantenimiento. | D28: =Organización_Modular!F42 -> ONDULACIÓN Y LACEADO | E28: =Organización_Modular!G42 -> II | F28: =Organización_Modular!H42 -> 2 | G28: =Organización_Modular!I42 -> 4 | H28: =SUM(F28:G28) -> 6 | I28: =F28*16 -> 32 | J28: =G28*32 -> 128 | K28: =SUM(I28:J28) -> 160 | L28: Docente de Educación Técnica con especialidad en en Peluqueria y/o Cosmetología | M28: =B28 -> C2I1 Acondiciona su zona de trabajo, herramientas y materiales, teniendo en cuenta los procedimientos técnicos establecidos y según el servicio a realizar.
B29: =Capacidades!M322 -> C2I2 Identifica las características del cuero cabelludo y la hebra capilar, tomando en cuenta los procedimientos técnicos establecidos, tendencias y criterios estéticos, así como requerimientos del cliente. | C29: • Historia, concepto, característica,Ondulación . • Diagnóstico del cabello, (características, elasticidad, resistencia , porosidad) - Ficha Técnica. | M29: =B29 -> C2I2 Identifica las características del cuero cabelludo y la hebra capilar, tomando en cuenta los procedimientos técnicos establecidos, tendencias y criterios estéticos, así como requerimientos del cliente.
B30: =Capacidades!M323 -> C2I3 Identifica los productos a utilizar teniendo en cuenta los procedimientos técnicos establecidos y según el servicio a realizar. | C30: •Tecnología de los productos cosmético,medidas de seguridad e higiene •Propiedades - Usos- conservaciòn Formula | M30: =B30 -> C2I3 Identifica los productos a utilizar teniendo en cuenta los procedimientos técnicos establecidos y según el servicio a realizar.
B31: =Capacidades!M324 -> C2I4 Realiza la ondulacion del cabello tomando en cuenta tendencias y criterios estéticos, así como las diferentes morfologías y requerimientos del cliente. | C31: Técnicas de enrolle del cabello • Técnicas de ondulacion indirecta - Indirecta | M31: =B31 -> C2I4 Realiza la ondulacion del cabello tomando en cuenta tendencias y criterios estéticos, así como las diferentes morfologías y requerimientos del cliente.
B32: =Capacidades!M325 -> C2I5 Realiza el laceado del cabello tomando en cuenta tendencias y criterios estéticos, así como las diferentes morfologías y requerimientos del cliente. | C32: • Propiedades y uso de productos para el laceado del cabello. Técnicas de laceado -alisado | M32: =B32 -> C2I5 Realiza el laceado del cabello tomando en cuenta tendencias y criterios estéticos, así como las diferentes morfologías y requerimientos del cliente.
B33: =Capacidades!M326 | M33: =B33
B34: =Capacidades!M327 | M34: =B34
B35: =Capacidades!M328 | M35: =B35
B36: =Capacidades!M329 | M36: =B36
B37: =Capacidades!M330 | M37: =B37
A38: =Capacidades!L331 -> UC2C3 Ejecutar cambios en la decoloración y/o coloración del cabello con tecnicas directas e indirectas aplicando criterios técnicos, estéticos y de bioseguridad e higiene.. | B38: =Capacidades!M331 -> C3I1 Acondiciona su zona de trabajo, herramientas y materiales, teniendo en cuenta los procedimientos técnicos establecidos y según el servicio a realizar. | C38: • Organización del área de trabajo, manejo de presupuestos, control de calidad , bioseguridad e higiene. •Herramientas,materiales y productos cosméticos para la coloración y decoloración del cabello. | D38: =Organización_Modular!F43 -> TINTURACIÓN Y DECOLORACION DEL CABELLO | E38: =Organización_Modular!G43 -> II | F38: =Organización_Modular!H43 -> 2 | G38: =Organización_Modular!I43 -> 2 | H38: =SUM(F38:G38) -> 4 | I38: =F38*16 -> 32 | J38: =G38*32 -> 64 | K38: =SUM(I38:J38) -> 96 | M38: =B38 -> C3I1 Acondiciona su zona de trabajo, herramientas y materiales, teniendo en cuenta los procedimientos técnicos establecidos y según el servicio a realizar.
B39: =Capacidades!M332 -> C3I2 Realiza el diagnóstico del cuero cabelludo y la hebra capilar, tomando en cuenta los procedimientos técnicos establecidos, tendencias y criterios estéticos, así como requerimientos del cliente. | C39: • Diagnóstico del cabello,Características , elasticidad, resistencia, y porosidad . • -Prueba de sensibilidad, Prueba de mechón ,ficha diagnostica. | M39: =B39 -> C3I2 Realiza el diagnóstico del cuero cabelludo y la hebra capilar, tomando en cuenta los procedimientos técnicos establecidos, tendencias y criterios estéticos, así como requerimientos del cliente.
B40: =Capacidades!M333 -> C3I3 Ejecuta la tinturacion directa del cabello aplicando productos cosméticos, procedimientos técnicos establecidos y de bioseguridad e higiene. | C40: • Tinturaciòn- Teoria del color - Tintes naturales - reflejos - aclarantes Técnicas de tinturacion directa. técnicas de oscurecimiento ( cabellos canosos) Técnicas del aclaramiento del cabello(cabello virgen, cabello tratado). • Tratamiento del cabello tinturado con baño de color | M40: =B40 -> C3I3 Ejecuta la tinturacion directa del cabello aplicando productos cosméticos, procedimientos técnicos establecidos y de bioseguridad e higiene.
B41: =Capacidades!M334 -> C3I4 Ejecuta la tinturacion indirecta (decoloración) del cabello aplicando productos cosméticos, procedimientos técnicos establecidos y de bioseguridad e higiene. | C41: Tinte indirecto Técnicas de tecnica en mechas.(Balayage,Californianas,etc) •Técnicas de Iluminacion del cabello,rayitos. • Aplicación de Tintes de fantacia en el cabello | M41: =B41 -> C3I4 Ejecuta la tinturacion indirecta (decoloración) del cabello aplicando productos cosméticos, procedimientos técnicos establecidos y de bioseguridad e higiene.
B42: =Capacidades!M335 | M42: =B42
B43: =Capacidades!M336 | M43: =B43
B44: =Capacidades!M337 | M44: =B44
B45: =Capacidades!M338 | M45: =B45
B46: =Capacidades!M339 | M46: =B46
B47: =Capacidades!M340 | M47: =B47
A48: =Capacidades!L341 | B48: =Capacidades!M341 | D48: =Organización_Modular!F44 -> 0 | E48: =Organización_Modular!G44 -> 0 | F48: =Organización_Modular!H44 -> 0 | G48: =Organización_Modular!I44 -> 0 | H48: =SUM(F48:G48) -> 0 | I48: =F48*16 -> 0 | J48: =G48*32 -> 0 | K48: =SUM(I48:J48) -> 0 | M48: =B48
B49: =Capacidades!M342 | M49: =B49
B50: =Capacidades!M343 | M50: =B50
B51: =Capacidades!M344 | M51: =B51
B52: =Capacidades!M345 | M52: =B52
B53: =Capacidades!M346 | M53: =B53
B54: =Capacidades!M347 | M54: =B54
B55: =Capacidades!M348 | M55: =B55
B56: =Capacidades!M349 | M56: =B56
B57: =Capacidades!M350 | M57: =B57
A58: =Capacidades!L351 | B58: =Capacidades!M351 | D58: =Organización_Modular!F45 -> 0 | E58: =Organización_Modular!G45 -> 0 | F58: =Organización_Modular!H45 -> 0 | G58: =Organización_Modular!I45 -> 0 | H58: =SUM(F58:G58) -> 0 | I58: =F58*16 -> 0 | J58: =G58*32 -> 0 | K58: =SUM(I58:J58) -> 0 | M58: =B58
B59: =Capacidades!M352 | M59: =B59
B60: =Capacidades!M353 | M60: =B60
B61: =Capacidades!M354 | M61: =B61
B62: =Capacidades!M355 | M62: =B62
B63: =Capacidades!M356 | M63: =B63
B64: =Capacidades!M357 | M64: =B64
B65: =Capacidades!M358 | M65: =B65
B66: =Capacidades!M359 | M66: =B66
B67: =Capacidades!M360 | M67: =B67
A68: =Capacidades!L361 | B68: =Capacidades!M361 | D68: =Organización_Modular!F46 -> 0 | E68: =Organización_Modular!G46 -> 0 | F68: =Organización_Modular!H46 -> 0 | G68: =Organización_Modular!I46 -> 0 | H68: =SUM(F68:G68) -> 0 | I68: =F68*16 -> 0 | J68: =G68*32 -> 0 | K68: =SUM(I68:J68) -> 0 | M68: =B68
B69: =Capacidades!M362 | M69: =B69
B70: =Capacidades!M363 | M70: =B70
B71: =Capacidades!M364 | M71: =B71
B72: =Capacidades!M365 | M72: =B72
B73: =Capacidades!M366 | M73: =B73
B74: =Capacidades!M367 | M74: =B74
B75: =Capacidades!M368 | M75: =B75
B76: =Capacidades!M369 | M76: =B76
B77: =Capacidades!M370 | M77: =B77
A78: =Capacidades!L371 | B78: =Capacidades!M371 | D78: =Organización_Modular!F47 -> 0 | E78: =Organización_Modular!G47 -> 0 | F78: =Organización_Modular!H47 -> 0 | G78: =Organización_Modular!I47 -> 0 | H78: =SUM(F78:G78) -> 0 | I78: =F78*16 -> 0 | J78: =G78*32 -> 0 | K78: =SUM(I78:J78) -> 0 | M78: =B78
B79: =Capacidades!M372 | M79: =B79
B80: =Capacidades!M373 | M80: =B80
B81: =Capacidades!M374 | M81: =B81
B82: =Capacidades!M375 | M82: =B82
B83: =Capacidades!M376 | M83: =B83
B84: =Capacidades!M377 | M84: =B84
B85: =Capacidades!M378 | M85: =B85
B86: =Capacidades!M379 | M86: =B86
B87: =Capacidades!M380 | M87: =B87
A88: =Capacidades!L381 | B88: =Capacidades!M381 | D88: =Organización_Modular!F48 -> 0 | E88: =Organización_Modular!G48 -> 0 | F88: =Organización_Modular!H48 -> 0 | G88: =Organización_Modular!I48 -> 0 | H88: =SUM(F88:G88) -> 0 | I88: =F88*16 -> 0 | J88: =G88*32 -> 0 | K88: =SUM(I88:J88) -> 0 | M88: =B88
B89: =Capacidades!M382 | M89: =B89
B90: =Capacidades!M383 | M90: =B90
B91: =Capacidades!M384 | M91: =B91
B92: =Capacidades!M385 | M92: =B92
B93: =Capacidades!M386 | M93: =B93
B94: =Capacidades!M387 | M94: =B94
B95: =Capacidades!M388 | M95: =B95
B96: =Capacidades!M389 | M96: =B96
B97: =Capacidades!M390 | M97: =B97
A98: =Capacidades!L391 | B98: =Capacidades!M391 | D98: =Organización_Modular!F49 -> 0 | E98: =Organización_Modular!G49 -> 0 | F98: =Organización_Modular!H49 -> 0 | G98: =Organización_Modular!I49 -> 0 | H98: =SUM(F98:G98) -> 0 | I98: =F98*16 -> 0 | J98: =G98*32 -> 0 | K98: =SUM(I98:J98) -> 0 | M98: =B98
B99: =Capacidades!M392 | M99: =B99
B100: =Capacidades!M393 | M100: =B100
B101: =Capacidades!M394 | M101: =B101
B102: =Capacidades!M395 | M102: =B102
B103: =Capacidades!M396 | M103: =B103
B104: =Capacidades!M397 | M104: =B104
B105: =Capacidades!M398 | M105: =B105
B106: =Capacidades!M399 | M106: =B106
...

Sheet M3
A1: ='M2'!A1:L1 -> ORGANIZACIÓN DE LOS ELEMENTOS DEL MÓDULO
A3: DENOMINACIÓN DE LA INSTITUCIÓN | B3: =Perfil_Egreso!B3 -> CETPRO JUANJUI | F3: CÓDIGO MODULAR DEL INSTITUTO | I3: =Perfil_Egreso!E3 -> 533836
A5: SECTOR ECONÓMICO | B5: =Perfil_Egreso!B5 -> OTRAS ACTIVIDADES DE SERVICIO | C5: FAMILIA PRODUCTIVA | D5: =Perfil_Egreso!D5 -> SERVICIOS PERSONALES Y DE HOGARES | F5: ACTIVIDAD ECONÓMICA | I5: =Perfil_Egreso!B7 -> OTRAS ACTIVIDADES DE SERVICIOS PERSONALES
A7: =Perfil_Egreso!A11 -> DENOMINACIÓN DEL PROGRAMA DE ESTUDIOS | B7: =Perfil_Egreso!B11 -> ESTILISMO | C7: CÓDIGO * | D7: =Perfil_Egreso!E11 -> S3496-2-001 | F7: =Perfil_Egreso!A9 -> DENOMINACIÓN VARIANTE | I7: =Perfil_Egreso!B9 -> 0
A9: =Perfil_Egreso!A13 -> FORMACIÓN** | B9: =Perfil_Egreso!B13 -> 0 | C9: N°. HORAS: | D9: =Itinerario!W17 -> 2272 | F9: N° CRÉDITOS: | I9: =Itinerario!T17 -> 83
A11: =Perfil_Egreso!C13 -> MODALIDAD DEL SERVICIO EDUCATIVO *** | B11: =Perfil_Egreso!D13 -> PRESENCIAL | F11: =Perfil_Egreso!A15 -> CICLO FORMATIVO | I11: =Perfil_Egreso!B15 -> TÉCNICO
A13: UNIDAD DE COMPETENCIA DEL CATÁLOGO NACIONAL DE LA OFERTA FORMATIVA
A14: =Organización_Modular!C72 -> UC3 Efectuar el servicio de maquillaje de belleza de acuerdo con los requerimientos del cliente, criterios técnicos, estéticos y de bioseguridad e higiene. UC4 Efectuar el servicio de maquillaje de caracterización aplicando materiales para efectos especiales, de acuerdo con los requerimientos del cliente, criterios técnicos, estéticos, de acuerdo con los requerimientos del cliente, criterios técnicos, estéticos éticos y de bioseguridad e higiene.
A15: DENOMINACIÓN DEL MÓDULO | B15: =Organización_Modular!A72 -> M3. MAQUILLAJE DE BELLEZA Y CARACTERIZACIÓN
A16: CAPACIDADES TÉCNICAS O ESPECÍFICAS | B16: INDICADORES DE LOGRO DE LA CAPACIDAD | C16: CONTENIDOS | D16: UNIDAD DIDÁCTICA | E16: Periodo | F16: CRÉDITOS | H16: CRÉDITOS | I16: HORAS | K16: HORAS | L16: PERFIL DOCENTE | M16: Filtrar
F17: Teórico | G17: Práctica | I17: Teórico | J17: Práctica
A18: =Capacidades!L612 -> UC3 C1 Realizar la preparación de la piel de acuerdo a las especificaciones tecnicas y requerimientos del cliente. | B18: =Capacidades!M612 -> C1 I1 Identifica el biotipo cutáneo teniendo en cuenta el diagnostico dermatológico y morfológico del cliente | C18: • Organización del área de trabajo, Materiales,productos cosmeticos. • Manejo de presupuestos, Control de calidad • Normas de bioseguridad e higiene. • Morfologia facial biotipo y fototipo cutaneo.Alteraciones de la piel. | D18: =Organización_Modular!F72 -> PREPARACION FACIAL | E18: =Organización_Modular!G72 -> III | F18: =Organización_Modular!H72 -> 1 | G18: =Organización_Modular!I72 -> 2 | H18: =SUM(F18:G18) -> 3 | I18: =F18*16 -> 16 | J18: =G18*32 -> 64 | K18: =SUM(I18:J18) -> 80 | L18: Docente de Educación Técnica con especialidad en en Peluqueria y/o Cosmetología | M18: =B18 -> C1 I1 Identifica el biotipo cutáneo teniendo en cuenta el diagnostico dermatológico y morfológico del cliente
B19: =Capacidades!M613 -> C1 I2 Prepara la piel del cliente para el maquillaje teniendo en cuenta la ficha diagnóstica, especificaciones técnicas y procedimientos de bio seguridad e higiene establecidos. | C19: • Tecnicas de Preparación de la piel, segun el biotipo cutaneo(graso,Mixto;Seco.etc) Ficha diagnostica. | M19: =B19 -> C1 I2 Prepara la piel del cliente para el maquillaje teniendo en cuenta la ficha diagnóstica, especificaciones técnicas y procedimientos de bio seguridad e higiene establecidos.
B20: =Capacidades!M614 | M20: =B20
B21: =Capacidades!M615 | M21: =B21
B22: =Capacidades!M616 | M22: =B22
B23: =Capacidades!M617 | M23: =B23
B24: =Capacidades!M618 | M24: =B24
B25: =Capacidades!M619 | M25: =B25
B26: =Capacidades!M620 | M26: =B26
B27: =Capacidades!M621 | M27: =B27
A28: =Capacidades!L622 -> UC3 C2 Ejecutar maquillajes de belleza tomando en cuenta la ocasión, criterios estéticos, así como la morfología facial y requerimientos del cliente. | B28: =Capacidades!M622 -> C2 I1 Organiza el area de trabajo, materiales, instrumentos siguiendo procedimientos del establecimiento y criterios de bioseguridad e higiene. | C28: • Organización del área de maquillaje ,selección de materiales , equipos, herramientas, productos cosmeticos.Manejo de presupuestos, Control de calidad • Normas de bioseguridad e higiene. | D28: =Organización_Modular!F73 -> MAQUILLAJES DE BELLEZA | E28: =Organización_Modular!G73 -> III | F28: =Organización_Modular!H73 -> 1 | G28: =Organización_Modular!I73 -> 3 | H28: =SUM(F28:G28) -> 4 | I28: =F28*16 -> 16 | J28: =G28*32 -> 96 | K28: =SUM(I28:J28) -> 112 | M28: =B28 -> C2 I1 Organiza el area de trabajo, materiales, instrumentos siguiendo procedimientos del establecimiento y criterios de bioseguridad e higiene.
B29: =Capacidades!M623 -> C2 I2 Realizar la preparación la piel para el maquillaje siguiendo procedimientos del establecimiento y criterios de bioseguridad e higiene. | C29: • Morfologia - Dermatologia Preparación de la piel Tècnicas de Limpieza | M29: =B29 -> C2 I2 Realizar la preparación la piel para el maquillaje siguiendo procedimientos del establecimiento y criterios de bioseguridad e higiene.
B30: =Capacidades!M624 -> C2 I3 Efectúa diversos tipos de maquillajes tomando en cuenta la ocasión, criterios estéticos, así como la morfología facial y requerimientos del cliente. | C30: • Teoría de claro y oscuro(circulo cromático). Técnicas de maquillaje de cejas ,rizado y pegado de pestañas. • Maquillaje - Tipos - Ocasiòn • Maquillaje de Dia - Noche. • Maquillaje quince años. • Maquillaje de novia, clásica, vanguardista, moderna,.Etc. | M30: =B30 -> C2 I3 Efectúa diversos tipos de maquillajes tomando en cuenta la ocasión, criterios estéticos, así como la morfología facial y requerimientos del cliente.
B31: =Capacidades!M625 -> C2 I4 Brinda recomendaciones post servicio según el tipo de maquillaje realizado. | C31: Productos cosméticos para el cuidado de la piel post maquillaje. | M31: =B31 -> C2 I4 Brinda recomendaciones post servicio según el tipo de maquillaje realizado.
B32: =Capacidades!M626 | M32: =B32
B33: =Capacidades!M627 | M33: =B33
B34: =Capacidades!M628 | M34: =B34
B35: =Capacidades!M629 | M35: =B35
B36: =Capacidades!M630 | M36: =B36
B37: =Capacidades!M631 | M37: =B37
A38: =Capacidades!L632 -> UC3 C3 Ejecutar depilaciones de la piel del rostro aplicando técnicas mecánicas y tomando en cuenta criterios estéticos y de bioseguridad e higiene. | B38: =Capacidades!M632 -> C3 I1 Identifica las caracteristicas de la piel del rostro aplicando criterios técnicos establecidos | C38: • Concepto de depilaciòn - tipos • Historia de la depilación, • Normas de Bioseguridad • Diagnostico dermatológico - Piel- caracteristicas- alteraciones | D38: =Organización_Modular!F74 -> DEPILACIÓN Y EPILACIÓN | E38: =Organización_Modular!G74 -> III | F38: =Organización_Modular!H74 -> 1 | G38: =Organización_Modular!I74 -> 2 | H38: =SUM(F38:G38) -> 3 | I38: =F38*16 -> 16 | J38: =G38*32 -> 64 | K38: =SUM(I38:J38) -> 80 | L38: Docente de Educación Técnica con especialidad en en Peluqueria y/o Cosmetología | M38: =B38 -> C3 I1 Identifica las caracteristicas de la piel del rostro aplicando criterios técnicos establecidos
B39: =Capacidades!M633 -> C3 I2 Realiza la prueba de sensibilización teniendo en cuenta el diagnóstico, servicio requerido por el cliente y criterios de bioseguridad e higiene. | C39: • Técnicas de sensibilidad • Técnicas de preparación de la piel( limpieza y Exfoliación) | M39: =B39 -> C3 I2 Realiza la prueba de sensibilización teniendo en cuenta el diagnóstico, servicio requerido por el cliente y criterios de bioseguridad e higiene.
B40: =Capacidades!M634 -> C3 I3 Realiza depilaciones aplicando técnicas mecanicas (cremas) y tomando en cuenta criterios estéticos y de bioseguridad e higiene. | C40: • Técnicas de depilación (navaja,perfilador y cremas) •.Recomendación post tratamiento. | M40: =B40 -> C3 I3 Realiza depilaciones aplicando técnicas mecanicas (cremas) y tomando en cuenta criterios estéticos y de bioseguridad e higiene.
B41: =Capacidades!M635 -> C3 I4 Efectua epilaciones aplicando técnicas mecánicas (hilo, pinza y cera) y tomando en cuenta criterios estéticos y de bioseguridad e higiene. | C41: • Técnicas de epilación mecanica(hilo, cera y pinza) •.Recomendación post tratamiento. | M41: =B41 -> C3 I4 Efectua epilaciones aplicando técnicas mecánicas (hilo, pinza y cera) y tomando en cuenta criterios estéticos y de bioseguridad e higiene.
B42: =Capacidades!M636 | M42: =B42
B43: =Capacidades!M637 | M43: =B43
B44: =Capacidades!M638 | M44: =B44
B45: =Capacidades!M639 | M45: =B45
B46: =Capacidades!M640 | M46: =B46
B47: =Capacidades!M641 | M47: =B47
A48: =Capacidades!L642 -> UC4 C1 Realizar la preparación de la piel y postizos faciales de acuerdo a las especificaciones tecnicas y requerimientos del cliente. UC4 C2 Ejecutar maquillajes de caracterización usando técnicas de posticería, según el personaje a interpretar, tomando en cuenta sus características. | B48: =Capacidades!M642 -> C1I1 Organiza el area de trabajo, materiales, instrumentos e insumos para la preparación de la piel siguiendo procedimientos del establecimiento y criterios de bioseguridad e higiene. | C48: • Organización del área de trabajo • Tecnología de los equipos, herramientas- tipos- caracteristicas- usos- mantenimiento preventivo • Manejo de presupuestos • Control de calidad | D48: =Organización_Modular!F75 -> MAQUILLAJES DE CARACTERIZACIÓN | E48: =Organización_Modular!G75 -> III | F48: =Organización_Modular!H75 -> 1 | G48: =Organización_Modular!I75 -> 2 | H48: =SUM(F48:G48) -> 3 | I48: =F48*16 -> 16 | J48: =G48*32 -> 64 | K48: =SUM(I48:J48) -> 80 | M48: =B48 -> C1I1 Organiza el area de trabajo, materiales, instrumentos e insumos para la preparación de la piel siguiendo procedimientos del establecimiento y criterios de bioseguridad e higiene.
B49: =Capacidades!M643 -> C1I2 Identifica el biotipo cutáneo teniendo en cuenta el diagnostico dermatológico y morfológico del cliente | C49: • Normas de bioseguridad e higiene. • Morfología facial -Piel - Tipos | M49: =B49 -> C1I2 Identifica el biotipo cutáneo teniendo en cuenta el diagnostico dermatológico y morfológico del cliente
B50: =Capacidades!M644 -> C1I3 Prepara la piel para el maquillaje de caracterización del cliente teniendo en cuenta la ficha diagnóstica, especificaciones técnicas y procedimientos de bio seguridad e higiene establecidos. | C50: • Historia del maquillaje de caracterización. • Tipos de maquillaje. • Técnicas de sensibilidad y condiciones de la piel ficha técnica. • Técnicas de preparación de la piel | M50: =B50 -> C1I3 Prepara la piel para el maquillaje de caracterización del cliente teniendo en cuenta la ficha diagnóstica, especificaciones técnicas y procedimientos de bio seguridad e higiene establecidos.
B51: =Capacidades!M645 -> C1I4 Identifica las caracteristicas del personaje a caracterizar tomando en cuenta los requerimientos del cliente. | C51: • Personajes- caracteristicas - ocasiòn • Diseño del personaje | M51: =B51 -> C1I4 Identifica las caracteristicas del personaje a caracterizar tomando en cuenta los requerimientos del cliente.
B52: =Capacidades!M646 -> C1I5 Prepara los postizos faciales o corporales en funcion al requerimiento del personaje y cliente. | C52: • Tecnologia de los materiales de caracterizaciòn - tipos. caracteristicas- usos - conservacion • Prótesis de personajes - tipos | M52: =B52 -> C1I5 Prepara los postizos faciales o corporales en funcion al requerimiento del personaje y cliente.
B53: =Capacidades!M647 -> C2I1 Efectua maquillajes de personificación según el personaje a interpretar, tomando en cuenta sus características, y normas de bioseguridad. | C53: • Teoria de Color • Caritas pintadas. • Tècnicas de maquillaje de caracterización Personajes • Colocaciòn de postizos (nariz, orejas, ojos, cejas, barbilla, etc) tecnicas de acabados del personaje | M53: =B53 -> C2I1 Efectua maquillajes de personificación según el personaje a interpretar, tomando en cuenta sus características, y normas de bioseguridad.
B54: =Capacidades!M648 -> C2I2 Brinda recomendaciones post servicio según el tipo de maquillaje realizado. | C54: • Técnicas de retoque y retiro de elementos de la caracterización según el protocolo e indicaciones del fabricante.,Recomendaciones post maquillaje. | M54: =B54 -> C2I2 Brinda recomendaciones post servicio según el tipo de maquillaje realizado.
B55: =Capacidades!M649 | M55: =B55
M56: =B56 -> 0
B57: =Capacidades!M651 | M57: =B57
A58: =Capacidades!L652 | B58: =Capacidades!M652 | D58: =Organización_Modular!F76 -> 0 | E58: =Organización_Modular!G76 -> 0 | F58: =Organización_Modular!H76 -> 0 | G58: =Organización_Modular!I76 -> 0 | H58: =SUM(F58:G58) -> 0 | I58: =F58*16 -> 0 | J58: =G58*32 -> 0 | K58: =SUM(I58:J58) -> 0 | M58: =B58
B59: =Capacidades!M653 | M59: =B59
B60: =Capacidades!M654 | M60: =B60
B61: =Capacidades!M655 | M61: =B61
B62: =Capacidades!M656 | M62: =B62
B63: =Capacidades!M657 | M63: =B63
B64: =Capacidades!M658 | M64: =B64
B65: =Capacidades!M659 | M65: =B65
B66: =Capacidades!M660 | M66: =B66
B67: =Capacidades!M661 | M67: =B67
A68: =Capacidades!L662 | B68: =Capacidades!M662 | D68: =Organización_Modular!F77 -> 0 | E68: =Organización_Modular!G77 -> 0 | F68: =Organización_Modular!H77 -> 0 | G68: =Organización_Modular!I77 -> 0 | H68: =SUM(F68:G68) -> 0 | I68: =F68*16 -> 0 | J68: =G68*32 -> 0 | K68: =SUM(I68:J68) -> 0 | M68: =B68
B69: =Capacidades!M663 | M69: =B69
B70: =Capacidades!M664 | M70: =B70
B71: =Capacidades!M665 | M71: =B71
B72: =Capacidades!M666 | M72: =B72
B73: =Capacidades!M667 | M73: =B73
B74: =Capacidades!M668 | M74: =B74
B75: =Capacidades!M669 | M75: =B75
B76: =Capacidades!M670 | M76: =B76
B77: =Capacidades!M671 | M77: =B77
A78: =Capacidades!L672 | B78: =Capacidades!M672 | D78: =Organización_Modular!F78 -> 0 | E78: =Organización_Modular!G78 -> 0 | F78: =Organización_Modular!H78 -> 0 | G78: =Organización_Modular!I78 -> 0 | H78: =SUM(F78:G78) -> 0 | I78: =F78*16 -> 0 | J78: =G78*32 -> 0 | K78: =SUM(I78:J78) -> 0 | M78: =B78
B79: =Capacidades!M673 | M79: =B79
B80: =Capacidades!M674 | M80: =B80
B81: =Capacidades!M675 | M81: =B81
B82: =Capacidades!M676 | M82: =B82
B83: =Capacidades!M677 | M83: =B83
B84: =Capacidades!M678 | M84: =B84
B85: =Capacidades!M679 | M85: =B85
B86: =Capacidades!M680 | M86: =B86
B87: =Capacidades!M681 | M87: =B87
A88: =Capacidades!L682 | B88: =Capacidades!M682 | D88: =Organización_Modular!F79 -> 0 | E88: =Organización_Modular!G79 -> 0 | F88: =Organización_Modular!H79 -> 0 | G88: =Organización_Modular!I79 -> 0 | H88: =SUM(F88:G88) -> 0 | I88: =F88*16 -> 0 | J88: =G88*32 -> 0 | K88: =SUM(I88:J88) -> 0 | M88: =B88
B89: =Capacidades!M683 | M89: =B89
B90: =Capacidades!M684 | M90: =B90
B91: =Capacidades!M685 | M91: =B91
B92: =Capacidades!M686 | M92: =B92
B93: =Capacidades!M687 | M93: =B93
B94: =Capacidades!M688 | M94: =B94
B95: =Capacidades!M689 | M95: =B95
B96: =Capacidades!M690 | M96: =B96
B97: =Capacidades!M691 | M97: =B97
A98: =Capacidades!L692 | B98: =Capacidades!M692 | D98: =Organización_Modular!F80 -> 0 | E98: =Organización_Modular!G80 -> 0 | F98: =Organización_Modular!H80 -> 0 | G98: =Organización_Modular!I80 -> 0 | H98: =SUM(F98:G98) -> 0 | I98: =F98*16 -> 0 | J98: =G98*32 -> 0 | K98: =SUM(I98:J98) -> 0 | M98: =B98
B99: =Capacidades!M693 | M99: =B99
B100: =Capacidades!M694 | M100: =B100
B101: =Capacidades!M695 | M101: =B101
B102: =Capacidades!M696 | M102: =B102
B103: =Capacidades!M697 | M103: =B103
B104: =Capacidades!M698 | M104: =B104
B105: =Capacidades!M699 | M105: =B105
B106: =Capacidades!M700 | M106: =B106
...

Sheet M4
A1: ='M3'!A1:L1 -> ORGANIZACIÓN DE LOS ELEMENTOS DEL MÓDULO
A3: DENOMINACIÓN DE LA INSTITUCIÓN | B3: =Perfil_Egreso!B3 -> CETPRO JUANJUI | F3: CÓDIGO MODULAR DEL INSTITUTO | I3: =Perfil_Egreso!E3 -> 533836
A5: SECTOR ECONÓMICO | B5: =Perfil_Egreso!B5 -> OTRAS ACTIVIDADES DE SERVICIO | C5: FAMILIA PRODUCTIVA | D5: =Perfil_Egreso!D5 -> SERVICIOS PERSONALES Y DE HOGARES | F5: ACTIVIDAD ECONÓMICA | I5: =Perfil_Egreso!B7 -> OTRAS ACTIVIDADES DE SERVICIOS PERSONALES
A7: =Perfil_Egreso!A11 -> DENOMINACIÓN DEL PROGRAMA DE ESTUDIOS | B7: =Perfil_Egreso!B11 -> ESTILISMO | C7: CÓDIGO * | D7: =Perfil_Egreso!E11 -> S3496-2-001 | F7: =Perfil_Egreso!A9 -> DENOMINACIÓN VARIANTE | I7: =Perfil_Egreso!B9 -> 0
A9: =Perfil_Egreso!A13 -> FORMACIÓN** | B9: =Perfil_Egreso!B13 -> 0 | C9: N°. HORAS: | D9: =Itinerario!W17 -> 2272 | F9: N° CRÉDITOS: | I9: =Itinerario!T17 -> 83
A11: =Perfil_Egreso!C13 -> MODALIDAD DEL SERVICIO EDUCATIVO *** | B11: =Perfil_Egreso!D13 -> PRESENCIAL | F11: =Perfil_Egreso!A15 -> CICLO FORMATIVO | I11: =Perfil_Egreso!B15 -> TÉCNICO
A13: UNIDAD DE COMPETENCIA DEL CATÁLOGO NACIONAL DE LA OFERTA FORMATIVA
A14: =Organización_Modular!C103 -> UC5 Ejecutar el servicio de estética en manos y pies teniendo en cuenta los requerimientos del cliente, los procedimientos del establecimiento, criterios técnicos, estéticos y de bioseguridad e higiene.
A15: DENOMINACIÓN DEL MÓDULO | B15: =Organización_Modular!A103 -> M4. MANICURE Y PEDICURE
A16: CAPACIDADES TÉCNICAS O ESPECÍFICAS | B16: INDICADORES DE LOGRO DE LA CAPACIDAD | C16: CONTENIDOS | D16: UNIDAD DIDÁCTICA | E16: Periodo | F16: CRÉDITOS | H16: CRÉDITOS | I16: HORAS | K16: HORAS | L16: PERFIL DOCENTE | M16: Filtrar
F17: Teórico | G17: Práctica | I17: Teórico | J17: Práctica
A18: =Capacidades!L913 -> UC5 C1 Ejecutar procedimientos de limpieza, desinfección y preparación de manos y pies teniendo en cuenta los requerimientos del cliente, los procedimientos del establecimiento, criterios técnicos y normas de bioseguridad e higiene. | B18: =Capacidades!M913 -> C1I1 Organiza el area de trabajo, equipos, instrumentos y materiales, considerando criterios técnicos y normas de bioseguridad e higiene. | C18: • Organizacion del taller -señalizacion- normas de seguridad e higiene •Tecnologia de los equipos de peluqueria- tipos- Caracteristicas - usos. mantenimiento preventivo- Normas de Bioseguridad • Tecnología de los materiales - tipos- marcas- caractetristicas- conservaciòn. | D18: =Organización_Modular!F103 -> PREPARACION DE MANOS Y PIES | E18: =Organización_Modular!G103 -> IV | F18: =Organización_Modular!H103 -> 1 | G18: =Organización_Modular!I103 -> 3 | H18: =SUM(F18:G18) -> 4 | I18: =F18*16 -> 16 | J18: =G18*32 -> 96 | K18: =SUM(I18:J18) -> 112 | L18: Docente de Educación Técnica con especialidad en en Peluqueria y/o Cosmetología | M18: =B18 -> C1I1 Organiza el area de trabajo, equipos, instrumentos y materiales, considerando criterios técnicos y normas de bioseguridad e higiene.
B19: =Capacidades!M914 -> C1I2 Diagnostica el estado de la piel, manos y pies de acuerdo a las especificaciones de la ficha diagnóstica, y aplicando normas de bioseguridad e higiene. | C19: • Definiciòn de la manicure y pedicure • Anatomía de las uñas manos y pies •Morfologia de mano y uñas - Alteraciones • Morfologia de los Pies y Uñas- alteracionesFicha técnica | M19: =B19 -> C1I2 Diagnostica el estado de la piel, manos y pies de acuerdo a las especificaciones de la ficha diagnóstica, y aplicando normas de bioseguridad e higiene.
B20: =Capacidades!M915 -> C1I3 Realiza la limpieza, desinfección y esterilización de equipos e instrumentos aplicando procedimientos técnicos, criterios estéticos, y normas de bioseguridad e higiene. | C20: • Equipos - Tècnicas de Limpieza- desinfección - estirilización normas de Bioseguridad | M20: =B20 -> C1I3 Realiza la limpieza, desinfección y esterilización de equipos e instrumentos aplicando procedimientos técnicos, criterios estéticos, y normas de bioseguridad e higiene.
B21: =Capacidades!M916 -> C1I4 Realiza la limpieza de manos aplicando diversas técnicas, criterios estéticos, y normas de bioseguridad e higiene. | C21: • concepto - Limpieza de las manos - procedimientos • Estirilizacion - normas de bioseguridad Reflexologia de manos | M21: =B21 -> C1I4 Realiza la limpieza de manos aplicando diversas técnicas, criterios estéticos, y normas de bioseguridad e higiene.
B22: =Capacidades!M917 | M22: =B22
B23: =Capacidades!M918 | M23: =B23
B24: =Capacidades!M919 | M24: =B24
B25: =Capacidades!M920 | M25: =B25
B26: =Capacidades!M921 | M26: =B26
B27: =Capacidades!M922 | M27: =B27
A28: =Capacidades!L923 -> UC5 C2 Realizar técnicas de manicure teniendo en cuenta los requerimientos del cliente, criterios técnicos, estéticos y de bioseguridad e higiene. | B28: =Capacidades!M923 -> C2 I1 Efectua manicure considerando criterios estéticos y normas de bioseguridad e higiene y de acuerdo a los requerimientos del cliente. | C28: • Tecnología de materiales, tipos- marcas- usos- conservación • Teoría del color. • Esmaltado básico de uñas. • Trazos lineales, circulares y formas. Diseño basico de uñas ( Francesa) acabados y recomendaciones | D28: =Organización_Modular!F104 -> MANICURE | E28: =Organización_Modular!G104 -> IV | F28: =Organización_Modular!H104 -> 1 | G28: =Organización_Modular!I104 -> 3 | H28: =SUM(F28:G28) -> 4 | I28: =F28*16 -> 16 | J28: =G28*32 -> 96 | K28: =SUM(I28:J28) -> 112 | L28: Docente de Educación Técnica con especialidad en en Peluqueria y/o Cosmetología | M28: =B28 -> C2 I1 Efectua manicure considerando criterios estéticos y normas de bioseguridad e higiene y de acuerdo a los requerimientos del cliente.
B29: =Capacidades!M924 -> C2 I2 Aplica técnicas de diseño, arte y decoración de uñas considerando criterios estéticos y normas de bioseguridad e higiene y de acuerdo a los requerimientos del cliente. | C29: • Técnica de Diseños - tipos • Diseños florales • Diseños con accesorios. • Diseños para ocasiones especiales. • Diseños artísticos. Control de calidad y productos de acabados - recomendaciones | M29: =B29 -> C2 I2 Aplica técnicas de diseño, arte y decoración de uñas considerando criterios estéticos y normas de bioseguridad e higiene y de acuerdo a los requerimientos del cliente.
B30: =Capacidades!M925 -> C2 I3 Aplica extensiones de uñas considerando criterios estéticos y normas de bioseguridad e higiene y de acuerdo a los requerimientos del cliente. | C30: • Técnica de aplicación de extensiones • Técnicas de aplicación de postisos • Uñas gel • Uñas acrilícas • Uñas acrigel • Uñas esculpidas • Uñas baby bumer • Uñas dual system Control de calidad y productos de acabados - recomendaciones | M30: =B30 -> C2 I3 Aplica extensiones de uñas considerando criterios estéticos y normas de bioseguridad e higiene y de acuerdo a los requerimientos del cliente.
B31: =Capacidades!M926 | M31: =B31
B32: =Capacidades!M927 | M32: =B32
B33: =Capacidades!M928 | M33: =B33
B34: =Capacidades!M929 | M34: =B34
B35: =Capacidades!M930 | M35: =B35
B36: =Capacidades!M931 | M36: =B36
B37: =Capacidades!M932 | M37: =B37
A38: =Capacidades!L933 -> UC5 C3 Ejecutar técnicas de pedicure teniendo en cuenta los requerimientos del cliente, criterios técnicos, estéticos y de bioseguridad e higiene. | B38: =Capacidades!M933 -> C3 I1 Realiza la limpieza de pies aplicando diversas técnicas, criterios estéticos, y normas de bioseguridad e higiene. | C38: • Esmaltado de uñas • Trazos básicos • Diseño artistícos | D38: =Organización_Modular!F105 -> PEDICURE | E38: =Organización_Modular!G105 -> IV | F38: =Organización_Modular!H105 -> 1 | G38: =Organización_Modular!I105 -> 3 | H38: =SUM(F38:G38) -> 4 | I38: =F38*16 -> 16 | J38: =G38*32 -> 96 | K38: =SUM(I38:J38) -> 112 | M38: =B38 -> C3 I1 Realiza la limpieza de pies aplicando diversas técnicas, criterios estéticos, y normas de bioseguridad e higiene.
B39: =Capacidades!M934 -> C3 I2 Realiza técnicas de pedicure, diseño y decoración de uñas aplicando criterios estéticos y normas de bioseguridad e higiene y de acuerdo a los requerimientos del cliente. | C39: • Técnicas de postizos en pedicure • Técnicas de extensiones en pedicure Procedimientos control de calidad y productos de acabados - recomendaciones | M39: =B39 -> C3 I2 Realiza técnicas de pedicure, diseño y decoración de uñas aplicando criterios estéticos y normas de bioseguridad e higiene y de acuerdo a los requerimientos del cliente.
B40: =Capacidades!M935 | M40: =B40
B41: =Capacidades!M936 | M41: =B41
B42: =Capacidades!M937 | M42: =B42
B43: =Capacidades!M938 | M43: =B43
B44: =Capacidades!M939 | M44: =B44
B45: =Capacidades!M940 | M45: =B45
B46: =Capacidades!M941 | M46: =B46
B47: =Capacidades!M942 | M47: =B47
A48: =Capacidades!L943 | B48: =Capacidades!M943 | D48: =Organización_Modular!F106 -> 0 | E48: =Organización_Modular!G106 -> 0 | F48: =Organización_Modular!H106 -> 0 | G48: =Organización_Modular!I106 -> 0 | H48: =SUM(F48:G48) -> 0 | I48: =F48*16 -> 0 | J48: =G48*32 -> 0 | K48: =SUM(I48:J48) -> 0 | M48: =B48
B49: =Capacidades!M944 | M49: =B49
B50: =Capacidades!M945 | M50: =B50
B51: =Capacidades!M946 | M51: =B51
B52: =Capacidades!M947 | M52: =B52
B53: =Capacidades!M948 | M53: =B53
B54: =Capacidades!M949 | M54: =B54
B55: =Capacidades!M950 | M55: =B55
B56: =Capacidades!M951 | M56: =B56
B57: =Capacidades!M952 | M57: =B57
A58: =Capacidades!L953 | B58: =Capacidades!M953 | D58: =Organización_Modular!F107 -> 0 | E58: =Organización_Modular!G107 -> 0 | F58: =Organización_Modular!H107 -> 0 | G58: =Organización_Modular!I107 -> 0 | H58: =SUM(F58:G58) -> 0 | I58: =F58*16 -> 0 | J58: =G58*32 -> 0 | K58: =SUM(I58:J58) -> 0 | M58: =B58
B59: =Capacidades!M954 | M59: =B59
B60: =Capacidades!M955 | M60: =B60
B61: =Capacidades!M956 | M61: =B61
B62: =Capacidades!M957 | M62: =B62
B63: =Capacidades!M958 | M63: =B63
B64: =Capacidades!M959 | M64: =B64
B65: =Capacidades!M960 | M65: =B65
B66: =Capacidades!M961 | M66: =B66
B67: =Capacidades!M962 | M67: =B67
A68: =Capacidades!L963 | B68: =Capacidades!M963 | D68: =Organización_Modular!F108 -> 0 | E68: =Organización_Modular!G108 -> 0 | F68: =Organización_Modular!H108 -> 0 | G68: =Organización_Modular!I108 -> 0 | H68: =SUM(F68:G68) -> 0 | I68: =F68*16 -> 0 | J68: =G68*32 -> 0 | K68: =SUM(I68:J68) -> 0 | M68: =B68
B69: =Capacidades!M964 | M69: =B69
B70: =Capacidades!M965 | M70: =B70
B71: =Capacidades!M966 | M71: =B71
B72: =Capacidades!M967 | M72: =B72
B73: =Capacidades!M968 | M73: =B73
B74: =Capacidades!M969 | M74: =B74
B75: =Capacidades!M970 | M75: =B75
B76: =Capacidades!M971 | M76: =B76
B77: =Capacidades!M972 | M77: =B77
A78: =Capacidades!L973 | B78: =Capacidades!M973 | D78: =Organización_Modular!F109 -> 0 | E78: =Organización_Modular!G109 -> 0 | F78: =Organización_Modular!H109 -> 0 | G78: =Organización_Modular!I109 -> 0 | H78: =SUM(F78:G78) -> 0 | I78: =F78*16 -> 0 | J78: =G78*32 -> 0 | K78: =SUM(I78:J78) -> 0 | M78: =B78
B79: =Capacidades!M974 | M79: =B79
B80: =Capacidades!M975 | M80: =B80
B81: =Capacidades!M976 | M81: =B81
B82: =Capacidades!M977 | M82: =B82
B83: =Capacidades!M978 | M83: =B83
B84: =Capacidades!M979 | M84: =B84
B85: =Capacidades!M980 | M85: =B85
B86: =Capacidades!M981 | M86: =B86
B87: =Capacidades!M982 | M87: =B87
A88: =Capacidades!L983 | B88: =Capacidades!M983 | D88: =Organización_Modular!F110 -> 0 | E88: =Organización_Modular!G110 -> 0 | F88: =Organización_Modular!H110 -> 0 | G88: =Organización_Modular!I110 -> 0 | H88: =SUM(F88:G88) -> 0 | I88: =F88*16 -> 0 | J88: =G88*32 -> 0 | K88: =SUM(I88:J88) -> 0 | M88: =B88
B89: =Capacidades!M984 | M89: =B89
B90: =Capacidades!M985 | M90: =B90
B91: =Capacidades!M986 | M91: =B91
B92: =Capacidades!M987 | M92: =B92
B93: =Capacidades!M988 | M93: =B93
B94: =Capacidades!M989 | M94: =B94
B95: =Capacidades!M990 | M95: =B95
B96: =Capacidades!M991 | M96: =B96
B97: =Capacidades!M992 | M97: =B97
A98: =Capacidades!L993 | B98: =Capacidades!M993 | D98: =Organización_Modular!F111 -> 0 | E98: =Organización_Modular!G111 -> 0 | F98: =Organización_Modular!H111 -> 0 | G98: =Organización_Modular!I111 -> 0 | H98: =SUM(F98:G98) -> 0 | I98: =F98*16 -> 0 | J98: =G98*32 -> 0 | K98: =SUM(I98:J98) -> 0 | M98: =B98
B99: =Capacidades!M994 | M99: =B99
B100: =Capacidades!M995 | M100: =B100
B101: =Capacidades!M996 | M101: =B101
B102: =Capacidades!M997 | M102: =B102
B103: =Capacidades!M998 | M103: =B103
B104: =Capacidades!M999 | M104: =B104
B105: =Capacidades!M1000 | M105: =B105
B106: =Capacidades!M1001 | M106: =B106
...

Sheet M5
A1: ='M4'!A1:L1 -> ORGANIZACIÓN DE LOS ELEMENTOS DEL MÓDULO
A3: DENOMINACIÓN DE LA INSTITUCIÓN | B3: =Perfil_Egreso!B3 -> CETPRO JUANJUI | F3: CÓDIGO MODULAR DEL INSTITUTO | I3: =Perfil_Egreso!E3 -> 533836
A5: SECTOR ECONÓMICO | B5: =Perfil_Egreso!B5 -> OTRAS ACTIVIDADES DE SERVICIO | C5: FAMILIA PRODUCTIVA | D5: =Perfil_Egreso!D5 -> SERVICIOS PERSONALES Y DE HOGARES | F5: ACTIVIDAD ECONÓMICA | I5: =Perfil_Egreso!B7 -> OTRAS ACTIVIDADES DE SERVICIOS PERSONALES
A7: =Perfil_Egreso!A11 -> DENOMINACIÓN DEL PROGRAMA DE ESTUDIOS | B7: =Perfil_Egreso!B11 -> ESTILISMO | C7: CÓDIGO * | D7: =Perfil_Egreso!E11 -> S3496-2-001 | F7: =Perfil_Egreso!A9 -> DENOMINACIÓN VARIANTE | I7: =Perfil_Egreso!B9 -> 0
A9: =Perfil_Egreso!A13 -> FORMACIÓN** | B9: =Perfil_Egreso!B13 -> 0 | C9: N°. HORAS: | D9: =Itinerario!W17 -> 2272 | F9: N° CRÉDITOS: | I9: =Itinerario!T17 -> 83
A11: =Perfil_Egreso!C13 -> MODALIDAD DEL SERVICIO EDUCATIVO *** | B11: =Perfil_Egreso!D13 -> PRESENCIAL | F11: =Perfil_Egreso!A15 -> CICLO FORMATIVO | I11: =Perfil_Egreso!B15 -> TÉCNICO
A13: UNIDAD DE COMPETENCIA DEL CATÁLOGO NACIONAL DE LA OFERTA FORMATIVA
A14: =Organización_Modular!C134 -> 0
A15: DENOMINACIÓN DEL MÓDULO | B15: =Organización_Modular!A134 -> 0
A16: CAPACIDADES TÉCNICAS O ESPECÍFICAS | B16: INDICADORES DE LOGRO DE LA CAPACIDAD | C16: CONTENIDOS | D16: UNIDAD DIDÁCTICA | E16: Periodo | F16: CRÉDITOS | H16: CRÉDITOS | I16: HORAS | K16: HORAS | L16: PERFIL DOCENTE | M16: Filtrar
F17: Teórico | G17: Práctica | I17: Teórico | J17: Práctica
A18: =Capacidades!L1214 | B18: =Capacidades!M1214 | D18: =Organización_Modular!F134 -> 0 | E18: =Organización_Modular!G134 -> 0 | F18: =Organización_Modular!H134 -> 0 | G18: =Organización_Modular!I134 -> 0 | H18: =SUM(F18:G18) -> 0 | I18: =F18*16 -> 0 | J18: =G18*32 -> 0 | K18: =SUM(I18:J18) -> 0 | M18: =B18
B19: =Capacidades!M1215 | M19: =B19
B20: =Capacidades!M1216 | M20: =B20
B21: =Capacidades!M1217 | M21: =B21
B22: =Capacidades!M1218 | M22: =B22
B23: =Capacidades!M1219 | M23: =B23
B24: =Capacidades!M1220 | M24: =B24
B25: =Capacidades!M1221 | M25: =B25
B26: =Capacidades!M1222 | M26: =B26
B27: =Capacidades!M1223 | M27: =B27
A28: =Capacidades!L1224 | B28: =Capacidades!M1224 | D28: =Organización_Modular!F135 -> 0 | E28: =Organización_Modular!G135 -> 0 | F28: =Organización_Modular!H135 -> 0 | G28: =Organización_Modular!I135 -> 0 | H28: =SUM(F28:G28) -> 0 | I28: =F28*16 -> 0 | J28: =G28*32 -> 0 | K28: =SUM(I28:J28) -> 0 | M28: =B28
B29: =Capacidades!M1225 | M29: =B29
B30: =Capacidades!M1226 | M30: =B30
B31: =Capacidades!M1227 | M31: =B31
B32: =Capacidades!M1228 | M32: =B32
B33: =Capacidades!M1229 | M33: =B33
B34: =Capacidades!M1230 | M34: =B34
B35: =Capacidades!M1231 | M35: =B35
B36: =Capacidades!M1232 | M36: =B36
B37: =Capacidades!M1233 | M37: =B37
A38: =Capacidades!L1234 | B38: =Capacidades!M1234 | D38: =Organización_Modular!F136 -> 0 | E38: =Organización_Modular!G136 -> 0 | F38: =Organización_Modular!H136 -> 0 | G38: =Organización_Modular!I136 -> 0 | H38: =SUM(F38:G38) -> 0 | I38: =F38*16 -> 0 | J38: =G38*32 -> 0 | K38: =SUM(I38:J38) -> 0 | M38: =B38
B39: =Capacidades!M1235 | M39: =B39
B40: =Capacidades!M1236 | M40: =B40
B41: =Capacidades!M1237 | M41: =B41
B42: =Capacidades!M1238 | M42: =B42
B43: =Capacidades!M1239 | M43: =B43
B44: =Capacidades!M1240 | M44: =B44
B45: =Capacidades!M1241 | M45: =B45
B46: =Capacidades!M1242 | M46: =B46
B47: =Capacidades!M1243 | M47: =B47
A48: =Capacidades!L1244 | B48: =Capacidades!M1244 | D48: =Organización_Modular!F137 -> 0 | E48: =Organización_Modular!G137 -> 0 | F48: =Organización_Modular!H137 -> 0 | G48: =Organización_Modular!I137 -> 0 | H48: =SUM(F48:G48) -> 0 | I48: =F48*16 -> 0 | J48: =G48*32 -> 0 | K48: =SUM(I48:J48) -> 0 | M48: =B48
B49: =Capacidades!M1245 | M49: =B49
B50: =Capacidades!M1246 | M50: =B50
B51: =Capacidades!M1247 | M51: =B51
B52: =Capacidades!M1248 | M52: =B52
B53: =Capacidades!M1249 | M53: =B53
B54: =Capacidades!M1250 | M54: =B54
B55: =Capacidades!M1251 | M55: =B55
B56: =Capacidades!M1252 | M56: =B56
B57: =Capacidades!M1253 | M57: =B57
A58: =Capacidades!L1254 | B58: =Capacidades!M1254 | D58: =Organización_Modular!F138 -> 0 | E58: =Organización_Modular!G138 -> 0 | F58: =Organización_Modular!H138 -> 0 | G58: =Organización_Modular!I138 -> 0 | H58: =SUM(F58:G58) -> 0 | I58: =F58*16 -> 0 | J58: =G58*32 -> 0 | K58: =SUM(I58:J58) -> 0 | M58: =B58
B59: =Capacidades!M1255 | M59: =B59
B60: =Capacidades!M1256 | M60: =B60
B61: =Capacidades!M1257 | M61: =B61
B62: =Capacidades!M1258 | M62: =B62
B63: =Capacidades!M1259 | M63: =B63
B64: =Capacidades!M1260 | M64: =B64
B65: =Capacidades!M1261 | M65: =B65
B66: =Capacidades!M1262 | M66: =B66
B67: =Capacidades!M1263 | M67: =B67
A68: =Capacidades!L1264 | B68: =Capacidades!M1264 | D68: =Organización_Modular!F139 -> 0 | E68: =Organización_Modular!G139 -> 0 | F68: =Organización_Modular!H139 -> 0 | G68: =Organización_Modular!I139 -> 0 | H68: =SUM(F68:G68) -> 0 | I68: =F68*16 -> 0 | J68: =G68*32 -> 0 | K68: =SUM(I68:J68) -> 0 | M68: =B68
B69: =Capacidades!M1265 | M69: =B69
B70: =Capacidades!M1266 | M70: =B70
B71: =Capacidades!M1267 | M71: =B71
B72: =Capacidades!M1268 | M72: =B72
B73: =Capacidades!M1269 | M73: =B73
B74: =Capacidades!M1270 | M74: =B74
B75: =Capacidades!M1271 | M75: =B75
B76: =Capacidades!M1272 | M76: =B76
B77: =Capacidades!M1273 | M77: =B77
A78: =Capacidades!L1274 | B78: =Capacidades!M1274 | D78: =Organización_Modular!F140 -> 0 | E78: =Organización_Modular!G140 -> 0 | F78: =Organización_Modular!H140 -> 0 | G78: =Organización_Modular!I140 -> 0 | H78: =SUM(F78:G78) -> 0 | I78: =F78*16 -> 0 | J78: =G78*32 -> 0 | K78: =SUM(I78:J78) -> 0 | M78: =B78
B79: =Capacidades!M1275 | M79: =B79
B80: =Capacidades!M1276 | M80: =B80
B81: =Capacidades!M1277 | M81: =B81
B82: =Capacidades!M1278 | M82: =B82
B83: =Capacidades!M1279 | M83: =B83
B84: =Capacidades!M1280 | M84: =B84
B85: =Capacidades!M1281 | M85: =B85
B86: =Capacidades!M1282 | M86: =B86
B87: =Capacidades!M1283 | M87: =B87
A88: =Capacidades!L1284 | B88: =Capacidades!M1284 | D88: =Organización_Modular!F141 -> 0 | E88: =Organización_Modular!G141 -> 0 | F88: =Organización_Modular!H141 -> 0 | G88: =Organización_Modular!I141 -> 0 | H88: =SUM(F88:G88) -> 0 | I88: =F88*16 -> 0 | J88: =G88*32 -> 0 | K88: =SUM(I88:J88) -> 0 | M88: =B88
B89: =Capacidades!M1285 | M89: =B89
B90: =Capacidades!M1286 | M90: =B90
B91: =Capacidades!M1287 | M91: =B91
B92: =Capacidades!M1288 | M92: =B92
B93: =Capacidades!M1289 | M93: =B93
B94: =Capacidades!M1290 | M94: =B94
B95: =Capacidades!M1291 | M95: =B95
B96: =Capacidades!M1292 | M96: =B96
B97: =Capacidades!M1293 | M97: =B97
A98: =Capacidades!L1294 | B98: =Capacidades!M1294 | D98: =Organización_Modular!F142 -> 0 | E98: =Organización_Modular!G142 -> 0 | F98: =Organización_Modular!H142 -> 0 | G98: =Organización_Modular!I142 -> 0 | H98: =SUM(F98:G98) -> 0 | I98: =F98*16 -> 0 | J98: =G98*32 -> 0 | K98: =SUM(I98:J98) -> 0 | M98: =B98
B99: =Capacidades!M1295 | M99: =B99
B100: =Capacidades!M1296 | M100: =B100
B101: =Capacidades!M1297 | M101: =B101
B102: =Capacidades!M1298 | M102: =B102
B103: =Capacidades!M1299 | M103: =B103
B104: =Capacidades!M1300 | M104: =B104
B105: =Capacidades!M1301 | M105: =B105
B106: =Capacidades!M1302 | M106: =B106
...

Sheet M6
A1: ='M5'!A1:L1 -> ORGANIZACIÓN DE LOS ELEMENTOS DEL MÓDULO
A3: DENOMINACIÓN DE LA INSTITUCIÓN | B3: =Perfil_Egreso!B3 -> CETPRO JUANJUI | F3: CÓDIGO MODULAR DEL INSTITUTO | I3: =Perfil_Egreso!E3 -> 533836
A5: SECTOR ECONÓMICO | B5: =Perfil_Egreso!B5 -> OTRAS ACTIVIDADES DE SERVICIO | C5: FAMILIA PRODUCTIVA | D5: =Perfil_Egreso!D5 -> SERVICIOS PERSONALES Y DE HOGARES | F5: ACTIVIDAD ECONÓMICA | I5: =Perfil_Egreso!B7 -> OTRAS ACTIVIDADES DE SERVICIOS PERSONALES
A7: =Perfil_Egreso!A11 -> DENOMINACIÓN DEL PROGRAMA DE ESTUDIOS | B7: =Perfil_Egreso!B11 -> ESTILISMO | C7: CÓDIGO * | D7: =Perfil_Egreso!E11 -> S3496-2-001 | F7: =Perfil_Egreso!A9 -> DENOMINACIÓN VARIANTE | I7: =Perfil_Egreso!B9 -> 0
A9: =Perfil_Egreso!A13 -> FORMACIÓN** | B9: =Perfil_Egreso!B13 -> 0 | C9: N°. HORAS: | D9: =Itinerario!W17 -> 2272 | F9: N° CRÉDITOS: | I9: =Itinerario!T17 -> 83
A11: =Perfil_Egreso!C13 -> MODALIDAD DEL SERVICIO EDUCATIVO *** | B11: =Perfil_Egreso!D13 -> PRESENCIAL | F11: =Perfil_Egreso!A15 -> CICLO FORMATIVO | I11: =Perfil_Egreso!B15 -> TÉCNICO
A13: UNIDAD DE COMPETENCIA DEL CATÁLOGO NACIONAL DE LA OFERTA FORMATIVA
A14: =Organización_Modular!C134 -> 0
A15: DENOMINACIÓN DEL MÓDULO | B15: =Organización_Modular!A165 -> 0
A16: CAPACIDADES TÉCNICAS O ESPECÍFICAS | B16: INDICADORES DE LOGRO DE LA CAPACIDAD | C16: CONTENIDOS | D16: UNIDAD DIDÁCTICA | E16: Periodo | F16: CRÉDITOS | H16: CRÉDITOS | I16: HORAS | K16: HORAS | L16: PERFIL DOCENTE | M16: Filtrar
F17: Teórico | G17: Práctica | I17: Teórico | J17: Práctica
A18: =Capacidades!L1515 | B18: =Capacidades!M1515 | D18: =Organización_Modular!F165 -> 0 | E18: =Organización_Modular!G165 -> 0 | F18: =Organización_Modular!H165 -> 0 | G18: =Organización_Modular!I165 -> 0 | H18: =SUM(F18:G18) -> 0 | I18: =F18*16 -> 0 | J18: =G18*32 -> 0 | K18: =SUM(I18:J18) -> 0 | M18: =B18
B19: =Capacidades!M1516 | M19: =B19
B20: =Capacidades!M1517 | M20: =B20
B21: =Capacidades!M1518 | M21: =B21
B22: =Capacidades!M1519 | M22: =B22
B23: =Capacidades!M1520 | M23: =B23
B24: =Capacidades!M1521 | M24: =B24
B25: =Capacidades!M1522 | M25: =B25
B26: =Capacidades!M1523 | M26: =B26
B27: =Capacidades!M1524 | M27: =B27
A28: =Capacidades!L1525 | B28: =Capacidades!M1525 | D28: =Organización_Modular!F166 -> 0 | E28: =Organización_Modular!G166 -> 0 | F28: =Organización_Modular!H166 -> 0 | G28: =Organización_Modular!I166 -> 0 | H28: =SUM(F28:G28) -> 0 | I28: =F28*16 -> 0 | J28: =G28*32 -> 0 | K28: =SUM(I28:J28) -> 0 | M28: =B28
B29: =Capacidades!M1526 | M29: =B29
B30: =Capacidades!M1527 | M30: =B30
B31: =Capacidades!M1528 | M31: =B31
B32: =Capacidades!M1529 | M32: =B32
B33: =Capacidades!M1530 | M33: =B33
B34: =Capacidades!M1531 | M34: =B34
B35: =Capacidades!M1532 | M35: =B35
B36: =Capacidades!M1533 | M36: =B36
B37: =Capacidades!M1534 | M37: =B37
A38: =Capacidades!L1535 | B38: =Capacidades!M1535 | D38: =Organización_Modular!F167 -> 0 | E38: =Organización_Modular!G167 -> 0 | F38: =Organización_Modular!H167 -> 0 | G38: =Organización_Modular!I167 -> 0 | H38: =SUM(F38:G38) -> 0 | I38: =F38*16 -> 0 | J38: =G38*32 -> 0 | K38: =SUM(I38:J38) -> 0 | M38: =B38
B39: =Capacidades!M1536 | M39: =B39
B40: =Capacidades!M1537 | M40: =B40
B41: =Capacidades!M1538 | M41: =B41
B42: =Capacidades!M1539 | M42: =B42
B43: =Capacidades!M1540 | M43: =B43
B44: =Capacidades!M1541 | M44: =B44
B45: =Capacidades!M1542 | M45: =B45
B46: =Capacidades!M1543 | M46: =B46
B47: =Capacidades!M1544 | M47: =B47
A48: =Capacidades!L1545 | B48: =Capacidades!M1545 | D48: =Organización_Modular!F168 -> 0 | E48: =Organización_Modular!G168 -> 0 | F48: =Organización_Modular!H168 -> 0 | G48: =Organización_Modular!I168 -> 0 | H48: =SUM(F48:G48) -> 0 | I48: =F48*16 -> 0 | J48: =G48*32 -> 0 | K48: =SUM(I48:J48) -> 0 | M48: =B48
B49: =Capacidades!M1546 | M49: =B49
B50: =Capacidades!M1547 | M50: =B50
B51: =Capacidades!M1548 | M51: =B51
B52: =Capacidades!M1549 | M52: =B52
B53: =Capacidades!M1550 | M53: =B53
B54: =Capacidades!M1551 | M54: =B54
B55: =Capacidades!M1552 | M55: =B55
B56: =Capacidades!M1553 | M56: =B56
B57: =Capacidades!M1554 | M57: =B57
A58: =Capacidades!L1555 | B58: =Capacidades!M1555 | D58: =Organización_Modular!F169 -> 0 | E58: =Organización_Modular!G169 -> 0 | F58: =Organización_Modular!H169 -> 0 | G58: =Organización_Modular!I169 -> 0 | H58: =SUM(F58:G58) -> 0 | I58: =F58*16 -> 0 | J58: =G58*32 -> 0 | K58: =SUM(I58:J58) -> 0 | M58: =B58
B59: =Capacidades!M1556 | M59: =B59
B60: =Capacidades!M1557 | M60: =B60
B61: =Capacidades!M1558 | M61: =B61
B62: =Capacidades!M1559 | M62: =B62
B63: =Capacidades!M1560 | M63: =B63
B64: =Capacidades!M1561 | M64: =B64
B65: =Capacidades!M1562 | M65: =B65
B66: =Capacidades!M1563 | M66: =B66
B67: =Capacidades!M1564 | M67: =B67
A68: =Capacidades!L1565 | B68: =Capacidades!M1565 | D68: =Organización_Modular!F170 -> 0 | E68: =Organización_Modular!G170 -> 0 | F68: =Organización_Modular!H170 -> 0 | G68: =Organización_Modular!I170 -> 0 | H68: =SUM(F68:G68) -> 0 | I68: =F68*16 -> 0 | J68: =G68*32 -> 0 | K68: =SUM(I68:J68) -> 0 | M68: =B68
B69: =Capacidades!M1566 | M69: =B69
B70: =Capacidades!M1567 | M70: =B70
B71: =Capacidades!M1568 | M71: =B71
B72: =Capacidades!M1569 | M72: =B72
B73: =Capacidades!M1570 | M73: =B73
B74: =Capacidades!M1571 | M74: =B74
B75: =Capacidades!M1572 | M75: =B75
B76: =Capacidades!M1573 | M76: =B76
B77: =Capacidades!M1574 | M77: =B77
A78: =Capacidades!L1575 | B78: =Capacidades!M1575 | D78: =Organización_Modular!F171 -> 0 | E78: =Organización_Modular!G171 -> 0 | F78: =Organización_Modular!H171 -> 0 | G78: =Organización_Modular!I171 -> 0 | H78: =SUM(F78:G78) -> 0 | I78: =F78*16 -> 0 | J78: =G78*32 -> 0 | K78: =SUM(I78:J78) -> 0 | M78: =B78
B79: =Capacidades!M1576 | M79: =B79
B80: =Capacidades!M1577 | M80: =B80
B81: =Capacidades!M1578 | M81: =B81
B82: =Capacidades!M1579 | M82: =B82
B83: =Capacidades!M1580 | M83: =B83
B84: =Capacidades!M1581 | M84: =B84
B85: =Capacidades!M1582 | M85: =B85
B86: =Capacidades!M1583 | M86: =B86
B87: =Capacidades!M1584 | M87: =B87
A88: =Capacidades!L1585 | B88: =Capacidades!M1585 | D88: =Organización_Modular!F172 -> 0 | E88: =Organización_Modular!G172 -> 0 | F88: =Organización_Modular!H172 -> 0 | G88: =Organización_Modular!I172 -> 0 | H88: =SUM(F88:G88) -> 0 | I88: =F88*16 -> 0 | J88: =G88*32 -> 0 | K88: =SUM(I88:J88) -> 0 | M88: =B88
B89: =Capacidades!M1586 | M89: =B89
B90: =Capacidades!M1587 | M90: =B90
B91: =Capacidades!M1588 | M91: =B91
B92: =Capacidades!M1589 | M92: =B92
B93: =Capacidades!M1590 | M93: =B93
B94: =Capacidades!M1591 | M94: =B94
B95: =Capacidades!M1592 | M95: =B95
B96: =Capacidades!M1593 | M96: =B96
B97: =Capacidades!M1594 | M97: =B97
A98: =Capacidades!L1595 | B98: =Capacidades!M1595 | D98: =Organización_Modular!F173 -> 0 | E98: =Organización_Modular!G173 -> 0 | F98: =Organización_Modular!H173 -> 0 | G98: =Organización_Modular!I173 -> 0 | H98: =SUM(F98:G98) -> 0 | I98: =F98*16 -> 0 | J98: =G98*32 -> 0 | K98: =SUM(I98:J98) -> 0 | M98: =B98
B99: =Capacidades!M1596 | M99: =B99
B100: =Capacidades!M1597 | M100: =B100
B101: =Capacidades!M1598 | M101: =B101
B102: =Capacidades!M1599 | M102: =B102
B103: =Capacidades!M1600 | M103: =B103
B104: =Capacidades!M1601 | M104: =B104
B105: =Capacidades!M1602 | M105: =B105
B106: =Capacidades!M1603 | M106: =B106
...

Sheet Itinerario
A3: DENOMINACIÓN DE LA INSTITUCIÓN EDUCATIVA | C3: =Perfil_Egreso!B3 -> CETPRO JUANJUI | L3: CÓDIGO MODULAR DEL CETPRO | S3: =Perfil_Egreso!E3 -> 533836
A5: SECTOR ECONÓMICO | C5: =Perfil_Egreso!B5 -> OTRAS ACTIVIDADES DE SERVICIO | E5: FAMILIA PRODUCTIVA | G5: =Perfil_Egreso!D5 -> SERVICIOS PERSONALES Y DE HOGARES | P5: ACTIVIDAD ECONÓMICA | T5: =Perfil_Egreso!B7 -> OTRAS ACTIVIDADES DE SERVICIOS PERSONALES
A7: DENOMINACIÓN DEL PROGRAMA DE ESTUDIOS | C7: =Perfil_Egreso!B11 -> ESTILISMO
A9: CÓDIGO DE SER EL CASO * | C9: =Perfil_Egreso!E11 -> S3496-2-001 | E9: NIVEL FORMATIVO | G9: =Perfil_Egreso!B15 -> TÉCNICO | S9: N° CRÉDITOS: | U9: =T17 -> 83
A11: MODALIDAD DEL SERVICIO EDUCATIVO | C11: =Perfil_Egreso!D13 -> PRESENCIAL | S11: N° HORAS: | U11: =W17 -> 2272
A13: N° de créditos en forma virtual (**) | G13: COMPONENTES CURRICULARES | R13: Créd. T | S13: Créd. P | T13: Total créditos | U13: HT | V13: HP | W13: Total horas | Y13: Ayuda para verificar - f(x) criterios
G14: Competencias técnicas o específicas | R14: =SUM(R24:R43,R55:R74,R86:R105,R117:R136,R148:R167,R179:R198) -> 17 | S14: =SUM(S24:S43,S55:S74,S86:S105,S117:S136,S148:S167,S179:S198) -> 36 | T14: =SUM(R14:S14) -> 53 | U14: =R14*$S$19 -> 272 | V14: =S14*$U$19 -> 1152 | W14: =SUM(U14:V14) -> 1424 | Y14: Total horas (UD) | AD14: =SUM(W14:W15) -> 1824
A15: % de créditos en forma virtual (**) | G15: Competencias para la empleabilidad | R15: =SUM(R44:R53,R75:R84,R106:R115,R137:R146,R168:R177,R199:R208) -> 7 | S15: =SUM(S44:S53,S75:S84,S106:S115,S137:S146,S168:S177,S199:S208) -> 9 | T15: =SUM(R15:S15) -> 16 | U15: =R15*$S$19 -> 112 | V15: =S15*$U$19 -> 288 | W15: =SUM(U15:V15) -> 400 | Y15: c | Z15: h | AA15: c | AB15: h | AC15: c | AD15: h | AE15: c | AF15: h | AG15: c | AH15: h | AI15: c | AJ15: h
G16: EFSRT | S16: =SUM(S54,S85,S116,S147,S178,S209) -> 14 | T16: =SUM(R16:S16) -> 14 | V16: =S16*$U$19 -> 448 | W16: =SUM(U16:V16) -> 448 | Y16: I | Z16: I | AA16: II | AB16: II | AC16: III | AD16: III | AE16: IV | AF16: IV | AG16: V | AH16: V | AI16: VI | AJ16: VI
A17: % de créditos prácticos respecto del total de créditos: | C17: =IFERROR($S$17/$T$17,"") -> 0.71084337 | G17: TOTALES | R17: =SUM(R14:R16) -> 24 | S17: =SUM(S14:S16) -> 59 | T17: =SUM(T14:T16) -> 83 | U17: =SUM(U14:U16) -> 384 | V17: =SUM(V14:V16) -> 1888 | W17: =SUM(U17:V17) -> 2272 | Y17: =SUM(F24:F53,F55:F84,F86:F115,F117:F146,F148:F177,F179:F208,F54) -> 20 | Z17: =SUM(G24:G53,G55:G84,G86:G115,G117:G146,G148:G177,G179:G208,G54) -> 560 | AA17: =SUM(H24:H53,H55:H84,H86:H115,H117:H146,H148:H177,H179:H208,H85) -> 21 | AB17: =SUM(I24:I53,I55:I84,I86:I115,I117:I146,I148:I177,I179:I208,I85) -> 560 | AC17: =SUM(J24:J53,J55:J84,J86:J116,J117:J146,J148:J177,J179:J208) -> 21 | AD17: =SUM(K24:K53,K55:K84,K86:K116,K117:K146,K148:K177,K179:K208) -> 576 | AE17: =SUM(L24:L53,L55:L84,L86:L115,L117:L147,L148:L177,L179:L208) -> 21 | AF17: =SUM(M24:M53,M55:M84,M86:M115,M117:M147,M148:M177,M179:M208) -> 576 | AG17: =SUM(N24:N53,N55:N84,N86:N115,N117:N146,N148:N177,N179:N208) -> #NAME? | AH17: =SUM(O24:O53,O55:O84,O86:O115,O117:O146,O148:O177,O179:O208) -> #NAME? | AI17: =SUM(P24:P53,P55:P84,P86:P115,P117:P146,P148:P177,P179:P208) -> #NAME? | AJ17: =SUM(Q24:Q53,Q55:Q84,Q86:Q115,Q117:Q146,Q148:Q177,Q179:Q208) -> #NAME?
G19: Equivalencia de un (1) crédito:(4) | R19: HT | S19: 16 | T19: HP | U19: 32
AB20: Créditos:
A21: MÓDULO | B21: DESCRIPCION DE LA COMPETENCIA | D21: UNIDAD DIDÁCTICA | F21: Periodos Académicos (créditos y horas) | R21: Créditos Académicos | U21: Horas | X21: Filtro | AB21: Fuera del rango
F22: I(c) | G22: I(h) | H22: II (c) | I22: II (h) | J22: III (c) | K22: III (h) | L22: IV (c) | M22: IV (h) | N22: V (c) | O22: V (h) | P22: VI (c) | Q22: VI (h) | R22: Teóricos | S22: Prácticos | T22: Total | U22: De teoría | V22: Prácticas | W22: Total | X22: =W22 -> Total | AB22: Dentro del límite permitido
F23: I | G23: I | H23: II | I23: II | J23: III | K23: III | L23: IV | M23: IV | N23: V | O23: V | P23: VI | Q23: VI | W23: 0 | X23: =W23 -> 0 | AB23: Dentro del rango
A24: =Organización_Modular!A10 -> M1. PELUQUERIA, BARBERÍA Y PEINADOS | B24: =Organización_Modular!B10 -> Competencias técnicas (Unidad de competencia) | C24: =Organización_Modular!C10 -> UC1. Ejecutar el servicio de peluquería y barbería, teniendo en cuenta el diagnóstico capilar, requerimientos del cliente, procedimientos del establecimiento, criterios técnicos, estéticos y de bioseguridad e higiene. . | D24: =Organización_Modular!F10 -> CORTE DE CABELLO | F24: =_xlfn.IFNA(IF(VLOOKUP($D24,Organización_Modular!$F$10:$G$195,2,FALSE)=F$23,Itinerario!T24," ")," ") -> 7 | G24: =_xlfn.IFNA(IF(VLOOKUP($D24,Organización_Modular!$F$10:$G$195,2,FALSE)=G$23,Itinerario!W24," ")," ") -> 192 | H24: =_xlfn.IFNA(IF(VLOOKUP($D24,Organización_Modular!$F$10:$G$195,2,FALSE)=H$23,Itinerario!T24," ")," ") | I24: =_xlfn.IFNA(IF(VLOOKUP($D24,Organización_Modular!$F$10:$G$195,2,FALSE)=I$23,Itinerario!W24," ")," ") | J24: =_xlfn.IFNA(IF(VLOOKUP($D24,Organización_Modular!$F$10:$G$195,2,FALSE)=J$23,Itinerario!T24," ")," ") | K24: =_xlfn.IFNA(IF(VLOOKUP($D24,Organización_Modular!$F$10:$G$195,2,FALSE)=K$23,Itinerario!W24," ")," ") | L24: =_xlfn.IFNA(IF(VLOOKUP($D24,Organización_Modular!$F$10:$G$195,2,FALSE)=L$23,Itinerario!T24," ")," ") | M24: =_xlfn.IFNA(IF(VLOOKUP($D24,Organización_Modular!$F$10:$G$195,2,FALSE)=M$23,Itinerario!W24," ")," ") | N24: =_xludf.IFNA(IF(VLOOKUP($D24,Organización_Modular!$F$10:$G$195,2,FALSE)=N$23,Itinerario!T24," ")," ") -> #NAME? | O24: =_xludf.IFNA(IF(VLOOKUP($D24,Organización_Modular!$F$10:$G$195,2,FALSE)=O$23,Itinerario!W24," ")," ") -> #NAME? | P24: =_xludf.IFNA(IF(VLOOKUP($D24,Organización_Modular!$F$10:$G$195,2,FALSE)=P$23,Itinerario!T24," ")," ") -> #NAME? | Q24: =_xludf.IFNA(IF(VLOOKUP($D24,Organización_Modular!$F$10:$G$195,2,FALSE)=Q$23,Itinerario!W24," ")," ") -> #NAME? | R24: =Organización_Modular!H10 -> 2 | S24: =Organización_Modular!I10 -> 5 | T24: =SUM(R24:S24) -> 7 | U24: =+R24*$S$19 -> 32 | V24: =+S24*$U$19 -> 160 | W24: =SUM(U24:V24) -> 192 | X24: =W24 -> 192 | AB24: Dentro del rango
D25: =Organización_Modular!F11 -> CORTE Y DISEÑO DE BARBA | F25: =_xlfn.IFNA(IF(VLOOKUP($D25,Organización_Modular!$F$10:$G$195,2,FALSE)=F$23,Itinerario!T25," ")," ") -> 3 | G25: =_xlfn.IFNA(IF(VLOOKUP($D25,Organización_Modular!$F$10:$G$195,2,FALSE)=G$23,Itinerario!W25," ")," ") -> 80 | H25: =_xlfn.IFNA(IF(VLOOKUP($D25,Organización_Modular!$F$10:$G$195,2,FALSE)=H$23,Itinerario!T25," ")," ") | I25: =_xlfn.IFNA(IF(VLOOKUP($D25,Organización_Modular!$F$10:$G$195,2,FALSE)=I$23,Itinerario!W25," ")," ") | J25: =_xlfn.IFNA(IF(VLOOKUP($D25,Organización_Modular!$F$10:$G$195,2,FALSE)=J$23,Itinerario!T25," ")," ") | K25: =_xlfn.IFNA(IF(VLOOKUP($D25,Organización_Modular!$F$10:$G$195,2,FALSE)=K$23,Itinerario!W25," ")," ") | L25: =_xlfn.IFNA(IF(VLOOKUP($D25,Organización_Modular!$F$10:$G$195,2,FALSE)=L$23,Itinerario!T25," ")," ") | M25: =_xlfn.IFNA(IF(VLOOKUP($D25,Organización_Modular!$F$10:$G$195,2,FALSE)=M$23,Itinerario!W25," ")," ") | N25: =_xludf.IFNA(IF(VLOOKUP($D25,Organización_Modular!$F$10:$G$195,2,FALSE)=N$23,Itinerario!T25," ")," ") -> #NAME? | O25: =_xludf.IFNA(IF(VLOOKUP($D25,Organización_Modular!$F$10:$G$195,2,FALSE)=O$23,Itinerario!W25," ")," ") -> #NAME? | P25: =_xludf.IFNA(IF(VLOOKUP($D25,Organización_Modular!$F$10:$G$195,2,FALSE)=P$23,Itinerario!T25," ")," ") -> #NAME? | Q25: =_xludf.IFNA(IF(VLOOKUP($D25,Organización_Modular!$F$10:$G$195,2,FALSE)=Q$23,Itinerario!W25," ")," ") -> #NAME? | R25: =Organización_Modular!H11 -> 1 | S25: =Organización_Modular!I11 -> 2 | T25: =SUM(R25:S25) -> 3 | U25: =+R25*$S$19 -> 16 | V25: =+S25*$U$19 -> 64 | W25: =SUM(U25:V25) -> 80 | X25: =W25 -> 80
D26: =Organización_Modular!F12 -> PEINADOS | F26: =_xlfn.IFNA(IF(VLOOKUP($D26,Organización_Modular!$F$10:$G$195,2,FALSE)=F$23,Itinerario!T26," ")," ") -> 3 | G26: =_xlfn.IFNA(IF(VLOOKUP($D26,Organización_Modular!$F$10:$G$195,2,FALSE)=G$23,Itinerario!W26," ")," ") -> 80 | H26: =_xlfn.IFNA(IF(VLOOKUP($D26,Organización_Modular!$F$10:$G$195,2,FALSE)=H$23,Itinerario!T26," ")," ") | I26: =_xlfn.IFNA(IF(VLOOKUP($D26,Organización_Modular!$F$10:$G$195,2,FALSE)=I$23,Itinerario!W26," ")," ") | J26: =_xlfn.IFNA(IF(VLOOKUP($D26,Organización_Modular!$F$10:$G$195,2,FALSE)=J$23,Itinerario!T26," ")," ") | K26: =_xlfn.IFNA(IF(VLOOKUP($D26,Organización_Modular!$F$10:$G$195,2,FALSE)=K$23,Itinerario!W26," ")," ") | L26: =_xlfn.IFNA(IF(VLOOKUP($D26,Organización_Modular!$F$10:$G$195,2,FALSE)=L$23,Itinerario!T26," ")," ") | M26: =_xlfn.IFNA(IF(VLOOKUP($D26,Organización_Modular!$F$10:$G$195,2,FALSE)=M$23,Itinerario!W26," ")," ") | N26: =_xludf.IFNA(IF(VLOOKUP($D26,Organización_Modular!$F$10:$G$195,2,FALSE)=N$23,Itinerario!T26," ")," ") -> #NAME? | O26: =_xludf.IFNA(IF(VLOOKUP($D26,Organización_Modular!$F$10:$G$195,2,FALSE)=O$23,Itinerario!W26," ")," ") -> #NAME? | P26: =_xludf.IFNA(IF(VLOOKUP($D26,Organización_Modular!$F$10:$G$195,2,FALSE)=P$23,Itinerario!T26," ")," ") -> #NAME? | Q26: =_xludf.IFNA(IF(VLOOKUP($D26,Organización_Modular!$F$10:$G$195,2,FALSE)=Q$23,Itinerario!W26," ")," ") -> #NAME? | R26: =Organización_Modular!H12 -> 1 | S26: =Organización_Modular!I12 -> 2 | T26: =SUM(R26:S26) -> 3 | U26: =+R26*$S$19 -> 16 | V26: =+S26*$U$19 -> 64 | W26: =SUM(U26:V26) -> 80 | X26: =W26 -> 80
D27: =Organización_Modular!F13 -> 0 | F27: =_xlfn.IFNA(IF(VLOOKUP($D27,Organización_Modular!$F$10:$G$195,2,FALSE)=F$23,Itinerario!T27," ")," ") | G27: =_xlfn.IFNA(IF(VLOOKUP($D27,Organización_Modular!$F$10:$G$195,2,FALSE)=G$23,Itinerario!W27," ")," ") | H27: =_xlfn.IFNA(IF(VLOOKUP($D27,Organización_Modular!$F$10:$G$195,2,FALSE)=H$23,Itinerario!T27," ")," ") | I27: =_xlfn.IFNA(IF(VLOOKUP($D27,Organización_Modular!$F$10:$G$195,2,FALSE)=I$23,Itinerario!W27," ")," ") | J27: =_xlfn.IFNA(IF(VLOOKUP($D27,Organización_Modular!$F$10:$G$195,2,FALSE)=J$23,Itinerario!T27," ")," ") | K27: =_xlfn.IFNA(IF(VLOOKUP($D27,Organización_Modular!$F$10:$G$195,2,FALSE)=K$23,Itinerario!W27," ")," ") | L27: =_xlfn.IFNA(IF(VLOOKUP($D27,Organización_Modular!$F$10:$G$195,2,FALSE)=L$23,Itinerario!T27," ")," ") | M27: =_xlfn.IFNA(IF(VLOOKUP($D27,Organización_Modular!$F$10:$G$195,2,FALSE)=M$23,Itinerario!W27," ")," ") | N27: =_xludf.IFNA(IF(VLOOKUP($D27,Organización_Modular!$F$10:$G$195,2,FALSE)=N$23,Itinerario!T27," ")," ") -> #NAME? | O27: =_xludf.IFNA(IF(VLOOKUP($D27,Organización_Modular!$F$10:$G$195,2,FALSE)=O$23,Itinerario!W27," ")," ") -> #NAME? | P27: =_xludf.IFNA(IF(VLOOKUP($D27,Organización_Modular!$F$10:$G$195,2,FALSE)=P$23,Itinerario!T27," ")," ") -> #NAME? | Q27: =_xludf.IFNA(IF(VLOOKUP($D27,Organización_Modular!$F$10:$G$195,2,FALSE)=Q$23,Itinerario!W27," ")," ") -> #NAME? | R27: =Organización_Modular!H13 -> 0 | S27: =Organización_Modular!I13 -> 0 | T27: =SUM(R27:S27) -> 0 | U27: =+R27*$S$19 -> 0 | V27: =+S27*$U$19 -> 0 | W27: =SUM(U27:V27) -> 0 | X27: =W27 -> 0
D28: =Organización_Modular!F14 -> 0 | F28: =_xlfn.IFNA(IF(VLOOKUP($D28,Organización_Modular!$F$10:$G$195,2,FALSE)=F$23,Itinerario!T28," ")," ") | G28: =_xlfn.IFNA(IF(VLOOKUP($D28,Organización_Modular!$F$10:$G$195,2,FALSE)=G$23,Itinerario!W28," ")," ") | H28: =_xlfn.IFNA(IF(VLOOKUP($D28,Organización_Modular!$F$10:$G$195,2,FALSE)=H$23,Itinerario!T28," ")," ") | I28: =_xlfn.IFNA(IF(VLOOKUP($D28,Organización_Modular!$F$10:$G$195,2,FALSE)=I$23,Itinerario!W28," ")," ") | J28: =_xlfn.IFNA(IF(VLOOKUP($D28,Organización_Modular!$F$10:$G$195,2,FALSE)=J$23,Itinerario!T28," ")," ") | K28: =_xlfn.IFNA(IF(VLOOKUP($D28,Organización_Modular!$F$10:$G$195,2,FALSE)=K$23,Itinerario!W28," ")," ") | L28: =_xlfn.IFNA(IF(VLOOKUP($D28,Organización_Modular!$F$10:$G$195,2,FALSE)=L$23,Itinerario!T28," ")," ") | M28: =_xlfn.IFNA(IF(VLOOKUP($D28,Organización_Modular!$F$10:$G$195,2,FALSE)=M$23,Itinerario!W28," ")," ") | N28: =_xludf.IFNA(IF(VLOOKUP($D28,Organización_Modular!$F$10:$G$195,2,FALSE)=N$23,Itinerario!T28," ")," ") -> #NAME? | O28: =_xludf.IFNA(IF(VLOOKUP($D28,Organización_Modular!$F$10:$G$195,2,FALSE)=O$23,Itinerario!W28," ")," ") -> #NAME? | P28: =_xludf.IFNA(IF(VLOOKUP($D28,Organización_Modular!$F$10:$G$195,2,FALSE)=P$23,Itinerario!T28," ")," ") -> #NAME? | Q28: =_xludf.IFNA(IF(VLOOKUP($D28,Organización_Modular!$F$10:$G$195,2,FALSE)=Q$23,Itinerario!W28," ")," ") -> #NAME? | R28: =Organización_Modular!H14 -> 0 | S28: =Organización_Modular!I14 -> 0 | T28: =SUM(R28:S28) -> 0 | U28: =+R28*$S$19 -> 0 | V28: =+S28*$U$19 -> 0 | W28: =SUM(U28:V28) -> 0 | X28: =W28 -> 0 | Z28: =if -> #NAME?
D29: =Organización_Modular!F15 -> 0 | F29: =_xlfn.IFNA(IF(VLOOKUP($D29,Organización_Modular!$F$10:$G$195,2,FALSE)=F$23,Itinerario!T29," ")," ") | G29: =_xlfn.IFNA(IF(VLOOKUP($D29,Organización_Modular!$F$10:$G$195,2,FALSE)=G$23,Itinerario!W29," ")," ") | H29: =_xlfn.IFNA(IF(VLOOKUP($D29,Organización_Modular!$F$10:$G$195,2,FALSE)=H$23,Itinerario!T29," ")," ") | I29: =_xlfn.IFNA(IF(VLOOKUP($D29,Organización_Modular!$F$10:$G$195,2,FALSE)=I$23,Itinerario!W29," ")," ") | J29: =_xlfn.IFNA(IF(VLOOKUP($D29,Organización_Modular!$F$10:$G$195,2,FALSE)=J$23,Itinerario!T29," ")," ") | K29: =_xlfn.IFNA(IF(VLOOKUP($D29,Organización_Modular!$F$10:$G$195,2,FALSE)=K$23,Itinerario!W29," ")," ") | L29: =_xlfn.IFNA(IF(VLOOKUP($D29,Organización_Modular!$F$10:$G$195,2,FALSE)=L$23,Itinerario!T29," ")," ") | M29: =_xlfn.IFNA(IF(VLOOKUP($D29,Organización_Modular!$F$10:$G$195,2,FALSE)=M$23,Itinerario!W29," ")," ") | N29: =_xludf.IFNA(IF(VLOOKUP($D29,Organización_Modular!$F$10:$G$195,2,FALSE)=N$23,Itinerario!T29," ")," ") -> #NAME? | O29: =_xludf.IFNA(IF(VLOOKUP($D29,Organización_Modular!$F$10:$G$195,2,FALSE)=O$23,Itinerario!W29," ")," ") -> #NAME? | P29: =_xludf.IFNA(IF(VLOOKUP($D29,Organización_Modular!$F$10:$G$195,2,FALSE)=P$23,Itinerario!T29," ")," ") -> #NAME? | Q29: =_xludf.IFNA(IF(VLOOKUP($D29,Organización_Modular!$F$10:$G$195,2,FALSE)=Q$23,Itinerario!W29," ")," ") -> #NAME? | R29: =Organización_Modular!H15 -> 0 | S29: =Organización_Modular!I15 -> 0 | T29: =SUM(R29:S29) -> 0 | U29: =+R29*$S$19 -> 0 | V29: =+S29*$U$19 -> 0 | W29: =SUM(U29:V29) -> 0 | X29: =W29 -> 0
D30: =Organización_Modular!F16 -> 0 | F30: =_xlfn.IFNA(IF(VLOOKUP($D30,Organización_Modular!$F$10:$G$195,2,FALSE)=F$23,Itinerario!T30," ")," ") | G30: =_xlfn.IFNA(IF(VLOOKUP($D30,Organización_Modular!$F$10:$G$195,2,FALSE)=G$23,Itinerario!W30," ")," ") | H30: =_xlfn.IFNA(IF(VLOOKUP($D30,Organización_Modular!$F$10:$G$195,2,FALSE)=H$23,Itinerario!T30," ")," ") | I30: =_xlfn.IFNA(IF(VLOOKUP($D30,Organización_Modular!$F$10:$G$195,2,FALSE)=I$23,Itinerario!W30," ")," ") | J30: =_xlfn.IFNA(IF(VLOOKUP($D30,Organización_Modular!$F$10:$G$195,2,FALSE)=J$23,Itinerario!T30," ")," ") | K30: =_xlfn.IFNA(IF(VLOOKUP($D30,Organización_Modular!$F$10:$G$195,2,FALSE)=K$23,Itinerario!W30," ")," ") | L30: =_xlfn.IFNA(IF(VLOOKUP($D30,Organización_Modular!$F$10:$G$195,2,FALSE)=L$23,Itinerario!T30," ")," ") | M30: =_xlfn.IFNA(IF(VLOOKUP($D30,Organización_Modular!$F$10:$G$195,2,FALSE)=M$23,Itinerario!W30," ")," ") | N30: =_xludf.IFNA(IF(VLOOKUP($D30,Organización_Modular!$F$10:$G$195,2,FALSE)=N$23,Itinerario!T30," ")," ") -> #NAME? | O30: =_xludf.IFNA(IF(VLOOKUP($D30,Organización_Modular!$F$10:$G$195,2,FALSE)=O$23,Itinerario!W30," ")," ") -> #NAME? | P30: =_xludf.IFNA(IF(VLOOKUP($D30,Organización_Modular!$F$10:$G$195,2,FALSE)=P$23,Itinerario!T30," ")," ") -> #NAME? | Q30: =_xludf.IFNA(IF(VLOOKUP($D30,Organización_Modular!$F$10:$G$195,2,FALSE)=Q$23,Itinerario!W30," ")," ") -> #NAME? | R30: =Organización_Modular!H16 -> 0 | S30: =Organización_Modular!I16 -> 0 | T30: =SUM(R30:S30) -> 0 | U30: =+R30*$S$19 -> 0 | V30: =+S30*$U$19 -> 0 | W30: =SUM(U30:V30) -> 0 | X30: =W30 -> 0
D31: =Organización_Modular!F17 -> 0 | F31: =_xlfn.IFNA(IF(VLOOKUP($D31,Organización_Modular!$F$10:$G$195,2,FALSE)=F$23,Itinerario!T31," ")," ") | G31: =_xlfn.IFNA(IF(VLOOKUP($D31,Organización_Modular!$F$10:$G$195,2,FALSE)=G$23,Itinerario!W31," ")," ") | H31: =_xlfn.IFNA(IF(VLOOKUP($D31,Organización_Modular!$F$10:$G$195,2,FALSE)=H$23,Itinerario!T31," ")," ") | I31: =_xlfn.IFNA(IF(VLOOKUP($D31,Organización_Modular!$F$10:$G$195,2,FALSE)=I$23,Itinerario!W31," ")," ") | J31: =_xlfn.IFNA(IF(VLOOKUP($D31,Organización_Modular!$F$10:$G$195,2,FALSE)=J$23,Itinerario!T31," ")," ") | K31: =_xlfn.IFNA(IF(VLOOKUP($D31,Organización_Modular!$F$10:$G$195,2,FALSE)=K$23,Itinerario!W31," ")," ") | L31: =_xlfn.IFNA(IF(VLOOKUP($D31,Organización_Modular!$F$10:$G$195,2,FALSE)=L$23,Itinerario!T31," ")," ") | M31: =_xlfn.IFNA(IF(VLOOKUP($D31,Organización_Modular!$F$10:$G$195,2,FALSE)=M$23,Itinerario!W31," ")," ") | N31: =_xludf.IFNA(IF(VLOOKUP($D31,Organización_Modular!$F$10:$G$195,2,FALSE)=N$23,Itinerario!T31," ")," ") -> #NAME? | O31: =_xludf.IFNA(IF(VLOOKUP($D31,Organización_Modular!$F$10:$G$195,2,FALSE)=O$23,Itinerario!W31," ")," ") -> #NAME? | P31: =_xludf.IFNA(IF(VLOOKUP($D31,Organización_Modular!$F$10:$G$195,2,FALSE)=P$23,Itinerario!T31," ")," ") -> #NAME? | Q31: =_xludf.IFNA(IF(VLOOKUP($D31,Organización_Modular!$F$10:$G$195,2,FALSE)=Q$23,Itinerario!W31," ")," ") -> #NAME? | R31: =Organización_Modular!H17 -> 0 | S31: =Organización_Modular!I17 -> 0 | T31: =SUM(R31:S31) -> 0 | U31: =+R31*$S$19 -> 0 | V31: =+S31*$U$19 -> 0 | W31: =SUM(U31:V31) -> 0 | X31: =W31 -> 0
D32: =Organización_Modular!F18 -> 0 | F32: =_xlfn.IFNA(IF(VLOOKUP($D32,Organización_Modular!$F$10:$G$195,2,FALSE)=F$23,Itinerario!T32," ")," ") | G32: =_xlfn.IFNA(IF(VLOOKUP($D32,Organización_Modular!$F$10:$G$195,2,FALSE)=G$23,Itinerario!W32," ")," ") | H32: =_xlfn.IFNA(IF(VLOOKUP($D32,Organización_Modular!$F$10:$G$195,2,FALSE)=H$23,Itinerario!T32," ")," ") | I32: =_xlfn.IFNA(IF(VLOOKUP($D32,Organización_Modular!$F$10:$G$195,2,FALSE)=I$23,Itinerario!W32," ")," ") | J32: =_xlfn.IFNA(IF(VLOOKUP($D32,Organización_Modular!$F$10:$G$195,2,FALSE)=J$23,Itinerario!T32," ")," ") | K32: =_xlfn.IFNA(IF(VLOOKUP($D32,Organización_Modular!$F$10:$G$195,2,FALSE)=K$23,Itinerario!W32," ")," ") | L32: =_xlfn.IFNA(IF(VLOOKUP($D32,Organización_Modular!$F$10:$G$195,2,FALSE)=L$23,Itinerario!T32," ")," ") | M32: =_xlfn.IFNA(IF(VLOOKUP($D32,Organización_Modular!$F$10:$G$195,2,FALSE)=M$23,Itinerario!W32," ")," ") | N32: =_xludf.IFNA(IF(VLOOKUP($D32,Organización_Modular!$F$10:$G$195,2,FALSE)=N$23,Itinerario!T32," ")," ") -> #NAME? | O32: =_xludf.IFNA(IF(VLOOKUP($D32,Organización_Modular!$F$10:$G$195,2,FALSE)=O$23,Itinerario!W32," ")," ") -> #NAME? | P32: =_xludf.IFNA(IF(VLOOKUP($D32,Organización_Modular!$F$10:$G$195,2,FALSE)=P$23,Itinerario!T32," ")," ") -> #NAME? | Q32: =_xludf.IFNA(IF(VLOOKUP($D32,Organización_Modular!$F$10:$G$195,2,FALSE)=Q$23,Itinerario!W32," ")," ") -> #NAME? | R32: =Organización_Modular!H18 -> 0 | S32: =Organización_Modular!I18 -> 0 | T32: =SUM(R32:S32) -> 0 | U32: =+R32*$S$19 -> 0 | V32: =+S32*$U$19 -> 0 | W32: =SUM(U32:V32) -> 0 | X32: =W32 -> 0
D33: =Organización_Modular!F19 -> 0 | F33: =_xlfn.IFNA(IF(VLOOKUP($D33,Organización_Modular!$F$10:$G$195,2,FALSE)=F$23,Itinerario!T33," ")," ") | G33: =_xlfn.IFNA(IF(VLOOKUP($D33,Organización_Modular!$F$10:$G$195,2,FALSE)=G$23,Itinerario!W33," ")," ") | H33: =_xlfn.IFNA(IF(VLOOKUP($D33,Organización_Modular!$F$10:$G$195,2,FALSE)=H$23,Itinerario!T33," ")," ") | I33: =_xlfn.IFNA(IF(VLOOKUP($D33,Organización_Modular!$F$10:$G$195,2,FALSE)=I$23,Itinerario!W33," ")," ") | J33: =_xlfn.IFNA(IF(VLOOKUP($D33,Organización_Modular!$F$10:$G$195,2,FALSE)=J$23,Itinerario!T33," ")," ") | K33: =_xlfn.IFNA(IF(VLOOKUP($D33,Organización_Modular!$F$10:$G$195,2,FALSE)=K$23,Itinerario!W33," ")," ") | L33: =_xlfn.IFNA(IF(VLOOKUP($D33,Organización_Modular!$F$10:$G$195,2,FALSE)=L$23,Itinerario!T33," ")," ") | M33: =_xlfn.IFNA(IF(VLOOKUP($D33,Organización_Modular!$F$10:$G$195,2,FALSE)=M$23,Itinerario!W33," ")," ") | N33: =_xludf.IFNA(IF(VLOOKUP($D33,Organización_Modular!$F$10:$G$195,2,FALSE)=N$23,Itinerario!T33," ")," ") -> #NAME? | O33: =_xludf.IFNA(IF(VLOOKUP($D33,Organización_Modular!$F$10:$G$195,2,FALSE)=O$23,Itinerario!W33," ")," ") -> #NAME? | P33: =_xludf.IFNA(IF(VLOOKUP($D33,Organización_Modular!$F$10:$G$195,2,FALSE)=P$23,Itinerario!T33," ")," ") -> #NAME? | Q33: =_xludf.IFNA(IF(VLOOKUP($D33,Organización_Modular!$F$10:$G$195,2,FALSE)=Q$23,Itinerario!W33," ")," ") -> #NAME? | R33: =Organización_Modular!H19 -> 0 | S33: =Organización_Modular!I19 -> 0 | T33: =SUM(R33:S33) -> 0 | U33: =+R33*$S$19 -> 0 | V33: =+S33*$U$19 -> 0 | W33: =SUM(U33:V33) -> 0 | X33: =W33 -> 0
D34: =Organización_Modular!F20 -> 0 | F34: =_xlfn.IFNA(IF(VLOOKUP($D34,Organización_Modular!$F$10:$G$195,2,FALSE)=F$23,Itinerario!T34," ")," ") | G34: =_xlfn.IFNA(IF(VLOOKUP($D34,Organización_Modular!$F$10:$G$195,2,FALSE)=G$23,Itinerario!W34," ")," ") | H34: =_xlfn.IFNA(IF(VLOOKUP($D34,Organización_Modular!$F$10:$G$195,2,FALSE)=H$23,Itinerario!T34," ")," ") | I34: =_xlfn.IFNA(IF(VLOOKUP($D34,Organización_Modular!$F$10:$G$195,2,FALSE)=I$23,Itinerario!W34," ")," ") | J34: =_xlfn.IFNA(IF(VLOOKUP($D34,Organización_Modular!$F$10:$G$195,2,FALSE)=J$23,Itinerario!T34," ")," ") | K34: =_xlfn.IFNA(IF(VLOOKUP($D34,Organización_Modular!$F$10:$G$195,2,FALSE)=K$23,Itinerario!W34," ")," ") | L34: =_xlfn.IFNA(IF(VLOOKUP($D34,Organización_Modular!$F$10:$G$195,2,FALSE)=L$23,Itinerario!T34," ")," ") | M34: =_xlfn.IFNA(IF(VLOOKUP($D34,Organización_Modular!$F$10:$G$195,2,FALSE)=M$23,Itinerario!W34," ")," ") | N34: =_xludf.IFNA(IF(VLOOKUP($D34,Organización_Modular!$F$10:$G$195,2,FALSE)=N$23,Itinerario!T34," ")," ") -> #NAME? | O34: =_xludf.IFNA(IF(VLOOKUP($D34,Organización_Modular!$F$10:$G$195,2,FALSE)=O$23,Itinerario!W34," ")," ") -> #NAME? | P34: =_xludf.IFNA(IF(VLOOKUP($D34,Organización_Modular!$F$10:$G$195,2,FALSE)=P$23,Itinerario!T34," ")," ") -> #NAME? | Q34: =_xludf.IFNA(IF(VLOOKUP($D34,Organización_Modular!$F$10:$G$195,2,FALSE)=Q$23,Itinerario!W34," ")," ") -> #NAME? | R34: =Organización_Modular!H20 -> 0 | S34: =Organización_Modular!I20 -> 0 | T34: =SUM(R34:S34) -> 0 | U34: =+R34*$S$19 -> 0 | V34: =+S34*$U$19 -> 0 | W34: =SUM(U34:V34) -> 0 | X34: =W34 -> 0
D35: =Organización_Modular!F21 -> 0 | F35: =_xlfn.IFNA(IF(VLOOKUP($D35,Organización_Modular!$F$10:$G$195,2,FALSE)=F$23,Itinerario!T35," ")," ") | G35: =_xlfn.IFNA(IF(VLOOKUP($D35,Organización_Modular!$F$10:$G$195,2,FALSE)=G$23,Itinerario!W35," ")," ") | H35: =_xlfn.IFNA(IF(VLOOKUP($D35,Organización_Modular!$F$10:$G$195,2,FALSE)=H$23,Itinerario!T35," ")," ") | I35: =_xlfn.IFNA(IF(VLOOKUP($D35,Organización_Modular!$F$10:$G$195,2,FALSE)=I$23,Itinerario!W35," ")," ") | J35: =_xlfn.IFNA(IF(VLOOKUP($D35,Organización_Modular!$F$10:$G$195,2,FALSE)=J$23,Itinerario!T35," ")," ") | K35: =_xlfn.IFNA(IF(VLOOKUP($D35,Organización_Modular!$F$10:$G$195,2,FALSE)=K$23,Itinerario!W35," ")," ") | L35: =_xlfn.IFNA(IF(VLOOKUP($D35,Organización_Modular!$F$10:$G$195,2,FALSE)=L$23,Itinerario!T35," ")," ") | M35: =_xlfn.IFNA(IF(VLOOKUP($D35,Organización_Modular!$F$10:$G$195,2,FALSE)=M$23,Itinerario!W35," ")," ") | N35: =_xludf.IFNA(IF(VLOOKUP($D35,Organización_Modular!$F$10:$G$195,2,FALSE)=N$23,Itinerario!T35," ")," ") -> #NAME? | O35: =_xludf.IFNA(IF(VLOOKUP($D35,Organización_Modular!$F$10:$G$195,2,FALSE)=O$23,Itinerario!W35," ")," ") -> #NAME? | P35: =_xludf.IFNA(IF(VLOOKUP($D35,Organización_Modular!$F$10:$G$195,2,FALSE)=P$23,Itinerario!T35," ")," ") -> #NAME? | Q35: =_xludf.IFNA(IF(VLOOKUP($D35,Organización_Modular!$F$10:$G$195,2,FALSE)=Q$23,Itinerario!W35," ")," ") -> #NAME? | R35: =Organización_Modular!H21 -> 0 | S35: =Organización_Modular!I21 -> 0 | T35: =SUM(R35:S35) -> 0 | U35: =+R35*$S$19 -> 0 | V35: =+S35*$U$19 -> 0 | W35: =SUM(U35:V35) -> 0 | X35: =W35 -> 0
D36: =Organización_Modular!F22 -> 0 | F36: =_xlfn.IFNA(IF(VLOOKUP($D36,Organización_Modular!$F$10:$G$195,2,FALSE)=F$23,Itinerario!T36," ")," ") | G36: =_xlfn.IFNA(IF(VLOOKUP($D36,Organización_Modular!$F$10:$G$195,2,FALSE)=G$23,Itinerario!W36," ")," ") | H36: =_xlfn.IFNA(IF(VLOOKUP($D36,Organización_Modular!$F$10:$G$195,2,FALSE)=H$23,Itinerario!T36," ")," ") | I36: =_xlfn.IFNA(IF(VLOOKUP($D36,Organización_Modular!$F$10:$G$195,2,FALSE)=I$23,Itinerario!W36," ")," ") | J36: =_xlfn.IFNA(IF(VLOOKUP($D36,Organización_Modular!$F$10:$G$195,2,FALSE)=J$23,Itinerario!T36," ")," ") | K36: =_xlfn.IFNA(IF(VLOOKUP($D36,Organización_Modular!$F$10:$G$195,2,FALSE)=K$23,Itinerario!W36," ")," ") | L36: =_xlfn.IFNA(IF(VLOOKUP($D36,Organización_Modular!$F$10:$G$195,2,FALSE)=L$23,Itinerario!T36," ")," ") | M36: =_xlfn.IFNA(IF(VLOOKUP($D36,Organización_Modular!$F$10:$G$195,2,FALSE)=M$23,Itinerario!W36," ")," ") | N36: =_xludf.IFNA(IF(VLOOKUP($D36,Organización_Modular!$F$10:$G$195,2,FALSE)=N$23,Itinerario!T36," ")," ") -> #NAME? | O36: =_xludf.IFNA(IF(VLOOKUP($D36,Organización_Modular!$F$10:$G$195,2,FALSE)=O$23,Itinerario!W36," ")," ") -> #NAME? | P36: =_xludf.IFNA(IF(VLOOKUP($D36,Organización_Modular!$F$10:$G$195,2,FALSE)=P$23,Itinerario!T36," ")," ") -> #NAME? | Q36: =_xludf.IFNA(IF(VLOOKUP($D36,Organización_Modular!$F$10:$G$195,2,FALSE)=Q$23,Itinerario!W36," ")," ") -> #NAME? | R36: =Organización_Modular!H22 -> 0 | S36: =Organización_Modular!I22 -> 0 | T36: =SUM(R36:S36) -> 0 | U36: =+R36*$S$19 -> 0 | V36: =+S36*$U$19 -> 0 | W36: =SUM(U36:V36) -> 0 | X36: =W36 -> 0
D37: =Organización_Modular!F23 -> 0 | F37: =_xlfn.IFNA(IF(VLOOKUP($D37,Organización_Modular!$F$10:$G$195,2,FALSE)=F$23,Itinerario!T37," ")," ") | G37: =_xlfn.IFNA(IF(VLOOKUP($D37,Organización_Modular!$F$10:$G$195,2,FALSE)=G$23,Itinerario!W37," ")," ") | H37: =_xlfn.IFNA(IF(VLOOKUP($D37,Organización_Modular!$F$10:$G$195,2,FALSE)=H$23,Itinerario!T37," ")," ") | I37: =_xlfn.IFNA(IF(VLOOKUP($D37,Organización_Modular!$F$10:$G$195,2,FALSE)=I$23,Itinerario!W37," ")," ") | J37: =_xlfn.IFNA(IF(VLOOKUP($D37,Organización_Modular!$F$10:$G$195,2,FALSE)=J$23,Itinerario!T37," ")," ") | K37: =_xlfn.IFNA(IF(VLOOKUP($D37,Organización_Modular!$F$10:$G$195,2,FALSE)=K$23,Itinerario!W37," ")," ") | L37: =_xlfn.IFNA(IF(VLOOKUP($D37,Organización_Modular!$F$10:$G$195,2,FALSE)=L$23,Itinerario!T37," ")," ") | M37: =_xlfn.IFNA(IF(VLOOKUP($D37,Organización_Modular!$F$10:$G$195,2,FALSE)=M$23,Itinerario!W37," ")," ") | N37: =_xludf.IFNA(IF(VLOOKUP($D37,Organización_Modular!$F$10:$G$195,2,FALSE)=N$23,Itinerario!T37," ")," ") -> #NAME? | O37: =_xludf.IFNA(IF(VLOOKUP($D37,Organización_Modular!$F$10:$G$195,2,FALSE)=O$23,Itinerario!W37," ")," ") -> #NAME? | P37: =_xludf.IFNA(IF(VLOOKUP($D37,Organización_Modular!$F$10:$G$195,2,FALSE)=P$23,Itinerario!T37," ")," ") -> #NAME? | Q37: =_xludf.IFNA(IF(VLOOKUP($D37,Organización_Modular!$F$10:$G$195,2,FALSE)=Q$23,Itinerario!W37," ")," ") -> #NAME? | R37: =Organización_Modular!H23 -> 0 | S37: =Organización_Modular!I23 -> 0 | T37: =SUM(R37:S37) -> 0 | U37: =+R37*$S$19 -> 0 | V37: =+S37*$U$19 -> 0 | W37: =SUM(U37:V37) -> 0 | X37: =W37 -> 0
D38: =Organización_Modular!F24 -> 0 | F38: =_xlfn.IFNA(IF(VLOOKUP($D38,Organización_Modular!$F$10:$G$195,2,FALSE)=F$23,Itinerario!T38," ")," ") | G38: =_xlfn.IFNA(IF(VLOOKUP($D38,Organización_Modular!$F$10:$G$195,2,FALSE)=G$23,Itinerario!W38," ")," ") | H38: =_xlfn.IFNA(IF(VLOOKUP($D38,Organización_Modular!$F$10:$G$195,2,FALSE)=H$23,Itinerario!T38," ")," ") | I38: =_xlfn.IFNA(IF(VLOOKUP($D38,Organización_Modular!$F$10:$G$195,2,FALSE)=I$23,Itinerario!W38," ")," ") | J38: =_xlfn.IFNA(IF(VLOOKUP($D38,Organización_Modular!$F$10:$G$195,2,FALSE)=J$23,Itinerario!T38," ")," ") | K38: =_xlfn.IFNA(IF(VLOOKUP($D38,Organización_Modular!$F$10:$G$195,2,FALSE)=K$23,Itinerario!W38," ")," ") | L38: =_xlfn.IFNA(IF(VLOOKUP($D38,Organización_Modular!$F$10:$G$195,2,FALSE)=L$23,Itinerario!T38," ")," ") | M38: =_xlfn.IFNA(IF(VLOOKUP($D38,Organización_Modular!$F$10:$G$195,2,FALSE)=M$23,Itinerario!W38," ")," ") | N38: =_xludf.IFNA(IF(VLOOKUP($D38,Organización_Modular!$F$10:$G$195,2,FALSE)=N$23,Itinerario!T38," ")," ") -> #NAME? | O38: =_xludf.IFNA(IF(VLOOKUP($D38,Organización_Modular!$F$10:$G$195,2,FALSE)=O$23,Itinerario!W38," ")," ") -> #NAME? | P38: =_xludf.IFNA(IF(VLOOKUP($D38,Organización_Modular!$F$10:$G$195,2,FALSE)=P$23,Itinerario!T38," ")," ") -> #NAME? | Q38: =_xludf.IFNA(IF(VLOOKUP($D38,Organización_Modular!$F$10:$G$195,2,FALSE)=Q$23,Itinerario!W38," ")," ") -> #NAME? | R38: =Organización_Modular!H24 -> 0 | S38: =Organización_Modular!I24 -> 0 | T38: =SUM(R38:S38) -> 0 | U38: =+R38*$S$19 -> 0 | V38: =+S38*$U$19 -> 0 | W38: =SUM(U38:V38) -> 0 | X38: =W38 -> 0
D39: =Organización_Modular!F25 -> 0 | F39: =_xlfn.IFNA(IF(VLOOKUP($D39,Organización_Modular!$F$10:$G$195,2,FALSE)=F$23,Itinerario!T39," ")," ") | G39: =_xlfn.IFNA(IF(VLOOKUP($D39,Organización_Modular!$F$10:$G$195,2,FALSE)=G$23,Itinerario!W39," ")," ") | H39: =_xlfn.IFNA(IF(VLOOKUP($D39,Organización_Modular!$F$10:$G$195,2,FALSE)=H$23,Itinerario!T39," ")," ") | I39: =_xlfn.IFNA(IF(VLOOKUP($D39,Organización_Modular!$F$10:$G$195,2,FALSE)=I$23,Itinerario!W39," ")," ") | J39: =_xlfn.IFNA(IF(VLOOKUP($D39,Organización_Modular!$F$10:$G$195,2,FALSE)=J$23,Itinerario!T39," ")," ") | K39: =_xlfn.IFNA(IF(VLOOKUP($D39,Organización_Modular!$F$10:$G$195,2,FALSE)=K$23,Itinerario!W39," ")," ") | L39: =_xlfn.IFNA(IF(VLOOKUP($D39,Organización_Modular!$F$10:$G$195,2,FALSE)=L$23,Itinerario!T39," ")," ") | M39: =_xlfn.IFNA(IF(VLOOKUP($D39,Organización_Modular!$F$10:$G$195,2,FALSE)=M$23,Itinerario!W39," ")," ") | N39: =_xludf.IFNA(IF(VLOOKUP($D39,Organización_Modular!$F$10:$G$195,2,FALSE)=N$23,Itinerario!T39," ")," ") -> #NAME? | O39: =_xludf.IFNA(IF(VLOOKUP($D39,Organización_Modular!$F$10:$G$195,2,FALSE)=O$23,Itinerario!W39," ")," ") -> #NAME? | P39: =_xludf.IFNA(IF(VLOOKUP($D39,Organización_Modular!$F$10:$G$195,2,FALSE)=P$23,Itinerario!T39," ")," ") -> #NAME? | Q39: =_xludf.IFNA(IF(VLOOKUP($D39,Organización_Modular!$F$10:$G$195,2,FALSE)=Q$23,Itinerario!W39," ")," ") -> #NAME? | R39: =Organización_Modular!H25 -> 0 | S39: =Organización_Modular!I25 -> 0 | T39: =SUM(R39:S39) -> 0 | U39: =+R39*$S$19 -> 0 | V39: =+S39*$U$19 -> 0 | W39: =SUM(U39:V39) -> 0 | X39: =W39 -> 0
D40: =Organización_Modular!F26 -> 0 | F40: =_xlfn.IFNA(IF(VLOOKUP($D40,Organización_Modular!$F$10:$G$195,2,FALSE)=F$23,Itinerario!T40," ")," ") | G40: =_xlfn.IFNA(IF(VLOOKUP($D40,Organización_Modular!$F$10:$G$195,2,FALSE)=G$23,Itinerario!W40," ")," ") | H40: =_xlfn.IFNA(IF(VLOOKUP($D40,Organización_Modular!$F$10:$G$195,2,FALSE)=H$23,Itinerario!T40," ")," ") | I40: =_xlfn.IFNA(IF(VLOOKUP($D40,Organización_Modular!$F$10:$G$195,2,FALSE)=I$23,Itinerario!W40," ")," ") | J40: =_xlfn.IFNA(IF(VLOOKUP($D40,Organización_Modular!$F$10:$G$195,2,FALSE)=J$23,Itinerario!T40," ")," ") | K40: =_xlfn.IFNA(IF(VLOOKUP($D40,Organización_Modular!$F$10:$G$195,2,FALSE)=K$23,Itinerario!W40," ")," ") | L40: =_xlfn.IFNA(IF(VLOOKUP($D40,Organización_Modular!$F$10:$G$195,2,FALSE)=L$23,Itinerario!T40," ")," ") | M40: =_xlfn.IFNA(IF(VLOOKUP($D40,Organización_Modular!$F$10:$G$195,2,FALSE)=M$23,Itinerario!W40," ")," ") | N40: =_xludf.IFNA(IF(VLOOKUP($D40,Organización_Modular!$F$10:$G$195,2,FALSE)=N$23,Itinerario!T40," ")," ") -> #NAME? | O40: =_xludf.IFNA(IF(VLOOKUP($D40,Organización_Modular!$F$10:$G$195,2,FALSE)=O$23,Itinerario!W40," ")," ") -> #NAME? | P40: =_xludf.IFNA(IF(VLOOKUP($D40,Organización_Modular!$F$10:$G$195,2,FALSE)=P$23,Itinerario!T40," ")," ") -> #NAME? | Q40: =_xludf.IFNA(IF(VLOOKUP($D40,Organización_Modular!$F$10:$G$195,2,FALSE)=Q$23,Itinerario!W40," ")," ") -> #NAME? | R40: =Organización_Modular!H26 -> 0 | S40: =Organización_Modular!I26 -> 0 | T40: =SUM(R40:S40) -> 0 | U40: =+R40*$S$19 -> 0 | V40: =+S40*$U$19 -> 0 | W40: =SUM(U40:V40) -> 0 | X40: =W40 -> 0
... D43: =Organización_Modular!F29 -> 0 | F43: =_xlfn.IFNA(IF(VLOOKUP($D43,Organización_Modular!$F$10:$G$195,2,FALSE)=F$23,Itinerario!T43," ")," ") | G43: =_xlfn.IFNA(IF(VLOOKUP($D43,Organización_Modular!$F$10:$G$195,2,FALSE)=G$23,Itinerario!W43," ")," ") | H43: =_xlfn.IFNA(IF(VLOOKUP($D43,Organización_Modular!$F$10:$G$195,2,FALSE)=H$23,Itinerario!T43," ")," ") | I43: =_xlfn.IFNA(IF(VLOOKUP($D43,Organización_Modular!$F$10:$G$195,2,FALSE)=I$23,Itinerario!W43," ")," ") | J43: =_xlfn.IFNA(IF(VLOOKUP($D43,Organización_Modular!$F$10:$G$195,2,FALSE)=J$23,Itinerario!T43," ")," ") | K43: =_xlfn.IFNA(IF(VLOOKUP($D43,Organización_Modular!$F$10:$G$195,2,FALSE)=K$23,Itinerario!W43," ")," ") | L43: =_xlfn.IFNA(IF(VLOOKUP($D43,Organización_Modular!$F$10:$G$195,2,FALSE)=L$23,Itinerario!T43," ")," ") | M43: =_xlfn.IFNA(IF(VLOOKUP($D43,Organización_Modular!$F$10:$G$195,2,FALSE)=M$23,Itinerario!W43," ")," ") | N43: =_xludf.IFNA(IF(VLOOKUP($D43,Organización_Modular!$F$10:$G$195,2,FALSE)=N$23,Itinerario!T43," ")," ") -> #NAME? | O43: =_xludf.IFNA(IF(VLOOKUP($D43,Organización_Modular!$F$10:$G$195,2,FALSE)=O$23,Itinerario!W43," ")," ") -> #NAME? | P43: =_xludf.IFNA(IF(VLOOKUP($D43,Organización_Modular!$F$10:$G$195,2,FALSE)=P$23,Itinerario!T43," ")," ") -> #NAME? | Q43: =_xludf.IFNA(IF(VLOOKUP($D43,Organización_Modular!$F$10:$G$195,2,FALSE)=Q$23,Itinerario!W43," ")," ") -> #NAME? | R43: =Organización_Modular!H29 -> 0 | S43: =Organización_Modular!I29 -> 0 | T43: =SUM(R43:S43) -> 0 | U43: =+R43*$S$19 -> 0 | V43: =+S43*$U$19 -> 0 | W43: =SUM(U43:V43) -> 0 | X43: =W43 -> 0
B44: =Organización_Modular!B30 -> Competencias para la empleabilidad | C44: =Organización_Modular!C30 -> CE1 Comunicación efectiva.- expresar y comprender de manera clara conceptos, ideas, sentimientos, hechos y opiniones en forma oral y escrita para comunicarse e interactuar con otras personas en contextos sociales y laborales diversos. | D44: =Organización_Modular!F30 -> COMUNICACIÓN VERBAL EFECTIVA | F44: =_xlfn.IFNA(IF(VLOOKUP($D44,Organización_Modular!$F$10:$G$195,2,FALSE)=F$23,Itinerario!T44," ")," ") -> 2 | G44: =_xlfn.IFNA(IF(VLOOKUP($D44,Organización_Modular!$F$10:$G$195,2,FALSE)=G$23,Itinerario!W44," ")," ") -> 48 | H44: =_xlfn.IFNA(IF(VLOOKUP($D44,Organización_Modular!$F$10:$G$195,2,FALSE)=H$23,Itinerario!T44," ")," ") | I44: =_xlfn.IFNA(IF(VLOOKUP($D44,Organización_Modular!$F$10:$G$195,2,FALSE)=I$23,Itinerario!W44," ")," ") | J44: =_xlfn.IFNA(IF(VLOOKUP($D44,Organización_Modular!$F$10:$G$195,2,FALSE)=J$23,Itinerario!T44," ")," ") | K44: =_xlfn.IFNA(IF(VLOOKUP($D44,Organización_Modular!$F$10:$G$195,2,FALSE)=K$23,Itinerario!W44," ")," ") | L44: =_xlfn.IFNA(IF(VLOOKUP($D44,Organización_Modular!$F$10:$G$195,2,FALSE)=L$23,Itinerario!T44," ")," ") | M44: =_xlfn.IFNA(IF(VLOOKUP($D44,Organización_Modular!$F$10:$G$195,2,FALSE)=M$23,Itinerario!W44," ")," ") | N44: =_xludf.IFNA(IF(VLOOKUP($D44,Organización_Modular!$F$10:$G$195,2,FALSE)=N$23,Itinerario!T44," ")," ") -> #NAME? | O44: =_xludf.IFNA(IF(VLOOKUP($D44,Organización_Modular!$F$10:$G$195,2,FALSE)=O$23,Itinerario!W44," ")," ") -> #NAME? | P44: =_xludf.IFNA(IF(VLOOKUP($D44,Organización_Modular!$F$10:$G$195,2,FALSE)=P$23,Itinerario!T44," ")," ") -> #NAME? | Q44: =_xludf.IFNA(IF(VLOOKUP($D44,Organización_Modular!$F$10:$G$195,2,FALSE)=Q$23,Itinerario!W44," ")," ") -> #NAME? | R44: =Organización_Modular!H30 -> 1 | S44: =Organización_Modular!I30 -> 1 | T44: =SUM(R44:S44) -> 2 | U44: =+R44*$S$19 -> 16 | V44: =+S44*$U$19 -> 32 | W44: =SUM(U44:V44) -> 48 | X44: =W44 -> 48
D45: =Organización_Modular!F31 -> COMUNICACIÓN ESCRITA | F45: =_xlfn.IFNA(IF(VLOOKUP($D45,Organización_Modular!$F$10:$G$195,2,FALSE)=F$23,Itinerario!T45," ")," ") -> 1 | G45: =_xlfn.IFNA(IF(VLOOKUP($D45,Organización_Modular!$F$10:$G$195,2,FALSE)=G$23,Itinerario!W45," ")," ") -> 32 | H45: =_xlfn.IFNA(IF(VLOOKUP($D45,Organización_Modular!$F$10:$G$195,2,FALSE)=H$23,Itinerario!T45," ")," ") | I45: =_xlfn.IFNA(IF(VLOOKUP($D45,Organización_Modular!$F$10:$G$195,2,FALSE)=I$23,Itinerario!W45," ")," ") | J45: =_xlfn.IFNA(IF(VLOOKUP($D45,Organización_Modular!$F$10:$G$195,2,FALSE)=J$23,Itinerario!T45," ")," ") | K45: =_xlfn.IFNA(IF(VLOOKUP($D45,Organización_Modular!$F$10:$G$195,2,FALSE)=K$23,Itinerario!W45," ")," ") | L45: =_xlfn.IFNA(IF(VLOOKUP($D45,Organización_Modular!$F$10:$G$195,2,FALSE)=L$23,Itinerario!T45," ")," ") | M45: =_xlfn.IFNA(IF(VLOOKUP($D45,Organización_Modular!$F$10:$G$195,2,FALSE)=M$23,Itinerario!W45," ")," ") | N45: =_xludf.IFNA(IF(VLOOKUP($D45,Organización_Modular!$F$10:$G$195,2,FALSE)=N$23,Itinerario!T45," ")," ") -> #NAME? | O45: =_xludf.IFNA(IF(VLOOKUP($D45,Organización_Modular!$F$10:$G$195,2,FALSE)=O$23,Itinerario!W45," ")," ") -> #NAME? | P45: =_xludf.IFNA(IF(VLOOKUP($D45,Organización_Modular!$F$10:$G$195,2,FALSE)=P$23,Itinerario!T45," ")," ") -> #NAME? | Q45: =_xludf.IFNA(IF(VLOOKUP($D45,Organización_Modular!$F$10:$G$195,2,FALSE)=Q$23,Itinerario!W45," ")," ") -> #NAME? | R45: =Organización_Modular!H31 -> 0 | S45: =Organización_Modular!I31 -> 1 | T45: =SUM(R45:S45) -> 1 | U45: =+R45*$S$19 -> 0 | V45: =+S45*$U$19 -> 32 | W45: =SUM(U45:V45) -> 32 | X45: =W45 -> 32
D46: =Organización_Modular!F32 -> 0 | F46: =_xlfn.IFNA(IF(VLOOKUP($D46,Organización_Modular!$F$10:$G$195,2,FALSE)=F$23,Itinerario!T46," ")," ") | G46: =_xlfn.IFNA(IF(VLOOKUP($D46,Organización_Modular!$F$10:$G$195,2,FALSE)=G$23,Itinerario!W46," ")," ") | H46: =_xlfn.IFNA(IF(VLOOKUP($D46,Organización_Modular!$F$10:$G$195,2,FALSE)=H$23,Itinerario!T46," ")," ") | I46: =_xlfn.IFNA(IF(VLOOKUP($D46,Organización_Modular!$F$10:$G$195,2,FALSE)=I$23,Itinerario!W46," ")," ") | J46: =_xlfn.IFNA(IF(VLOOKUP($D46,Organización_Modular!$F$10:$G$195,2,FALSE)=J$23,Itinerario!T46," ")," ") | K46: =_xlfn.IFNA(IF(VLOOKUP($D46,Organización_Modular!$F$10:$G$195,2,FALSE)=K$23,Itinerario!W46," ")," ") | L46: =_xlfn.IFNA(IF(VLOOKUP($D46,Organización_Modular!$F$10:$G$195,2,FALSE)=L$23,Itinerario!T46," ")," ") | M46: =_xlfn.IFNA(IF(VLOOKUP($D46,Organización_Modular!$F$10:$G$195,2,FALSE)=M$23,Itinerario!W46," ")," ") | N46: =_xludf.IFNA(IF(VLOOKUP($D46,Organización_Modular!$F$10:$G$195,2,FALSE)=N$23,Itinerario!T46," ")," ") -> #NAME? | O46: =_xludf.IFNA(IF(VLOOKUP($D46,Organización_Modular!$F$10:$G$195,2,FALSE)=O$23,Itinerario!W46," ")," ") -> #NAME? | P46: =_xludf.IFNA(IF(VLOOKUP($D46,Organización_Modular!$F$10:$G$195,2,FALSE)=P$23,Itinerario!T46," ")," ") -> #NAME? | Q46: =_xludf.IFNA(IF(VLOOKUP($D46,Organización_Modular!$F$10:$G$195,2,FALSE)=Q$23,Itinerario!W46," ")," ") -> #NAME? | R46: =Organización_Modular!H32 -> 0 | S46: =Organización_Modular!I32 -> 0 | T46: =SUM(R46:S46) -> 0 | U46: =+R46*$S$19 -> 0 | V46: =+S46*$U$19 -> 0 | W46: =SUM(U46:V46) -> 0 | X46: =W46 -> 0
D47: =Organización_Modular!F33 -> 0 | F47: =_xlfn.IFNA(IF(VLOOKUP($D47,Organización_Modular!$F$10:$G$195,2,FALSE)=F$23,Itinerario!T47," ")," ") | G47: =_xlfn.IFNA(IF(VLOOKUP($D47,Organización_Modular!$F$10:$G$195,2,FALSE)=G$23,Itinerario!W47," ")," ") | H47: =_xlfn.IFNA(IF(VLOOKUP($D47,Organización_Modular!$F$10:$G$195,2,FALSE)=H$23,Itinerario!T47," ")," ") | I47: =_xlfn.IFNA(IF(VLOOKUP($D47,Organización_Modular!$F$10:$G$195,2,FALSE)=I$23,Itinerario!W47," ")," ") | J47: =_xlfn.IFNA(IF(VLOOKUP($D47,Organización_Modular!$F$10:$G$195,2,FALSE)=J$23,Itinerario!T47," ")," ") | K47: =_xlfn.IFNA(IF(VLOOKUP($D47,Organización_Modular!$F$10:$G$195,2,FALSE)=K$23,Itinerario!W47," ")," ") | L47: =_xlfn.IFNA(IF(VLOOKUP($D47,Organización_Modular!$F$10:$G$195,2,FALSE)=L$23,Itinerario!T47," ")," ") | M47: =_xlfn.IFNA(IF(VLOOKUP($D47,Organización_Modular!$F$10:$G$195,2,FALSE)=M$23,Itinerario!W47," ")," ") | N47: =_xludf.IFNA(IF(VLOOKUP($D47,Organización_Modular!$F$10:$G$195,2,FALSE)=N$23,Itinerario!T47," ")," ") -> #NAME? | O47: =_xludf.IFNA(IF(VLOOKUP($D47,Organización_Modular!$F$10:$G$195,2,FALSE)=O$23,Itinerario!W47," ")," ") -> #NAME? | P47: =_xludf.IFNA(IF(VLOOKUP($D47,Organización_Modular!$F$10:$G$195,2,FALSE)=P$23,Itinerario!T47," ")," ") -> #NAME? | Q47: =_xludf.IFNA(IF(VLOOKUP($D47,Organización_Modular!$F$10:$G$195,2,FALSE)=Q$23,Itinerario!W47," ")," ") -> #NAME? | R47: =Organización_Modular!H33 -> 0 | S47: =Organización_Modular!I33 -> 0 | T47: =SUM(R47:S47) -> 0 | U47: =+R47*$S$19 -> 0 | V47: =+S47*$U$19 -> 0 | W47: =SUM(U47:V47) -> 0 | X47: =W47 -> 0
D48: =Organización_Modular!F34 -> 0 | F48: =_xlfn.IFNA(IF(VLOOKUP($D48,Organización_Modular!$F$10:$G$195,2,FALSE)=F$23,Itinerario!T48," ")," ") | G48: =_xlfn.IFNA(IF(VLOOKUP($D48,Organización_Modular!$F$10:$G$195,2,FALSE)=G$23,Itinerario!W48," ")," ") | H48: =_xlfn.IFNA(IF(VLOOKUP($D48,Organización_Modular!$F$10:$G$195,2,FALSE)=H$23,Itinerario!T48," ")," ") | I48: =_xlfn.IFNA(IF(VLOOKUP($D48,Organización_Modular!$F$10:$G$195,2,FALSE)=I$23,Itinerario!W48," ")," ") | J48: =_xlfn.IFNA(IF(VLOOKUP($D48,Organización_Modular!$F$10:$G$195,2,FALSE)=J$23,Itinerario!T48," ")," ") | K48: =_xlfn.IFNA(IF(VLOOKUP($D48,Organización_Modular!$F$10:$G$195,2,FALSE)=K$23,Itinerario!W48," ")," ") | L48: =_xlfn.IFNA(IF(VLOOKUP($D48,Organización_Modular!$F$10:$G$195,2,FALSE)=L$23,Itinerario!T48," ")," ") | M48: =_xlfn.IFNA(IF(VLOOKUP($D48,Organización_Modular!$F$10:$G$195,2,FALSE)=M$23,Itinerario!W48," ")," ") | N48: =_xludf.IFNA(IF(VLOOKUP($D48,Organización_Modular!$F$10:$G$195,2,FALSE)=N$23,Itinerario!T48," ")," ") -> #NAME? | O48: =_xludf.IFNA(IF(VLOOKUP($D48,Organización_Modular!$F$10:$G$195,2,FALSE)=O$23,Itinerario!W48," ")," ") -> #NAME? | P48: =_xludf.IFNA(IF(VLOOKUP($D48,Organización_Modular!$F$10:$G$195,2,FALSE)=P$23,Itinerario!T48," ")," ") -> #NAME? | Q48: =_xludf.IFNA(IF(VLOOKUP($D48,Organización_Modular!$F$10:$G$195,2,FALSE)=Q$23,Itinerario!W48," ")," ") -> #NAME? | R48: =Organización_Modular!H34 -> 0 | S48: =Organización_Modular!I34 -> 0 | T48: =SUM(R48:S48) -> 0 | U48: =+R48*$S$19 -> 0 | V48: =+S48*$U$19 -> 0 | W48: =SUM(U48:V48) -> 0 | X48: =W48 -> 0
D49: =Organización_Modular!F35 -> 0 | F49: =_xlfn.IFNA(IF(VLOOKUP($D49,Organización_Modular!$F$10:$G$195,2,FALSE)=F$23,Itinerario!T49," ")," ") | G49: =_xlfn.IFNA(IF(VLOOKUP($D49,Organización_Modular!$F$10:$G$195,2,FALSE)=G$23,Itinerario!W49," ")," ") | H49: =_xlfn.IFNA(IF(VLOOKUP($D49,Organización_Modular!$F$10:$G$195,2,FALSE)=H$23,Itinerario!T49," ")," ") | I49: =_xlfn.IFNA(IF(VLOOKUP($D49,Organización_Modular!$F$10:$G$195,2,FALSE)=I$23,Itinerario!W49," ")," ") | J49: =_xlfn.IFNA(IF(VLOOKUP($D49,Organización_Modular!$F$10:$G$195,2,FALSE)=J$23,Itinerario!T49," ")," ") | K49: =_xlfn.IFNA(IF(VLOOKUP($D49,Organización_Modular!$F$10:$G$195,2,FALSE)=K$23,Itinerario!W49," ")," ") | L49: =_xlfn.IFNA(IF(VLOOKUP($D49,Organización_Modular!$F$10:$G$195,2,FALSE)=L$23,Itinerario!T49," ")," ") | M49: =_xlfn.IFNA(IF(VLOOKUP($D49,Organización_Modular!$F$10:$G$195,2,FALSE)=M$23,Itinerario!W49," ")," ") | N49: =_xludf.IFNA(IF(VLOOKUP($D49,Organización_Modular!$F$10:$G$195,2,FALSE)=N$23,Itinerario!T49," ")," ") -> #NAME? | O49: =_xludf.IFNA(IF(VLOOKUP($D49,Organización_Modular!$F$10:$G$195,2,FALSE)=O$23,Itinerario!W49," ")," ") -> #NAME? | P49: =_xludf.IFNA(IF(VLOOKUP($D49,Organización_Modular!$F$10:$G$195,2,FALSE)=P$23,Itinerario!T49," ")," ") -> #NAME? | Q49: =_xludf.IFNA(IF(VLOOKUP($D49,Organización_Modular!$F$10:$G$195,2,FALSE)=Q$23,Itinerario!W49," ")," ") -> #NAME? | R49: =Organización_Modular!H35 -> 0 | S49: =Organización_Modular!I35 -> 0 | T49: =SUM(R49:S49) -> 0 | U49: =+R49*$S$19 -> 0 | V49: =+S49*$U$19 -> 0 | W49: =SUM(U49:V49) -> 0 | X49: =W49 -> 0
D50: =Organización_Modular!F36 -> 0 | F50: =_xlfn.IFNA(IF(VLOOKUP($D50,Organización_Modular!$F$10:$G$195,2,FALSE)=F$23,Itinerario!T50," ")," ") | G50: =_xlfn.IFNA(IF(VLOOKUP($D50,Organización_Modular!$F$10:$G$195,2,FALSE)=G$23,Itinerario!W50," ")," ") | H50: =_xlfn.IFNA(IF(VLOOKUP($D50,Organización_Modular!$F$10:$G$195,2,FALSE)=H$23,Itinerario!T50," ")," ") | I50: =_xlfn.IFNA(IF(VLOOKUP($D50,Organización_Modular!$F$10:$G$195,2,FALSE)=I$23,Itinerario!W50," ")," ") | J50: =_xlfn.IFNA(IF(VLOOKUP($D50,Organización_Modular!$F$10:$G$195,2,FALSE)=J$23,Itinerario!T50," ")," ") | K50: =_xlfn.IFNA(IF(VLOOKUP($D50,Organización_Modular!$F$10:$G$195,2,FALSE)=K$23,Itinerario!W50," ")," ") | L50: =_xlfn.IFNA(IF(VLOOKUP($D50,Organización_Modular!$F$10:$G$195,2,FALSE)=L$23,Itinerario!T50," ")," ") | M50: =_xlfn.IFNA(IF(VLOOKUP($D50,Organización_Modular!$F$10:$G$195,2,FALSE)=M$23,Itinerario!W50," ")," ") | N50: =_xludf.IFNA(IF(VLOOKUP($D50,Organización_Modular!$F$10:$G$195,2,FALSE)=N$23,Itinerario!T50," ")," ") -> #NAME? | O50: =_xludf.IFNA(IF(VLOOKUP($D50,Organización_Modular!$F$10:$G$195,2,FALSE)=O$23,Itinerario!W50," ")," ") -> #NAME? | P50: =_xludf.IFNA(IF(VLOOKUP($D50,Organización_Modular!$F$10:$G$195,2,FALSE)=P$23,Itinerario!T50," ")," ") -> #NAME? | Q50: =_xludf.IFNA(IF(VLOOKUP($D50,Organización_Modular!$F$10:$G$195,2,FALSE)=Q$23,Itinerario!W50," ")," ") -> #NAME? | R50: =Organización_Modular!H36 -> 0 | S50: =Organización_Modular!I36 -> 0 | T50: =SUM(R50:S50) -> 0 | U50: =+R50*$S$19 -> 0 | V50: =+S50*$U$19 -> 0 | W50: =SUM(U50:V50) -> 0 | X50: =W50 -> 0
D51: =Organización_Modular!F37 -> 0 | F51: =_xlfn.IFNA(IF(VLOOKUP($D51,Organización_Modular!$F$10:$G$195,2,FALSE)=F$23,Itinerario!T51," ")," ") | G51: =_xlfn.IFNA(IF(VLOOKUP($D51,Organización_Modular!$F$10:$G$195,2,FALSE)=G$23,Itinerario!W51," ")," ") | H51: =_xlfn.IFNA(IF(VLOOKUP($D51,Organización_Modular!$F$10:$G$195,2,FALSE)=H$23,Itinerario!T51," ")," ") | I51: =_xlfn.IFNA(IF(VLOOKUP($D51,Organización_Modular!$F$10:$G$195,2,FALSE)=I$23,Itinerario!W51," ")," ") | J51: =_xlfn.IFNA(IF(VLOOKUP($D51,Organización_Modular!$F$10:$G$195,2,FALSE)=J$23,Itinerario!T51," ")," ") | K51: =_xlfn.IFNA(IF(VLOOKUP($D51,Organización_Modular!$F$10:$G$195,2,FALSE)=K$23,Itinerario!W51," ")," ") | L51: =_xlfn.IFNA(IF(VLOOKUP($D51,Organización_Modular!$F$10:$G$195,2,FALSE)=L$23,Itinerario!T51," ")," ") | M51: =_xlfn.IFNA(IF(VLOOKUP($D51,Organización_Modular!$F$10:$G$195,2,FALSE)=M$23,Itinerario!W51," ")," ") | N51: =_xludf.IFNA(IF(VLOOKUP($D51,Organización_Modular!$F$10:$G$195,2,FALSE)=N$23,Itinerario!T51," ")," ") -> #NAME? | O51: =_xludf.IFNA(IF(VLOOKUP($D51,Organización_Modular!$F$10:$G$195,2,FALSE)=O$23,Itinerario!W51," ")," ") -> #NAME? | P51: =_xludf.IFNA(IF(VLOOKUP($D51,Organización_Modular!$F$10:$G$195,2,FALSE)=P$23,Itinerario!T51," ")," ") -> #NAME? | Q51: =_xludf.IFNA(IF(VLOOKUP($D51,Organización_Modular!$F$10:$G$195,2,FALSE)=Q$23,Itinerario!W51," ")," ") -> #NAME? | R51: =Organización_Modular!H37 -> 0 | S51: =Organización_Modular!I37 -> 0 | T51: =SUM(R51:S51) -> 0 | U51: =+R51*$S$19 -> 0 | V51: =+S51*$U$19 -> 0 | W51: =SUM(U51:V51) -> 0 | X51: =W51 -> 0
D52: =Organización_Modular!F38 -> 0 | F52: =_xlfn.IFNA(IF(VLOOKUP($D52,Organización_Modular!$F$10:$G$195,2,FALSE)=F$23,Itinerario!T52," ")," ") | G52: =_xlfn.IFNA(IF(VLOOKUP($D52,Organización_Modular!$F$10:$G$195,2,FALSE)=G$23,Itinerario!W52," ")," ") | H52: =_xlfn.IFNA(IF(VLOOKUP($D52,Organización_Modular!$F$10:$G$195,2,FALSE)=H$23,Itinerario!T52," ")," ") | I52: =_xlfn.IFNA(IF(VLOOKUP($D52,Organización_Modular!$F$10:$G$195,2,FALSE)=I$23,Itinerario!W52," ")," ") | J52: =_xlfn.IFNA(IF(VLOOKUP($D52,Organización_Modular!$F$10:$G$195,2,FALSE)=J$23,Itinerario!T52," ")," ") | K52: =_xlfn.IFNA(IF(VLOOKUP($D52,Organización_Modular!$F$10:$G$195,2,FALSE)=K$23,Itinerario!W52," ")," ") | L52: =_xlfn.IFNA(IF(VLOOKUP($D52,Organización_Modular!$F$10:$G$195,2,FALSE)=L$23,Itinerario!T52," ")," ") | M52: =_xlfn.IFNA(IF(VLOOKUP($D52,Organización_Modular!$F$10:$G$195,2,FALSE)=M$23,Itinerario!W52," ")," ") | N52: =_xludf.IFNA(IF(VLOOKUP($D52,Organización_Modular!$F$10:$G$195,2,FALSE)=N$23,Itinerario!T52," ")," ") -> #NAME? | O52: =_xludf.IFNA(IF(VLOOKUP($D52,Organización_Modular!$F$10:$G$195,2,FALSE)=O$23,Itinerario!W52," ")," ") -> #NAME? | P52: =_xludf.IFNA(IF(VLOOKUP($D52,Organización_Modular!$F$10:$G$195,2,FALSE)=P$23,Itinerario!T52," ")," ") -> #NAME? | Q52: =_xludf.IFNA(IF(VLOOKUP($D52,Organización_Modular!$F$10:$G$195,2,FALSE)=Q$23,Itinerario!W52," ")," ") -> #NAME? | R52: =Organización_Modular!H38 -> 0 | S52: =Organización_Modular!I38 -> 0 | T52: =SUM(R52:S52) -> 0 | U52: =+R52*$S$19 -> 0 | V52: =+S52*$U$19 -> 0 | W52: =SUM(U52:V52) -> 0 | X52: =W52 -> 0
D53: =Organización_Modular!F39 -> 0 | F53: =_xlfn.IFNA(IF(VLOOKUP($D53,Organización_Modular!$F$10:$G$195,2,FALSE)=F$23,Itinerario!T53," ")," ") | G53: =_xlfn.IFNA(IF(VLOOKUP($D53,Organización_Modular!$F$10:$G$195,2,FALSE)=G$23,Itinerario!W53," ")," ") | H53: =_xlfn.IFNA(IF(VLOOKUP($D53,Organización_Modular!$F$10:$G$195,2,FALSE)=H$23,Itinerario!T53," ")," ") | I53: =_xlfn.IFNA(IF(VLOOKUP($D53,Organización_Modular!$F$10:$G$195,2,FALSE)=I$23,Itinerario!W53," ")," ") | J53: =_xlfn.IFNA(IF(VLOOKUP($D53,Organización_Modular!$F$10:$G$195,2,FALSE)=J$23,Itinerario!T53," ")," ") | K53: =_xlfn.IFNA(IF(VLOOKUP($D53,Organización_Modular!$F$10:$G$195,2,FALSE)=K$23,Itinerario!W53," ")," ") | L53: =_xlfn.IFNA(IF(VLOOKUP($D53,Organización_Modular!$F$10:$G$195,2,FALSE)=L$23,Itinerario!T53," ")," ") | M53: =_xlfn.IFNA(IF(VLOOKUP($D53,Organización_Modular!$F$10:$G$195,2,FALSE)=M$23,Itinerario!W53," ")," ") | N53: =_xludf.IFNA(IF(VLOOKUP($D53,Organización_Modular!$F$10:$G$195,2,FALSE)=N$23,Itinerario!T53," ")," ") -> #NAME? | O53: =_xludf.IFNA(IF(VLOOKUP($D53,Organización_Modular!$F$10:$G$195,2,FALSE)=O$23,Itinerario!W53," ")," ") -> #NAME? | P53: =_xludf.IFNA(IF(VLOOKUP($D53,Organización_Modular!$F$10:$G$195,2,FALSE)=P$23,Itinerario!T53," ")," ") -> #NAME? | Q53: =_xludf.IFNA(IF(VLOOKUP($D53,Organización_Modular!$F$10:$G$195,2,FALSE)=Q$23,Itinerario!W53," ")," ") -> #NAME? | R53: =Organización_Modular!H39 -> 0 | S53: =Organización_Modular!I39 -> 0 | T53: =SUM(R53:S53) -> 0 | U53: =+R53*$S$19 -> 0 | V53: =+S53*$U$19 -> 0 | W53: =SUM(U53:V53) -> 0 | X53: =W53 -> 0
B54: =Organización_Modular!B40 -> Experiencias formativas en situaciones reales de trabajo (EFSRT) | F54: 4 | G54: 128 | R54: =Organización_Modular!H40 -> 0 | S54: =Organización_Modular!I40 -> 4 | T54: =SUM(R54:S54) -> 4 | U54: =+R54*$S$19 -> 0 | V54: =+S54*$U$19 -> 128 | W54: =SUM(U54:V54) -> 128 | X54: =W54 -> 128
A55: =Organización_Modular!A41 -> M2. ONDULACIÓN, LACEADO Y TINTURACIÓN DEL CABELLO | B55: =B24 -> Competencias técnicas (Unidad de competencia) | C55: =Organización_Modular!C41 -> UC2. Realizar procedimientos técnicos capilares, tomando en cuenta su diagnóstico, requerimientos del cliente, y de bioseguridad e higiene técnicos capilares, tomando en cuenta su diagnóstico, requerimientos del cliente, y de bioseguridad e higiene. | D55: =Organización_Modular!F41 -> TRATAMIENTO CAPILAR | F55: =_xlfn.IFNA(IF(VLOOKUP($D55,Organización_Modular!$F$10:$G$195,2,FALSE)=F$23,Itinerario!T55," ")," ") | G55: =_xlfn.IFNA(IF(VLOOKUP($D55,Organización_Modular!$F$10:$G$195,2,FALSE)=G$23,Itinerario!W55," ")," ") | H55: =_xlfn.IFNA(IF(VLOOKUP($D55,Organización_Modular!$F$10:$G$195,2,FALSE)=H$23,Itinerario!T55," ")," ") -> 5 | I55: =_xlfn.IFNA(IF(VLOOKUP($D55,Organización_Modular!$F$10:$G$195,2,FALSE)=I$23,Itinerario!W55," ")," ") -> 128 | J55: =_xlfn.IFNA(IF(VLOOKUP($D55,Organización_Modular!$F$10:$G$195,2,FALSE)=J$23,Itinerario!T55," ")," ") | K55: =_xlfn.IFNA(IF(VLOOKUP($D55,Organización_Modular!$F$10:$G$195,2,FALSE)=K$23,Itinerario!W55," ")," ") | L55: =_xlfn.IFNA(IF(VLOOKUP($D55,Organización_Modular!$F$10:$G$195,2,FALSE)=L$23,Itinerario!T55," ")," ") | M55: =_xlfn.IFNA(IF(VLOOKUP($D55,Organización_Modular!$F$10:$G$195,2,FALSE)=M$23,Itinerario!W55," ")," ") | N55: =_xludf.IFNA(IF(VLOOKUP($D55,Organización_Modular!$F$10:$G$195,2,FALSE)=N$23,Itinerario!T55," ")," ") -> #NAME? | O55: =_xludf.IFNA(IF(VLOOKUP($D55,Organización_Modular!$F$10:$G$195,2,FALSE)=O$23,Itinerario!W55," ")," ") -> #NAME? | P55: =_xludf.IFNA(IF(VLOOKUP($D55,Organización_Modular!$F$10:$G$195,2,FALSE)=P$23,Itinerario!T55," ")," ") -> #NAME? | Q55: =_xludf.IFNA(IF(VLOOKUP($D55,Organización_Modular!$F$10:$G$195,2,FALSE)=Q$23,Itinerario!W55," ")," ") -> #NAME? | R55: =Organización_Modular!H41 -> 2 | S55: =Organización_Modular!I41 -> 3 | T55: =SUM(R55:S55) -> 5 | U55: =+R55*$S$19 -> 32 | V55: =+S55*$U$19 -> 96 | W55: =SUM(U55:V55) -> 128 | X55: =W55 -> 128
D56: =Organización_Modular!F42 -> ONDULACIÓN Y LACEADO | F56: =_xlfn.IFNA(IF(VLOOKUP($D56,Organización_Modular!$F$10:$G$195,2,FALSE)=F$23,Itinerario!T56," ")," ") | G56: =_xlfn.IFNA(IF(VLOOKUP($D56,Organización_Modular!$F$10:$G$195,2,FALSE)=G$23,Itinerario!W56," ")," ") | H56: =_xlfn.IFNA(IF(VLOOKUP($D56,Organización_Modular!$F$10:$G$195,2,FALSE)=H$23,Itinerario!T56," ")," ") -> 6 | I56: =_xlfn.IFNA(IF(VLOOKUP($D56,Organización_Modular!$F$10:$G$195,2,FALSE)=I$23,Itinerario!W56," ")," ") -> 160 | J56: =_xlfn.IFNA(IF(VLOOKUP($D56,Organización_Modular!$F$10:$G$195,2,FALSE)=J$23,Itinerario!T56," ")," ") | K56: =_xlfn.IFNA(IF(VLOOKUP($D56,Organización_Modular!$F$10:$G$195,2,FALSE)=K$23,Itinerario!W56," ")," ") | L56: =_xlfn.IFNA(IF(VLOOKUP($D56,Organización_Modular!$F$10:$G$195,2,FALSE)=L$23,Itinerario!T56," ")," ") | M56: =_xlfn.IFNA(IF(VLOOKUP($D56,Organización_Modular!$F$10:$G$195,2,FALSE)=M$23,Itinerario!W56," ")," ") | N56: =_xludf.IFNA(IF(VLOOKUP($D56,Organización_Modular!$F$10:$G$195,2,FALSE)=N$23,Itinerario!T56," ")," ") -> #NAME? | O56: =_xludf.IFNA(IF(VLOOKUP($D56,Organización_Modular!$F$10:$G$195,2,FALSE)=O$23,Itinerario!W56," ")," ") -> #NAME? | P56: =_xludf.IFNA(IF(VLOOKUP($D56,Organización_Modular!$F$10:$G$195,2,FALSE)=P$23,Itinerario!T56," ")," ") -> #NAME? | Q56: =_xludf.IFNA(IF(VLOOKUP($D56,Organización_Modular!$F$10:$G$195,2,FALSE)=Q$23,Itinerario!W56," ")," ") -> #NAME? | R56: =Organización_Modular!H42 -> 2 | S56: =Organización_Modular!I42 -> 4 | T56: =SUM(R56:S56) -> 6 | U56: =+R56*$S$19 -> 32 | V56: =+S56*$U$19 -> 128 | W56: =SUM(U56:V56) -> 160 | X56: =W56 -> 160
D57: =Organización_Modular!F43 -> TINTURACIÓN Y DECOLORACION DEL CABELLO | F57: =_xlfn.IFNA(IF(VLOOKUP($D57,Organización_Modular!$F$10:$G$195,2,FALSE)=F$23,Itinerario!T57," ")," ") | G57: =_xlfn.IFNA(IF(VLOOKUP($D57,Organización_Modular!$F$10:$G$195,2,FALSE)=G$23,Itinerario!W57," ")," ") | H57: =_xlfn.IFNA(IF(VLOOKUP($D57,Organización_Modular!$F$10:$G$195,2,FALSE)=H$23,Itinerario!T57," ")," ") -> 4 | I57: =_xlfn.IFNA(IF(VLOOKUP($D57,Organización_Modular!$F$10:$G$195,2,FALSE)=I$23,Itinerario!W57," ")," ") -> 96 | J57: =_xlfn.IFNA(IF(VLOOKUP($D57,Organización_Modular!$F$10:$G$195,2,FALSE)=J$23,Itinerario!T57," ")," ") | K57: =_xlfn.IFNA(IF(VLOOKUP($D57,Organización_Modular!$F$10:$G$195,2,FALSE)=K$23,Itinerario!W57," ")," ") | L57: =_xlfn.IFNA(IF(VLOOKUP($D57,Organización_Modular!$F$10:$G$195,2,FALSE)=L$23,Itinerario!T57," ")," ") | M57: =_xlfn.IFNA(IF(VLOOKUP($D57,Organización_Modular!$F$10:$G$195,2,FALSE)=M$23,Itinerario!W57," ")," ") | N57: =_xludf.IFNA(IF(VLOOKUP($D57,Organización_Modular!$F$10:$G$195,2,FALSE)=N$23,Itinerario!T57," ")," ") -> #NAME? | O57: =_xludf.IFNA(IF(VLOOKUP($D57,Organización_Modular!$F$10:$G$195,2,FALSE)=O$23,Itinerario!W57," ")," ") -> #NAME? | P57: =_xludf.IFNA(IF(VLOOKUP($D57,Organización_Modular!$F$10:$G$195,2,FALSE)=P$23,Itinerario!T57," ")," ") -> #NAME? | Q57: =_xludf.IFNA(IF(VLOOKUP($D57,Organización_Modular!$F$10:$G$195,2,FALSE)=Q$23,Itinerario!W57," ")," ") -> #NAME? | R57: =Organización_Modular!H43 -> 2 | S57: =Organización_Modular!I43 -> 2 | T57: =SUM(R57:S57) -> 4 | U57: =+R57*$S$19 -> 32 | V57: =+S57*$U$19 -> 64 | W57: =SUM(U57:V57) -> 96 | X57: =W57 -> 96
D58: =Organización_Modular!F44 -> 0 | F58: =_xlfn.IFNA(IF(VLOOKUP($D58,Organización_Modular!$F$10:$G$195,2,FALSE)=F$23,Itinerario!T58," ")," ") | G58: =_xlfn.IFNA(IF(VLOOKUP($D58,Organización_Modular!$F$10:$G$195,2,FALSE)=G$23,Itinerario!W58," ")," ") | H58: =_xlfn.IFNA(IF(VLOOKUP($D58,Organización_Modular!$F$10:$G$195,2,FALSE)=H$23,Itinerario!T58," ")," ") | I58: =_xlfn.IFNA(IF(VLOOKUP($D58,Organización_Modular!$F$10:$G$195,2,FALSE)=I$23,Itinerario!W58," ")," ") | J58: =_xlfn.IFNA(IF(VLOOKUP($D58,Organización_Modular!$F$10:$G$195,2,FALSE)=J$23,Itinerario!T58," ")," ") | K58: =_xlfn.IFNA(IF(VLOOKUP($D58,Organización_Modular!$F$10:$G$195,2,FALSE)=K$23,Itinerario!W58," ")," ") | L58: =_xlfn.IFNA(IF(VLOOKUP($D58,Organización_Modular!$F$10:$G$195,2,FALSE)=L$23,Itinerario!T58," ")," ") | M58: =_xlfn.IFNA(IF(VLOOKUP($D58,Organización_Modular!$F$10:$G$195,2,FALSE)=M$23,Itinerario!W58," ")," ") | N58: =_xludf.IFNA(IF(VLOOKUP($D58,Organización_Modular!$F$10:$G$195,2,FALSE)=N$23,Itinerario!T58," ")," ") -> #NAME? | O58: =_xludf.IFNA(IF(VLOOKUP($D58,Organización_Modular!$F$10:$G$195,2,FALSE)=O$23,Itinerario!W58," ")," ") -> #NAME? | P58: =_xludf.IFNA(IF(VLOOKUP($D58,Organización_Modular!$F$10:$G$195,2,FALSE)=P$23,Itinerario!T58," ")," ") -> #NAME? | Q58: =_xludf.IFNA(IF(VLOOKUP($D58,Organización_Modular!$F$10:$G$195,2,FALSE)=Q$23,Itinerario!W58," ")," ") -> #NAME? | R58: =Organización_Modular!H44 -> 0 | S58: =Organización_Modular!I44 -> 0 | T58: =SUM(R58:S58) -> 0 | U58: =+R58*$S$19 -> 0 | V58: =+S58*$U$19 -> 0 | W58: =SUM(U58:V58) -> 0 | X58: =W58 -> 0
D59: =Organización_Modular!F45 -> 0 | F59: =_xlfn.IFNA(IF(VLOOKUP($D59,Organización_Modular!$F$10:$G$195,2,FALSE)=F$23,Itinerario!T59," ")," ") | G59: =_xlfn.IFNA(IF(VLOOKUP($D59,Organización_Modular!$F$10:$G$195,2,FALSE)=G$23,Itinerario!W59," ")," ") | H59: =_xlfn.IFNA(IF(VLOOKUP($D59,Organización_Modular!$F$10:$G$195,2,FALSE)=H$23,Itinerario!T59," ")," ") | I59: =_xlfn.IFNA(IF(VLOOKUP($D59,Organización_Modular!$F$10:$G$195,2,FALSE)=I$23,Itinerario!W59," ")," ") | J59: =_xlfn.IFNA(IF(VLOOKUP($D59,Organización_Modular!$F$10:$G$195,2,FALSE)=J$23,Itinerario!T59," ")," ") | K59: =_xlfn.IFNA(IF(VLOOKUP($D59,Organización_Modular!$F$10:$G$195,2,FALSE)=K$23,Itinerario!W59," ")," ") | L59: =_xlfn.IFNA(IF(VLOOKUP($D59,Organización_Modular!$F$10:$G$195,2,FALSE)=L$23,Itinerario!T59," ")," ") | M59: =_xlfn.IFNA(IF(VLOOKUP($D59,Organización_Modular!$F$10:$G$195,2,FALSE)=M$23,Itinerario!W59," ")," ") | N59: =_xludf.IFNA(IF(VLOOKUP($D59,Organización_Modular!$F$10:$G$195,2,FALSE)=N$23,Itinerario!T59," ")," ") -> #NAME? | O59: =_xludf.IFNA(IF(VLOOKUP($D59,Organización_Modular!$F$10:$G$195,2,FALSE)=O$23,Itinerario!W59," ")," ") -> #NAME? | P59: =_xludf.IFNA(IF(VLOOKUP($D59,Organización_Modular!$F$10:$G$195,2,FALSE)=P$23,Itinerario!T59," ")," ") -> #NAME? | Q59: =_xludf.IFNA(IF(VLOOKUP($D59,Organización_Modular!$F$10:$G$195,2,FALSE)=Q$23,Itinerario!W59," ")," ") -> #NAME? | R59: =Organización_Modular!H45 -> 0 | S59: =Organización_Modular!I45 -> 0 | T59: =SUM(R59:S59) -> 0 | U59: =+R59*$S$19 -> 0 | V59: =+S59*$U$19 -> 0 | W59: =SUM(U59:V59) -> 0 | X59: =W59 -> 0
D60: =Organización_Modular!F46 -> 0 | F60: =_xlfn.IFNA(IF(VLOOKUP($D60,Organización_Modular!$F$10:$G$195,2,FALSE)=F$23,Itinerario!T60," ")," ") | G60: =_xlfn.IFNA(IF(VLOOKUP($D60,Organización_Modular!$F$10:$G$195,2,FALSE)=G$23,Itinerario!W60," ")," ") | H60: =_xlfn.IFNA(IF(VLOOKUP($D60,Organización_Modular!$F$10:$G$195,2,FALSE)=H$23,Itinerario!T60," ")," ") | I60: =_xlfn.IFNA(IF(VLOOKUP($D60,Organización_Modular!$F$10:$G$195,2,FALSE)=I$23,Itinerario!W60," ")," ") | J60: =_xlfn.IFNA(IF(VLOOKUP($D60,Organización_Modular!$F$10:$G$195,2,FALSE)=J$23,Itinerario!T60," ")," ") | K60: =_xlfn.IFNA(IF(VLOOKUP($D60,Organización_Modular!$F$10:$G$195,2,FALSE)=K$23,Itinerario!W60," ")," ") | L60: =_xlfn.IFNA(IF(VLOOKUP($D60,Organización_Modular!$F$10:$G$195,2,FALSE)=L$23,Itinerario!T60," ")," ") | M60: =_xlfn.IFNA(IF(VLOOKUP($D60,Organización_Modular!$F$10:$G$195,2,FALSE)=M$23,Itinerario!W60," ")," ") | N60: =_xludf.IFNA(IF(VLOOKUP($D60,Organización_Modular!$F$10:$G$195,2,FALSE)=N$23,Itinerario!T60," ")," ") -> #NAME? | O60: =_xludf.IFNA(IF(VLOOKUP($D60,Organización_Modular!$F$10:$G$195,2,FALSE)=O$23,Itinerario!W60," ")," ") -> #NAME? | P60: =_xludf.IFNA(IF(VLOOKUP($D60,Organización_Modular!$F$10:$G$195,2,FALSE)=P$23,Itinerario!T60," ")," ") -> #NAME? | Q60: =_xludf.IFNA(IF(VLOOKUP($D60,Organización_Modular!$F$10:$G$195,2,FALSE)=Q$23,Itinerario!W60," ")," ") -> #NAME? | R60: =Organización_Modular!H46 -> 0 | S60: =Organización_Modular!I46 -> 0 | T60: =SUM(R60:S60) -> 0 | U60: =+R60*$S$19 -> 0 | V60: =+S60*$U$19 -> 0 | W60: =SUM(U60:V60) -> 0 | X60: =W60 -> 0
